Workbook

Sheet Inicio
C2: Control de Créditos
C3: =IF(Datos!$C$6="","Tu marca aquí (hoja Datos)",Datos!$C$6) -> Tu marca aquí (hoja Datos)
C7: Cliente | D7: =IF(Datos!$C$5="","",Datos!$C$5)
B9: Cómo se usa
B10: # | C10: Cuándo | D10: Qué hacer
B11: 1 | C11: Una sola vez | D11: Hoja Datos: ingresos y tasa de cambio. Cada hoja Crédito: nombre, saldo, fecha de la primera cuota, tasa y cuota (o plazo).
B12: 2 | C12: Cada mes | D12: En cada crédito, escribe "Sí" en Pagado y la fecha real de pago de la cuota del mes.
B13: 3 | C13: Si abonas extra | D13: Escribe el valor en la columna Abono extra del mes en que lo hiciste. El saldo y la fecha fin se recalculan.
B14: 4 | C14: Si cambia la cuota | D14: Escribe la nueva cuota en "Cuota distinta este mes" (por ejemplo, un mes con cuota especial).
B15: 5 | C15: Para revisar | D15: Panel: deuda total, pagos del mes, calendario, cuotas vencidas y el plan de pago.
B16: 6 | C16: Plan de pago | D16: Elige el método. El Panel muestra a qué crédito va el abono extra del próximo mes.
B18: Casos especiales
C19: Préstamo familiar sin interés | D19: Tasa 0% y "¿Acepta abonos extra?" = No si se acordó pagar a un ritmo fijo.
C20: Hipotecario con FRECH | D20: Escribe los puntos de tasa cubiertos y hasta qué cuota. Si no se debe abonar antes de cierta cuota, escríbela en "Abonos extra desde".
C21: Crédito que ya va avanzado | D21: Usa el saldo actual del extracto, la fecha de la próxima cuota y su número.
C22: Ingresos en dólares | D22: Hoja Datos: moneda USD y la tasa de cambio que te pagan. Mira la tabla de sensibilidad.
B24: Leyenda
C25: Dato que llenas | D25: Celda para llenar o actualizar.
C26: Por confirmar | D26: Dato pendiente de confirmar.
C27: Cálculo automático | D27: Fórmula: no se edita.
C29: Cifras en pesos. Los cálculos son una guía: confirma saldos y cuotas con los extractos de cada entidad.

Sheet Panel
B1: Panel de créditos
B2: Se actualiza solo: marca "Sí" en Pagado en cada crédito y aquí cambian saldos, calendario y proyección.
B4: Deuda total hoy | D4: Pago del próximo mes | F4: Intereses por pagar | H4: Capital ya pagado | J4: Libre de deudas (con el plan) | L4: Cuotas vencidas sin marcar
B5: ='Crédito 1'!$I$6+'Crédito 2'!$I$6+'Crédito 3'!$I$6+'Crédito 4'!$I$6+'Crédito 5'!$I$6+'Crédito 6'!$I$6+'Crédito 7'!$I$6+'Crédito 8'!$I$6 -> 0 | D5: ='Crédito 1'!$I$10+'Crédito 2'!$I$10+'Crédito 3'!$I$10+'Crédito 4'!$I$10+'Crédito 5'!$I$10+'Crédito 6'!$I$10+'Crédito 7'!$I$10+'Crédito 8'!$I$10 -> 0 | F5: ='Crédito 1'!$I$13+'Crédito 2'!$I$13+'Crédito 3'!$I$13+'Crédito 4'!$I$13+'Crédito 5'!$I$13+'Crédito 6'!$I$13+'Crédito 7'!$I$13+'Crédito 8'!$I$13 -> 0 | H5: =IF(SUM(N13:N20)=0,0,1-B5/SUM(N13:N20)) -> 0 | J5: =IF(COUNT('Plan de pago'!$M$12:$M$19)=0,"",IF(COUNTIF('Plan de pago'!$M$12:$M$19,"Más de 360")>0,"Más de 30 años",MAX('Plan de pago'!$M$12:$M$19))) | L5: ='Crédito 1'!$I$17+'Crédito 2'!$I$17+'Crédito 3'!$I$17+'Crédito 4'!$I$17+'Crédito 5'!$I$17+'Crédito 6'!$I$17+'Crédito 7'!$I$17+'Crédito 8'!$I$17 -> 0
B7: Carga financiera (deudas / ingreso): | D7: =Datos!$C$21 | E7: =Datos!$D$21
B10: 1. Resumen de créditos
B12: Crédito | C12: Saldo actual | D12: Tasa EA | E12: Próximo pago | F12: Cuotas restantes | G12: Fecha fin | H12: Intereses pendientes | I12: Total pendiente | J12: % capital pagado | K12: Estado | L12: Entidad | N12: Base %
B13: =IF('Crédito 1'!$F$6="Sí",'Crédito 1'!$C$6,"") | C13: =IF($B13="","",'Crédito 1'!$I$6) | D13: =IF($B13="","",'Crédito 1'!$C$13) | E13: =IF($B13="","",'Crédito 1'!$I$10) | F13: =IF($B13="","",'Crédito 1'!$I$11) | G13: =IF($B13="","",'Crédito 1'!$I$12) | H13: =IF($B13="","",'Crédito 1'!$I$13) | I13: =IF($B13="","",'Crédito 1'!$I$14) | J13: =IF($B13="","",'Crédito 1'!$I$15) | K13: =IF($B13="","",'Crédito 1'!$I$19) | L13: =IF($B13="","",'Crédito 1'!$C$7) | N13: =IF($B13="",0,IF(N('Crédito 1'!$C$16)>0,'Crédito 1'!$C$16,N('Crédito 1'!$C$9))) -> 0 | O13: =IF(ISNUMBER('Crédito 1'!$I$9),'Crédito 1'!$I$9+1/100,"")
B14: =IF('Crédito 2'!$F$6="Sí",'Crédito 2'!$C$6,"") | C14: =IF($B14="","",'Crédito 2'!$I$6) | D14: =IF($B14="","",'Crédito 2'!$C$13) | E14: =IF($B14="","",'Crédito 2'!$I$10) | F14: =IF($B14="","",'Crédito 2'!$I$11) | G14: =IF($B14="","",'Crédito 2'!$I$12) | H14: =IF($B14="","",'Crédito 2'!$I$13) | I14: =IF($B14="","",'Crédito 2'!$I$14) | J14: =IF($B14="","",'Crédito 2'!$I$15) | K14: =IF($B14="","",'Crédito 2'!$I$19) | L14: =IF($B14="","",'Crédito 2'!$C$7) | N14: =IF($B14="",0,IF(N('Crédito 2'!$C$16)>0,'Crédito 2'!$C$16,N('Crédito 2'!$C$9))) -> 0 | O14: =IF(ISNUMBER('Crédito 2'!$I$9),'Crédito 2'!$I$9+2/100,"")
B15: =IF('Crédito 3'!$F$6="Sí",'Crédito 3'!$C$6,"") | C15: =IF($B15="","",'Crédito 3'!$I$6) | D15: =IF($B15="","",'Crédito 3'!$C$13) | E15: =IF($B15="","",'Crédito 3'!$I$10) | F15: =IF($B15="","",'Crédito 3'!$I$11) | G15: =IF($B15="","",'Crédito 3'!$I$12) | H15: =IF($B15="","",'Crédito 3'!$I$13) | I15: =IF($B15="","",'Crédito 3'!$I$14) | J15: =IF($B15="","",'Crédito 3'!$I$15) | K15: =IF($B15="","",'Crédito 3'!$I$19) | L15: =IF($B15="","",'Crédito 3'!$C$7) | N15: =IF($B15="",0,IF(N('Crédito 3'!$C$16)>0,'Crédito 3'!$C$16,N('Crédito 3'!$C$9))) -> 0 | O15: =IF(ISNUMBER('Crédito 3'!$I$9),'Crédito 3'!$I$9+3/100,"")
B16: =IF('Crédito 4'!$F$6="Sí",'Crédito 4'!$C$6,"") | C16: =IF($B16="","",'Crédito 4'!$I$6) | D16: =IF($B16="","",'Crédito 4'!$C$13) | E16: =IF($B16="","",'Crédito 4'!$I$10) | F16: =IF($B16="","",'Crédito 4'!$I$11) | G16: =IF($B16="","",'Crédito 4'!$I$12) | H16: =IF($B16="","",'Crédito 4'!$I$13) | I16: =IF($B16="","",'Crédito 4'!$I$14) | J16: =IF($B16="","",'Crédito 4'!$I$15) | K16: =IF($B16="","",'Crédito 4'!$I$19) | L16: =IF($B16="","",'Crédito 4'!$C$7) | N16: =IF($B16="",0,IF(N('Crédito 4'!$C$16)>0,'Crédito 4'!$C$16,N('Crédito 4'!$C$9))) -> 0 | O16: =IF(ISNUMBER('Crédito 4'!$I$9),'Crédito 4'!$I$9+4/100,"")
B17: =IF('Crédito 5'!$F$6="Sí",'Crédito 5'!$C$6,"") | C17: =IF($B17="","",'Crédito 5'!$I$6) | D17: =IF($B17="","",'Crédito 5'!$C$13) | E17: =IF($B17="","",'Crédito 5'!$I$10) | F17: =IF($B17="","",'Crédito 5'!$I$11) | G17: =IF($B17="","",'Crédito 5'!$I$12) | H17: =IF($B17="","",'Crédito 5'!$I$13) | I17: =IF($B17="","",'Crédito 5'!$I$14) | J17: =IF($B17="","",'Crédito 5'!$I$15) | K17: =IF($B17="","",'Crédito 5'!$I$19) | L17: =IF($B17="","",'Crédito 5'!$C$7) | N17: =IF($B17="",0,IF(N('Crédito 5'!$C$16)>0,'Crédito 5'!$C$16,N('Crédito 5'!$C$9))) -> 0 | O17: =IF(ISNUMBER('Crédito 5'!$I$9),'Crédito 5'!$I$9+5/100,"")
B18: =IF('Crédito 6'!$F$6="Sí",'Crédito 6'!$C$6,"") | C18: =IF($B18="","",'Crédito 6'!$I$6) | D18: =IF($B18="","",'Crédito 6'!$C$13) | E18: =IF($B18="","",'Crédito 6'!$I$10) | F18: =IF($B18="","",'Crédito 6'!$I$11) | G18: =IF($B18="","",'Crédito 6'!$I$12) | H18: =IF($B18="","",'Crédito 6'!$I$13) | I18: =IF($B18="","",'Crédito 6'!$I$14) | J18: =IF($B18="","",'Crédito 6'!$I$15) | K18: =IF($B18="","",'Crédito 6'!$I$19) | L18: =IF($B18="","",'Crédito 6'!$C$7) | N18: =IF($B18="",0,IF(N('Crédito 6'!$C$16)>0,'Crédito 6'!$C$16,N('Crédito 6'!$C$9))) -> 0 | O18: =IF(ISNUMBER('Crédito 6'!$I$9),'Crédito 6'!$I$9+6/100,"")
B19: =IF('Crédito 7'!$F$6="Sí",'Crédito 7'!$C$6,"") | C19: =IF($B19="","",'Crédito 7'!$I$6) | D19: =IF($B19="","",'Crédito 7'!$C$13) | E19: =IF($B19="","",'Crédito 7'!$I$10) | F19: =IF($B19="","",'Crédito 7'!$I$11) | G19: =IF($B19="","",'Crédito 7'!$I$12) | H19: =IF($B19="","",'Crédito 7'!$I$13) | I19: =IF($B19="","",'Crédito 7'!$I$14) | J19: =IF($B19="","",'Crédito 7'!$I$15) | K19: =IF($B19="","",'Crédito 7'!$I$19) | L19: =IF($B19="","",'Crédito 7'!$C$7) | N19: =IF($B19="",0,IF(N('Crédito 7'!$C$16)>0,'Crédito 7'!$C$16,N('Crédito 7'!$C$9))) -> 0 | O19: =IF(ISNUMBER('Crédito 7'!$I$9),'Crédito 7'!$I$9+7/100,"")
B20: =IF('Crédito 8'!$F$6="Sí",'Crédito 8'!$C$6,"") | C20: =IF($B20="","",'Crédito 8'!$I$6) | D20: =IF($B20="","",'Crédito 8'!$C$13) | E20: =IF($B20="","",'Crédito 8'!$I$10) | F20: =IF($B20="","",'Crédito 8'!$I$11) | G20: =IF($B20="","",'Crédito 8'!$I$12) | H20: =IF($B20="","",'Crédito 8'!$I$13) | I20: =IF($B20="","",'Crédito 8'!$I$14) | J20: =IF($B20="","",'Crédito 8'!$I$15) | K20: =IF($B20="","",'Crédito 8'!$I$19) | L20: =IF($B20="","",'Crédito 8'!$C$7) | N20: =IF($B20="",0,IF(N('Crédito 8'!$C$16)>0,'Crédito 8'!$C$16,N('Crédito 8'!$C$9))) -> 0 | O20: =IF(ISNUMBER('Crédito 8'!$I$9),'Crédito 8'!$I$9+8/100,"")
B21: Total | C21: =SUM(C13:C20) -> 0 | E21: =SUM(E13:E20) -> 0 | H21: =SUM(H13:H20) -> 0 | I21: =SUM(I13:I20) -> 0
B23: 2. Calendario: próxima cuota de cada crédito (ordenado por fecha) | I23: 3. Pagos según el día del mes
B24: Crédito | C24: Próxima fecha | D24: Monto a pagar | E24: Día | F24: Estado
B25: =IF(IFERROR(MATCH(SMALL($O$13:$O$20,1),$O$13:$O$20,0),0)=0,"",INDEX($B$13:$B$20,IFERROR(MATCH(SMALL($O$13:$O$20,1),$O$13:$O$20,0),0))) | C25: =IF(B25="","",CHOOSE(IFERROR(MATCH(SMALL($O$13:$O$20,1),$O$13:$O$20,0),0),'Crédito 1'!$I$9,'Crédito 2'!$I$9,'Crédito 3'!$I$9,'Crédito 4'!$I$9,'Crédito 5'!$I$9,'Crédito 6'!$I$9,'Crédito 7'!$I$9,'Crédito 8'!$I$9)) | D25: =IF(B25="","",CHOOSE(IFERROR(MATCH(SMALL($O$13:$O$20,1),$O$13:$O$20,0),0),'Crédito 1'!$I$10,'Crédito 2'!$I$10,'Crédito 3'!$I$10,'Crédito 4'!$I$10,'Crédito 5'!$I$10,'Crédito 6'!$I$10,'Crédito 7'!$I$10,'Crédito 8'!$I$10)) | E25: =IF(B25="","",DAY(C25)) | F25: =IF(B25="","",IF(C25<Datos!$C$7,"Vencida",IF(C25-Datos!$C$7<=7,"Paga esta semana","Al día"))) | I25: Días 1 a 10 | K25: =SUMIFS($D$25:$D$32,$E$25:$E$32,">=1",$E$25:$E$32,"<=10") -> 0
B26: =IF(IFERROR(MATCH(SMALL($O$13:$O$20,2),$O$13:$O$20,0),0)=0,"",INDEX($B$13:$B$20,IFERROR(MATCH(SMALL($O$13:$O$20,2),$O$13:$O$20,0),0))) | C26: =IF(B26="","",CHOOSE(IFERROR(MATCH(SMALL($O$13:$O$20,2),$O$13:$O$20,0),0),'Crédito 1'!$I$9,'Crédito 2'!$I$9,'Crédito 3'!$I$9,'Crédito 4'!$I$9,'Crédito 5'!$I$9,'Crédito 6'!$I$9,'Crédito 7'!$I$9,'Crédito 8'!$I$9)) | D26: =IF(B26="","",CHOOSE(IFERROR(MATCH(SMALL($O$13:$O$20,2),$O$13:$O$20,0),0),'Crédito 1'!$I$10,'Crédito 2'!$I$10,'Crédito 3'!$I$10,'Crédito 4'!$I$10,'Crédito 5'!$I$10,'Crédito 6'!$I$10,'Crédito 7'!$I$10,'Crédito 8'!$I$10)) | E26: =IF(B26="","",DAY(C26)) | F26: =IF(B26="","",IF(C26<Datos!$C$7,"Vencida",IF(C26-Datos!$C$7<=7,"Paga esta semana","Al día"))) | I26: Días 11 a 20 | K26: =SUMIFS($D$25:$D$32,$E$25:$E$32,">=11",$E$25:$E$32,"<=20") -> 0
B27: =IF(IFERROR(MATCH(SMALL($O$13:$O$20,3),$O$13:$O$20,0),0)=0,"",INDEX($B$13:$B$20,IFERROR(MATCH(SMALL($O$13:$O$20,3),$O$13:$O$20,0),0))) | C27: =IF(B27="","",CHOOSE(IFERROR(MATCH(SMALL($O$13:$O$20,3),$O$13:$O$20,0),0),'Crédito 1'!$I$9,'Crédito 2'!$I$9,'Crédito 3'!$I$9,'Crédito 4'!$I$9,'Crédito 5'!$I$9,'Crédito 6'!$I$9,'Crédito 7'!$I$9,'Crédito 8'!$I$9)) | D27: =IF(B27="","",CHOOSE(IFERROR(MATCH(SMALL($O$13:$O$20,3),$O$13:$O$20,0),0),'Crédito 1'!$I$10,'Crédito 2'!$I$10,'Crédito 3'!$I$10,'Crédito 4'!$I$10,'Crédito 5'!$I$10,'Crédito 6'!$I$10,'Crédito 7'!$I$10,'Crédito 8'!$I$10)) | E27: =IF(B27="","",DAY(C27)) | F27: =IF(B27="","",IF(C27<Datos!$C$7,"Vencida",IF(C27-Datos!$C$7<=7,"Paga esta semana","Al día"))) | I27: Días 21 a 31 | K27: =SUMIFS($D$25:$D$32,$E$25:$E$32,">=21",$E$25:$E$32,"<=31") -> 0
B28: =IF(IFERROR(MATCH(SMALL($O$13:$O$20,4),$O$13:$O$20,0),0)=0,"",INDEX($B$13:$B$20,IFERROR(MATCH(SMALL($O$13:$O$20,4),$O$13:$O$20,0),0))) | C28: =IF(B28="","",CHOOSE(IFERROR(MATCH(SMALL($O$13:$O$20,4),$O$13:$O$20,0),0),'Crédito 1'!$I$9,'Crédito 2'!$I$9,'Crédito 3'!$I$9,'Crédito 4'!$I$9,'Crédito 5'!$I$9,'Crédito 6'!$I$9,'Crédito 7'!$I$9,'Crédito 8'!$I$9)) | D28: =IF(B28="","",CHOOSE(IFERROR(MATCH(SMALL($O$13:$O$20,4),$O$13:$O$20,0),0),'Crédito 1'!$I$10,'Crédito 2'!$I$10,'Crédito 3'!$I$10,'Crédito 4'!$I$10,'Crédito 5'!$I$10,'Crédito 6'!$I$10,'Crédito 7'!$I$10,'Crédito 8'!$I$10)) | E28: =IF(B28="","",DAY(C28)) | F28: =IF(B28="","",IF(C28<Datos!$C$7,"Vencida",IF(C28-Datos!$C$7<=7,"Paga esta semana","Al día"))) | I28: Total | K28: =SUM(K25:K27) -> 0
B29: =IF(IFERROR(MATCH(SMALL($O$13:$O$20,5),$O$13:$O$20,0),0)=0,"",INDEX($B$13:$B$20,IFERROR(MATCH(SMALL($O$13:$O$20,5),$O$13:$O$20,0),0))) | C29: =IF(B29="","",CHOOSE(IFERROR(MATCH(SMALL($O$13:$O$20,5),$O$13:$O$20,0),0),'Crédito 1'!$I$9,'Crédito 2'!$I$9,'Crédito 3'!$I$9,'Crédito 4'!$I$9,'Crédito 5'!$I$9,'Crédito 6'!$I$9,'Crédito 7'!$I$9,'Crédito 8'!$I$9)) | D29: =IF(B29="","",CHOOSE(IFERROR(MATCH(SMALL($O$13:$O$20,5),$O$13:$O$20,0),0),'Crédito 1'!$I$10,'Crédito 2'!$I$10,'Crédito 3'!$I$10,'Crédito 4'!$I$10,'Crédito 5'!$I$10,'Crédito 6'!$I$10,'Crédito 7'!$I$10,'Crédito 8'!$I$10)) | E29: =IF(B29="","",DAY(C29)) | F29: =IF(B29="","",IF(C29<Datos!$C$7,"Vencida",IF(C29-Datos!$C$7<=7,"Paga esta semana","Al día"))) | I29: Ten ese dinero en la cuenta antes de cada tramo.
B30: =IF(IFERROR(MATCH(SMALL($O$13:$O$20,6),$O$13:$O$20,0),0)=0,"",INDEX($B$13:$B$20,IFERROR(MATCH(SMALL($O$13:$O$20,6),$O$13:$O$20,0),0))) | C30: =IF(B30="","",CHOOSE(IFERROR(MATCH(SMALL($O$13:$O$20,6),$O$13:$O$20,0),0),'Crédito 1'!$I$9,'Crédito 2'!$I$9,'Crédito 3'!$I$9,'Crédito 4'!$I$9,'Crédito 5'!$I$9,'Crédito 6'!$I$9,'Crédito 7'!$I$9,'Crédito 8'!$I$9)) | D30: =IF(B30="","",CHOOSE(IFERROR(MATCH(SMALL($O$13:$O$20,6),$O$13:$O$20,0),0),'Crédito 1'!$I$10,'Crédito 2'!$I$10,'Crédito 3'!$I$10,'Crédito 4'!$I$10,'Crédito 5'!$I$10,'Crédito 6'!$I$10,'Crédito 7'!$I$10,'Crédito 8'!$I$10)) | E30: =IF(B30="","",DAY(C30)) | F30: =IF(B30="","",IF(C30<Datos!$C$7,"Vencida",IF(C30-Datos!$C$7<=7,"Paga esta semana","Al día")))
B31: =IF(IFERROR(MATCH(SMALL($O$13:$O$20,7),$O$13:$O$20,0),0)=0,"",INDEX($B$13:$B$20,IFERROR(MATCH(SMALL($O$13:$O$20,7),$O$13:$O$20,0),0))) | C31: =IF(B31="","",CHOOSE(IFERROR(MATCH(SMALL($O$13:$O$20,7),$O$13:$O$20,0),0),'Crédito 1'!$I$9,'Crédito 2'!$I$9,'Crédito 3'!$I$9,'Crédito 4'!$I$9,'Crédito 5'!$I$9,'Crédito 6'!$I$9,'Crédito 7'!$I$9,'Crédito 8'!$I$9)) | D31: =IF(B31="","",CHOOSE(IFERROR(MATCH(SMALL($O$13:$O$20,7),$O$13:$O$20,0),0),'Crédito 1'!$I$10,'Crédito 2'!$I$10,'Crédito 3'!$I$10,'Crédito 4'!$I$10,'Crédito 5'!$I$10,'Crédito 6'!$I$10,'Crédito 7'!$I$10,'Crédito 8'!$I$10)) | E31: =IF(B31="","",DAY(C31)) | F31: =IF(B31="","",IF(C31<Datos!$C$7,"Vencida",IF(C31-Datos!$C$7<=7,"Paga esta semana","Al día")))
B32: =IF(IFERROR(MATCH(SMALL($O$13:$O$20,8),$O$13:$O$20,0),0)=0,"",INDEX($B$13:$B$20,IFERROR(MATCH(SMALL($O$13:$O$20,8),$O$13:$O$20,0),0))) | C32: =IF(B32="","",CHOOSE(IFERROR(MATCH(SMALL($O$13:$O$20,8),$O$13:$O$20,0),0),'Crédito 1'!$I$9,'Crédito 2'!$I$9,'Crédito 3'!$I$9,'Crédito 4'!$I$9,'Crédito 5'!$I$9,'Crédito 6'!$I$9,'Crédito 7'!$I$9,'Crédito 8'!$I$9)) | D32: =IF(B32="","",CHOOSE(IFERROR(MATCH(SMALL($O$13:$O$20,8),$O$13:$O$20,0),0),'Crédito 1'!$I$10,'Crédito 2'!$I$10,'Crédito 3'!$I$10,'Crédito 4'!$I$10,'Crédito 5'!$I$10,'Crédito 6'!$I$10,'Crédito 7'!$I$10,'Crédito 8'!$I$10)) | E32: =IF(B32="","",DAY(C32)) | F32: =IF(B32="","",IF(C32<Datos!$C$7,"Vencida",IF(C32-Datos!$C$7<=7,"Paga esta semana","Al día")))
B33: Total del mes | D33: =SUM(D25:D32) -> 0
B35: 4. Plan de pago (hoja Plan de pago) | G35: Abono extra sugerido el próximo mes | I35: Valor
B36: Método | D36: ='Plan de pago'!$C$5 -> Avalancha | G36: =IF('Plan de pago'!$E$22=0,"",INDEX('Plan de pago'!$B$12:$B$19,'Plan de pago'!$E$22)) | I36: =IF(G36="","",'Plan de pago'!$G$28)
B37: Pago mensual total del plan | D37: ='Plan de pago'!$C$8 -> 0 | G37: =IF('Plan de pago'!$I$22=0,"",INDEX('Plan de pago'!$B$12:$B$19,'Plan de pago'!$I$22)) | I37: =IF(G37="","",'Plan de pago'!$K$28)
B38: Intereses y seguros solo con cuotas | D38: ='Plan de pago'!$O$20 -> 0 | G38: =IF('Plan de pago'!$M$22=0,"",INDEX('Plan de pago'!$B$12:$B$19,'Plan de pago'!$M$22)) | I38: =IF(G38="","",'Plan de pago'!$O$28)
B39: Intereses y seguros con el plan | D39: ='Plan de pago'!$P$20 -> 0 | G39: =IF('Plan de pago'!$Q$22=0,"",INDEX('Plan de pago'!$B$12:$B$19,'Plan de pago'!$Q$22)) | I39: =IF(G39="","",'Plan de pago'!$S$28)
B40: Ahorro con el plan | D40: ='Plan de pago'!$C$21 -> 0 | G40: =IF('Plan de pago'!$U$22=0,"",INDEX('Plan de pago'!$B$12:$B$19,'Plan de pago'!$U$22)) | I40: =IF(G40="","",'Plan de pago'!$W$28)
G41: =IF('Plan de pago'!$Y$22=0,"",INDEX('Plan de pago'!$B$12:$B$19,'Plan de pago'!$Y$22)) | I41: =IF(G41="","",'Plan de pago'!$AA$28)
G42: =IF('Plan de pago'!$AC$22=0,"",INDEX('Plan de pago'!$B$12:$B$19,'Plan de pago'!$AC$22)) | I42: =IF(G42="","",'Plan de pago'!$AE$28)
G43: =IF('Plan de pago'!$AG$22=0,"",INDEX('Plan de pago'!$B$12:$B$19,'Plan de pago'!$AG$22)) | I43: =IF(G43="","",'Plan de pago'!$AI$28)
G44: Si el valor es 0, este mes solo se pagan las cuotas normales.
B46: 5. Hitos: cuándo termina cada crédito y cuánto se libera (con las cuotas actuales)
B47: Crédito | C47: Termina | D47: Cuota que se libera | E47: Pago mensual después (cuotas completas) | F47: Años desde hoy | G47: Carga después
B48: =IF(IFERROR(MATCH(SMALL($N$60:$N$67,1),$N$60:$N$67,0),0)=0,"",INDEX($B$13:$B$20,IFERROR(MATCH(SMALL($N$60:$N$67,1),$N$60:$N$67,0),0))) | C48: =IF(B48="","",CHOOSE(IFERROR(MATCH(SMALL($N$60:$N$67,1),$N$60:$N$67,0),0),'Crédito 1'!$I$12,'Crédito 2'!$I$12,'Crédito 3'!$I$12,'Crédito 4'!$I$12,'Crédito 5'!$I$12,'Crédito 6'!$I$12,'Crédito 7'!$I$12,'Crédito 8'!$I$12)) | D48: =IF(B48="","",CHOOSE(IFERROR(MATCH(SMALL($N$60:$N$67,1),$N$60:$N$67,0),0),'Crédito 1'!$I$18,'Crédito 2'!$I$18,'Crédito 3'!$I$18,'Crédito 4'!$I$18,'Crédito 5'!$I$18,'Crédito 6'!$I$18,'Crédito 7'!$I$18,'Crédito 8'!$I$18)) | E48: =IF(B48="","",MAX(0,SUMIFS('Plan de pago'!$F$12:$F$19,'Plan de pago'!$C$12:$C$19,">0.5")-(D48))) | F48: =IF(B48="","",ROUND((C48-Datos!$C$7)/365.25,1)) | G48: =IF(OR(B48="",N(Datos!$F$16)=0),"",E48/Datos!$F$16)
B49: =IF(IFERROR(MATCH(SMALL($N$60:$N$67,2),$N$60:$N$67,0),0)=0,"",INDEX($B$13:$B$20,IFERROR(MATCH(SMALL($N$60:$N$67,2),$N$60:$N$67,0),0))) | C49: =IF(B49="","",CHOOSE(IFERROR(MATCH(SMALL($N$60:$N$67,2),$N$60:$N$67,0),0),'Crédito 1'!$I$12,'Crédito 2'!$I$12,'Crédito 3'!$I$12,'Crédito 4'!$I$12,'Crédito 5'!$I$12,'Crédito 6'!$I$12,'Crédito 7'!$I$12,'Crédito 8'!$I$12)) | D49: =IF(B49="","",CHOOSE(IFERROR(MATCH(SMALL($N$60:$N$67,2),$N$60:$N$67,0),0),'Crédito 1'!$I$18,'Crédito 2'!$I$18,'Crédito 3'!$I$18,'Crédito 4'!$I$18,'Crédito 5'!$I$18,'Crédito 6'!$I$18,'Crédito 7'!$I$18,'Crédito 8'!$I$18)) | E49: =IF(B49="","",MAX(0,SUMIFS('Plan de pago'!$F$12:$F$19,'Plan de pago'!$C$12:$C$19,">0.5")-(D48+D49))) | F49: =IF(B49="","",ROUND((C49-Datos!$C$7)/365.25,1)) | G49: =IF(OR(B49="",N(Datos!$F$16)=0),"",E49/Datos!$F$16)
B50: =IF(IFERROR(MATCH(SMALL($N$60:$N$67,3),$N$60:$N$67,0),0)=0,"",INDEX($B$13:$B$20,IFERROR(MATCH(SMALL($N$60:$N$67,3),$N$60:$N$67,0),0))) | C50: =IF(B50="","",CHOOSE(IFERROR(MATCH(SMALL($N$60:$N$67,3),$N$60:$N$67,0),0),'Crédito 1'!$I$12,'Crédito 2'!$I$12,'Crédito 3'!$I$12,'Crédito 4'!$I$12,'Crédito 5'!$I$12,'Crédito 6'!$I$12,'Crédito 7'!$I$12,'Crédito 8'!$I$12)) | D50: =IF(B50="","",CHOOSE(IFERROR(MATCH(SMALL($N$60:$N$67,3),$N$60:$N$67,0),0),'Crédito 1'!$I$18,'Crédito 2'!$I$18,'Crédito 3'!$I$18,'Crédito 4'!$I$18,'Crédito 5'!$I$18,'Crédito 6'!$I$18,'Crédito 7'!$I$18,'Crédito 8'!$I$18)) | E50: =IF(B50="","",MAX(0,SUMIFS('Plan de pago'!$F$12:$F$19,'Plan de pago'!$C$12:$C$19,">0.5")-(D48+D49+D50))) | F50: =IF(B50="","",ROUND((C50-Datos!$C$7)/365.25,1)) | G50: =IF(OR(B50="",N(Datos!$F$16)=0),"",E50/Datos!$F$16)
B51: =IF(IFERROR(MATCH(SMALL($N$60:$N$67,4),$N$60:$N$67,0),0)=0,"",INDEX($B$13:$B$20,IFERROR(MATCH(SMALL($N$60:$N$67,4),$N$60:$N$67,0),0))) | C51: =IF(B51="","",CHOOSE(IFERROR(MATCH(SMALL($N$60:$N$67,4),$N$60:$N$67,0),0),'Crédito 1'!$I$12,'Crédito 2'!$I$12,'Crédito 3'!$I$12,'Crédito 4'!$I$12,'Crédito 5'!$I$12,'Crédito 6'!$I$12,'Crédito 7'!$I$12,'Crédito 8'!$I$12)) | D51: =IF(B51="","",CHOOSE(IFERROR(MATCH(SMALL($N$60:$N$67,4),$N$60:$N$67,0),0),'Crédito 1'!$I$18,'Crédito 2'!$I$18,'Crédito 3'!$I$18,'Crédito 4'!$I$18,'Crédito 5'!$I$18,'Crédito 6'!$I$18,'Crédito 7'!$I$18,'Crédito 8'!$I$18)) | E51: =IF(B51="","",MAX(0,SUMIFS('Plan de pago'!$F$12:$F$19,'Plan de pago'!$C$12:$C$19,">0.5")-(D48+D49+D50+D51))) | F51: =IF(B51="","",ROUND((C51-Datos!$C$7)/365.25,1)) | G51: =IF(OR(B51="",N(Datos!$F$16)=0),"",E51/Datos!$F$16)
B52: =IF(IFERROR(MATCH(SMALL($N$60:$N$67,5),$N$60:$N$67,0),0)=0,"",INDEX($B$13:$B$20,IFERROR(MATCH(SMALL($N$60:$N$67,5),$N$60:$N$67,0),0))) | C52: =IF(B52="","",CHOOSE(IFERROR(MATCH(SMALL($N$60:$N$67,5),$N$60:$N$67,0),0),'Crédito 1'!$I$12,'Crédito 2'!$I$12,'Crédito 3'!$I$12,'Crédito 4'!$I$12,'Crédito 5'!$I$12,'Crédito 6'!$I$12,'Crédito 7'!$I$12,'Crédito 8'!$I$12)) | D52: =IF(B52="","",CHOOSE(IFERROR(MATCH(SMALL($N$60:$N$67,5),$N$60:$N$67,0),0),'Crédito 1'!$I$18,'Crédito 2'!$I$18,'Crédito 3'!$I$18,'Crédito 4'!$I$18,'Crédito 5'!$I$18,'Crédito 6'!$I$18,'Crédito 7'!$I$18,'Crédito 8'!$I$18)) | E52: =IF(B52="","",MAX(0,SUMIFS('Plan de pago'!$F$12:$F$19,'Plan de pago'!$C$12:$C$19,">0.5")-(D48+D49+D50+D51+D52))) | F52: =IF(B52="","",ROUND((C52-Datos!$C$7)/365.25,1)) | G52: =IF(OR(B52="",N(Datos!$F$16)=0),"",E52/Datos!$F$16)
B53: =IF(IFERROR(MATCH(SMALL($N$60:$N$67,6),$N$60:$N$67,0),0)=0,"",INDEX($B$13:$B$20,IFERROR(MATCH(SMALL($N$60:$N$67,6),$N$60:$N$67,0),0))) | C53: =IF(B53="","",CHOOSE(IFERROR(MATCH(SMALL($N$60:$N$67,6),$N$60:$N$67,0),0),'Crédito 1'!$I$12,'Crédito 2'!$I$12,'Crédito 3'!$I$12,'Crédito 4'!$I$12,'Crédito 5'!$I$12,'Crédito 6'!$I$12,'Crédito 7'!$I$12,'Crédito 8'!$I$12)) | D53: =IF(B53="","",CHOOSE(IFERROR(MATCH(SMALL($N$60:$N$67,6),$N$60:$N$67,0),0),'Crédito 1'!$I$18,'Crédito 2'!$I$18,'Crédito 3'!$I$18,'Crédito 4'!$I$18,'Crédito 5'!$I$18,'Crédito 6'!$I$18,'Crédito 7'!$I$18,'Crédito 8'!$I$18)) | E53: =IF(B53="","",MAX(0,SUMIFS('Plan de pago'!$F$12:$F$19,'Plan de pago'!$C$12:$C$19,">0.5")-(D48+D49+D50+D51+D52+D53))) | F53: =IF(B53="","",ROUND((C53-Datos!$C$7)/365.25,1)) | G53: =IF(OR(B53="",N(Datos!$F$16)=0),"",E53/Datos!$F$16)
B54: =IF(IFERROR(MATCH(SMALL($N$60:$N$67,7),$N$60:$N$67,0),0)=0,"",INDEX($B$13:$B$20,IFERROR(MATCH(SMALL($N$60:$N$67,7),$N$60:$N$67,0),0))) | C54: =IF(B54="","",CHOOSE(IFERROR(MATCH(SMALL($N$60:$N$67,7),$N$60:$N$67,0),0),'Crédito 1'!$I$12,'Crédito 2'!$I$12,'Crédito 3'!$I$12,'Crédito 4'!$I$12,'Crédito 5'!$I$12,'Crédito 6'!$I$12,'Crédito 7'!$I$12,'Crédito 8'!$I$12)) | D54: =IF(B54="","",CHOOSE(IFERROR(MATCH(SMALL($N$60:$N$67,7),$N$60:$N$67,0),0),'Crédito 1'!$I$18,'Crédito 2'!$I$18,'Crédito 3'!$I$18,'Crédito 4'!$I$18,'Crédito 5'!$I$18,'Crédito 6'!$I$18,'Crédito 7'!$I$18,'Crédito 8'!$I$18)) | E54: =IF(B54="","",MAX(0,SUMIFS('Plan de pago'!$F$12:$F$19,'Plan de pago'!$C$12:$C$19,">0.5")-(D48+D49+D50+D51+D52+D53+D54))) | F54: =IF(B54="","",ROUND((C54-Datos!$C$7)/365.25,1)) | G54: =IF(OR(B54="",N(Datos!$F$16)=0),"",E54/Datos!$F$16)
B55: =IF(IFERROR(MATCH(SMALL($N$60:$N$67,8),$N$60:$N$67,0),0)=0,"",INDEX($B$13:$B$20,IFERROR(MATCH(SMALL($N$60:$N$67,8),$N$60:$N$67,0),0))) | C55: =IF(B55="","",CHOOSE(IFERROR(MATCH(SMALL($N$60:$N$67,8),$N$60:$N$67,0),0),'Crédito 1'!$I$12,'Crédito 2'!$I$12,'Crédito 3'!$I$12,'Crédito 4'!$I$12,'Crédito 5'!$I$12,'Crédito 6'!$I$12,'Crédito 7'!$I$12,'Crédito 8'!$I$12)) | D55: =IF(B55="","",CHOOSE(IFERROR(MATCH(SMALL($N$60:$N$67,8),$N$60:$N$67,0),0),'Crédito 1'!$I$18,'Crédito 2'!$I$18,'Crédito 3'!$I$18,'Crédito 4'!$I$18,'Crédito 5'!$I$18,'Crédito 6'!$I$18,'Crédito 7'!$I$18,'Crédito 8'!$I$18)) | E55: =IF(B55="","",MAX(0,SUMIFS('Plan de pago'!$F$12:$F$19,'Plan de pago'!$C$12:$C$19,">0.5")-(D48+D49+D50+D51+D52+D53+D54+D55))) | F55: =IF(B55="","",ROUND((C55-Datos!$C$7)/365.25,1)) | G55: =IF(OR(B55="",N(Datos!$F$16)=0),"",E55/Datos!$F$16)
B58: 6. Deuda año por año
B59: Año | C59: Deuda al cierre con el plan | D59: Deuda al cierre solo con cuotas | E59: Pagos del año con el plan | F59: Carga promedio
B60: =YEAR('Plan de pago'!$C$7)+0 -> 2026 | C60: =IFERROR(INDEX('Plan de pago'!$AS$28:$AS$387,MATCH(DATE(B60,12,1),'Plan de pago'!$C$28:$C$387,0)),0) -> 0 | D60: =IFERROR(INDEX('Plan de pago'!$AT$28:$AT$387,MATCH(DATE(B60,12,1),'Plan de pago'!$C$28:$C$387,0)),0) -> 0 | E60: =SUMIFS('Plan de pago'!$AU$28:$AU$387,'Plan de pago'!$C$28:$C$387,">="&DATE(B60,1,1),'Plan de pago'!$C$28:$C$387,"<="&DATE(B60,12,1)) -> 0 | F60: =IF(OR(N(Datos!$F$16)=0,E60=0),"",E60/COUNTIFS('Plan de pago'!$C$28:$C$387,">="&DATE(B60,1,1),'Plan de pago'!$C$28:$C$387,"<="&DATE(B60,12,1))/Datos!$F$16) | N60: =IF(ISNUMBER('Crédito 1'!$I$12),'Crédito 1'!$I$12+1/100,"")
B61: =YEAR('Plan de pago'!$C$7)+1 -> 2027 | C61: =IFERROR(INDEX('Plan de pago'!$AS$28:$AS$387,MATCH(DATE(B61,12,1),'Plan de pago'!$C$28:$C$387,0)),0) -> 0 | D61: =IFERROR(INDEX('Plan de pago'!$AT$28:$AT$387,MATCH(DATE(B61,12,1),'Plan de pago'!$C$28:$C$387,0)),0) -> 0 | E61: =SUMIFS('Plan de pago'!$AU$28:$AU$387,'Plan de pago'!$C$28:$C$387,">="&DATE(B61,1,1),'Plan de pago'!$C$28:$C$387,"<="&DATE(B61,12,1)) -> 0 | F61: =IF(OR(N(Datos!$F$16)=0,E61=0),"",E61/COUNTIFS('Plan de pago'!$C$28:$C$387,">="&DATE(B61,1,1),'Plan de pago'!$C$28:$C$387,"<="&DATE(B61,12,1))/Datos!$F$16) | N61: =IF(ISNUMBER('Crédito 2'!$I$12),'Crédito 2'!$I$12+2/100,"")
B62: =YEAR('Plan de pago'!$C$7)+2 -> 2028 | C62: =IFERROR(INDEX('Plan de pago'!$AS$28:$AS$387,MATCH(DATE(B62,12,1),'Plan de pago'!$C$28:$C$387,0)),0) -> 0 | D62: =IFERROR(INDEX('Plan de pago'!$AT$28:$AT$387,MATCH(DATE(B62,12,1),'Plan de pago'!$C$28:$C$387,0)),0) -> 0 | E62: =SUMIFS('Plan de pago'!$AU$28:$AU$387,'Plan de pago'!$C$28:$C$387,">="&DATE(B62,1,1),'Plan de pago'!$C$28:$C$387,"<="&DATE(B62,12,1)) -> 0 | F62: =IF(OR(N(Datos!$F$16)=0,E62=0),"",E62/COUNTIFS('Plan de pago'!$C$28:$C$387,">="&DATE(B62,1,1),'Plan de pago'!$C$28:$C$387,"<="&DATE(B62,12,1))/Datos!$F$16) | N62: =IF(ISNUMBER('Crédito 3'!$I$12),'Crédito 3'!$I$12+3/100,"")
B63: =YEAR('Plan de pago'!$C$7)+3 -> 2029 | C63: =IFERROR(INDEX('Plan de pago'!$AS$28:$AS$387,MATCH(DATE(B63,12,1),'Plan de pago'!$C$28:$C$387,0)),0) -> 0 | D63: =IFERROR(INDEX('Plan de pago'!$AT$28:$AT$387,MATCH(DATE(B63,12,1),'Plan de pago'!$C$28:$C$387,0)),0) -> 0 | E63: =SUMIFS('Plan de pago'!$AU$28:$AU$387,'Plan de pago'!$C$28:$C$387,">="&DATE(B63,1,1),'Plan de pago'!$C$28:$C$387,"<="&DATE(B63,12,1)) -> 0 | F63: =IF(OR(N(Datos!$F$16)=0,E63=0),"",E63/COUNTIFS('Plan de pago'!$C$28:$C$387,">="&DATE(B63,1,1),'Plan de pago'!$C$28:$C$387,"<="&DATE(B63,12,1))/Datos!$F$16) | N63: =IF(ISNUMBER('Crédito 4'!$I$12),'Crédito 4'!$I$12+4/100,"")
B64: =YEAR('Plan de pago'!$C$7)+4 -> 2030 | C64: =IFERROR(INDEX('Plan de pago'!$AS$28:$AS$387,MATCH(DATE(B64,12,1),'Plan de pago'!$C$28:$C$387,0)),0) -> 0 | D64: =IFERROR(INDEX('Plan de pago'!$AT$28:$AT$387,MATCH(DATE(B64,12,1),'Plan de pago'!$C$28:$C$387,0)),0) -> 0 | E64: =SUMIFS('Plan de pago'!$AU$28:$AU$387,'Plan de pago'!$C$28:$C$387,">="&DATE(B64,1,1),'Plan de pago'!$C$28:$C$387,"<="&DATE(B64,12,1)) -> 0 | F64: =IF(OR(N(Datos!$F$16)=0,E64=0),"",E64/COUNTIFS('Plan de pago'!$C$28:$C$387,">="&DATE(B64,1,1),'Plan de pago'!$C$28:$C$387,"<="&DATE(B64,12,1))/Datos!$F$16) | N64: =IF(ISNUMBER('Crédito 5'!$I$12),'Crédito 5'!$I$12+5/100,"")
B65: =YEAR('Plan de pago'!$C$7)+5 -> 2031 | C65: =IFERROR(INDEX('Plan de pago'!$AS$28:$AS$387,MATCH(DATE(B65,12,1),'Plan de pago'!$C$28:$C$387,0)),0) -> 0 | D65: =IFERROR(INDEX('Plan de pago'!$AT$28:$AT$387,MATCH(DATE(B65,12,1),'Plan de pago'!$C$28:$C$387,0)),0) -> 0 | E65: =SUMIFS('Plan de pago'!$AU$28:$AU$387,'Plan de pago'!$C$28:$C$387,">="&DATE(B65,1,1),'Plan de pago'!$C$28:$C$387,"<="&DATE(B65,12,1)) -> 0 | F65: =IF(OR(N(Datos!$F$16)=0,E65=0),"",E65/COUNTIFS('Plan de pago'!$C$28:$C$387,">="&DATE(B65,1,1),'Plan de pago'!$C$28:$C$387,"<="&DATE(B65,12,1))/Datos!$F$16) | N65: =IF(ISNUMBER('Crédito 6'!$I$12),'Crédito 6'!$I$12+6/100,"")
B66: =YEAR('Plan de pago'!$C$7)+6 -> 2032 | C66: =IFERROR(INDEX('Plan de pago'!$AS$28:$AS$387,MATCH(DATE(B66,12,1),'Plan de pago'!$C$28:$C$387,0)),0) -> 0 | D66: =IFERROR(INDEX('Plan de pago'!$AT$28:$AT$387,MATCH(DATE(B66,12,1),'Plan de pago'!$C$28:$C$387,0)),0) -> 0 | E66: =SUMIFS('Plan de pago'!$AU$28:$AU$387,'Plan de pago'!$C$28:$C$387,">="&DATE(B66,1,1),'Plan de pago'!$C$28:$C$387,"<="&DATE(B66,12,1)) -> 0 | F66: =IF(OR(N(Datos!$F$16)=0,E66=0),"",E66/COUNTIFS('Plan de pago'!$C$28:$C$387,">="&DATE(B66,1,1),'Plan de pago'!$C$28:$C$387,"<="&DATE(B66,12,1))/Datos!$F$16) | N66: =IF(ISNUMBER('Crédito 7'!$I$12),'Crédito 7'!$I$12+7/100,"")
B67: =YEAR('Plan de pago'!$C$7)+7 -> 2033 | C67: =IFERROR(INDEX('Plan de pago'!$AS$28:$AS$387,MATCH(DATE(B67,12,1),'Plan de pago'!$C$28:$C$387,0)),0) -> 0 | D67: =IFERROR(INDEX('Plan de pago'!$AT$28:$AT$387,MATCH(DATE(B67,12,1),'Plan de pago'!$C$28:$C$387,0)),0) -> 0 | E67: =SUMIFS('Plan de pago'!$AU$28:$AU$387,'Plan de pago'!$C$28:$C$387,">="&DATE(B67,1,1),'Plan de pago'!$C$28:$C$387,"<="&DATE(B67,12,1)) -> 0 | F67: =IF(OR(N(Datos!$F$16)=0,E67=0),"",E67/COUNTIFS('Plan de pago'!$C$28:$C$387,">="&DATE(B67,1,1),'Plan de pago'!$C$28:$C$387,"<="&DATE(B67,12,1))/Datos!$F$16) | N67: =IF(ISNUMBER('Crédito 8'!$I$12),'Crédito 8'!$I$12+8/100,"")
B68: =YEAR('Plan de pago'!$C$7)+8 -> 2034 | C68: =IFERROR(INDEX('Plan de pago'!$AS$28:$AS$387,MATCH(DATE(B68,12,1),'Plan de pago'!$C$28:$C$387,0)),0) -> 0 | D68: =IFERROR(INDEX('Plan de pago'!$AT$28:$AT$387,MATCH(DATE(B68,12,1),'Plan de pago'!$C$28:$C$387,0)),0) -> 0 | E68: =SUMIFS('Plan de pago'!$AU$28:$AU$387,'Plan de pago'!$C$28:$C$387,">="&DATE(B68,1,1),'Plan de pago'!$C$28:$C$387,"<="&DATE(B68,12,1)) -> 0 | F68: =IF(OR(N(Datos!$F$16)=0,E68=0),"",E68/COUNTIFS('Plan de pago'!$C$28:$C$387,">="&DATE(B68,1,1),'Plan de pago'!$C$28:$C$387,"<="&DATE(B68,12,1))/Datos!$F$16)
B69: =YEAR('Plan de pago'!$C$7)+9 -> 2035 | C69: =IFERROR(INDEX('Plan de pago'!$AS$28:$AS$387,MATCH(DATE(B69,12,1),'Plan de pago'!$C$28:$C$387,0)),0) -> 0 | D69: =IFERROR(INDEX('Plan de pago'!$AT$28:$AT$387,MATCH(DATE(B69,12,1),'Plan de pago'!$C$28:$C$387,0)),0) -> 0 | E69: =SUMIFS('Plan de pago'!$AU$28:$AU$387,'Plan de pago'!$C$28:$C$387,">="&DATE(B69,1,1),'Plan de pago'!$C$28:$C$387,"<="&DATE(B69,12,1)) -> 0 | F69: =IF(OR(N(Datos!$F$16)=0,E69=0),"",E69/COUNTIFS('Plan de pago'!$C$28:$C$387,">="&DATE(B69,1,1),'Plan de pago'!$C$28:$C$387,"<="&DATE(B69,12,1))/Datos!$F$16)
B70: =YEAR('Plan de pago'!$C$7)+10 -> 2036 | C70: =IFERROR(INDEX('Plan de pago'!$AS$28:$AS$387,MATCH(DATE(B70,12,1),'Plan de pago'!$C$28:$C$387,0)),0) -> 0 | D70: =IFERROR(INDEX('Plan de pago'!$AT$28:$AT$387,MATCH(DATE(B70,12,1),'Plan de pago'!$C$28:$C$387,0)),0) -> 0 | E70: =SUMIFS('Plan de pago'!$AU$28:$AU$387,'Plan de pago'!$C$28:$C$387,">="&DATE(B70,1,1),'Plan de pago'!$C$28:$C$387,"<="&DATE(B70,12,1)) -> 0 | F70: =IF(OR(N(Datos!$F$16)=0,E70=0),"",E70/COUNTIFS('Plan de pago'!$C$28:$C$387,">="&DATE(B70,1,1),'Plan de pago'!$C$28:$C$387,"<="&DATE(B70,12,1))/Datos!$F$16)
B71: =YEAR('Plan de pago'!$C$7)+11 -> 2037 | C71: =IFERROR(INDEX('Plan de pago'!$AS$28:$AS$387,MATCH(DATE(B71,12,1),'Plan de pago'!$C$28:$C$387,0)),0) -> 0 | D71: =IFERROR(INDEX('Plan de pago'!$AT$28:$AT$387,MATCH(DATE(B71,12,1),'Plan de pago'!$C$28:$C$387,0)),0) -> 0 | E71: =SUMIFS('Plan de pago'!$AU$28:$AU$387,'Plan de pago'!$C$28:$C$387,">="&DATE(B71,1,1),'Plan de pago'!$C$28:$C$387,"<="&DATE(B71,12,1)) -> 0 | F71: =IF(OR(N(Datos!$F$16)=0,E71=0),"",E71/COUNTIFS('Plan de pago'!$C$28:$C$387,">="&DATE(B71,1,1),'Plan de pago'!$C$28:$C$387,"<="&DATE(B71,12,1))/Datos!$F$16)
B72: =YEAR('Plan de pago'!$C$7)+12 -> 2038 | C72: =IFERROR(INDEX('Plan de pago'!$AS$28:$AS$387,MATCH(DATE(B72,12,1),'Plan de pago'!$C$28:$C$387,0)),0) -> 0 | D72: =IFERROR(INDEX('Plan de pago'!$AT$28:$AT$387,MATCH(DATE(B72,12,1),'Plan de pago'!$C$28:$C$387,0)),0) -> 0 | E72: =SUMIFS('Plan de pago'!$AU$28:$AU$387,'Plan de pago'!$C$28:$C$387,">="&DATE(B72,1,1),'Plan de pago'!$C$28:$C$387,"<="&DATE(B72,12,1)) -> 0 | F72: =IF(OR(N(Datos!$F$16)=0,E72=0),"",E72/COUNTIFS('Plan de pago'!$C$28:$C$387,">="&DATE(B72,1,1),'Plan de pago'!$C$28:$C$387,"<="&DATE(B72,12,1))/Datos!$F$16)
B73: =YEAR('Plan de pago'!$C$7)+13 -> 2039 | C73: =IFERROR(INDEX('Plan de pago'!$AS$28:$AS$387,MATCH(DATE(B73,12,1),'Plan de pago'!$C$28:$C$387,0)),0) -> 0 | D73: =IFERROR(INDEX('Plan de pago'!$AT$28:$AT$387,MATCH(DATE(B73,12,1),'Plan de pago'!$C$28:$C$387,0)),0) -> 0 | E73: =SUMIFS('Plan de pago'!$AU$28:$AU$387,'Plan de pago'!$C$28:$C$387,">="&DATE(B73,1,1),'Plan de pago'!$C$28:$C$387,"<="&DATE(B73,12,1)) -> 0 | F73: =IF(OR(N(Datos!$F$16)=0,E73=0),"",E73/COUNTIFS('Plan de pago'!$C$28:$C$387,">="&DATE(B73,1,1),'Plan de pago'!$C$28:$C$387,"<="&DATE(B73,12,1))/Datos!$F$16)
B74: =YEAR('Plan de pago'!$C$7)+14 -> 2040 | C74: =IFERROR(INDEX('Plan de pago'!$AS$28:$AS$387,MATCH(DATE(B74,12,1),'Plan de pago'!$C$28:$C$387,0)),0) -> 0 | D74: =IFERROR(INDEX('Plan de pago'!$AT$28:$AT$387,MATCH(DATE(B74,12,1),'Plan de pago'!$C$28:$C$387,0)),0) -> 0 | E74: =SUMIFS('Plan de pago'!$AU$28:$AU$387,'Plan de pago'!$C$28:$C$387,">="&DATE(B74,1,1),'Plan de pago'!$C$28:$C$387,"<="&DATE(B74,12,1)) -> 0 | F74: =IF(OR(N(Datos!$F$16)=0,E74=0),"",E74/COUNTIFS('Plan de pago'!$C$28:$C$387,">="&DATE(B74,1,1),'Plan de pago'!$C$28:$C$387,"<="&DATE(B74,12,1))/Datos!$F$16)
B75: =YEAR('Plan de pago'!$C$7)+15 -> 2041 | C75: =IFERROR(INDEX('Plan de pago'!$AS$28:$AS$387,MATCH(DATE(B75,12,1),'Plan de pago'!$C$28:$C$387,0)),0) -> 0 | D75: =IFERROR(INDEX('Plan de pago'!$AT$28:$AT$387,MATCH(DATE(B75,12,1),'Plan de pago'!$C$28:$C$387,0)),0) -> 0 | E75: =SUMIFS('Plan de pago'!$AU$28:$AU$387,'Plan de pago'!$C$28:$C$387,">="&DATE(B75,1,1),'Plan de pago'!$C$28:$C$387,"<="&DATE(B75,12,1)) -> 0 | F75: =IF(OR(N(Datos!$F$16)=0,E75=0),"",E75/COUNTIFS('Plan de pago'!$C$28:$C$387,">="&DATE(B75,1,1),'Plan de pago'!$C$28:$C$387,"<="&DATE(B75,12,1))/Datos!$F$16)
B76: =YEAR('Plan de pago'!$C$7)+16 -> 2042 | C76: =IFERROR(INDEX('Plan de pago'!$AS$28:$AS$387,MATCH(DATE(B76,12,1),'Plan de pago'!$C$28:$C$387,0)),0) -> 0 | D76: =IFERROR(INDEX('Plan de pago'!$AT$28:$AT$387,MATCH(DATE(B76,12,1),'Plan de pago'!$C$28:$C$387,0)),0) -> 0 | E76: =SUMIFS('Plan de pago'!$AU$28:$AU$387,'Plan de pago'!$C$28:$C$387,">="&DATE(B76,1,1),'Plan de pago'!$C$28:$C$387,"<="&DATE(B76,12,1)) -> 0 | F76: =IF(OR(N(Datos!$F$16)=0,E76=0),"",E76/COUNTIFS('Plan de pago'!$C$28:$C$387,">="&DATE(B76,1,1),'Plan de pago'!$C$28:$C$387,"<="&DATE(B76,12,1))/Datos!$F$16)
B77: =YEAR('Plan de pago'!$C$7)+17 -> 2043 | C77: =IFERROR(INDEX('Plan de pago'!$AS$28:$AS$387,MATCH(DATE(B77,12,1),'Plan de pago'!$C$28:$C$387,0)),0) -> 0 | D77: =IFERROR(INDEX('Plan de pago'!$AT$28:$AT$387,MATCH(DATE(B77,12,1),'Plan de pago'!$C$28:$C$387,0)),0) -> 0 | E77: =SUMIFS('Plan de pago'!$AU$28:$AU$387,'Plan de pago'!$C$28:$C$387,">="&DATE(B77,1,1),'Plan de pago'!$C$28:$C$387,"<="&DATE(B77,12,1)) -> 0 | F77: =IF(OR(N(Datos!$F$16)=0,E77=0),"",E77/COUNTIFS('Plan de pago'!$C$28:$C$387,">="&DATE(B77,1,1),'Plan de pago'!$C$28:$C$387,"<="&DATE(B77,12,1))/Datos!$F$16)
B78: =YEAR('Plan de pago'!$C$7)+18 -> 2044 | C78: =IFERROR(INDEX('Plan de pago'!$AS$28:$AS$387,MATCH(DATE(B78,12,1),'Plan de pago'!$C$28:$C$387,0)),0) -> 0 | D78: =IFERROR(INDEX('Plan de pago'!$AT$28:$AT$387,MATCH(DATE(B78,12,1),'Plan de pago'!$C$28:$C$387,0)),0) -> 0 | E78: =SUMIFS('Plan de pago'!$AU$28:$AU$387,'Plan de pago'!$C$28:$C$387,">="&DATE(B78,1,1),'Plan de pago'!$C$28:$C$387,"<="&DATE(B78,12,1)) -> 0 | F78: =IF(OR(N(Datos!$F$16)=0,E78=0),"",E78/COUNTIFS('Plan de pago'!$C$28:$C$387,">="&DATE(B78,1,1),'Plan de pago'!$C$28:$C$387,"<="&DATE(B78,12,1))/Datos!$F$16)
B79: =YEAR('Plan de pago'!$C$7)+19 -> 2045 | C79: =IFERROR(INDEX('Plan de pago'!$AS$28:$AS$387,MATCH(DATE(B79,12,1),'Plan de pago'!$C$28:$C$387,0)),0) -> 0 | D79: =IFERROR(INDEX('Plan de pago'!$AT$28:$AT$387,MATCH(DATE(B79,12,1),'Plan de pago'!$C$28:$C$387,0)),0) -> 0 | E79: =SUMIFS('Plan de pago'!$AU$28:$AU$387,'Plan de pago'!$C$28:$C$387,">="&DATE(B79,1,1),'Plan de pago'!$C$28:$C$387,"<="&DATE(B79,12,1)) -> 0 | F79: =IF(OR(N(Datos!$F$16)=0,E79=0),"",E79/COUNTIFS('Plan de pago'!$C$28:$C$387,">="&DATE(B79,1,1),'Plan de pago'!$C$28:$C$387,"<="&DATE(B79,12,1))/Datos!$F$16)
B80: =YEAR('Plan de pago'!$C$7)+20 -> 2046 | C80: =IFERROR(INDEX('Plan de pago'!$AS$28:$AS$387,MATCH(DATE(B80,12,1),'Plan de pago'!$C$28:$C$387,0)),0) -> 0 | D80: =IFERROR(INDEX('Plan de pago'!$AT$28:$AT$387,MATCH(DATE(B80,12,1),'Plan de pago'!$C$28:$C$387,0)),0) -> 0 | E80: =SUMIFS('Plan de pago'!$AU$28:$AU$387,'Plan de pago'!$C$28:$C$387,">="&DATE(B80,1,1),'Plan de pago'!$C$28:$C$387,"<="&DATE(B80,12,1)) -> 0 | F80: =IF(OR(N(Datos!$F$16)=0,E80=0),"",E80/COUNTIFS('Plan de pago'!$C$28:$C$387,">="&DATE(B80,1,1),'Plan de pago'!$C$28:$C$387,"<="&DATE(B80,12,1))/Datos!$F$16)
B81: =YEAR('Plan de pago'!$C$7)+21 -> 2047 | C81: =IFERROR(INDEX('Plan de pago'!$AS$28:$AS$387,MATCH(DATE(B81,12,1),'Plan de pago'!$C$28:$C$387,0)),0) -> 0 | D81: =IFERROR(INDEX('Plan de pago'!$AT$28:$AT$387,MATCH(DATE(B81,12,1),'Plan de pago'!$C$28:$C$387,0)),0) -> 0 | E81: =SUMIFS('Plan de pago'!$AU$28:$AU$387,'Plan de pago'!$C$28:$C$387,">="&DATE(B81,1,1),'Plan de pago'!$C$28:$C$387,"<="&DATE(B81,12,1)) -> 0 | F81: =IF(OR(N(Datos!$F$16)=0,E81=0),"",E81/COUNTIFS('Plan de pago'!$C$28:$C$387,">="&DATE(B81,1,1),'Plan de pago'!$C$28:$C$387,"<="&DATE(B81,12,1))/Datos!$F$16)
B82: =YEAR('Plan de pago'!$C$7)+22 -> 2048 | C82: =IFERROR(INDEX('Plan de pago'!$AS$28:$AS$387,MATCH(DATE(B82,12,1),'Plan de pago'!$C$28:$C$387,0)),0) -> 0 | D82: =IFERROR(INDEX('Plan de pago'!$AT$28:$AT$387,MATCH(DATE(B82,12,1),'Plan de pago'!$C$28:$C$387,0)),0) -> 0 | E82: =SUMIFS('Plan de pago'!$AU$28:$AU$387,'Plan de pago'!$C$28:$C$387,">="&DATE(B82,1,1),'Plan de pago'!$C$28:$C$387,"<="&DATE(B82,12,1)) -> 0 | F82: =IF(OR(N(Datos!$F$16)=0,E82=0),"",E82/COUNTIFS('Plan de pago'!$C$28:$C$387,">="&DATE(B82,1,1),'Plan de pago'!$C$28:$C$387,"<="&DATE(B82,12,1))/Datos!$F$16)
B83: =YEAR('Plan de pago'!$C$7)+23 -> 2049 | C83: =IFERROR(INDEX('Plan de pago'!$AS$28:$AS$387,MATCH(DATE(B83,12,1),'Plan de pago'!$C$28:$C$387,0)),0) -> 0 | D83: =IFERROR(INDEX('Plan de pago'!$AT$28:$AT$387,MATCH(DATE(B83,12,1),'Plan de pago'!$C$28:$C$387,0)),0) -> 0 | E83: =SUMIFS('Plan de pago'!$AU$28:$AU$387,'Plan de pago'!$C$28:$C$387,">="&DATE(B83,1,1),'Plan de pago'!$C$28:$C$387,"<="&DATE(B83,12,1)) -> 0 | F83: =IF(OR(N(Datos!$F$16)=0,E83=0),"",E83/COUNTIFS('Plan de pago'!$C$28:$C$387,">="&DATE(B83,1,1),'Plan de pago'!$C$28:$C$387,"<="&DATE(B83,12,1))/Datos!$F$16)
B84: =YEAR('Plan de pago'!$C$7)+24 -> 2050 | C84: =IFERROR(INDEX('Plan de pago'!$AS$28:$AS$387,MATCH(DATE(B84,12,1),'Plan de pago'!$C$28:$C$387,0)),0) -> 0 | D84: =IFERROR(INDEX('Plan de pago'!$AT$28:$AT$387,MATCH(DATE(B84,12,1),'Plan de pago'!$C$28:$C$387,0)),0) -> 0 | E84: =SUMIFS('Plan de pago'!$AU$28:$AU$387,'Plan de pago'!$C$28:$C$387,">="&DATE(B84,1,1),'Plan de pago'!$C$28:$C$387,"<="&DATE(B84,12,1)) -> 0 | F84: =IF(OR(N(Datos!$F$16)=0,E84=0),"",E84/COUNTIFS('Plan de pago'!$C$28:$C$387,">="&DATE(B84,1,1),'Plan de pago'!$C$28:$C$387,"<="&DATE(B84,12,1))/Datos!$F$16)
B85: =YEAR('Plan de pago'!$C$7)+25 -> 2051 | C85: =IFERROR(INDEX('Plan de pago'!$AS$28:$AS$387,MATCH(DATE(B85,12,1),'Plan de pago'!$C$28:$C$387,0)),0) -> 0 | D85: =IFERROR(INDEX('Plan de pago'!$AT$28:$AT$387,MATCH(DATE(B85,12,1),'Plan de pago'!$C$28:$C$387,0)),0) -> 0 | E85: =SUMIFS('Plan de pago'!$AU$28:$AU$387,'Plan de pago'!$C$28:$C$387,">="&DATE(B85,1,1),'Plan de pago'!$C$28:$C$387,"<="&DATE(B85,12,1)) -> 0 | F85: =IF(OR(N(Datos!$F$16)=0,E85=0),"",E85/COUNTIFS('Plan de pago'!$C$28:$C$387,">="&DATE(B85,1,1),'Plan de pago'!$C$28:$C$387,"<="&DATE(B85,12,1))/Datos!$F$16)
B86: =YEAR('Plan de pago'!$C$7)+26 -> 2052 | C86: =IFERROR(INDEX('Plan de pago'!$AS$28:$AS$387,MATCH(DATE(B86,12,1),'Plan de pago'!$C$28:$C$387,0)),0) -> 0 | D86: =IFERROR(INDEX('Plan de pago'!$AT$28:$AT$387,MATCH(DATE(B86,12,1),'Plan de pago'!$C$28:$C$387,0)),0) -> 0 | E86: =SUMIFS('Plan de pago'!$AU$28:$AU$387,'Plan de pago'!$C$28:$C$387,">="&DATE(B86,1,1),'Plan de pago'!$C$28:$C$387,"<="&DATE(B86,12,1)) -> 0 | F86: =IF(OR(N(Datos!$F$16)=0,E86=0),"",E86/COUNTIFS('Plan de pago'!$C$28:$C$387,">="&DATE(B86,1,1),'Plan de pago'!$C$28:$C$387,"<="&DATE(B86,12,1))/Datos!$F$16)
B87: =YEAR('Plan de pago'!$C$7)+27 -> 2053 | C87: =IFERROR(INDEX('Plan de pago'!$AS$28:$AS$387,MATCH(DATE(B87,12,1),'Plan de pago'!$C$28:$C$387,0)),0) -> 0 | D87: =IFERROR(INDEX('Plan de pago'!$AT$28:$AT$387,MATCH(DATE(B87,12,1),'Plan de pago'!$C$28:$C$387,0)),0) -> 0 | E87: =SUMIFS('Plan de pago'!$AU$28:$AU$387,'Plan de pago'!$C$28:$C$387,">="&DATE(B87,1,1),'Plan de pago'!$C$28:$C$387,"<="&DATE(B87,12,1)) -> 0 | F87: =IF(OR(N(Datos!$F$16)=0,E87=0),"",E87/COUNTIFS('Plan de pago'!$C$28:$C$387,">="&DATE(B87,1,1),'Plan de pago'!$C$28:$C$387,"<="&DATE(B87,12,1))/Datos!$F$16)
B88: =YEAR('Plan de pago'!$C$7)+28 -> 2054 | C88: =IFERROR(INDEX('Plan de pago'!$AS$28:$AS$387,MATCH(DATE(B88,12,1),'Plan de pago'!$C$28:$C$387,0)),0) -> 0 | D88: =IFERROR(INDEX('Plan de pago'!$AT$28:$AT$387,MATCH(DATE(B88,12,1),'Plan de pago'!$C$28:$C$387,0)),0) -> 0 | E88: =SUMIFS('Plan de pago'!$AU$28:$AU$387,'Plan de pago'!$C$28:$C$387,">="&DATE(B88,1,1),'Plan de pago'!$C$28:$C$387,"<="&DATE(B88,12,1)) -> 0 | F88: =IF(OR(N(Datos!$F$16)=0,E88=0),"",E88/COUNTIFS('Plan de pago'!$C$28:$C$387,">="&DATE(B88,1,1),'Plan de pago'!$C$28:$C$387,"<="&DATE(B88,12,1))/Datos!$F$16)
B89: =YEAR('Plan de pago'!$C$7)+29 -> 2055 | C89: =IFERROR(INDEX('Plan de pago'!$AS$28:$AS$387,MATCH(DATE(B89,12,1),'Plan de pago'!$C$28:$C$387,0)),0) -> 0 | D89: =IFERROR(INDEX('Plan de pago'!$AT$28:$AT$387,MATCH(DATE(B89,12,1),'Plan de pago'!$C$28:$C$387,0)),0) -> 0 | E89: =SUMIFS('Plan de pago'!$AU$28:$AU$387,'Plan de pago'!$C$28:$C$387,">="&DATE(B89,1,1),'Plan de pago'!$C$28:$C$387,"<="&DATE(B89,12,1)) -> 0 | F89: =IF(OR(N(Datos!$F$16)=0,E89=0),"",E89/COUNTIFS('Plan de pago'!$C$28:$C$387,">="&DATE(B89,1,1),'Plan de pago'!$C$28:$C$387,"<="&DATE(B89,12,1))/Datos!$F$16)
B90: =YEAR('Plan de pago'!$C$7)+30 -> 2056 | C90: =IFERROR(INDEX('Plan de pago'!$AS$28:$AS$387,MATCH(DATE(B90,12,1),'Plan de pago'!$C$28:$C$387,0)),0) -> 0 | D90: =IFERROR(INDEX('Plan de pago'!$AT$28:$AT$387,MATCH(DATE(B90,12,1),'Plan de pago'!$C$28:$C$387,0)),0) -> 0 | E90: =SUMIFS('Plan de pago'!$AU$28:$AU$387,'Plan de pago'!$C$28:$C$387,">="&DATE(B90,1,1),'Plan de pago'!$C$28:$C$387,"<="&DATE(B90,12,1)) -> 0 | F90: =IF(OR(N(Datos!$F$16)=0,E90=0),"",E90/COUNTIFS('Plan de pago'!$C$28:$C$387,">="&DATE(B90,1,1),'Plan de pago'!$C$28:$C$387,"<="&DATE(B90,12,1))/Datos!$F$16)
B93: 7. Para la plantilla de asesoría (copiar y pegar como valores en la hoja Deudas, desde la columna B)
B94: Deuda | C94: Tipo | D94: Saldo | E94: Tasa EA | F94: Cuota mínima mensual | G94: ¿Acepta abonos extra? | H94: Abonos extra desde
B95: =IF('Crédito 1'!$F$6="Sí",'Crédito 1'!$C$6,"") | C95: =IF(B95="","",'Crédito 1'!$C$8) | D95: =IF(B95="","",'Crédito 1'!$I$6) | E95: =IF(B95="","",'Crédito 1'!$C$13) | F95: =IF(OR(B95="",'Crédito 1'!$F$13=0),"",INDEX('Crédito 1'!$H$27:$H$386,'Crédito 1'!$F$13)-INDEX('Crédito 1'!$G$27:$G$386,'Crédito 1'!$F$13)) | G95: =IF(B95="","",IF('Crédito 1'!$C$17="No","No","Sí")) | H95: =IF(B95="","",'Crédito 1'!$F$11)
B96: =IF('Crédito 2'!$F$6="Sí",'Crédito 2'!$C$6,"") | C96: =IF(B96="","",'Crédito 2'!$C$8) | D96: =IF(B96="","",'Crédito 2'!$I$6) | E96: =IF(B96="","",'Crédito 2'!$C$13) | F96: =IF(OR(B96="",'Crédito 2'!$F$13=0),"",INDEX('Crédito 2'!$H$27:$H$386,'Crédito 2'!$F$13)-INDEX('Crédito 2'!$G$27:$G$386,'Crédito 2'!$F$13)) | G96: =IF(B96="","",IF('Crédito 2'!$C$17="No","No","Sí")) | H96: =IF(B96="","",'Crédito 2'!$F$11)
B97: =IF('Crédito 3'!$F$6="Sí",'Crédito 3'!$C$6,"") | C97: =IF(B97="","",'Crédito 3'!$C$8) | D97: =IF(B97="","",'Crédito 3'!$I$6) | E97: =IF(B97="","",'Crédito 3'!$C$13) | F97: =IF(OR(B97="",'Crédito 3'!$F$13=0),"",INDEX('Crédito 3'!$H$27:$H$386,'Crédito 3'!$F$13)-INDEX('Crédito 3'!$G$27:$G$386,'Crédito 3'!$F$13)) | G97: =IF(B97="","",IF('Crédito 3'!$C$17="No","No","Sí")) | H97: =IF(B97="","",'Crédito 3'!$F$11)
B98: =IF('Crédito 4'!$F$6="Sí",'Crédito 4'!$C$6,"") | C98: =IF(B98="","",'Crédito 4'!$C$8) | D98: =IF(B98="","",'Crédito 4'!$I$6) | E98: =IF(B98="","",'Crédito 4'!$C$13) | F98: =IF(OR(B98="",'Crédito 4'!$F$13=0),"",INDEX('Crédito 4'!$H$27:$H$386,'Crédito 4'!$F$13)-INDEX('Crédito 4'!$G$27:$G$386,'Crédito 4'!$F$13)) | G98: =IF(B98="","",IF('Crédito 4'!$C$17="No","No","Sí")) | H98: =IF(B98="","",'Crédito 4'!$F$11)
B99: =IF('Crédito 5'!$F$6="Sí",'Crédito 5'!$C$6,"") | C99: =IF(B99="","",'Crédito 5'!$C$8) | D99: =IF(B99="","",'Crédito 5'!$I$6) | E99: =IF(B99="","",'Crédito 5'!$C$13) | F99: =IF(OR(B99="",'Crédito 5'!$F$13=0),"",INDEX('Crédito 5'!$H$27:$H$386,'Crédito 5'!$F$13)-INDEX('Crédito 5'!$G$27:$G$386,'Crédito 5'!$F$13)) | G99: =IF(B99="","",IF('Crédito 5'!$C$17="No","No","Sí")) | H99: =IF(B99="","",'Crédito 5'!$F$11)
B100: =IF('Crédito 6'!$F$6="Sí",'Crédito 6'!$C$6,"") | C100: =IF(B100="","",'Crédito 6'!$C$8) | D100: =IF(B100="","",'Crédito 6'!$I$6) | E100: =IF(B100="","",'Crédito 6'!$C$13) | F100: =IF(OR(B100="",'Crédito 6'!$F$13=0),"",INDEX('Crédito 6'!$H$27:$H$386,'Crédito 6'!$F$13)-INDEX('Crédito 6'!$G$27:$G$386,'Crédito 6'!$F$13)) | G100: =IF(B100="","",IF('Crédito 6'!$C$17="No","No","Sí")) | H100: =IF(B100="","",'Crédito 6'!$F$11)
B101: =IF('Crédito 7'!$F$6="Sí",'Crédito 7'!$C$6,"") | C101: =IF(B101="","",'Crédito 7'!$C$8) | D101: =IF(B101="","",'Crédito 7'!$I$6) | E101: =IF(B101="","",'Crédito 7'!$C$13) | F101: =IF(OR(B101="",'Crédito 7'!$F$13=0),"",INDEX('Crédito 7'!$H$27:$H$386,'Crédito 7'!$F$13)-INDEX('Crédito 7'!$G$27:$G$386,'Crédito 7'!$F$13)) | G101: =IF(B101="","",IF('Crédito 7'!$C$17="No","No","Sí")) | H101: =IF(B101="","",'Crédito 7'!$F$11)
B102: =IF('Crédito 8'!$F$6="Sí",'Crédito 8'!$C$6,"") | C102: =IF(B102="","",'Crédito 8'!$C$8) | D102: =IF(B102="","",'Crédito 8'!$I$6) | E102: =IF(B102="","",'Crédito 8'!$C$13) | F102: =IF(OR(B102="",'Crédito 8'!$F$13=0),"",INDEX('Crédito 8'!$H$27:$H$386,'Crédito 8'!$F$13)-INDEX('Crédito 8'!$G$27:$G$386,'Crédito 8'!$F$13)) | G102: =IF(B102="","",IF('Crédito 8'!$C$17="No","No","Sí")) | H102: =IF(B102="","",'Crédito 8'!$F$11)
B103: Cuota mínima = lo que paga el cliente cada mes (sin abonos extra y descontando el subsidio FRECH vigente).

Sheet Datos
B1: Datos generales, ingresos y carga financiera
B2: Celdas crema: datos que llenas. La fecha de corte por defecto es hoy.
B5: Cliente
B6: Asesor o marca
B7: Fecha de corte | C7: =TODAY() -> 46290 | D7: Define qué cuotas están vencidas.
B8: Tasa de cambio (pesos por dólar) | D8: La tasa que realmente te pagan.
B10: Ingreso | C10: Moneda | D10: Valor mensual en su moneda | E10: Meses al año que llega | F10: Promedio mensual en pesos | G10: Nota
C11: COP | E11: 12 | F11: =IF(N(D11)=0,0,IF(C11="USD",D11*N($C$8),D11)*N(E11)/12) -> 0
C12: COP | E12: 12 | F12: =IF(N(D12)=0,0,IF(C12="USD",D12*N($C$8),D12)*N(E12)/12) -> 0
C13: COP | E13: 12 | F13: =IF(N(D13)=0,0,IF(C13="USD",D13*N($C$8),D13)*N(E13)/12) -> 0
C14: COP | E14: 12 | F14: =IF(N(D14)=0,0,IF(C14="USD",D14*N($C$8),D14)*N(E14)/12) -> 0
C15: COP | E15: 12 | F15: =IF(N(D15)=0,0,IF(C15="USD",D15*N($C$8),D15)*N(E15)/12) -> 0
B16: Ingreso mensual promedio | F16: =SUM(F11:F15) -> 0
B17: De ese ingreso, dólares al mes (promedio) | F17: =SUMPRODUCT((C11:C15="USD")*D11:D15*E11:E15)/12 -> 0
B19: Gastos de vida al mes (sin deudas) | D19: Opcional. Mercado, servicios, transporte, etc.
B20: Pagos de deudas del próximo mes | C20: =Panel!$D$5 -> 0
B21: Carga financiera (deudas / ingreso) | C21: =IF(F16=0,"",C20/F16) | D21: =IF(C21="","",IF(C21<=0.3,"Sana (hasta 30%)",IF(C21<=0.4,"Alta (30% a 40%)",IF(C21<=0.5,"Muy alta (40% a 50%)","Crítica (más de 50%)"))))
B22: Disponible después de deudas y gastos | C22: =F16-C20-N(C19) -> 0
B24: Si la tasa de cambio fuera... (solo si hay ingresos en dólares)
B25: Tasa de cambio | C25: Ingreso mensual | D25: Carga financiera | E25: Disponible
B26: =IF(N($C$8)=0,"",$C$8*0.85) | C26: =IF(B26="","",$F$16+$F$17*(B26-$C$8)) | D26: =IF(OR(B26="",N(C26)=0),"",$C$20/C26) | E26: =IF(B26="","",C26-$C$20-N($C$19))
B27: =IF(N($C$8)=0,"",$C$8*0.9) | C27: =IF(B27="","",$F$16+$F$17*(B27-$C$8)) | D27: =IF(OR(B27="",N(C27)=0),"",$C$20/C27) | E27: =IF(B27="","",C27-$C$20-N($C$19))
B28: =IF(N($C$8)=0,"",$C$8*0.95) | C28: =IF(B28="","",$F$16+$F$17*(B28-$C$8)) | D28: =IF(OR(B28="",N(C28)=0),"",$C$20/C28) | E28: =IF(B28="","",C28-$C$20-N($C$19))
B29: =IF(N($C$8)=0,"",$C$8*1) | C29: =IF(B29="","",$F$16+$F$17*(B29-$C$8)) | D29: =IF(OR(B29="",N(C29)=0),"",$C$20/C29) | E29: =IF(B29="","",C29-$C$20-N($C$19))
B30: =IF(N($C$8)=0,"",$C$8*1.05) | C30: =IF(B30="","",$F$16+$F$17*(B30-$C$8)) | D30: =IF(OR(B30="",N(C30)=0),"",$C$20/C30) | E30: =IF(B30="","",C30-$C$20-N($C$19))
B31: =IF(N($C$8)=0,"",$C$8*1.1) | C31: =IF(B31="","",$F$16+$F$17*(B31-$C$8)) | D31: =IF(OR(B31="",N(C31)=0),"",$C$20/C31) | E31: =IF(B31="","",C31-$C$20-N($C$19))
B32: =IF(F17=0,"Sin ingresos en dólares: la tabla no aplica.","Cada 100 pesos que baje la tasa de cambio son "&ROUND(F17*100,0)&" pesos menos al mes.") -> Sin ingresos en dólares: la tabla no aplica.

Sheet Plan de pago
B1: Plan de pago: con plan frente a solo cuotas
B2: Con el plan, el pago total se mantiene: cuando un crédito termina, su cuota pasa como abono al siguiente de la lista.
B5: Método | C5: Avalancha | D5: Avalancha: mayor tasa primero. Bola de nieve: menor saldo primero. Orden manual: escribe el orden en la columna J.
B6: Dinero extra adicional al mes | C6: 0 | D6: 0 = el plan solo usa las cuotas que se liberan.
B7: Primer mes del plan | C7: =DATE(YEAR(Datos!$C$7),MONTH(Datos!$C$7)+1,1) -> 46296
B8: Pago mensual total del plan | C8: =SUMIFS(F12:F19,C12:C19,">0.5")+N(C6) -> 0
B11: Crédito | C11: Saldo actual | D11: Tasa EA | E11: Tasa mensual | F11: Cuota | G11: Seguros | H11: ¿Acepta abonos? | I11: Abonos desde | J11: Orden manual | K11: Orden | L11: Termina solo con cuotas | M11: Termina con el plan | N11: Meses antes | O11: Intereses y seguros solo con cuotas | P11: Intereses y seguros con el plan | Q11: clave | R11: fila
B12: =IF('Crédito 1'!$F$6="Sí",'Crédito 1'!$C$6,"") | C12: =IF(B12="",0,'Crédito 1'!$I$6) -> 0 | D12: =IF(B12="","",'Crédito 1'!$C$13) | E12: =IF(B12="",0,'Crédito 1'!$F$7) -> 0 | F12: =IF(B12="",0,'Crédito 1'!$F$9) -> 0 | G12: =IF(B12="",0,N('Crédito 1'!$C$15)) -> 0 | H12: =IF(B12="","",IF('Crédito 1'!$C$17="No","No","Sí")) | I12: =IF(B12="","",'Crédito 1'!$F$11) | K12: =IF(C12<=0.5,"",1+COUNTIFS($C$12:$C$19,">0.5",$Q$12:$Q$19,"<"&Q12)+COUNTIFS($C$12:$C$19,">0.5",$Q$12:$Q$19,Q12,$R$12:$R$19,"<"&R12)) | L12: =IF(C12<=0.5,"",IF(ISNUMBER(AK22),EDATE($C$7,AK22-1),AK22)) | M12: =IF(K12="","",IF(ISNUMBER(INDEX($E$22:$AJ$22,1,4*(K12-1)+3)),EDATE($C$7,INDEX($E$22:$AJ$22,1,4*(K12-1)+3)-1),INDEX($E$22:$AJ$22,1,4*(K12-1)+3))) | N12: =IF(OR(K12="",NOT(ISNUMBER(L12)),NOT(ISNUMBER(M12))),"",(YEAR(L12)-YEAR(M12))*12+MONTH(L12)-MONTH(M12)) | O12: =IF(C12<=0.5,0,AK23) -> 0 | P12: =IF(K12="",0,INDEX($E$22:$AJ$22,1,4*(K12-1)+4)) -> 0 | Q12: =IF($C$5="Avalancha",-N(D12),IF($C$5="Bola de nieve",C12,IF(N(J12)=0,1000+R12,J12))) -> 0 | R12: =ROW() -> 12
B13: =IF('Crédito 2'!$F$6="Sí",'Crédito 2'!$C$6,"") | C13: =IF(B13="",0,'Crédito 2'!$I$6) -> 0 | D13: =IF(B13="","",'Crédito 2'!$C$13) | E13: =IF(B13="",0,'Crédito 2'!$F$7) -> 0 | F13: =IF(B13="",0,'Crédito 2'!$F$9) -> 0 | G13: =IF(B13="",0,N('Crédito 2'!$C$15)) -> 0 | H13: =IF(B13="","",IF('Crédito 2'!$C$17="No","No","Sí")) | I13: =IF(B13="","",'Crédito 2'!$F$11) | K13: =IF(C13<=0.5,"",1+COUNTIFS($C$12:$C$19,">0.5",$Q$12:$Q$19,"<"&Q13)+COUNTIFS($C$12:$C$19,">0.5",$Q$12:$Q$19,Q13,$R$12:$R$19,"<"&R13)) | L13: =IF(C13<=0.5,"",IF(ISNUMBER(AL22),EDATE($C$7,AL22-1),AL22)) | M13: =IF(K13="","",IF(ISNUMBER(INDEX($E$22:$AJ$22,1,4*(K13-1)+3)),EDATE($C$7,INDEX($E$22:$AJ$22,1,4*(K13-1)+3)-1),INDEX($E$22:$AJ$22,1,4*(K13-1)+3))) | N13: =IF(OR(K13="",NOT(ISNUMBER(L13)),NOT(ISNUMBER(M13))),"",(YEAR(L13)-YEAR(M13))*12+MONTH(L13)-MONTH(M13)) | O13: =IF(C13<=0.5,0,AL23) -> 0 | P13: =IF(K13="",0,INDEX($E$22:$AJ$22,1,4*(K13-1)+4)) -> 0 | Q13: =IF($C$5="Avalancha",-N(D13),IF($C$5="Bola de nieve",C13,IF(N(J13)=0,1000+R13,J13))) -> 0 | R13: =ROW() -> 13
B14: =IF('Crédito 3'!$F$6="Sí",'Crédito 3'!$C$6,"") | C14: =IF(B14="",0,'Crédito 3'!$I$6) -> 0 | D14: =IF(B14="","",'Crédito 3'!$C$13) | E14: =IF(B14="",0,'Crédito 3'!$F$7) -> 0 | F14: =IF(B14="",0,'Crédito 3'!$F$9) -> 0 | G14: =IF(B14="",0,N('Crédito 3'!$C$15)) -> 0 | H14: =IF(B14="","",IF('Crédito 3'!$C$17="No","No","Sí")) | I14: =IF(B14="","",'Crédito 3'!$F$11) | K14: =IF(C14<=0.5,"",1+COUNTIFS($C$12:$C$19,">0.5",$Q$12:$Q$19,"<"&Q14)+COUNTIFS($C$12:$C$19,">0.5",$Q$12:$Q$19,Q14,$R$12:$R$19,"<"&R14)) | L14: =IF(C14<=0.5,"",IF(ISNUMBER(AM22),EDATE($C$7,AM22-1),AM22)) | M14: =IF(K14="","",IF(ISNUMBER(INDEX($E$22:$AJ$22,1,4*(K14-1)+3)),EDATE($C$7,INDEX($E$22:$AJ$22,1,4*(K14-1)+3)-1),INDEX($E$22:$AJ$22,1,4*(K14-1)+3))) | N14: =IF(OR(K14="",NOT(ISNUMBER(L14)),NOT(ISNUMBER(M14))),"",(YEAR(L14)-YEAR(M14))*12+MONTH(L14)-MONTH(M14)) | O14: =IF(C14<=0.5,0,AM23) -> 0 | P14: =IF(K14="",0,INDEX($E$22:$AJ$22,1,4*(K14-1)+4)) -> 0 | Q14: =IF($C$5="Avalancha",-N(D14),IF($C$5="Bola de nieve",C14,IF(N(J14)=0,1000+R14,J14))) -> 0 | R14: =ROW() -> 14
B15: =IF('Crédito 4'!$F$6="Sí",'Crédito 4'!$C$6,"") | C15: =IF(B15="",0,'Crédito 4'!$I$6) -> 0 | D15: =IF(B15="","",'Crédito 4'!$C$13) | E15: =IF(B15="",0,'Crédito 4'!$F$7) -> 0 | F15: =IF(B15="",0,'Crédito 4'!$F$9) -> 0 | G15: =IF(B15="",0,N('Crédito 4'!$C$15)) -> 0 | H15: =IF(B15="","",IF('Crédito 4'!$C$17="No","No","Sí")) | I15: =IF(B15="","",'Crédito 4'!$F$11) | K15: =IF(C15<=0.5,"",1+COUNTIFS($C$12:$C$19,">0.5",$Q$12:$Q$19,"<"&Q15)+COUNTIFS($C$12:$C$19,">0.5",$Q$12:$Q$19,Q15,$R$12:$R$19,"<"&R15)) | L15: =IF(C15<=0.5,"",IF(ISNUMBER(AN22),EDATE($C$7,AN22-1),AN22)) | M15: =IF(K15="","",IF(ISNUMBER(INDEX($E$22:$AJ$22,1,4*(K15-1)+3)),EDATE($C$7,INDEX($E$22:$AJ$22,1,4*(K15-1)+3)-1),INDEX($E$22:$AJ$22,1,4*(K15-1)+3))) | N15: =IF(OR(K15="",NOT(ISNUMBER(L15)),NOT(ISNUMBER(M15))),"",(YEAR(L15)-YEAR(M15))*12+MONTH(L15)-MONTH(M15)) | O15: =IF(C15<=0.5,0,AN23) -> 0 | P15: =IF(K15="",0,INDEX($E$22:$AJ$22,1,4*(K15-1)+4)) -> 0 | Q15: =IF($C$5="Avalancha",-N(D15),IF($C$5="Bola de nieve",C15,IF(N(J15)=0,1000+R15,J15))) -> 0 | R15: =ROW() -> 15
B16: =IF('Crédito 5'!$F$6="Sí",'Crédito 5'!$C$6,"") | C16: =IF(B16="",0,'Crédito 5'!$I$6) -> 0 | D16: =IF(B16="","",'Crédito 5'!$C$13) | E16: =IF(B16="",0,'Crédito 5'!$F$7) -> 0 | F16: =IF(B16="",0,'Crédito 5'!$F$9) -> 0 | G16: =IF(B16="",0,N('Crédito 5'!$C$15)) -> 0 | H16: =IF(B16="","",IF('Crédito 5'!$C$17="No","No","Sí")) | I16: =IF(B16="","",'Crédito 5'!$F$11) | K16: =IF(C16<=0.5,"",1+COUNTIFS($C$12:$C$19,">0.5",$Q$12:$Q$19,"<"&Q16)+COUNTIFS($C$12:$C$19,">0.5",$Q$12:$Q$19,Q16,$R$12:$R$19,"<"&R16)) | L16: =IF(C16<=0.5,"",IF(ISNUMBER(AO22),EDATE($C$7,AO22-1),AO22)) | M16: =IF(K16="","",IF(ISNUMBER(INDEX($E$22:$AJ$22,1,4*(K16-1)+3)),EDATE($C$7,INDEX($E$22:$AJ$22,1,4*(K16-1)+3)-1),INDEX($E$22:$AJ$22,1,4*(K16-1)+3))) | N16: =IF(OR(K16="",NOT(ISNUMBER(L16)),NOT(ISNUMBER(M16))),"",(YEAR(L16)-YEAR(M16))*12+MONTH(L16)-MONTH(M16)) | O16: =IF(C16<=0.5,0,AO23) -> 0 | P16: =IF(K16="",0,INDEX($E$22:$AJ$22,1,4*(K16-1)+4)) -> 0 | Q16: =IF($C$5="Avalancha",-N(D16),IF($C$5="Bola de nieve",C16,IF(N(J16)=0,1000+R16,J16))) -> 0 | R16: =ROW() -> 16
B17: =IF('Crédito 6'!$F$6="Sí",'Crédito 6'!$C$6,"") | C17: =IF(B17="",0,'Crédito 6'!$I$6) -> 0 | D17: =IF(B17="","",'Crédito 6'!$C$13) | E17: =IF(B17="",0,'Crédito 6'!$F$7) -> 0 | F17: =IF(B17="",0,'Crédito 6'!$F$9) -> 0 | G17: =IF(B17="",0,N('Crédito 6'!$C$15)) -> 0 | H17: =IF(B17="","",IF('Crédito 6'!$C$17="No","No","Sí")) | I17: =IF(B17="","",'Crédito 6'!$F$11) | K17: =IF(C17<=0.5,"",1+COUNTIFS($C$12:$C$19,">0.5",$Q$12:$Q$19,"<"&Q17)+COUNTIFS($C$12:$C$19,">0.5",$Q$12:$Q$19,Q17,$R$12:$R$19,"<"&R17)) | L17: =IF(C17<=0.5,"",IF(ISNUMBER(AP22),EDATE($C$7,AP22-1),AP22)) | M17: =IF(K17="","",IF(ISNUMBER(INDEX($E$22:$AJ$22,1,4*(K17-1)+3)),EDATE($C$7,INDEX($E$22:$AJ$22,1,4*(K17-1)+3)-1),INDEX($E$22:$AJ$22,1,4*(K17-1)+3))) | N17: =IF(OR(K17="",NOT(ISNUMBER(L17)),NOT(ISNUMBER(M17))),"",(YEAR(L17)-YEAR(M17))*12+MONTH(L17)-MONTH(M17)) | O17: =IF(C17<=0.5,0,AP23) -> 0 | P17: =IF(K17="",0,INDEX($E$22:$AJ$22,1,4*(K17-1)+4)) -> 0 | Q17: =IF($C$5="Avalancha",-N(D17),IF($C$5="Bola de nieve",C17,IF(N(J17)=0,1000+R17,J17))) -> 0 | R17: =ROW() -> 17
B18: =IF('Crédito 7'!$F$6="Sí",'Crédito 7'!$C$6,"") | C18: =IF(B18="",0,'Crédito 7'!$I$6) -> 0 | D18: =IF(B18="","",'Crédito 7'!$C$13) | E18: =IF(B18="",0,'Crédito 7'!$F$7) -> 0 | F18: =IF(B18="",0,'Crédito 7'!$F$9) -> 0 | G18: =IF(B18="",0,N('Crédito 7'!$C$15)) -> 0 | H18: =IF(B18="","",IF('Crédito 7'!$C$17="No","No","Sí")) | I18: =IF(B18="","",'Crédito 7'!$F$11) | K18: =IF(C18<=0.5,"",1+COUNTIFS($C$12:$C$19,">0.5",$Q$12:$Q$19,"<"&Q18)+COUNTIFS($C$12:$C$19,">0.5",$Q$12:$Q$19,Q18,$R$12:$R$19,"<"&R18)) | L18: =IF(C18<=0.5,"",IF(ISNUMBER(AQ22),EDATE($C$7,AQ22-1),AQ22)) | M18: =IF(K18="","",IF(ISNUMBER(INDEX($E$22:$AJ$22,1,4*(K18-1)+3)),EDATE($C$7,INDEX($E$22:$AJ$22,1,4*(K18-1)+3)-1),INDEX($E$22:$AJ$22,1,4*(K18-1)+3))) | N18: =IF(OR(K18="",NOT(ISNUMBER(L18)),NOT(ISNUMBER(M18))),"",(YEAR(L18)-YEAR(M18))*12+MONTH(L18)-MONTH(M18)) | O18: =IF(C18<=0.5,0,AQ23) -> 0 | P18: =IF(K18="",0,INDEX($E$22:$AJ$22,1,4*(K18-1)+4)) -> 0 | Q18: =IF($C$5="Avalancha",-N(D18),IF($C$5="Bola de nieve",C18,IF(N(J18)=0,1000+R18,J18))) -> 0 | R18: =ROW() -> 18
B19: =IF('Crédito 8'!$F$6="Sí",'Crédito 8'!$C$6,"") | C19: =IF(B19="",0,'Crédito 8'!$I$6) -> 0 | D19: =IF(B19="","",'Crédito 8'!$C$13) | E19: =IF(B19="",0,'Crédito 8'!$F$7) -> 0 | F19: =IF(B19="",0,'Crédito 8'!$F$9) -> 0 | G19: =IF(B19="",0,N('Crédito 8'!$C$15)) -> 0 | H19: =IF(B19="","",IF('Crédito 8'!$C$17="No","No","Sí")) | I19: =IF(B19="","",'Crédito 8'!$F$11) | K19: =IF(C19<=0.5,"",1+COUNTIFS($C$12:$C$19,">0.5",$Q$12:$Q$19,"<"&Q19)+COUNTIFS($C$12:$C$19,">0.5",$Q$12:$Q$19,Q19,$R$12:$R$19,"<"&R19)) | L19: =IF(C19<=0.5,"",IF(ISNUMBER(AR22),EDATE($C$7,AR22-1),AR22)) | M19: =IF(K19="","",IF(ISNUMBER(INDEX($E$22:$AJ$22,1,4*(K19-1)+3)),EDATE($C$7,INDEX($E$22:$AJ$22,1,4*(K19-1)+3)-1),INDEX($E$22:$AJ$22,1,4*(K19-1)+3))) | N19: =IF(OR(K19="",NOT(ISNUMBER(L19)),NOT(ISNUMBER(M19))),"",(YEAR(L19)-YEAR(M19))*12+MONTH(L19)-MONTH(M19)) | O19: =IF(C19<=0.5,0,AR23) -> 0 | P19: =IF(K19="",0,INDEX($E$22:$AJ$22,1,4*(K19-1)+4)) -> 0 | Q19: =IF($C$5="Avalancha",-N(D19),IF($C$5="Bola de nieve",C19,IF(N(J19)=0,1000+R19,J19))) -> 0 | R19: =ROW() -> 19
B20: Total | C20: =SUM(C12:C19) -> 0 | F20: =SUM(F12:F19) -> 0 | O20: =SUM(O12:O19) -> 0 | P20: =SUM(P12:P19) -> 0
B21: Ahorro en intereses con el plan | C21: =O20-P20 -> 0 | E21: El FRECH no cambia el plan: el gobierno paga parte de la cuota y el saldo baja igual.
E22: =IFERROR(MATCH(1,$K$12:$K$19,0),0) -> 0 | F22: =IF(E22=0,"(vacío)","Orden 1: "&INDEX($B$12:$B$19,E22)) -> (vacío) | G22: =IF(F25<=0.5,0,IF(H387>0.5,"Más de 360",COUNTIF(H28:H387,">0.5")+1)) -> 0 | H22: =IF(F25<=0.5,0,SUM(F28:F387)+SUM(G28:G387)+H387-F25) -> 0 | I22: =IFERROR(MATCH(2,$K$12:$K$19,0),0) -> 0 | J22: =IF(I22=0,"(vacío)","Orden 2: "&INDEX($B$12:$B$19,I22)) -> (vacío) | K22: =IF(J25<=0.5,0,IF(L387>0.5,"Más de 360",COUNTIF(L28:L387,">0.5")+1)) -> 0 | L22: =IF(J25<=0.5,0,SUM(J28:J387)+SUM(K28:K387)+L387-J25) -> 0 | M22: =IFERROR(MATCH(3,$K$12:$K$19,0),0) -> 0 | N22: =IF(M22=0,"(vacío)","Orden 3: "&INDEX($B$12:$B$19,M22)) -> (vacío) | O22: =IF(N25<=0.5,0,IF(P387>0.5,"Más de 360",COUNTIF(P28:P387,">0.5")+1)) -> 0 | P22: =IF(N25<=0.5,0,SUM(N28:N387)+SUM(O28:O387)+P387-N25) -> 0 | Q22: =IFERROR(MATCH(4,$K$12:$K$19,0),0) -> 0 | R22: =IF(Q22=0,"(vacío)","Orden 4: "&INDEX($B$12:$B$19,Q22)) -> (vacío) | S22: =IF(R25<=0.5,0,IF(T387>0.5,"Más de 360",COUNTIF(T28:T387,">0.5")+1)) -> 0 | T22: =IF(R25<=0.5,0,SUM(R28:R387)+SUM(S28:S387)+T387-R25) -> 0 | U22: =IFERROR(MATCH(5,$K$12:$K$19,0),0) -> 0 | V22: =IF(U22=0,"(vacío)","Orden 5: "&INDEX($B$12:$B$19,U22)) -> (vacío) | W22: =IF(V25<=0.5,0,IF(X387>0.5,"Más de 360",COUNTIF(X28:X387,">0.5")+1)) -> 0 | X22: =IF(V25<=0.5,0,SUM(V28:V387)+SUM(W28:W387)+X387-V25) -> 0 | Y22: =IFERROR(MATCH(6,$K$12:$K$19,0),0) -> 0 | Z22: =IF(Y22=0,"(vacío)","Orden 6: "&INDEX($B$12:$B$19,Y22)) -> (vacío) | AA22: =IF(Z25<=0.5,0,IF(AB387>0.5,"Más de 360",COUNTIF(AB28:AB387,">0.5")+1)) -> 0 | AB22: =IF(Z25<=0.5,0,SUM(Z28:Z387)+SUM(AA28:AA387)+AB387-Z25) -> 0 | AC22: =IFERROR(MATCH(7,$K$12:$K$19,0),0) -> 0 | AD22: =IF(AC22=0,"(vacío)","Orden 7: "&INDEX($B$12:$B$19,AC22)) -> (vacío) | AE22: =IF(AD25<=0.5,0,IF(AF387>0.5,"Más de 360",COUNTIF(AF28:AF387,">0.5")+1)) -> 0 | AF22: =IF(AD25<=0.5,0,SUM(AD28:AD387)+SUM(AE28:AE387)+AF387-AD25) -> 0 | AG22: =IFERROR(MATCH(8,$K$12:$K$19,0),0) -> 0 | AH22: =IF(AG22=0,"(vacío)","Orden 8: "&INDEX($B$12:$B$19,AG22)) -> (vacío) | AI22: =IF(AH25<=0.5,0,IF(AJ387>0.5,"Más de 360",COUNTIF(AJ28:AJ387,">0.5")+1)) -> 0 | AJ22: =IF(AH25<=0.5,0,SUM(AH28:AH387)+SUM(AI28:AI387)+AJ387-AH25) -> 0 | AK22: =IF($C$12<=0.5,0,IF(AK387>0.5,"Más de 360",COUNTIF(AK28:AK387,">0.5")+1)) -> 0 | AL22: =IF($C$13<=0.5,0,IF(AL387>0.5,"Más de 360",COUNTIF(AL28:AL387,">0.5")+1)) -> 0 | AM22: =IF($C$14<=0.5,0,IF(AM387>0.5,"Más de 360",COUNTIF(AM28:AM387,">0.5")+1)) -> 0 | AN22: =IF($C$15<=0.5,0,IF(AN387>0.5,"Más de 360",COUNTIF(AN28:AN387,">0.5")+1)) -> 0 | AO22: =IF($C$16<=0.5,0,IF(AO387>0.5,"Más de 360",COUNTIF(AO28:AO387,">0.5")+1)) -> 0 | AP22: =IF($C$17<=0.5,0,IF(AP387>0.5,"Más de 360",COUNTIF(AP28:AP387,">0.5")+1)) -> 0 | AQ22: =IF($C$18<=0.5,0,IF(AQ387>0.5,"Más de 360",COUNTIF(AQ28:AQ387,">0.5")+1)) -> 0 | AR22: =IF($C$19<=0.5,0,IF(AR387>0.5,"Más de 360",COUNTIF(AR28:AR387,">0.5")+1)) -> 0
B23: Motor del plan (mes a mes) | E23: =IF(E22=0,0,INDEX($E$12:$E$19,E22)) -> 0 | F23: =IF(E22=0,0,INDEX($F$12:$F$19,E22)) -> 0 | I23: =IF(I22=0,0,INDEX($E$12:$E$19,I22)) -> 0 | J23: =IF(I22=0,0,INDEX($F$12:$F$19,I22)) -> 0 | M23: =IF(M22=0,0,INDEX($E$12:$E$19,M22)) -> 0 | N23: =IF(M22=0,0,INDEX($F$12:$F$19,M22)) -> 0 | Q23: =IF(Q22=0,0,INDEX($E$12:$E$19,Q22)) -> 0 | R23: =IF(Q22=0,0,INDEX($F$12:$F$19,Q22)) -> 0 | U23: =IF(U22=0,0,INDEX($E$12:$E$19,U22)) -> 0 | V23: =IF(U22=0,0,INDEX($F$12:$F$19,U22)) -> 0 | Y23: =IF(Y22=0,0,INDEX($E$12:$E$19,Y22)) -> 0 | Z23: =IF(Y22=0,0,INDEX($F$12:$F$19,Y22)) -> 0 | AC23: =IF(AC22=0,0,INDEX($E$12:$E$19,AC22)) -> 0 | AD23: =IF(AC22=0,0,INDEX($F$12:$F$19,AC22)) -> 0 | AG23: =IF(AG22=0,0,INDEX($E$12:$E$19,AG22)) -> 0 | AH23: =IF(AG22=0,0,INDEX($F$12:$F$19,AG22)) -> 0 | AK23: =IF($C$12<=0.5,0,$E$12*($C$12+SUM(AK28:AK386))+$G$12*(1+COUNTIF(AK28:AK386,">0.5"))) -> 0 | AL23: =IF($C$13<=0.5,0,$E$13*($C$13+SUM(AL28:AL386))+$G$13*(1+COUNTIF(AL28:AL386,">0.5"))) -> 0 | AM23: =IF($C$14<=0.5,0,$E$14*($C$14+SUM(AM28:AM386))+$G$14*(1+COUNTIF(AM28:AM386,">0.5"))) -> 0 | AN23: =IF($C$15<=0.5,0,$E$15*($C$15+SUM(AN28:AN386))+$G$15*(1+COUNTIF(AN28:AN386,">0.5"))) -> 0 | AO23: =IF($C$16<=0.5,0,$E$16*($C$16+SUM(AO28:AO386))+$G$16*(1+COUNTIF(AO28:AO386,">0.5"))) -> 0 | AP23: =IF($C$17<=0.5,0,$E$17*($C$17+SUM(AP28:AP386))+$G$17*(1+COUNTIF(AP28:AP386,">0.5"))) -> 0 | AQ23: =IF($C$18<=0.5,0,$E$18*($C$18+SUM(AQ28:AQ386))+$G$18*(1+COUNTIF(AQ28:AQ386,">0.5"))) -> 0 | AR23: =IF($C$19<=0.5,0,$E$19*($C$19+SUM(AR28:AR386))+$G$19*(1+COUNTIF(AR28:AR386,">0.5"))) -> 0
E24: =IF(E22=0,0,INDEX($G$12:$G$19,E22)) -> 0 | F24: =IF(E22=0,0,IF(INDEX($H$12:$H$19,E22)="No",0,1)) -> 0 | I24: =IF(I22=0,0,INDEX($G$12:$G$19,I22)) -> 0 | J24: =IF(I22=0,0,IF(INDEX($H$12:$H$19,I22)="No",0,1)) -> 0 | M24: =IF(M22=0,0,INDEX($G$12:$G$19,M22)) -> 0 | N24: =IF(M22=0,0,IF(INDEX($H$12:$H$19,M22)="No",0,1)) -> 0 | Q24: =IF(Q22=0,0,INDEX($G$12:$G$19,Q22)) -> 0 | R24: =IF(Q22=0,0,IF(INDEX($H$12:$H$19,Q22)="No",0,1)) -> 0 | U24: =IF(U22=0,0,INDEX($G$12:$G$19,U22)) -> 0 | V24: =IF(U22=0,0,IF(INDEX($H$12:$H$19,U22)="No",0,1)) -> 0 | Y24: =IF(Y22=0,0,INDEX($G$12:$G$19,Y22)) -> 0 | Z24: =IF(Y22=0,0,IF(INDEX($H$12:$H$19,Y22)="No",0,1)) -> 0 | AC24: =IF(AC22=0,0,INDEX($G$12:$G$19,AC22)) -> 0 | AD24: =IF(AC22=0,0,IF(INDEX($H$12:$H$19,AC22)="No",0,1)) -> 0 | AG24: =IF(AG22=0,0,INDEX($G$12:$G$19,AG22)) -> 0 | AH24: =IF(AG22=0,0,IF(INDEX($H$12:$H$19,AG22)="No",0,1)) -> 0
E25: =IF(E22=0,"",IF(N(INDEX($I$12:$I$19,E22))=0,"",INDEX($I$12:$I$19,E22))) | F25: =IF(E22=0,0,INDEX($C$12:$C$19,E22)) -> 0 | I25: =IF(I22=0,"",IF(N(INDEX($I$12:$I$19,I22))=0,"",INDEX($I$12:$I$19,I22))) | J25: =IF(I22=0,0,INDEX($C$12:$C$19,I22)) -> 0 | M25: =IF(M22=0,"",IF(N(INDEX($I$12:$I$19,M22))=0,"",INDEX($I$12:$I$19,M22))) | N25: =IF(M22=0,0,INDEX($C$12:$C$19,M22)) -> 0 | Q25: =IF(Q22=0,"",IF(N(INDEX($I$12:$I$19,Q22))=0,"",INDEX($I$12:$I$19,Q22))) | R25: =IF(Q22=0,0,INDEX($C$12:$C$19,Q22)) -> 0 | U25: =IF(U22=0,"",IF(N(INDEX($I$12:$I$19,U22))=0,"",INDEX($I$12:$I$19,U22))) | V25: =IF(U22=0,0,INDEX($C$12:$C$19,U22)) -> 0 | Y25: =IF(Y22=0,"",IF(N(INDEX($I$12:$I$19,Y22))=0,"",INDEX($I$12:$I$19,Y22))) | Z25: =IF(Y22=0,0,INDEX($C$12:$C$19,Y22)) -> 0 | AC25: =IF(AC22=0,"",IF(N(INDEX($I$12:$I$19,AC22))=0,"",INDEX($I$12:$I$19,AC22))) | AD25: =IF(AC22=0,0,INDEX($C$12:$C$19,AC22)) -> 0 | AG25: =IF(AG22=0,"",IF(N(INDEX($I$12:$I$19,AG22))=0,"",INDEX($I$12:$I$19,AG22))) | AH25: =IF(AG22=0,0,INDEX($C$12:$C$19,AG22)) -> 0
B26: Mes | C26: Fecha | D26: Disponible para extra | E26: Debe | F26: Cuota | G26: Extra | H26: Saldo | I26: Debe | J26: Cuota | K26: Extra | L26: Saldo | M26: Debe | N26: Cuota | O26: Extra | P26: Saldo | Q26: Debe | R26: Cuota | S26: Extra | T26: Saldo | U26: Debe | V26: Cuota | W26: Extra | X26: Saldo | Y26: Debe | Z26: Cuota | AA26: Extra | AB26: Saldo | AC26: Debe | AD26: Cuota | AE26: Extra | AF26: Saldo | AG26: Debe | AH26: Cuota | AI26: Extra | AJ26: Saldo | AK26: Solo cuotas 1 | AL26: Solo cuotas 2 | AM26: Solo cuotas 3 | AN26: Solo cuotas 4 | AO26: Solo cuotas 5 | AP26: Solo cuotas 6 | AQ26: Solo cuotas 7 | AR26: Solo cuotas 8 | AS26: Deuda con el plan | AT26: Deuda solo con cuotas | AU26: Pago del mes con el plan
B28: 1 | C28: =EDATE($C$7,0) -> 46296 | D28: =$C$8-(F28+J28+N28+R28+V28+Z28+AD28+AH28) -> 0 | E28: =IF(F$25>0.5,F$25*(1+E$23)+E$24,0) -> 0 | F28: =MIN(F$23,E28) -> 0 | G28: =IF(AND(F$24=1,OR(E$25="",$C28>=E$25)),MAX(0,MIN(E28-F28,$D28-(0))),0) -> 0 | H28: =E28-F28-G28 -> 0 | I28: =IF(J$25>0.5,J$25*(1+I$23)+I$24,0) -> 0 | J28: =MIN(J$23,I28) -> 0 | K28: =IF(AND(J$24=1,OR(I$25="",$C28>=I$25)),MAX(0,MIN(I28-J28,$D28-(G28))),0) -> 0 | L28: =I28-J28-K28 -> 0 | M28: =IF(N$25>0.5,N$25*(1+M$23)+M$24,0) -> 0 | N28: =MIN(N$23,M28) -> 0 | O28: =IF(AND(N$24=1,OR(M$25="",$C28>=M$25)),MAX(0,MIN(M28-N28,$D28-(G28+K28))),0) -> 0 | P28: =M28-N28-O28 -> 0 | Q28: =IF(R$25>0.5,R$25*(1+Q$23)+Q$24,0) -> 0 | R28: =MIN(R$23,Q28) -> 0 | S28: =IF(AND(R$24=1,OR(Q$25="",$C28>=Q$25)),MAX(0,MIN(Q28-R28,$D28-(G28+K28+O28))),0) -> 0 | T28: =Q28-R28-S28 -> 0 | U28: =IF(V$25>0.5,V$25*(1+U$23)+U$24,0) -> 0 | V28: =MIN(V$23,U28) -> 0 | W28: =IF(AND(V$24=1,OR(U$25="",$C28>=U$25)),MAX(0,MIN(U28-V28,$D28-(G28+K28+O28+S28))),0) -> 0 | X28: =U28-V28-W28 -> 0 | Y28: =IF(Z$25>0.5,Z$25*(1+Y$23)+Y$24,0) -> 0 | Z28: =MIN(Z$23,Y28) -> 0 | AA28: =IF(AND(Z$24=1,OR(Y$25="",$C28>=Y$25)),MAX(0,MIN(Y28-Z28,$D28-(G28+K28+O28+S28+W28))),0) -> 0 | AB28: =Y28-Z28-AA28 -> 0 | AC28: =IF(AD$25>0.5,AD$25*(1+AC$23)+AC$24,0) -> 0 | AD28: =MIN(AD$23,AC28) -> 0 | AE28: =IF(AND(AD$24=1,OR(AC$25="",$C28>=AC$25)),MAX(0,MIN(AC28-AD28,$D28-(G28+K28+O28+S28+W28+AA28))),0) -> 0 | AF28: =AC28-AD28-AE28 -> 0 | AG28: =IF(AH$25>0.5,AH$25*(1+AG$23)+AG$24,0) -> 0 | AH28: =MIN(AH$23,AG28) -> 0 | AI28: =IF(AND(AH$24=1,OR(AG$25="",$C28>=AG$25)),MAX(0,MIN(AG28-AH28,$D28-(G28+K28+O28+S28+W28+AA28+AE28))),0) -> 0 | AJ28: =AG28-AH28-AI28 -> 0 | AK28: =IF($C$12>0.5,$C$12*(1+$E$12)+$G$12-MIN($F$12,$C$12*(1+$E$12)+$G$12),0) -> 0 | AL28: =IF($C$13>0.5,$C$13*(1+$E$13)+$G$13-MIN($F$13,$C$13*(1+$E$13)+$G$13),0) -> 0 | AM28: =IF($C$14>0.5,$C$14*(1+$E$14)+$G$14-MIN($F$14,$C$14*(1+$E$14)+$G$14),0) -> 0 | AN28: =IF($C$15>0.5,$C$15*(1+$E$15)+$G$15-MIN($F$15,$C$15*(1+$E$15)+$G$15),0) -> 0 | AO28: =IF($C$16>0.5,$C$16*(1+$E$16)+$G$16-MIN($F$16,$C$16*(1+$E$16)+$G$16),0) -> 0 | AP28: =IF($C$17>0.5,$C$17*(1+$E$17)+$G$17-MIN($F$17,$C$17*(1+$E$17)+$G$17),0) -> 0 | AQ28: =IF($C$18>0.5,$C$18*(1+$E$18)+$G$18-MIN($F$18,$C$18*(1+$E$18)+$G$18),0) -> 0 | AR28: =IF($C$19>0.5,$C$19*(1+$E$19)+$G$19-MIN($F$19,$C$19*(1+$E$19)+$G$19),0) -> 0 | AS28: =H28+L28+P28+T28+X28+AB28+AF28+AJ28 -> 0 | AT28: =SUM(AK28:AR28) -> 0 | AU28: =F28+G28+J28+K28+N28+O28+R28+S28+V28+W28+Z28+AA28+AD28+AE28+AH28+AI28 -> 0
B29: 2 | C29: =EDATE($C$7,1) -> 46327 | D29: =$C$8-(F29+J29+N29+R29+V29+Z29+AD29+AH29) -> 0 | E29: =IF(H28>0.5,H28*(1+E$23)+E$24,0) -> 0 | F29: =MIN(F$23,E29) -> 0 | G29: =IF(AND(F$24=1,OR(E$25="",$C29>=E$25)),MAX(0,MIN(E29-F29,$D29-(0))),0) -> 0 | H29: =E29-F29-G29 -> 0 | I29: =IF(L28>0.5,L28*(1+I$23)+I$24,0) -> 0 | J29: =MIN(J$23,I29) -> 0 | K29: =IF(AND(J$24=1,OR(I$25="",$C29>=I$25)),MAX(0,MIN(I29-J29,$D29-(G29))),0) -> 0 | L29: =I29-J29-K29 -> 0 | M29: =IF(P28>0.5,P28*(1+M$23)+M$24,0) -> 0 | N29: =MIN(N$23,M29) -> 0 | O29: =IF(AND(N$24=1,OR(M$25="",$C29>=M$25)),MAX(0,MIN(M29-N29,$D29-(G29+K29))),0) -> 0 | P29: =M29-N29-O29 -> 0 | Q29: =IF(T28>0.5,T28*(1+Q$23)+Q$24,0) -> 0 | R29: =MIN(R$23,Q29) -> 0 | S29: =IF(AND(R$24=1,OR(Q$25="",$C29>=Q$25)),MAX(0,MIN(Q29-R29,$D29-(G29+K29+O29))),0) -> 0 | T29: =Q29-R29-S29 -> 0 | U29: =IF(X28>0.5,X28*(1+U$23)+U$24,0) -> 0 | V29: =MIN(V$23,U29) -> 0 | W29: =IF(AND(V$24=1,OR(U$25="",$C29>=U$25)),MAX(0,MIN(U29-V29,$D29-(G29+K29+O29+S29))),0) -> 0 | X29: =U29-V29-W29 -> 0 | Y29: =IF(AB28>0.5,AB28*(1+Y$23)+Y$24,0) -> 0 | Z29: =MIN(Z$23,Y29) -> 0 | AA29: =IF(AND(Z$24=1,OR(Y$25="",$C29>=Y$25)),MAX(0,MIN(Y29-Z29,$D29-(G29+K29+O29+S29+W29))),0) -> 0 | AB29: =Y29-Z29-AA29 -> 0 | AC29: =IF(AF28>0.5,AF28*(1+AC$23)+AC$24,0) -> 0 | AD29: =MIN(AD$23,AC29) -> 0 | AE29: =IF(AND(AD$24=1,OR(AC$25="",$C29>=AC$25)),MAX(0,MIN(AC29-AD29,$D29-(G29+K29+O29+S29+W29+AA29))),0) -> 0 | AF29: =AC29-AD29-AE29 -> 0 | AG29: =IF(AJ28>0.5,AJ28*(1+AG$23)+AG$24,0) -> 0 | AH29: =MIN(AH$23,AG29) -> 0 | AI29: =IF(AND(AH$24=1,OR(AG$25="",$C29>=AG$25)),MAX(0,MIN(AG29-AH29,$D29-(G29+K29+O29+S29+W29+AA29+AE29))),0) -> 0 | AJ29: =AG29-AH29-AI29 -> 0 | AK29: =IF(AK28>0.5,AK28*(1+$E$12)+$G$12-MIN($F$12,AK28*(1+$E$12)+$G$12),0) -> 0 | AL29: =IF(AL28>0.5,AL28*(1+$E$13)+$G$13-MIN($F$13,AL28*(1+$E$13)+$G$13),0) -> 0 | AM29: =IF(AM28>0.5,AM28*(1+$E$14)+$G$14-MIN($F$14,AM28*(1+$E$14)+$G$14),0) -> 0 | AN29: =IF(AN28>0.5,AN28*(1+$E$15)+$G$15-MIN($F$15,AN28*(1+$E$15)+$G$15),0) -> 0 | AO29: =IF(AO28>0.5,AO28*(1+$E$16)+$G$16-MIN($F$16,AO28*(1+$E$16)+$G$16),0) -> 0 | AP29: =IF(AP28>0.5,AP28*(1+$E$17)+$G$17-MIN($F$17,AP28*(1+$E$17)+$G$17),0) -> 0 | AQ29: =IF(AQ28>0.5,AQ28*(1+$E$18)+$G$18-MIN($F$18,AQ28*(1+$E$18)+$G$18),0) -> 0 | AR29: =IF(AR28>0.5,AR28*(1+$E$19)+$G$19-MIN($F$19,AR28*(1+$E$19)+$G$19),0) -> 0 | AS29: =H29+L29+P29+T29+X29+AB29+AF29+AJ29 -> 0 | AT29: =SUM(AK29:AR29) -> 0 | AU29: =F29+G29+J29+K29+N29+O29+R29+S29+V29+W29+Z29+AA29+AD29+AE29+AH29+AI29 -> 0
B30: 3 | C30: =EDATE($C$7,2) -> 46357 | D30: =$C$8-(F30+J30+N30+R30+V30+Z30+AD30+AH30) -> 0 | E30: =IF(H29>0.5,H29*(1+E$23)+E$24,0) -> 0 | F30: =MIN(F$23,E30) -> 0 | G30: =IF(AND(F$24=1,OR(E$25="",$C30>=E$25)),MAX(0,MIN(E30-F30,$D30-(0))),0) -> 0 | H30: =E30-F30-G30 -> 0 | I30: =IF(L29>0.5,L29*(1+I$23)+I$24,0) -> 0 | J30: =MIN(J$23,I30) -> 0 | K30: =IF(AND(J$24=1,OR(I$25="",$C30>=I$25)),MAX(0,MIN(I30-J30,$D30-(G30))),0) -> 0 | L30: =I30-J30-K30 -> 0 | M30: =IF(P29>0.5,P29*(1+M$23)+M$24,0) -> 0 | N30: =MIN(N$23,M30) -> 0 | O30: =IF(AND(N$24=1,OR(M$25="",$C30>=M$25)),MAX(0,MIN(M30-N30,$D30-(G30+K30))),0) -> 0 | P30: =M30-N30-O30 -> 0 | Q30: =IF(T29>0.5,T29*(1+Q$23)+Q$24,0) -> 0 | R30: =MIN(R$23,Q30) -> 0 | S30: =IF(AND(R$24=1,OR(Q$25="",$C30>=Q$25)),MAX(0,MIN(Q30-R30,$D30-(G30+K30+O30))),0) -> 0 | T30: =Q30-R30-S30 -> 0 | U30: =IF(X29>0.5,X29*(1+U$23)+U$24,0) -> 0 | V30: =MIN(V$23,U30) -> 0 | W30: =IF(AND(V$24=1,OR(U$25="",$C30>=U$25)),MAX(0,MIN(U30-V30,$D30-(G30+K30+O30+S30))),0) -> 0 | X30: =U30-V30-W30 -> 0 | Y30: =IF(AB29>0.5,AB29*(1+Y$23)+Y$24,0) -> 0 | Z30: =MIN(Z$23,Y30) -> 0 | AA30: =IF(AND(Z$24=1,OR(Y$25="",$C30>=Y$25)),MAX(0,MIN(Y30-Z30,$D30-(G30+K30+O30+S30+W30))),0) -> 0 | AB30: =Y30-Z30-AA30 -> 0 | AC30: =IF(AF29>0.5,AF29*(1+AC$23)+AC$24,0) -> 0 | AD30: =MIN(AD$23,AC30) -> 0 | AE30: =IF(AND(AD$24=1,OR(AC$25="",$C30>=AC$25)),MAX(0,MIN(AC30-AD30,$D30-(G30+K30+O30+S30+W30+AA30))),0) -> 0 | AF30: =AC30-AD30-AE30 -> 0 | AG30: =IF(AJ29>0.5,AJ29*(1+AG$23)+AG$24,0) -> 0 | AH30: =MIN(AH$23,AG30) -> 0 | AI30: =IF(AND(AH$24=1,OR(AG$25="",$C30>=AG$25)),MAX(0,MIN(AG30-AH30,$D30-(G30+K30+O30+S30+W30+AA30+AE30))),0) -> 0 | AJ30: =AG30-AH30-AI30 -> 0 | AK30: =IF(AK29>0.5,AK29*(1+$E$12)+$G$12-MIN($F$12,AK29*(1+$E$12)+$G$12),0) -> 0 | AL30: =IF(AL29>0.5,AL29*(1+$E$13)+$G$13-MIN($F$13,AL29*(1+$E$13)+$G$13),0) -> 0 | AM30: =IF(AM29>0.5,AM29*(1+$E$14)+$G$14-MIN($F$14,AM29*(1+$E$14)+$G$14),0) -> 0 | AN30: =IF(AN29>0.5,AN29*(1+$E$15)+$G$15-MIN($F$15,AN29*(1+$E$15)+$G$15),0) -> 0 | AO30: =IF(AO29>0.5,AO29*(1+$E$16)+$G$16-MIN($F$16,AO29*(1+$E$16)+$G$16),0) -> 0 | AP30: =IF(AP29>0.5,AP29*(1+$E$17)+$G$17-MIN($F$17,AP29*(1+$E$17)+$G$17),0) -> 0 | AQ30: =IF(AQ29>0.5,AQ29*(1+$E$18)+$G$18-MIN($F$18,AQ29*(1+$E$18)+$G$18),0) -> 0 | AR30: =IF(AR29>0.5,AR29*(1+$E$19)+$G$19-MIN($F$19,AR29*(1+$E$19)+$G$19),0) -> 0 | AS30: =H30+L30+P30+T30+X30+AB30+AF30+AJ30 -> 0 | AT30: =SUM(AK30:AR30) -> 0 | AU30: =F30+G30+J30+K30+N30+O30+R30+S30+V30+W30+Z30+AA30+AD30+AE30+AH30+AI30 -> 0
B31: 4 | C31: =EDATE($C$7,3) -> 46388 | D31: =$C$8-(F31+J31+N31+R31+V31+Z31+AD31+AH31) -> 0 | E31: =IF(H30>0.5,H30*(1+E$23)+E$24,0) -> 0 | F31: =MIN(F$23,E31) -> 0 | G31: =IF(AND(F$24=1,OR(E$25="",$C31>=E$25)),MAX(0,MIN(E31-F31,$D31-(0))),0) -> 0 | H31: =E31-F31-G31 -> 0 | I31: =IF(L30>0.5,L30*(1+I$23)+I$24,0) -> 0 | J31: =MIN(J$23,I31) -> 0 | K31: =IF(AND(J$24=1,OR(I$25="",$C31>=I$25)),MAX(0,MIN(I31-J31,$D31-(G31))),0) -> 0 | L31: =I31-J31-K31 -> 0 | M31: =IF(P30>0.5,P30*(1+M$23)+M$24,0) -> 0 | N31: =MIN(N$23,M31) -> 0 | O31: =IF(AND(N$24=1,OR(M$25="",$C31>=M$25)),MAX(0,MIN(M31-N31,$D31-(G31+K31))),0) -> 0 | P31: =M31-N31-O31 -> 0 | Q31: =IF(T30>0.5,T30*(1+Q$23)+Q$24,0) -> 0 | R31: =MIN(R$23,Q31) -> 0 | S31: =IF(AND(R$24=1,OR(Q$25="",$C31>=Q$25)),MAX(0,MIN(Q31-R31,$D31-(G31+K31+O31))),0) -> 0 | T31: =Q31-R31-S31 -> 0 | U31: =IF(X30>0.5,X30*(1+U$23)+U$24,0) -> 0 | V31: =MIN(V$23,U31) -> 0 | W31: =IF(AND(V$24=1,OR(U$25="",$C31>=U$25)),MAX(0,MIN(U31-V31,$D31-(G31+K31+O31+S31))),0) -> 0 | X31: =U31-V31-W31 -> 0 | Y31: =IF(AB30>0.5,AB30*(1+Y$23)+Y$24,0) -> 0 | Z31: =MIN(Z$23,Y31) -> 0 | AA31: =IF(AND(Z$24=1,OR(Y$25="",$C31>=Y$25)),MAX(0,MIN(Y31-Z31,$D31-(G31+K31+O31+S31+W31))),0) -> 0 | AB31: =Y31-Z31-AA31 -> 0 | AC31: =IF(AF30>0.5,AF30*(1+AC$23)+AC$24,0) -> 0 | AD31: =MIN(AD$23,AC31) -> 0 | AE31: =IF(AND(AD$24=1,OR(AC$25="",$C31>=AC$25)),MAX(0,MIN(AC31-AD31,$D31-(G31+K31+O31+S31+W31+AA31))),0) -> 0 | AF31: =AC31-AD31-AE31 -> 0 | AG31: =IF(AJ30>0.5,AJ30*(1+AG$23)+AG$24,0) -> 0 | AH31: =MIN(AH$23,AG31) -> 0 | AI31: =IF(AND(AH$24=1,OR(AG$25="",$C31>=AG$25)),MAX(0,MIN(AG31-AH31,$D31-(G31+K31+O31+S31+W31+AA31+AE31))),0) -> 0 | AJ31: =AG31-AH31-AI31 -> 0 | AK31: =IF(AK30>0.5,AK30*(1+$E$12)+$G$12-MIN($F$12,AK30*(1+$E$12)+$G$12),0) -> 0 | AL31: =IF(AL30>0.5,AL30*(1+$E$13)+$G$13-MIN($F$13,AL30*(1+$E$13)+$G$13),0) -> 0 | AM31: =IF(AM30>0.5,AM30*(1+$E$14)+$G$14-MIN($F$14,AM30*(1+$E$14)+$G$14),0) -> 0 | AN31: =IF(AN30>0.5,AN30*(1+$E$15)+$G$15-MIN($F$15,AN30*(1+$E$15)+$G$15),0) -> 0 | AO31: =IF(AO30>0.5,AO30*(1+$E$16)+$G$16-MIN($F$16,AO30*(1+$E$16)+$G$16),0) -> 0 | AP31: =IF(AP30>0.5,AP30*(1+$E$17)+$G$17-MIN($F$17,AP30*(1+$E$17)+$G$17),0) -> 0 | AQ31: =IF(AQ30>0.5,AQ30*(1+$E$18)+$G$18-MIN($F$18,AQ30*(1+$E$18)+$G$18),0) -> 0 | AR31: =IF(AR30>0.5,AR30*(1+$E$19)+$G$19-MIN($F$19,AR30*(1+$E$19)+$G$19),0) -> 0 | AS31: =H31+L31+P31+T31+X31+AB31+AF31+AJ31 -> 0 | AT31: =SUM(AK31:AR31) -> 0 | AU31: =F31+G31+J31+K31+N31+O31+R31+S31+V31+W31+Z31+AA31+AD31+AE31+AH31+AI31 -> 0
B32: 5 | C32: =EDATE($C$7,4) -> 46419 | D32: =$C$8-(F32+J32+N32+R32+V32+Z32+AD32+AH32) -> 0 | E32: =IF(H31>0.5,H31*(1+E$23)+E$24,0) -> 0 | F32: =MIN(F$23,E32) -> 0 | G32: =IF(AND(F$24=1,OR(E$25="",$C32>=E$25)),MAX(0,MIN(E32-F32,$D32-(0))),0) -> 0 | H32: =E32-F32-G32 -> 0 | I32: =IF(L31>0.5,L31*(1+I$23)+I$24,0) -> 0 | J32: =MIN(J$23,I32) -> 0 | K32: =IF(AND(J$24=1,OR(I$25="",$C32>=I$25)),MAX(0,MIN(I32-J32,$D32-(G32))),0) -> 0 | L32: =I32-J32-K32 -> 0 | M32: =IF(P31>0.5,P31*(1+M$23)+M$24,0) -> 0 | N32: =MIN(N$23,M32) -> 0 | O32: =IF(AND(N$24=1,OR(M$25="",$C32>=M$25)),MAX(0,MIN(M32-N32,$D32-(G32+K32))),0) -> 0 | P32: =M32-N32-O32 -> 0 | Q32: =IF(T31>0.5,T31*(1+Q$23)+Q$24,0) -> 0 | R32: =MIN(R$23,Q32) -> 0 | S32: =IF(AND(R$24=1,OR(Q$25="",$C32>=Q$25)),MAX(0,MIN(Q32-R32,$D32-(G32+K32+O32))),0) -> 0 | T32: =Q32-R32-S32 -> 0 | U32: =IF(X31>0.5,X31*(1+U$23)+U$24,0) -> 0 | V32: =MIN(V$23,U32) -> 0 | W32: =IF(AND(V$24=1,OR(U$25="",$C32>=U$25)),MAX(0,MIN(U32-V32,$D32-(G32+K32+O32+S32))),0) -> 0 | X32: =U32-V32-W32 -> 0 | Y32: =IF(AB31>0.5,AB31*(1+Y$23)+Y$24,0) -> 0 | Z32: =MIN(Z$23,Y32) -> 0 | AA32: =IF(AND(Z$24=1,OR(Y$25="",$C32>=Y$25)),MAX(0,MIN(Y32-Z32,$D32-(G32+K32+O32+S32+W32))),0) -> 0 | AB32: =Y32-Z32-AA32 -> 0 | AC32: =IF(AF31>0.5,AF31*(1+AC$23)+AC$24,0) -> 0 | AD32: =MIN(AD$23,AC32) -> 0 | AE32: =IF(AND(AD$24=1,OR(AC$25="",$C32>=AC$25)),MAX(0,MIN(AC32-AD32,$D32-(G32+K32+O32+S32+W32+AA32))),0) -> 0 | AF32: =AC32-AD32-AE32 -> 0 | AG32: =IF(AJ31>0.5,AJ31*(1+AG$23)+AG$24,0) -> 0 | AH32: =MIN(AH$23,AG32) -> 0 | AI32: =IF(AND(AH$24=1,OR(AG$25="",$C32>=AG$25)),MAX(0,MIN(AG32-AH32,$D32-(G32+K32+O32+S32+W32+AA32+AE32))),0) -> 0 | AJ32: =AG32-AH32-AI32 -> 0 | AK32: =IF(AK31>0.5,AK31*(1+$E$12)+$G$12-MIN($F$12,AK31*(1+$E$12)+$G$12),0) -> 0 | AL32: =IF(AL31>0.5,AL31*(1+$E$13)+$G$13-MIN($F$13,AL31*(1+$E$13)+$G$13),0) -> 0 | AM32: =IF(AM31>0.5,AM31*(1+$E$14)+$G$14-MIN($F$14,AM31*(1+$E$14)+$G$14),0) -> 0 | AN32: =IF(AN31>0.5,AN31*(1+$E$15)+$G$15-MIN($F$15,AN31*(1+$E$15)+$G$15),0) -> 0 | AO32: =IF(AO31>0.5,AO31*(1+$E$16)+$G$16-MIN($F$16,AO31*(1+$E$16)+$G$16),0) -> 0 | AP32: =IF(AP31>0.5,AP31*(1+$E$17)+$G$17-MIN($F$17,AP31*(1+$E$17)+$G$17),0) -> 0 | AQ32: =IF(AQ31>0.5,AQ31*(1+$E$18)+$G$18-MIN($F$18,AQ31*(1+$E$18)+$G$18),0) -> 0 | AR32: =IF(AR31>0.5,AR31*(1+$E$19)+$G$19-MIN($F$19,AR31*(1+$E$19)+$G$19),0) -> 0 | AS32: =H32+L32+P32+T32+X32+AB32+AF32+AJ32 -> 0 | AT32: =SUM(AK32:AR32) -> 0 | AU32: =F32+G32+J32+K32+N32+O32+R32+S32+V32+W32+Z32+AA32+AD32+AE32+AH32+AI32 -> 0
B33: 6 | C33: =EDATE($C$7,5) -> 46447 | D33: =$C$8-(F33+J33+N33+R33+V33+Z33+AD33+AH33) -> 0 | E33: =IF(H32>0.5,H32*(1+E$23)+E$24,0) -> 0 | F33: =MIN(F$23,E33) -> 0 | G33: =IF(AND(F$24=1,OR(E$25="",$C33>=E$25)),MAX(0,MIN(E33-F33,$D33-(0))),0) -> 0 | H33: =E33-F33-G33 -> 0 | I33: =IF(L32>0.5,L32*(1+I$23)+I$24,0) -> 0 | J33: =MIN(J$23,I33) -> 0 | K33: =IF(AND(J$24=1,OR(I$25="",$C33>=I$25)),MAX(0,MIN(I33-J33,$D33-(G33))),0) -> 0 | L33: =I33-J33-K33 -> 0 | M33: =IF(P32>0.5,P32*(1+M$23)+M$24,0) -> 0 | N33: =MIN(N$23,M33) -> 0 | O33: =IF(AND(N$24=1,OR(M$25="",$C33>=M$25)),MAX(0,MIN(M33-N33,$D33-(G33+K33))),0) -> 0 | P33: =M33-N33-O33 -> 0 | Q33: =IF(T32>0.5,T32*(1+Q$23)+Q$24,0) -> 0 | R33: =MIN(R$23,Q33) -> 0 | S33: =IF(AND(R$24=1,OR(Q$25="",$C33>=Q$25)),MAX(0,MIN(Q33-R33,$D33-(G33+K33+O33))),0) -> 0 | T33: =Q33-R33-S33 -> 0 | U33: =IF(X32>0.5,X32*(1+U$23)+U$24,0) -> 0 | V33: =MIN(V$23,U33) -> 0 | W33: =IF(AND(V$24=1,OR(U$25="",$C33>=U$25)),MAX(0,MIN(U33-V33,$D33-(G33+K33+O33+S33))),0) -> 0 | X33: =U33-V33-W33 -> 0 | Y33: =IF(AB32>0.5,AB32*(1+Y$23)+Y$24,0) -> 0 | Z33: =MIN(Z$23,Y33) -> 0 | AA33: =IF(AND(Z$24=1,OR(Y$25="",$C33>=Y$25)),MAX(0,MIN(Y33-Z33,$D33-(G33+K33+O33+S33+W33))),0) -> 0 | AB33: =Y33-Z33-AA33 -> 0 | AC33: =IF(AF32>0.5,AF32*(1+AC$23)+AC$24,0) -> 0 | AD33: =MIN(AD$23,AC33) -> 0 | AE33: =IF(AND(AD$24=1,OR(AC$25="",$C33>=AC$25)),MAX(0,MIN(AC33-AD33,$D33-(G33+K33+O33+S33+W33+AA33))),0) -> 0 | AF33: =AC33-AD33-AE33 -> 0 | AG33: =IF(AJ32>0.5,AJ32*(1+AG$23)+AG$24,0) -> 0 | AH33: =MIN(AH$23,AG33) -> 0 | AI33: =IF(AND(AH$24=1,OR(AG$25="",$C33>=AG$25)),MAX(0,MIN(AG33-AH33,$D33-(G33+K33+O33+S33+W33+AA33+AE33))),0) -> 0 | AJ33: =AG33-AH33-AI33 -> 0 | AK33: =IF(AK32>0.5,AK32*(1+$E$12)+$G$12-MIN($F$12,AK32*(1+$E$12)+$G$12),0) -> 0 | AL33: =IF(AL32>0.5,AL32*(1+$E$13)+$G$13-MIN($F$13,AL32*(1+$E$13)+$G$13),0) -> 0 | AM33: =IF(AM32>0.5,AM32*(1+$E$14)+$G$14-MIN($F$14,AM32*(1+$E$14)+$G$14),0) -> 0 | AN33: =IF(AN32>0.5,AN32*(1+$E$15)+$G$15-MIN($F$15,AN32*(1+$E$15)+$G$15),0) -> 0 | AO33: =IF(AO32>0.5,AO32*(1+$E$16)+$G$16-MIN($F$16,AO32*(1+$E$16)+$G$16),0) -> 0 | AP33: =IF(AP32>0.5,AP32*(1+$E$17)+$G$17-MIN($F$17,AP32*(1+$E$17)+$G$17),0) -> 0 | AQ33: =IF(AQ32>0.5,AQ32*(1+$E$18)+$G$18-MIN($F$18,AQ32*(1+$E$18)+$G$18),0) -> 0 | AR33: =IF(AR32>0.5,AR32*(1+$E$19)+$G$19-MIN($F$19,AR32*(1+$E$19)+$G$19),0) -> 0 | AS33: =H33+L33+P33+T33+X33+AB33+AF33+AJ33 -> 0 | AT33: =SUM(AK33:AR33) -> 0 | AU33: =F33+G33+J33+K33+N33+O33+R33+S33+V33+W33+Z33+AA33+AD33+AE33+AH33+AI33 -> 0
B34: 7 | C34: =EDATE($C$7,6) -> 46478 | D34: =$C$8-(F34+J34+N34+R34+V34+Z34+AD34+AH34) -> 0 | E34: =IF(H33>0.5,H33*(1+E$23)+E$24,0) -> 0 | F34: =MIN(F$23,E34) -> 0 | G34: =IF(AND(F$24=1,OR(E$25="",$C34>=E$25)),MAX(0,MIN(E34-F34,$D34-(0))),0) -> 0 | H34: =E34-F34-G34 -> 0 | I34: =IF(L33>0.5,L33*(1+I$23)+I$24,0) -> 0 | J34: =MIN(J$23,I34) -> 0 | K34: =IF(AND(J$24=1,OR(I$25="",$C34>=I$25)),MAX(0,MIN(I34-J34,$D34-(G34))),0) -> 0 | L34: =I34-J34-K34 -> 0 | M34: =IF(P33>0.5,P33*(1+M$23)+M$24,0) -> 0 | N34: =MIN(N$23,M34) -> 0 | O34: =IF(AND(N$24=1,OR(M$25="",$C34>=M$25)),MAX(0,MIN(M34-N34,$D34-(G34+K34))),0) -> 0 | P34: =M34-N34-O34 -> 0 | Q34: =IF(T33>0.5,T33*(1+Q$23)+Q$24,0) -> 0 | R34: =MIN(R$23,Q34) -> 0 | S34: =IF(AND(R$24=1,OR(Q$25="",$C34>=Q$25)),MAX(0,MIN(Q34-R34,$D34-(G34+K34+O34))),0) -> 0 | T34: =Q34-R34-S34 -> 0 | U34: =IF(X33>0.5,X33*(1+U$23)+U$24,0) -> 0 | V34: =MIN(V$23,U34) -> 0 | W34: =IF(AND(V$24=1,OR(U$25="",$C34>=U$25)),MAX(0,MIN(U34-V34,$D34-(G34+K34+O34+S34))),0) -> 0 | X34: =U34-V34-W34 -> 0 | Y34: =IF(AB33>0.5,AB33*(1+Y$23)+Y$24,0) -> 0 | Z34: =MIN(Z$23,Y34) -> 0 | AA34: =IF(AND(Z$24=1,OR(Y$25="",$C34>=Y$25)),MAX(0,MIN(Y34-Z34,$D34-(G34+K34+O34+S34+W34))),0) -> 0 | AB34: =Y34-Z34-AA34 -> 0 | AC34: =IF(AF33>0.5,AF33*(1+AC$23)+AC$24,0) -> 0 | AD34: =MIN(AD$23,AC34) -> 0 | AE34: =IF(AND(AD$24=1,OR(AC$25="",$C34>=AC$25)),MAX(0,MIN(AC34-AD34,$D34-(G34+K34+O34+S34+W34+AA34))),0) -> 0 | AF34: =AC34-AD34-AE34 -> 0 | AG34: =IF(AJ33>0.5,AJ33*(1+AG$23)+AG$24,0) -> 0 | AH34: =MIN(AH$23,AG34) -> 0 | AI34: =IF(AND(AH$24=1,OR(AG$25="",$C34>=AG$25)),MAX(0,MIN(AG34-AH34,$D34-(G34+K34+O34+S34+W34+AA34+AE34))),0) -> 0 | AJ34: =AG34-AH34-AI34 -> 0 | AK34: =IF(AK33>0.5,AK33*(1+$E$12)+$G$12-MIN($F$12,AK33*(1+$E$12)+$G$12),0) -> 0 | AL34: =IF(AL33>0.5,AL33*(1+$E$13)+$G$13-MIN($F$13,AL33*(1+$E$13)+$G$13),0) -> 0 | AM34: =IF(AM33>0.5,AM33*(1+$E$14)+$G$14-MIN($F$14,AM33*(1+$E$14)+$G$14),0) -> 0 | AN34: =IF(AN33>0.5,AN33*(1+$E$15)+$G$15-MIN($F$15,AN33*(1+$E$15)+$G$15),0) -> 0 | AO34: =IF(AO33>0.5,AO33*(1+$E$16)+$G$16-MIN($F$16,AO33*(1+$E$16)+$G$16),0) -> 0 | AP34: =IF(AP33>0.5,AP33*(1+$E$17)+$G$17-MIN($F$17,AP33*(1+$E$17)+$G$17),0) -> 0 | AQ34: =IF(AQ33>0.5,AQ33*(1+$E$18)+$G$18-MIN($F$18,AQ33*(1+$E$18)+$G$18),0) -> 0 | AR34: =IF(AR33>0.5,AR33*(1+$E$19)+$G$19-MIN($F$19,AR33*(1+$E$19)+$G$19),0) -> 0 | AS34: =H34+L34+P34+T34+X34+AB34+AF34+AJ34 -> 0 | AT34: =SUM(AK34:AR34) -> 0 | AU34: =F34+G34+J34+K34+N34+O34+R34+S34+V34+W34+Z34+AA34+AD34+AE34+AH34+AI34 -> 0
B35: 8 | C35: =EDATE($C$7,7) -> 46508 | D35: =$C$8-(F35+J35+N35+R35+V35+Z35+AD35+AH35) -> 0 | E35: =IF(H34>0.5,H34*(1+E$23)+E$24,0) -> 0 | F35: =MIN(F$23,E35) -> 0 | G35: =IF(AND(F$24=1,OR(E$25="",$C35>=E$25)),MAX(0,MIN(E35-F35,$D35-(0))),0) -> 0 | H35: =E35-F35-G35 -> 0 | I35: =IF(L34>0.5,L34*(1+I$23)+I$24,0) -> 0 | J35: =MIN(J$23,I35) -> 0 | K35: =IF(AND(J$24=1,OR(I$25="",$C35>=I$25)),MAX(0,MIN(I35-J35,$D35-(G35))),0) -> 0 | L35: =I35-J35-K35 -> 0 | M35: =IF(P34>0.5,P34*(1+M$23)+M$24,0) -> 0 | N35: =MIN(N$23,M35) -> 0 | O35: =IF(AND(N$24=1,OR(M$25="",$C35>=M$25)),MAX(0,MIN(M35-N35,$D35-(G35+K35))),0) -> 0 | P35: =M35-N35-O35 -> 0 | Q35: =IF(T34>0.5,T34*(1+Q$23)+Q$24,0) -> 0 | R35: =MIN(R$23,Q35) -> 0 | S35: =IF(AND(R$24=1,OR(Q$25="",$C35>=Q$25)),MAX(0,MIN(Q35-R35,$D35-(G35+K35+O35))),0) -> 0 | T35: =Q35-R35-S35 -> 0 | U35: =IF(X34>0.5,X34*(1+U$23)+U$24,0) -> 0 | V35: =MIN(V$23,U35) -> 0 | W35: =IF(AND(V$24=1,OR(U$25="",$C35>=U$25)),MAX(0,MIN(U35-V35,$D35-(G35+K35+O35+S35))),0) -> 0 | X35: =U35-V35-W35 -> 0 | Y35: =IF(AB34>0.5,AB34*(1+Y$23)+Y$24,0) -> 0 | Z35: =MIN(Z$23,Y35) -> 0 | AA35: =IF(AND(Z$24=1,OR(Y$25="",$C35>=Y$25)),MAX(0,MIN(Y35-Z35,$D35-(G35+K35+O35+S35+W35))),0) -> 0 | AB35: =Y35-Z35-AA35 -> 0 | AC35: =IF(AF34>0.5,AF34*(1+AC$23)+AC$24,0) -> 0 | AD35: =MIN(AD$23,AC35) -> 0 | AE35: =IF(AND(AD$24=1,OR(AC$25="",$C35>=AC$25)),MAX(0,MIN(AC35-AD35,$D35-(G35+K35+O35+S35+W35+AA35))),0) -> 0 | AF35: =AC35-AD35-AE35 -> 0 | AG35: =IF(AJ34>0.5,AJ34*(1+AG$23)+AG$24,0) -> 0 | AH35: =MIN(AH$23,AG35) -> 0 | AI35: =IF(AND(AH$24=1,OR(AG$25="",$C35>=AG$25)),MAX(0,MIN(AG35-AH35,$D35-(G35+K35+O35+S35+W35+AA35+AE35))),0) -> 0 | AJ35: =AG35-AH35-AI35 -> 0 | AK35: =IF(AK34>0.5,AK34*(1+$E$12)+$G$12-MIN($F$12,AK34*(1+$E$12)+$G$12),0) -> 0 | AL35: =IF(AL34>0.5,AL34*(1+$E$13)+$G$13-MIN($F$13,AL34*(1+$E$13)+$G$13),0) -> 0 | AM35: =IF(AM34>0.5,AM34*(1+$E$14)+$G$14-MIN($F$14,AM34*(1+$E$14)+$G$14),0) -> 0 | AN35: =IF(AN34>0.5,AN34*(1+$E$15)+$G$15-MIN($F$15,AN34*(1+$E$15)+$G$15),0) -> 0 | AO35: =IF(AO34>0.5,AO34*(1+$E$16)+$G$16-MIN($F$16,AO34*(1+$E$16)+$G$16),0) -> 0 | AP35: =IF(AP34>0.5,AP34*(1+$E$17)+$G$17-MIN($F$17,AP34*(1+$E$17)+$G$17),0) -> 0 | AQ35: =IF(AQ34>0.5,AQ34*(1+$E$18)+$G$18-MIN($F$18,AQ34*(1+$E$18)+$G$18),0) -> 0 | AR35: =IF(AR34>0.5,AR34*(1+$E$19)+$G$19-MIN($F$19,AR34*(1+$E$19)+$G$19),0) -> 0 | AS35: =H35+L35+P35+T35+X35+AB35+AF35+AJ35 -> 0 | AT35: =SUM(AK35:AR35) -> 0 | AU35: =F35+G35+J35+K35+N35+O35+R35+S35+V35+W35+Z35+AA35+AD35+AE35+AH35+AI35 -> 0
B36: 9 | C36: =EDATE($C$7,8) -> 46539 | D36: =$C$8-(F36+J36+N36+R36+V36+Z36+AD36+AH36) -> 0 | E36: =IF(H35>0.5,H35*(1+E$23)+E$24,0) -> 0 | F36: =MIN(F$23,E36) -> 0 | G36: =IF(AND(F$24=1,OR(E$25="",$C36>=E$25)),MAX(0,MIN(E36-F36,$D36-(0))),0) -> 0 | H36: =E36-F36-G36 -> 0 | I36: =IF(L35>0.5,L35*(1+I$23)+I$24,0) -> 0 | J36: =MIN(J$23,I36) -> 0 | K36: =IF(AND(J$24=1,OR(I$25="",$C36>=I$25)),MAX(0,MIN(I36-J36,$D36-(G36))),0) -> 0 | L36: =I36-J36-K36 -> 0 | M36: =IF(P35>0.5,P35*(1+M$23)+M$24,0) -> 0 | N36: =MIN(N$23,M36) -> 0 | O36: =IF(AND(N$24=1,OR(M$25="",$C36>=M$25)),MAX(0,MIN(M36-N36,$D36-(G36+K36))),0) -> 0 | P36: =M36-N36-O36 -> 0 | Q36: =IF(T35>0.5,T35*(1+Q$23)+Q$24,0) -> 0 | R36: =MIN(R$23,Q36) -> 0 | S36: =IF(AND(R$24=1,OR(Q$25="",$C36>=Q$25)),MAX(0,MIN(Q36-R36,$D36-(G36+K36+O36))),0) -> 0 | T36: =Q36-R36-S36 -> 0 | U36: =IF(X35>0.5,X35*(1+U$23)+U$24,0) -> 0 | V36: =MIN(V$23,U36) -> 0 | W36: =IF(AND(V$24=1,OR(U$25="",$C36>=U$25)),MAX(0,MIN(U36-V36,$D36-(G36+K36+O36+S36))),0) -> 0 | X36: =U36-V36-W36 -> 0 | Y36: =IF(AB35>0.5,AB35*(1+Y$23)+Y$24,0) -> 0 | Z36: =MIN(Z$23,Y36) -> 0 | AA36: =IF(AND(Z$24=1,OR(Y$25="",$C36>=Y$25)),MAX(0,MIN(Y36-Z36,$D36-(G36+K36+O36+S36+W36))),0) -> 0 | AB36: =Y36-Z36-AA36 -> 0 | AC36: =IF(AF35>0.5,AF35*(1+AC$23)+AC$24,0) -> 0 | AD36: =MIN(AD$23,AC36) -> 0 | AE36: =IF(AND(AD$24=1,OR(AC$25="",$C36>=AC$25)),MAX(0,MIN(AC36-AD36,$D36-(G36+K36+O36+S36+W36+AA36))),0) -> 0 | AF36: =AC36-AD36-AE36 -> 0 | AG36: =IF(AJ35>0.5,AJ35*(1+AG$23)+AG$24,0) -> 0 | AH36: =MIN(AH$23,AG36) -> 0 | AI36: =IF(AND(AH$24=1,OR(AG$25="",$C36>=AG$25)),MAX(0,MIN(AG36-AH36,$D36-(G36+K36+O36+S36+W36+AA36+AE36))),0) -> 0 | AJ36: =AG36-AH36-AI36 -> 0 | AK36: =IF(AK35>0.5,AK35*(1+$E$12)+$G$12-MIN($F$12,AK35*(1+$E$12)+$G$12),0) -> 0 | AL36: =IF(AL35>0.5,AL35*(1+$E$13)+$G$13-MIN($F$13,AL35*(1+$E$13)+$G$13),0) -> 0 | AM36: =IF(AM35>0.5,AM35*(1+$E$14)+$G$14-MIN($F$14,AM35*(1+$E$14)+$G$14),0) -> 0 | AN36: =IF(AN35>0.5,AN35*(1+$E$15)+$G$15-MIN($F$15,AN35*(1+$E$15)+$G$15),0) -> 0 | AO36: =IF(AO35>0.5,AO35*(1+$E$16)+$G$16-MIN($F$16,AO35*(1+$E$16)+$G$16),0) -> 0 | AP36: =IF(AP35>0.5,AP35*(1+$E$17)+$G$17-MIN($F$17,AP35*(1+$E$17)+$G$17),0) -> 0 | AQ36: =IF(AQ35>0.5,AQ35*(1+$E$18)+$G$18-MIN($F$18,AQ35*(1+$E$18)+$G$18),0) -> 0 | AR36: =IF(AR35>0.5,AR35*(1+$E$19)+$G$19-MIN($F$19,AR35*(1+$E$19)+$G$19),0) -> 0 | AS36: =H36+L36+P36+T36+X36+AB36+AF36+AJ36 -> 0 | AT36: =SUM(AK36:AR36) -> 0 | AU36: =F36+G36+J36+K36+N36+O36+R36+S36+V36+W36+Z36+AA36+AD36+AE36+AH36+AI36 -> 0
B37: 10 | C37: =EDATE($C$7,9) -> 46569 | D37: =$C$8-(F37+J37+N37+R37+V37+Z37+AD37+AH37) -> 0 | E37: =IF(H36>0.5,H36*(1+E$23)+E$24,0) -> 0 | F37: =MIN(F$23,E37) -> 0 | G37: =IF(AND(F$24=1,OR(E$25="",$C37>=E$25)),MAX(0,MIN(E37-F37,$D37-(0))),0) -> 0 | H37: =E37-F37-G37 -> 0 | I37: =IF(L36>0.5,L36*(1+I$23)+I$24,0) -> 0 | J37: =MIN(J$23,I37) -> 0 | K37: =IF(AND(J$24=1,OR(I$25="",$C37>=I$25)),MAX(0,MIN(I37-J37,$D37-(G37))),0) -> 0 | L37: =I37-J37-K37 -> 0 | M37: =IF(P36>0.5,P36*(1+M$23)+M$24,0) -> 0 | N37: =MIN(N$23,M37) -> 0 | O37: =IF(AND(N$24=1,OR(M$25="",$C37>=M$25)),MAX(0,MIN(M37-N37,$D37-(G37+K37))),0) -> 0 | P37: =M37-N37-O37 -> 0 | Q37: =IF(T36>0.5,T36*(1+Q$23)+Q$24,0) -> 0 | R37: =MIN(R$23,Q37) -> 0 | S37: =IF(AND(R$24=1,OR(Q$25="",$C37>=Q$25)),MAX(0,MIN(Q37-R37,$D37-(G37+K37+O37))),0) -> 0 | T37: =Q37-R37-S37 -> 0 | U37: =IF(X36>0.5,X36*(1+U$23)+U$24,0) -> 0 | V37: =MIN(V$23,U37) -> 0 | W37: =IF(AND(V$24=1,OR(U$25="",$C37>=U$25)),MAX(0,MIN(U37-V37,$D37-(G37+K37+O37+S37))),0) -> 0 | X37: =U37-V37-W37 -> 0 | Y37: =IF(AB36>0.5,AB36*(1+Y$23)+Y$24,0) -> 0 | Z37: =MIN(Z$23,Y37) -> 0 | AA37: =IF(AND(Z$24=1,OR(Y$25="",$C37>=Y$25)),MAX(0,MIN(Y37-Z37,$D37-(G37+K37+O37+S37+W37))),0) -> 0 | AB37: =Y37-Z37-AA37 -> 0 | AC37: =IF(AF36>0.5,AF36*(1+AC$23)+AC$24,0) -> 0 | AD37: =MIN(AD$23,AC37) -> 0 | AE37: =IF(AND(AD$24=1,OR(AC$25="",$C37>=AC$25)),MAX(0,MIN(AC37-AD37,$D37-(G37+K37+O37+S37+W37+AA37))),0) -> 0 | AF37: =AC37-AD37-AE37 -> 0 | AG37: =IF(AJ36>0.5,AJ36*(1+AG$23)+AG$24,0) -> 0 | AH37: =MIN(AH$23,AG37) -> 0 | AI37: =IF(AND(AH$24=1,OR(AG$25="",$C37>=AG$25)),MAX(0,MIN(AG37-AH37,$D37-(G37+K37+O37+S37+W37+AA37+AE37))),0) -> 0 | AJ37: =AG37-AH37-AI37 -> 0 | AK37: =IF(AK36>0.5,AK36*(1+$E$12)+$G$12-MIN($F$12,AK36*(1+$E$12)+$G$12),0) -> 0 | AL37: =IF(AL36>0.5,AL36*(1+$E$13)+$G$13-MIN($F$13,AL36*(1+$E$13)+$G$13),0) -> 0 | AM37: =IF(AM36>0.5,AM36*(1+$E$14)+$G$14-MIN($F$14,AM36*(1+$E$14)+$G$14),0) -> 0 | AN37: =IF(AN36>0.5,AN36*(1+$E$15)+$G$15-MIN($F$15,AN36*(1+$E$15)+$G$15),0) -> 0 | AO37: =IF(AO36>0.5,AO36*(1+$E$16)+$G$16-MIN($F$16,AO36*(1+$E$16)+$G$16),0) -> 0 | AP37: =IF(AP36>0.5,AP36*(1+$E$17)+$G$17-MIN($F$17,AP36*(1+$E$17)+$G$17),0) -> 0 | AQ37: =IF(AQ36>0.5,AQ36*(1+$E$18)+$G$18-MIN($F$18,AQ36*(1+$E$18)+$G$18),0) -> 0 | AR37: =IF(AR36>0.5,AR36*(1+$E$19)+$G$19-MIN($F$19,AR36*(1+$E$19)+$G$19),0) -> 0 | AS37: =H37+L37+P37+T37+X37+AB37+AF37+AJ37 -> 0 | AT37: =SUM(AK37:AR37) -> 0 | AU37: =F37+G37+J37+K37+N37+O37+R37+S37+V37+W37+Z37+AA37+AD37+AE37+AH37+AI37 -> 0
B38: 11 | C38: =EDATE($C$7,10) -> 46600 | D38: =$C$8-(F38+J38+N38+R38+V38+Z38+AD38+AH38) -> 0 | E38: =IF(H37>0.5,H37*(1+E$23)+E$24,0) -> 0 | F38: =MIN(F$23,E38) -> 0 | G38: =IF(AND(F$24=1,OR(E$25="",$C38>=E$25)),MAX(0,MIN(E38-F38,$D38-(0))),0) -> 0 | H38: =E38-F38-G38 -> 0 | I38: =IF(L37>0.5,L37*(1+I$23)+I$24,0) -> 0 | J38: =MIN(J$23,I38) -> 0 | K38: =IF(AND(J$24=1,OR(I$25="",$C38>=I$25)),MAX(0,MIN(I38-J38,$D38-(G38))),0) -> 0 | L38: =I38-J38-K38 -> 0 | M38: =IF(P37>0.5,P37*(1+M$23)+M$24,0) -> 0 | N38: =MIN(N$23,M38) -> 0 | O38: =IF(AND(N$24=1,OR(M$25="",$C38>=M$25)),MAX(0,MIN(M38-N38,$D38-(G38+K38))),0) -> 0 | P38: =M38-N38-O38 -> 0 | Q38: =IF(T37>0.5,T37*(1+Q$23)+Q$24,0) -> 0 | R38: =MIN(R$23,Q38) -> 0 | S38: =IF(AND(R$24=1,OR(Q$25="",$C38>=Q$25)),MAX(0,MIN(Q38-R38,$D38-(G38+K38+O38))),0) -> 0 | T38: =Q38-R38-S38 -> 0 | U38: =IF(X37>0.5,X37*(1+U$23)+U$24,0) -> 0 | V38: =MIN(V$23,U38) -> 0 | W38: =IF(AND(V$24=1,OR(U$25="",$C38>=U$25)),MAX(0,MIN(U38-V38,$D38-(G38+K38+O38+S38))),0) -> 0 | X38: =U38-V38-W38 -> 0 | Y38: =IF(AB37>0.5,AB37*(1+Y$23)+Y$24,0) -> 0 | Z38: =MIN(Z$23,Y38) -> 0 | AA38: =IF(AND(Z$24=1,OR(Y$25="",$C38>=Y$25)),MAX(0,MIN(Y38-Z38,$D38-(G38+K38+O38+S38+W38))),0) -> 0 | AB38: =Y38-Z38-AA38 -> 0 | AC38: =IF(AF37>0.5,AF37*(1+AC$23)+AC$24,0) -> 0 | AD38: =MIN(AD$23,AC38) -> 0 | AE38: =IF(AND(AD$24=1,OR(AC$25="",$C38>=AC$25)),MAX(0,MIN(AC38-AD38,$D38-(G38+K38+O38+S38+W38+AA38))),0) -> 0 | AF38: =AC38-AD38-AE38 -> 0 | AG38: =IF(AJ37>0.5,AJ37*(1+AG$23)+AG$24,0) -> 0 | AH38: =MIN(AH$23,AG38) -> 0 | AI38: =IF(AND(AH$24=1,OR(AG$25="",$C38>=AG$25)),MAX(0,MIN(AG38-AH38,$D38-(G38+K38+O38+S38+W38+AA38+AE38))),0) -> 0 | AJ38: =AG38-AH38-AI38 -> 0 | AK38: =IF(AK37>0.5,AK37*(1+$E$12)+$G$12-MIN($F$12,AK37*(1+$E$12)+$G$12),0) -> 0 | AL38: =IF(AL37>0.5,AL37*(1+$E$13)+$G$13-MIN($F$13,AL37*(1+$E$13)+$G$13),0) -> 0 | AM38: =IF(AM37>0.5,AM37*(1+$E$14)+$G$14-MIN($F$14,AM37*(1+$E$14)+$G$14),0) -> 0 | AN38: =IF(AN37>0.5,AN37*(1+$E$15)+$G$15-MIN($F$15,AN37*(1+$E$15)+$G$15),0) -> 0 | AO38: =IF(AO37>0.5,AO37*(1+$E$16)+$G$16-MIN($F$16,AO37*(1+$E$16)+$G$16),0) -> 0 | AP38: =IF(AP37>0.5,AP37*(1+$E$17)+$G$17-MIN($F$17,AP37*(1+$E$17)+$G$17),0) -> 0 | AQ38: =IF(AQ37>0.5,AQ37*(1+$E$18)+$G$18-MIN($F$18,AQ37*(1+$E$18)+$G$18),0) -> 0 | AR38: =IF(AR37>0.5,AR37*(1+$E$19)+$G$19-MIN($F$19,AR37*(1+$E$19)+$G$19),0) -> 0 | AS38: =H38+L38+P38+T38+X38+AB38+AF38+AJ38 -> 0 | AT38: =SUM(AK38:AR38) -> 0 | AU38: =F38+G38+J38+K38+N38+O38+R38+S38+V38+W38+Z38+AA38+AD38+AE38+AH38+AI38 -> 0
B39: 12 | C39: =EDATE($C$7,11) -> 46631 | D39: =$C$8-(F39+J39+N39+R39+V39+Z39+AD39+AH39) -> 0 | E39: =IF(H38>0.5,H38*(1+E$23)+E$24,0) -> 0 | F39: =MIN(F$23,E39) -> 0 | G39: =IF(AND(F$24=1,OR(E$25="",$C39>=E$25)),MAX(0,MIN(E39-F39,$D39-(0))),0) -> 0 | H39: =E39-F39-G39 -> 0 | I39: =IF(L38>0.5,L38*(1+I$23)+I$24,0) -> 0 | J39: =MIN(J$23,I39) -> 0 | K39: =IF(AND(J$24=1,OR(I$25="",$C39>=I$25)),MAX(0,MIN(I39-J39,$D39-(G39))),0) -> 0 | L39: =I39-J39-K39 -> 0 | M39: =IF(P38>0.5,P38*(1+M$23)+M$24,0) -> 0 | N39: =MIN(N$23,M39) -> 0 | O39: =IF(AND(N$24=1,OR(M$25="",$C39>=M$25)),MAX(0,MIN(M39-N39,$D39-(G39+K39))),0) -> 0 | P39: =M39-N39-O39 -> 0 | Q39: =IF(T38>0.5,T38*(1+Q$23)+Q$24,0) -> 0 | R39: =MIN(R$23,Q39) -> 0 | S39: =IF(AND(R$24=1,OR(Q$25="",$C39>=Q$25)),MAX(0,MIN(Q39-R39,$D39-(G39+K39+O39))),0) -> 0 | T39: =Q39-R39-S39 -> 0 | U39: =IF(X38>0.5,X38*(1+U$23)+U$24,0) -> 0 | V39: =MIN(V$23,U39) -> 0 | W39: =IF(AND(V$24=1,OR(U$25="",$C39>=U$25)),MAX(0,MIN(U39-V39,$D39-(G39+K39+O39+S39))),0) -> 0 | X39: =U39-V39-W39 -> 0 | Y39: =IF(AB38>0.5,AB38*(1+Y$23)+Y$24,0) -> 0 | Z39: =MIN(Z$23,Y39) -> 0 | AA39: =IF(AND(Z$24=1,OR(Y$25="",$C39>=Y$25)),MAX(0,MIN(Y39-Z39,$D39-(G39+K39+O39+S39+W39))),0) -> 0 | AB39: =Y39-Z39-AA39 -> 0 | AC39: =IF(AF38>0.5,AF38*(1+AC$23)+AC$24,0) -> 0 | AD39: =MIN(AD$23,AC39) -> 0 | AE39: =IF(AND(AD$24=1,OR(AC$25="",$C39>=AC$25)),MAX(0,MIN(AC39-AD39,$D39-(G39+K39+O39+S39+W39+AA39))),0) -> 0 | AF39: =AC39-AD39-AE39 -> 0 | AG39: =IF(AJ38>0.5,AJ38*(1+AG$23)+AG$24,0) -> 0 | AH39: =MIN(AH$23,AG39) -> 0 | AI39: =IF(AND(AH$24=1,OR(AG$25="",$C39>=AG$25)),MAX(0,MIN(AG39-AH39,$D39-(G39+K39+O39+S39+W39+AA39+AE39))),0) -> 0 | AJ39: =AG39-AH39-AI39 -> 0 | AK39: =IF(AK38>0.5,AK38*(1+$E$12)+$G$12-MIN($F$12,AK38*(1+$E$12)+$G$12),0) -> 0 | AL39: =IF(AL38>0.5,AL38*(1+$E$13)+$G$13-MIN($F$13,AL38*(1+$E$13)+$G$13),0) -> 0 | AM39: =IF(AM38>0.5,AM38*(1+$E$14)+$G$14-MIN($F$14,AM38*(1+$E$14)+$G$14),0) -> 0 | AN39: =IF(AN38>0.5,AN38*(1+$E$15)+$G$15-MIN($F$15,AN38*(1+$E$15)+$G$15),0) -> 0 | AO39: =IF(AO38>0.5,AO38*(1+$E$16)+$G$16-MIN($F$16,AO38*(1+$E$16)+$G$16),0) -> 0 | AP39: =IF(AP38>0.5,AP38*(1+$E$17)+$G$17-MIN($F$17,AP38*(1+$E$17)+$G$17),0) -> 0 | AQ39: =IF(AQ38>0.5,AQ38*(1+$E$18)+$G$18-MIN($F$18,AQ38*(1+$E$18)+$G$18),0) -> 0 | AR39: =IF(AR38>0.5,AR38*(1+$E$19)+$G$19-MIN($F$19,AR38*(1+$E$19)+$G$19),0) -> 0 | AS39: =H39+L39+P39+T39+X39+AB39+AF39+AJ39 -> 0 | AT39: =SUM(AK39:AR39) -> 0 | AU39: =F39+G39+J39+K39+N39+O39+R39+S39+V39+W39+Z39+AA39+AD39+AE39+AH39+AI39 -> 0
B40: 13 | C40: =EDATE($C$7,12) -> 46661 | D40: =$C$8-(F40+J40+N40+R40+V40+Z40+AD40+AH40) -> 0 | E40: =IF(H39>0.5,H39*(1+E$23)+E$24,0) -> 0 | F40: =MIN(F$23,E40) -> 0 | G40: =IF(AND(F$24=1,OR(E$25="",$C40>=E$25)),MAX(0,MIN(E40-F40,$D40-(0))),0) -> 0 | H40: =E40-F40-G40 -> 0 | I40: =IF(L39>0.5,L39*(1+I$23)+I$24,0) -> 0 | J40: =MIN(J$23,I40) -> 0 | K40: =IF(AND(J$24=1,OR(I$25="",$C40>=I$25)),MAX(0,MIN(I40-J40,$D40-(G40))),0) -> 0 | L40: =I40-J40-K40 -> 0 | M40: =IF(P39>0.5,P39*(1+M$23)+M$24,0) -> 0 | N40: =MIN(N$23,M40) -> 0 | O40: =IF(AND(N$24=1,OR(M$25="",$C40>=M$25)),MAX(0,MIN(M40-N40,$D40-(G40+K40))),0) -> 0 | P40: =M40-N40-O40 -> 0 | Q40: =IF(T39>0.5,T39*(1+Q$23)+Q$24,0) -> 0 | R40: =MIN(R$23,Q40) -> 0 | S40: =IF(AND(R$24=1,OR(Q$25="",$C40>=Q$25)),MAX(0,MIN(Q40-R40,$D40-(G40+K40+O40))),0) -> 0 | T40: =Q40-R40-S40 -> 0 | U40: =IF(X39>0.5,X39*(1+U$23)+U$24,0) -> 0 | V40: =MIN(V$23,U40) -> 0 | W40: =IF(AND(V$24=1,OR(U$25="",$C40>=U$25)),MAX(0,MIN(U40-V40,$D40-(G40+K40+O40+S40))),0) -> 0 | X40: =U40-V40-W40 -> 0 | Y40: =IF(AB39>0.5,AB39*(1+Y$23)+Y$24,0) -> 0 | Z40: =MIN(Z$23,Y40) -> 0 | AA40: =IF(AND(Z$24=1,OR(Y$25="",$C40>=Y$25)),MAX(0,MIN(Y40-Z40,$D40-(G40+K40+O40+S40+W40))),0) -> 0 | AB40: =Y40-Z40-AA40 -> 0 | AC40: =IF(AF39>0.5,AF39*(1+AC$23)+AC$24,0) -> 0 | AD40: =MIN(AD$23,AC40) -> 0 | AE40: =IF(AND(AD$24=1,OR(AC$25="",$C40>=AC$25)),MAX(0,MIN(AC40-AD40,$D40-(G40+K40+O40+S40+W40+AA40))),0) -> 0 | AF40: =AC40-AD40-AE40 -> 0 | AG40: =IF(AJ39>0.5,AJ39*(1+AG$23)+AG$24,0) -> 0 | AH40: =MIN(AH$23,AG40) -> 0 | AI40: =IF(AND(AH$24=1,OR(AG$25="",$C40>=AG$25)),MAX(0,MIN(AG40-AH40,$D40-(G40+K40+O40+S40+W40+AA40+AE40))),0) -> 0 | AJ40: =AG40-AH40-AI40 -> 0 | AK40: =IF(AK39>0.5,AK39*(1+$E$12)+$G$12-MIN($F$12,AK39*(1+$E$12)+$G$12),0) -> 0 | AL40: =IF(AL39>0.5,AL39*(1+$E$13)+$G$13-MIN($F$13,AL39*(1+$E$13)+$G$13),0) -> 0 | AM40: =IF(AM39>0.5,AM39*(1+$E$14)+$G$14-MIN($F$14,AM39*(1+$E$14)+$G$14),0) -> 0 | AN40: =IF(AN39>0.5,AN39*(1+$E$15)+$G$15-MIN($F$15,AN39*(1+$E$15)+$G$15),0) -> 0 | AO40: =IF(AO39>0.5,AO39*(1+$E$16)+$G$16-MIN($F$16,AO39*(1+$E$16)+$G$16),0) -> 0 | AP40: =IF(AP39>0.5,AP39*(1+$E$17)+$G$17-MIN($F$17,AP39*(1+$E$17)+$G$17),0) -> 0 | AQ40: =IF(AQ39>0.5,AQ39*(1+$E$18)+$G$18-MIN($F$18,AQ39*(1+$E$18)+$G$18),0) -> 0 | AR40: =IF(AR39>0.5,AR39*(1+$E$19)+$G$19-MIN($F$19,AR39*(1+$E$19)+$G$19),0) -> 0 | AS40: =H40+L40+P40+T40+X40+AB40+AF40+AJ40 -> 0 | AT40: =SUM(AK40:AR40) -> 0 | AU40: =F40+G40+J40+K40+N40+O40+R40+S40+V40+W40+Z40+AA40+AD40+AE40+AH40+AI40 -> 0
B41: 14 | C41: =EDATE($C$7,13) -> 46692 | D41: =$C$8-(F41+J41+N41+R41+V41+Z41+AD41+AH41) -> 0 | E41: =IF(H40>0.5,H40*(1+E$23)+E$24,0) -> 0 | F41: =MIN(F$23,E41) -> 0 | G41: =IF(AND(F$24=1,OR(E$25="",$C41>=E$25)),MAX(0,MIN(E41-F41,$D41-(0))),0) -> 0 | H41: =E41-F41-G41 -> 0 | I41: =IF(L40>0.5,L40*(1+I$23)+I$24,0) -> 0 | J41: =MIN(J$23,I41) -> 0 | K41: =IF(AND(J$24=1,OR(I$25="",$C41>=I$25)),MAX(0,MIN(I41-J41,$D41-(G41))),0) -> 0 | L41: =I41-J41-K41 -> 0 | M41: =IF(P40>0.5,P40*(1+M$23)+M$24,0) -> 0 | N41: =MIN(N$23,M41) -> 0 | O41: =IF(AND(N$24=1,OR(M$25="",$C41>=M$25)),MAX(0,MIN(M41-N41,$D41-(G41+K41))),0) -> 0 | P41: =M41-N41-O41 -> 0 | Q41: =IF(T40>0.5,T40*(1+Q$23)+Q$24,0) -> 0 | R41: =MIN(R$23,Q41) -> 0 | S41: =IF(AND(R$24=1,OR(Q$25="",$C41>=Q$25)),MAX(0,MIN(Q41-R41,$D41-(G41+K41+O41))),0) -> 0 | T41: =Q41-R41-S41 -> 0 | U41: =IF(X40>0.5,X40*(1+U$23)+U$24,0) -> 0 | V41: =MIN(V$23,U41) -> 0 | W41: =IF(AND(V$24=1,OR(U$25="",$C41>=U$25)),MAX(0,MIN(U41-V41,$D41-(G41+K41+O41+S41))),0) -> 0 | X41: =U41-V41-W41 -> 0 | Y41: =IF(AB40>0.5,AB40*(1+Y$23)+Y$24,0) -> 0 | Z41: =MIN(Z$23,Y41) -> 0 | AA41: =IF(AND(Z$24=1,OR(Y$25="",$C41>=Y$25)),MAX(0,MIN(Y41-Z41,$D41-(G41+K41+O41+S41+W41))),0) -> 0 | AB41: =Y41-Z41-AA41 -> 0 | AC41: =IF(AF40>0.5,AF40*(1+AC$23)+AC$24,0) -> 0 | AD41: =MIN(AD$23,AC41) -> 0 | AE41: =IF(AND(AD$24=1,OR(AC$25="",$C41>=AC$25)),MAX(0,MIN(AC41-AD41,$D41-(G41+K41+O41+S41+W41+AA41))),0) -> 0 | AF41: =AC41-AD41-AE41 -> 0 | AG41: =IF(AJ40>0.5,AJ40*(1+AG$23)+AG$24,0) -> 0 | AH41: =MIN(AH$23,AG41) -> 0 | AI41: =IF(AND(AH$24=1,OR(AG$25="",$C41>=AG$25)),MAX(0,MIN(AG41-AH41,$D41-(G41+K41+O41+S41+W41+AA41+AE41))),0) -> 0 | AJ41: =AG41-AH41-AI41 -> 0 | AK41: =IF(AK40>0.5,AK40*(1+$E$12)+$G$12-MIN($F$12,AK40*(1+$E$12)+$G$12),0) -> 0 | AL41: =IF(AL40>0.5,AL40*(1+$E$13)+$G$13-MIN($F$13,AL40*(1+$E$13)+$G$13),0) -> 0 | AM41: =IF(AM40>0.5,AM40*(1+$E$14)+$G$14-MIN($F$14,AM40*(1+$E$14)+$G$14),0) -> 0 | AN41: =IF(AN40>0.5,AN40*(1+$E$15)+$G$15-MIN($F$15,AN40*(1+$E$15)+$G$15),0) -> 0 | AO41: =IF(AO40>0.5,AO40*(1+$E$16)+$G$16-MIN($F$16,AO40*(1+$E$16)+$G$16),0) -> 0 | AP41: =IF(AP40>0.5,AP40*(1+$E$17)+$G$17-MIN($F$17,AP40*(1+$E$17)+$G$17),0) -> 0 | AQ41: =IF(AQ40>0.5,AQ40*(1+$E$18)+$G$18-MIN($F$18,AQ40*(1+$E$18)+$G$18),0) -> 0 | AR41: =IF(AR40>0.5,AR40*(1+$E$19)+$G$19-MIN($F$19,AR40*(1+$E$19)+$G$19),0) -> 0 | AS41: =H41+L41+P41+T41+X41+AB41+AF41+AJ41 -> 0 | AT41: =SUM(AK41:AR41) -> 0 | AU41: =F41+G41+J41+K41+N41+O41+R41+S41+V41+W41+Z41+AA41+AD41+AE41+AH41+AI41 -> 0
B42: 15 | C42: =EDATE($C$7,14) -> 46722 | D42: =$C$8-(F42+J42+N42+R42+V42+Z42+AD42+AH42) -> 0 | E42: =IF(H41>0.5,H41*(1+E$23)+E$24,0) -> 0 | F42: =MIN(F$23,E42) -> 0 | G42: =IF(AND(F$24=1,OR(E$25="",$C42>=E$25)),MAX(0,MIN(E42-F42,$D42-(0))),0) -> 0 | H42: =E42-F42-G42 -> 0 | I42: =IF(L41>0.5,L41*(1+I$23)+I$24,0) -> 0 | J42: =MIN(J$23,I42) -> 0 | K42: =IF(AND(J$24=1,OR(I$25="",$C42>=I$25)),MAX(0,MIN(I42-J42,$D42-(G42))),0) -> 0 | L42: =I42-J42-K42 -> 0 | M42: =IF(P41>0.5,P41*(1+M$23)+M$24,0) -> 0 | N42: =MIN(N$23,M42) -> 0 | O42: =IF(AND(N$24=1,OR(M$25="",$C42>=M$25)),MAX(0,MIN(M42-N42,$D42-(G42+K42))),0) -> 0 | P42: =M42-N42-O42 -> 0 | Q42: =IF(T41>0.5,T41*(1+Q$23)+Q$24,0) -> 0 | R42: =MIN(R$23,Q42) -> 0 | S42: =IF(AND(R$24=1,OR(Q$25="",$C42>=Q$25)),MAX(0,MIN(Q42-R42,$D42-(G42+K42+O42))),0) -> 0 | T42: =Q42-R42-S42 -> 0 | U42: =IF(X41>0.5,X41*(1+U$23)+U$24,0) -> 0 | V42: =MIN(V$23,U42) -> 0 | W42: =IF(AND(V$24=1,OR(U$25="",$C42>=U$25)),MAX(0,MIN(U42-V42,$D42-(G42+K42+O42+S42))),0) -> 0 | X42: =U42-V42-W42 -> 0 | Y42: =IF(AB41>0.5,AB41*(1+Y$23)+Y$24,0) -> 0 | Z42: =MIN(Z$23,Y42) -> 0 | AA42: =IF(AND(Z$24=1,OR(Y$25="",$C42>=Y$25)),MAX(0,MIN(Y42-Z42,$D42-(G42+K42+O42+S42+W42))),0) -> 0 | AB42: =Y42-Z42-AA42 -> 0 | AC42: =IF(AF41>0.5,AF41*(1+AC$23)+AC$24,0) -> 0 | AD42: =MIN(AD$23,AC42) -> 0 | AE42: =IF(AND(AD$24=1,OR(AC$25="",$C42>=AC$25)),MAX(0,MIN(AC42-AD42,$D42-(G42+K42+O42+S42+W42+AA42))),0) -> 0 | AF42: =AC42-AD42-AE42 -> 0 | AG42: =IF(AJ41>0.5,AJ41*(1+AG$23)+AG$24,0) -> 0 | AH42: =MIN(AH$23,AG42) -> 0 | AI42: =IF(AND(AH$24=1,OR(AG$25="",$C42>=AG$25)),MAX(0,MIN(AG42-AH42,$D42-(G42+K42+O42+S42+W42+AA42+AE42))),0) -> 0 | AJ42: =AG42-AH42-AI42 -> 0 | AK42: =IF(AK41>0.5,AK41*(1+$E$12)+$G$12-MIN($F$12,AK41*(1+$E$12)+$G$12),0) -> 0 | AL42: =IF(AL41>0.5,AL41*(1+$E$13)+$G$13-MIN($F$13,AL41*(1+$E$13)+$G$13),0) -> 0 | AM42: =IF(AM41>0.5,AM41*(1+$E$14)+$G$14-MIN($F$14,AM41*(1+$E$14)+$G$14),0) -> 0 | AN42: =IF(AN41>0.5,AN41*(1+$E$15)+$G$15-MIN($F$15,AN41*(1+$E$15)+$G$15),0) -> 0 | AO42: =IF(AO41>0.5,AO41*(1+$E$16)+$G$16-MIN($F$16,AO41*(1+$E$16)+$G$16),0) -> 0 | AP42: =IF(AP41>0.5,AP41*(1+$E$17)+$G$17-MIN($F$17,AP41*(1+$E$17)+$G$17),0) -> 0 | AQ42: =IF(AQ41>0.5,AQ41*(1+$E$18)+$G$18-MIN($F$18,AQ41*(1+$E$18)+$G$18),0) -> 0 | AR42: =IF(AR41>0.5,AR41*(1+$E$19)+$G$19-MIN($F$19,AR41*(1+$E$19)+$G$19),0) -> 0 | AS42: =H42+L42+P42+T42+X42+AB42+AF42+AJ42 -> 0 | AT42: =SUM(AK42:AR42) -> 0 | AU42: =F42+G42+J42+K42+N42+O42+R42+S42+V42+W42+Z42+AA42+AD42+AE42+AH42+AI42 -> 0
B43: 16 | C43: =EDATE($C$7,15) -> 46753 | D43: =$C$8-(F43+J43+N43+R43+V43+Z43+AD43+AH43) -> 0 | E43: =IF(H42>0.5,H42*(1+E$23)+E$24,0) -> 0 | F43: =MIN(F$23,E43) -> 0 | G43: =IF(AND(F$24=1,OR(E$25="",$C43>=E$25)),MAX(0,MIN(E43-F43,$D43-(0))),0) -> 0 | H43: =E43-F43-G43 -> 0 | I43: =IF(L42>0.5,L42*(1+I$23)+I$24,0) -> 0 | J43: =MIN(J$23,I43) -> 0 | K43: =IF(AND(J$24=1,OR(I$25="",$C43>=I$25)),MAX(0,MIN(I43-J43,$D43-(G43))),0) -> 0 | L43: =I43-J43-K43 -> 0 | M43: =IF(P42>0.5,P42*(1+M$23)+M$24,0) -> 0 | N43: =MIN(N$23,M43) -> 0 | O43: =IF(AND(N$24=1,OR(M$25="",$C43>=M$25)),MAX(0,MIN(M43-N43,$D43-(G43+K43))),0) -> 0 | P43: =M43-N43-O43 -> 0 | Q43: =IF(T42>0.5,T42*(1+Q$23)+Q$24,0) -> 0 | R43: =MIN(R$23,Q43) -> 0 | S43: =IF(AND(R$24=1,OR(Q$25="",$C43>=Q$25)),MAX(0,MIN(Q43-R43,$D43-(G43+K43+O43))),0) -> 0 | T43: =Q43-R43-S43 -> 0 | U43: =IF(X42>0.5,X42*(1+U$23)+U$24,0) -> 0 | V43: =MIN(V$23,U43) -> 0 | W43: =IF(AND(V$24=1,OR(U$25="",$C43>=U$25)),MAX(0,MIN(U43-V43,$D43-(G43+K43+O43+S43))),0) -> 0 | X43: =U43-V43-W43 -> 0 | Y43: =IF(AB42>0.5,AB42*(1+Y$23)+Y$24,0) -> 0 | Z43: =MIN(Z$23,Y43) -> 0 | AA43: =IF(AND(Z$24=1,OR(Y$25="",$C43>=Y$25)),MAX(0,MIN(Y43-Z43,$D43-(G43+K43+O43+S43+W43))),0) -> 0 | AB43: =Y43-Z43-AA43 -> 0 | AC43: =IF(AF42>0.5,AF42*(1+AC$23)+AC$24,0) -> 0 | AD43: =MIN(AD$23,AC43) -> 0 | AE43: =IF(AND(AD$24=1,OR(AC$25="",$C43>=AC$25)),MAX(0,MIN(AC43-AD43,$D43-(G43+K43+O43+S43+W43+AA43))),0) -> 0 | AF43: =AC43-AD43-AE43 -> 0 | AG43: =IF(AJ42>0.5,AJ42*(1+AG$23)+AG$24,0) -> 0 | AH43: =MIN(AH$23,AG43) -> 0 | AI43: =IF(AND(AH$24=1,OR(AG$25="",$C43>=AG$25)),MAX(0,MIN(AG43-AH43,$D43-(G43+K43+O43+S43+W43+AA43+AE43))),0) -> 0 | AJ43: =AG43-AH43-AI43 -> 0 | AK43: =IF(AK42>0.5,AK42*(1+$E$12)+$G$12-MIN($F$12,AK42*(1+$E$12)+$G$12),0) -> 0 | AL43: =IF(AL42>0.5,AL42*(1+$E$13)+$G$13-MIN($F$13,AL42*(1+$E$13)+$G$13),0) -> 0 | AM43: =IF(AM42>0.5,AM42*(1+$E$14)+$G$14-MIN($F$14,AM42*(1+$E$14)+$G$14),0) -> 0 | AN43: =IF(AN42>0.5,AN42*(1+$E$15)+$G$15-MIN($F$15,AN42*(1+$E$15)+$G$15),0) -> 0 | AO43: =IF(AO42>0.5,AO42*(1+$E$16)+$G$16-MIN($F$16,AO42*(1+$E$16)+$G$16),0) -> 0 | AP43: =IF(AP42>0.5,AP42*(1+$E$17)+$G$17-MIN($F$17,AP42*(1+$E$17)+$G$17),0) -> 0 | AQ43: =IF(AQ42>0.5,AQ42*(1+$E$18)+$G$18-MIN($F$18,AQ42*(1+$E$18)+$G$18),0) -> 0 | AR43: =IF(AR42>0.5,AR42*(1+$E$19)+$G$19-MIN($F$19,AR42*(1+$E$19)+$G$19),0) -> 0 | AS43: =H43+L43+P43+T43+X43+AB43+AF43+AJ43 -> 0 | AT43: =SUM(AK43:AR43) -> 0 | AU43: =F43+G43+J43+K43+N43+O43+R43+S43+V43+W43+Z43+AA43+AD43+AE43+AH43+AI43 -> 0
B44: 17 | C44: =EDATE($C$7,16) -> 46784 | D44: =$C$8-(F44+J44+N44+R44+V44+Z44+AD44+AH44) -> 0 | E44: =IF(H43>0.5,H43*(1+E$23)+E$24,0) -> 0 | F44: =MIN(F$23,E44) -> 0 | G44: =IF(AND(F$24=1,OR(E$25="",$C44>=E$25)),MAX(0,MIN(E44-F44,$D44-(0))),0) -> 0 | H44: =E44-F44-G44 -> 0 | I44: =IF(L43>0.5,L43*(1+I$23)+I$24,0) -> 0 | J44: =MIN(J$23,I44) -> 0 | K44: =IF(AND(J$24=1,OR(I$25="",$C44>=I$25)),MAX(0,MIN(I44-J44,$D44-(G44))),0) -> 0 | L44: =I44-J44-K44 -> 0 | M44: =IF(P43>0.5,P43*(1+M$23)+M$24,0) -> 0 | N44: =MIN(N$23,M44) -> 0 | O44: =IF(AND(N$24=1,OR(M$25="",$C44>=M$25)),MAX(0,MIN(M44-N44,$D44-(G44+K44))),0) -> 0 | P44: =M44-N44-O44 -> 0 | Q44: =IF(T43>0.5,T43*(1+Q$23)+Q$24,0) -> 0 | R44: =MIN(R$23,Q44) -> 0 | S44: =IF(AND(R$24=1,OR(Q$25="",$C44>=Q$25)),MAX(0,MIN(Q44-R44,$D44-(G44+K44+O44))),0) -> 0 | T44: =Q44-R44-S44 -> 0 | U44: =IF(X43>0.5,X43*(1+U$23)+U$24,0) -> 0 | V44: =MIN(V$23,U44) -> 0 | W44: =IF(AND(V$24=1,OR(U$25="",$C44>=U$25)),MAX(0,MIN(U44-V44,$D44-(G44+K44+O44+S44))),0) -> 0 | X44: =U44-V44-W44 -> 0 | Y44: =IF(AB43>0.5,AB43*(1+Y$23)+Y$24,0) -> 0 | Z44: =MIN(Z$23,Y44) -> 0 | AA44: =IF(AND(Z$24=1,OR(Y$25="",$C44>=Y$25)),MAX(0,MIN(Y44-Z44,$D44-(G44+K44+O44+S44+W44))),0) -> 0 | AB44: =Y44-Z44-AA44 -> 0 | AC44: =IF(AF43>0.5,AF43*(1+AC$23)+AC$24,0) -> 0 | AD44: =MIN(AD$23,AC44) -> 0 | AE44: =IF(AND(AD$24=1,OR(AC$25="",$C44>=AC$25)),MAX(0,MIN(AC44-AD44,$D44-(G44+K44+O44+S44+W44+AA44))),0) -> 0 | AF44: =AC44-AD44-AE44 -> 0 | AG44: =IF(AJ43>0.5,AJ43*(1+AG$23)+AG$24,0) -> 0 | AH44: =MIN(AH$23,AG44) -> 0 | AI44: =IF(AND(AH$24=1,OR(AG$25="",$C44>=AG$25)),MAX(0,MIN(AG44-AH44,$D44-(G44+K44+O44+S44+W44+AA44+AE44))),0) -> 0 | AJ44: =AG44-AH44-AI44 -> 0 | AK44: =IF(AK43>0.5,AK43*(1+$E$12)+$G$12-MIN($F$12,AK43*(1+$E$12)+$G$12),0) -> 0 | AL44: =IF(AL43>0.5,AL43*(1+$E$13)+$G$13-MIN($F$13,AL43*(1+$E$13)+$G$13),0) -> 0 | AM44: =IF(AM43>0.5,AM43*(1+$E$14)+$G$14-MIN($F$14,AM43*(1+$E$14)+$G$14),0) -> 0 | AN44: =IF(AN43>0.5,AN43*(1+$E$15)+$G$15-MIN($F$15,AN43*(1+$E$15)+$G$15),0) -> 0 | AO44: =IF(AO43>0.5,AO43*(1+$E$16)+$G$16-MIN($F$16,AO43*(1+$E$16)+$G$16),0) -> 0 | AP44: =IF(AP43>0.5,AP43*(1+$E$17)+$G$17-MIN($F$17,AP43*(1+$E$17)+$G$17),0) -> 0 | AQ44: =IF(AQ43>0.5,AQ43*(1+$E$18)+$G$18-MIN($F$18,AQ43*(1+$E$18)+$G$18),0) -> 0 | AR44: =IF(AR43>0.5,AR43*(1+$E$19)+$G$19-MIN($F$19,AR43*(1+$E$19)+$G$19),0) -> 0 | AS44: =H44+L44+P44+T44+X44+AB44+AF44+AJ44 -> 0 | AT44: =SUM(AK44:AR44) -> 0 | AU44: =F44+G44+J44+K44+N44+O44+R44+S44+V44+W44+Z44+AA44+AD44+AE44+AH44+AI44 -> 0
B45: 18 | C45: =EDATE($C$7,17) -> 46813 | D45: =$C$8-(F45+J45+N45+R45+V45+Z45+AD45+AH45) -> 0 | E45: =IF(H44>0.5,H44*(1+E$23)+E$24,0) -> 0 | F45: =MIN(F$23,E45) -> 0 | G45: =IF(AND(F$24=1,OR(E$25="",$C45>=E$25)),MAX(0,MIN(E45-F45,$D45-(0))),0) -> 0 | H45: =E45-F45-G45 -> 0 | I45: =IF(L44>0.5,L44*(1+I$23)+I$24,0) -> 0 | J45: =MIN(J$23,I45) -> 0 | K45: =IF(AND(J$24=1,OR(I$25="",$C45>=I$25)),MAX(0,MIN(I45-J45,$D45-(G45))),0) -> 0 | L45: =I45-J45-K45 -> 0 | M45: =IF(P44>0.5,P44*(1+M$23)+M$24,0) -> 0 | N45: =MIN(N$23,M45) -> 0 | O45: =IF(AND(N$24=1,OR(M$25="",$C45>=M$25)),MAX(0,MIN(M45-N45,$D45-(G45+K45))),0) -> 0 | P45: =M45-N45-O45 -> 0 | Q45: =IF(T44>0.5,T44*(1+Q$23)+Q$24,0) -> 0 | R45: =MIN(R$23,Q45) -> 0 | S45: =IF(AND(R$24=1,OR(Q$25="",$C45>=Q$25)),MAX(0,MIN(Q45-R45,$D45-(G45+K45+O45))),0) -> 0 | T45: =Q45-R45-S45 -> 0 | U45: =IF(X44>0.5,X44*(1+U$23)+U$24,0) -> 0 | V45: =MIN(V$23,U45) -> 0 | W45: =IF(AND(V$24=1,OR(U$25="",$C45>=U$25)),MAX(0,MIN(U45-V45,$D45-(G45+K45+O45+S45))),0) -> 0 | X45: =U45-V45-W45 -> 0 | Y45: =IF(AB44>0.5,AB44*(1+Y$23)+Y$24,0) -> 0 | Z45: =MIN(Z$23,Y45) -> 0 | AA45: =IF(AND(Z$24=1,OR(Y$25="",$C45>=Y$25)),MAX(0,MIN(Y45-Z45,$D45-(G45+K45+O45+S45+W45))),0) -> 0 | AB45: =Y45-Z45-AA45 -> 0 | AC45: =IF(AF44>0.5,AF44*(1+AC$23)+AC$24,0) -> 0 | AD45: =MIN(AD$23,AC45) -> 0 | AE45: =IF(AND(AD$24=1,OR(AC$25="",$C45>=AC$25)),MAX(0,MIN(AC45-AD45,$D45-(G45+K45+O45+S45+W45+AA45))),0) -> 0 | AF45: =AC45-AD45-AE45 -> 0 | AG45: =IF(AJ44>0.5,AJ44*(1+AG$23)+AG$24,0) -> 0 | AH45: =MIN(AH$23,AG45) -> 0 | AI45: =IF(AND(AH$24=1,OR(AG$25="",$C45>=AG$25)),MAX(0,MIN(AG45-AH45,$D45-(G45+K45+O45+S45+W45+AA45+AE45))),0) -> 0 | AJ45: =AG45-AH45-AI45 -> 0 | AK45: =IF(AK44>0.5,AK44*(1+$E$12)+$G$12-MIN($F$12,AK44*(1+$E$12)+$G$12),0) -> 0 | AL45: =IF(AL44>0.5,AL44*(1+$E$13)+$G$13-MIN($F$13,AL44*(1+$E$13)+$G$13),0) -> 0 | AM45: =IF(AM44>0.5,AM44*(1+$E$14)+$G$14-MIN($F$14,AM44*(1+$E$14)+$G$14),0) -> 0 | AN45: =IF(AN44>0.5,AN44*(1+$E$15)+$G$15-MIN($F$15,AN44*(1+$E$15)+$G$15),0) -> 0 | AO45: =IF(AO44>0.5,AO44*(1+$E$16)+$G$16-MIN($F$16,AO44*(1+$E$16)+$G$16),0) -> 0 | AP45: =IF(AP44>0.5,AP44*(1+$E$17)+$G$17-MIN($F$17,AP44*(1+$E$17)+$G$17),0) -> 0 | AQ45: =IF(AQ44>0.5,AQ44*(1+$E$18)+$G$18-MIN($F$18,AQ44*(1+$E$18)+$G$18),0) -> 0 | AR45: =IF(AR44>0.5,AR44*(1+$E$19)+$G$19-MIN($F$19,AR44*(1+$E$19)+$G$19),0) -> 0 | AS45: =H45+L45+P45+T45+X45+AB45+AF45+AJ45 -> 0 | AT45: =SUM(AK45:AR45) -> 0 | AU45: =F45+G45+J45+K45+N45+O45+R45+S45+V45+W45+Z45+AA45+AD45+AE45+AH45+AI45 -> 0
B46: 19 | C46: =EDATE($C$7,18) -> 46844 | D46: =$C$8-(F46+J46+N46+R46+V46+Z46+AD46+AH46) -> 0 | E46: =IF(H45>0.5,H45*(1+E$23)+E$24,0) -> 0 | F46: =MIN(F$23,E46) -> 0 | G46: =IF(AND(F$24=1,OR(E$25="",$C46>=E$25)),MAX(0,MIN(E46-F46,$D46-(0))),0) -> 0 | H46: =E46-F46-G46 -> 0 | I46: =IF(L45>0.5,L45*(1+I$23)+I$24,0) -> 0 | J46: =MIN(J$23,I46) -> 0 | K46: =IF(AND(J$24=1,OR(I$25="",$C46>=I$25)),MAX(0,MIN(I46-J46,$D46-(G46))),0) -> 0 | L46: =I46-J46-K46 -> 0 | M46: =IF(P45>0.5,P45*(1+M$23)+M$24,0) -> 0 | N46: =MIN(N$23,M46) -> 0 | O46: =IF(AND(N$24=1,OR(M$25="",$C46>=M$25)),MAX(0,MIN(M46-N46,$D46-(G46+K46))),0) -> 0 | P46: =M46-N46-O46 -> 0 | Q46: =IF(T45>0.5,T45*(1+Q$23)+Q$24,0) -> 0 | R46: =MIN(R$23,Q46) -> 0 | S46: =IF(AND(R$24=1,OR(Q$25="",$C46>=Q$25)),MAX(0,MIN(Q46-R46,$D46-(G46+K46+O46))),0) -> 0 | T46: =Q46-R46-S46 -> 0 | U46: =IF(X45>0.5,X45*(1+U$23)+U$24,0) -> 0 | V46: =MIN(V$23,U46) -> 0 | W46: =IF(AND(V$24=1,OR(U$25="",$C46>=U$25)),MAX(0,MIN(U46-V46,$D46-(G46+K46+O46+S46))),0) -> 0 | X46: =U46-V46-W46 -> 0 | Y46: =IF(AB45>0.5,AB45*(1+Y$23)+Y$24,0) -> 0 | Z46: =MIN(Z$23,Y46) -> 0 | AA46: =IF(AND(Z$24=1,OR(Y$25="",$C46>=Y$25)),MAX(0,MIN(Y46-Z46,$D46-(G46+K46+O46+S46+W46))),0) -> 0 | AB46: =Y46-Z46-AA46 -> 0 | AC46: =IF(AF45>0.5,AF45*(1+AC$23)+AC$24,0) -> 0 | AD46: =MIN(AD$23,AC46) -> 0 | AE46: =IF(AND(AD$24=1,OR(AC$25="",$C46>=AC$25)),MAX(0,MIN(AC46-AD46,$D46-(G46+K46+O46+S46+W46+AA46))),0) -> 0 | AF46: =AC46-AD46-AE46 -> 0 | AG46: =IF(AJ45>0.5,AJ45*(1+AG$23)+AG$24,0) -> 0 | AH46: =MIN(AH$23,AG46) -> 0 | AI46: =IF(AND(AH$24=1,OR(AG$25="",$C46>=AG$25)),MAX(0,MIN(AG46-AH46,$D46-(G46+K46+O46+S46+W46+AA46+AE46))),0) -> 0 | AJ46: =AG46-AH46-AI46 -> 0 | AK46: =IF(AK45>0.5,AK45*(1+$E$12)+$G$12-MIN($F$12,AK45*(1+$E$12)+$G$12),0) -> 0 | AL46: =IF(AL45>0.5,AL45*(1+$E$13)+$G$13-MIN($F$13,AL45*(1+$E$13)+$G$13),0) -> 0 | AM46: =IF(AM45>0.5,AM45*(1+$E$14)+$G$14-MIN($F$14,AM45*(1+$E$14)+$G$14),0) -> 0 | AN46: =IF(AN45>0.5,AN45*(1+$E$15)+$G$15-MIN($F$15,AN45*(1+$E$15)+$G$15),0) -> 0 | AO46: =IF(AO45>0.5,AO45*(1+$E$16)+$G$16-MIN($F$16,AO45*(1+$E$16)+$G$16),0) -> 0 | AP46: =IF(AP45>0.5,AP45*(1+$E$17)+$G$17-MIN($F$17,AP45*(1+$E$17)+$G$17),0) -> 0 | AQ46: =IF(AQ45>0.5,AQ45*(1+$E$18)+$G$18-MIN($F$18,AQ45*(1+$E$18)+$G$18),0) -> 0 | AR46: =IF(AR45>0.5,AR45*(1+$E$19)+$G$19-MIN($F$19,AR45*(1+$E$19)+$G$19),0) -> 0 | AS46: =H46+L46+P46+T46+X46+AB46+AF46+AJ46 -> 0 | AT46: =SUM(AK46:AR46) -> 0 | AU46: =F46+G46+J46+K46+N46+O46+R46+S46+V46+W46+Z46+AA46+AD46+AE46+AH46+AI46 -> 0
B47: 20 | C47: =EDATE($C$7,19) -> 46874 | D47: =$C$8-(F47+J47+N47+R47+V47+Z47+AD47+AH47) -> 0 | E47: =IF(H46>0.5,H46*(1+E$23)+E$24,0) -> 0 | F47: =MIN(F$23,E47) -> 0 | G47: =IF(AND(F$24=1,OR(E$25="",$C47>=E$25)),MAX(0,MIN(E47-F47,$D47-(0))),0) -> 0 | H47: =E47-F47-G47 -> 0 | I47: =IF(L46>0.5,L46*(1+I$23)+I$24,0) -> 0 | J47: =MIN(J$23,I47) -> 0 | K47: =IF(AND(J$24=1,OR(I$25="",$C47>=I$25)),MAX(0,MIN(I47-J47,$D47-(G47))),0) -> 0 | L47: =I47-J47-K47 -> 0 | M47: =IF(P46>0.5,P46*(1+M$23)+M$24,0) -> 0 | N47: =MIN(N$23,M47) -> 0 | O47: =IF(AND(N$24=1,OR(M$25="",$C47>=M$25)),MAX(0,MIN(M47-N47,$D47-(G47+K47))),0) -> 0 | P47: =M47-N47-O47 -> 0 | Q47: =IF(T46>0.5,T46*(1+Q$23)+Q$24,0) -> 0 | R47: =MIN(R$23,Q47) -> 0 | S47: =IF(AND(R$24=1,OR(Q$25="",$C47>=Q$25)),MAX(0,MIN(Q47-R47,$D47-(G47+K47+O47))),0) -> 0 | T47: =Q47-R47-S47 -> 0 | U47: =IF(X46>0.5,X46*(1+U$23)+U$24,0) -> 0 | V47: =MIN(V$23,U47) -> 0 | W47: =IF(AND(V$24=1,OR(U$25="",$C47>=U$25)),MAX(0,MIN(U47-V47,$D47-(G47+K47+O47+S47))),0) -> 0 | X47: =U47-V47-W47 -> 0 | Y47: =IF(AB46>0.5,AB46*(1+Y$23)+Y$24,0) -> 0 | Z47: =MIN(Z$23,Y47) -> 0 | AA47: =IF(AND(Z$24=1,OR(Y$25="",$C47>=Y$25)),MAX(0,MIN(Y47-Z47,$D47-(G47+K47+O47+S47+W47))),0) -> 0 | AB47: =Y47-Z47-AA47 -> 0 | AC47: =IF(AF46>0.5,AF46*(1+AC$23)+AC$24,0) -> 0 | AD47: =MIN(AD$23,AC47) -> 0 | AE47: =IF(AND(AD$24=1,OR(AC$25="",$C47>=AC$25)),MAX(0,MIN(AC47-AD47,$D47-(G47+K47+O47+S47+W47+AA47))),0) -> 0 | AF47: =AC47-AD47-AE47 -> 0 | AG47: =IF(AJ46>0.5,AJ46*(1+AG$23)+AG$24,0) -> 0 | AH47: =MIN(AH$23,AG47) -> 0 | AI47: =IF(AND(AH$24=1,OR(AG$25="",$C47>=AG$25)),MAX(0,MIN(AG47-AH47,$D47-(G47+K47+O47+S47+W47+AA47+AE47))),0) -> 0 | AJ47: =AG47-AH47-AI47 -> 0 | AK47: =IF(AK46>0.5,AK46*(1+$E$12)+$G$12-MIN($F$12,AK46*(1+$E$12)+$G$12),0) -> 0 | AL47: =IF(AL46>0.5,AL46*(1+$E$13)+$G$13-MIN($F$13,AL46*(1+$E$13)+$G$13),0) -> 0 | AM47: =IF(AM46>0.5,AM46*(1+$E$14)+$G$14-MIN($F$14,AM46*(1+$E$14)+$G$14),0) -> 0 | AN47: =IF(AN46>0.5,AN46*(1+$E$15)+$G$15-MIN($F$15,AN46*(1+$E$15)+$G$15),0) -> 0 | AO47: =IF(AO46>0.5,AO46*(1+$E$16)+$G$16-MIN($F$16,AO46*(1+$E$16)+$G$16),0) -> 0 | AP47: =IF(AP46>0.5,AP46*(1+$E$17)+$G$17-MIN($F$17,AP46*(1+$E$17)+$G$17),0) -> 0 | AQ47: =IF(AQ46>0.5,AQ46*(1+$E$18)+$G$18-MIN($F$18,AQ46*(1+$E$18)+$G$18),0) -> 0 | AR47: =IF(AR46>0.5,AR46*(1+$E$19)+$G$19-MIN($F$19,AR46*(1+$E$19)+$G$19),0) -> 0 | AS47: =H47+L47+P47+T47+X47+AB47+AF47+AJ47 -> 0 | AT47: =SUM(AK47:AR47) -> 0 | AU47: =F47+G47+J47+K47+N47+O47+R47+S47+V47+W47+Z47+AA47+AD47+AE47+AH47+AI47 -> 0
B48: 21 | C48: =EDATE($C$7,20) -> 46905 | D48: =$C$8-(F48+J48+N48+R48+V48+Z48+AD48+AH48) -> 0 | E48: =IF(H47>0.5,H47*(1+E$23)+E$24,0) -> 0 | F48: =MIN(F$23,E48) -> 0 | G48: =IF(AND(F$24=1,OR(E$25="",$C48>=E$25)),MAX(0,MIN(E48-F48,$D48-(0))),0) -> 0 | H48: =E48-F48-G48 -> 0 | I48: =IF(L47>0.5,L47*(1+I$23)+I$24,0) -> 0 | J48: =MIN(J$23,I48) -> 0 | K48: =IF(AND(J$24=1,OR(I$25="",$C48>=I$25)),MAX(0,MIN(I48-J48,$D48-(G48))),0) -> 0 | L48: =I48-J48-K48 -> 0 | M48: =IF(P47>0.5,P47*(1+M$23)+M$24,0) -> 0 | N48: =MIN(N$23,M48) -> 0 | O48: =IF(AND(N$24=1,OR(M$25="",$C48>=M$25)),MAX(0,MIN(M48-N48,$D48-(G48+K48))),0) -> 0 | P48: =M48-N48-O48 -> 0 | Q48: =IF(T47>0.5,T47*(1+Q$23)+Q$24,0) -> 0 | R48: =MIN(R$23,Q48) -> 0 | S48: =IF(AND(R$24=1,OR(Q$25="",$C48>=Q$25)),MAX(0,MIN(Q48-R48,$D48-(G48+K48+O48))),0) -> 0 | T48: =Q48-R48-S48 -> 0 | U48: =IF(X47>0.5,X47*(1+U$23)+U$24,0) -> 0 | V48: =MIN(V$23,U48) -> 0 | W48: =IF(AND(V$24=1,OR(U$25="",$C48>=U$25)),MAX(0,MIN(U48-V48,$D48-(G48+K48+O48+S48))),0) -> 0 | X48: =U48-V48-W48 -> 0 | Y48: =IF(AB47>0.5,AB47*(1+Y$23)+Y$24,0) -> 0 | Z48: =MIN(Z$23,Y48) -> 0 | AA48: =IF(AND(Z$24=1,OR(Y$25="",$C48>=Y$25)),MAX(0,MIN(Y48-Z48,$D48-(G48+K48+O48+S48+W48))),0) -> 0 | AB48: =Y48-Z48-AA48 -> 0 | AC48: =IF(AF47>0.5,AF47*(1+AC$23)+AC$24,0) -> 0 | AD48: =MIN(AD$23,AC48) -> 0 | AE48: =IF(AND(AD$24=1,OR(AC$25="",$C48>=AC$25)),MAX(0,MIN(AC48-AD48,$D48-(G48+K48+O48+S48+W48+AA48))),0) -> 0 | AF48: =AC48-AD48-AE48 -> 0 | AG48: =IF(AJ47>0.5,AJ47*(1+AG$23)+AG$24,0) -> 0 | AH48: =MIN(AH$23,AG48) -> 0 | AI48: =IF(AND(AH$24=1,OR(AG$25="",$C48>=AG$25)),MAX(0,MIN(AG48-AH48,$D48-(G48+K48+O48+S48+W48+AA48+AE48))),0) -> 0 | AJ48: =AG48-AH48-AI48 -> 0 | AK48: =IF(AK47>0.5,AK47*(1+$E$12)+$G$12-MIN($F$12,AK47*(1+$E$12)+$G$12),0) -> 0 | AL48: =IF(AL47>0.5,AL47*(1+$E$13)+$G$13-MIN($F$13,AL47*(1+$E$13)+$G$13),0) -> 0 | AM48: =IF(AM47>0.5,AM47*(1+$E$14)+$G$14-MIN($F$14,AM47*(1+$E$14)+$G$14),0) -> 0 | AN48: =IF(AN47>0.5,AN47*(1+$E$15)+$G$15-MIN($F$15,AN47*(1+$E$15)+$G$15),0) -> 0 | AO48: =IF(AO47>0.5,AO47*(1+$E$16)+$G$16-MIN($F$16,AO47*(1+$E$16)+$G$16),0) -> 0 | AP48: =IF(AP47>0.5,AP47*(1+$E$17)+$G$17-MIN($F$17,AP47*(1+$E$17)+$G$17),0) -> 0 | AQ48: =IF(AQ47>0.5,AQ47*(1+$E$18)+$G$18-MIN($F$18,AQ47*(1+$E$18)+$G$18),0) -> 0 | AR48: =IF(AR47>0.5,AR47*(1+$E$19)+$G$19-MIN($F$19,AR47*(1+$E$19)+$G$19),0) -> 0 | AS48: =H48+L48+P48+T48+X48+AB48+AF48+AJ48 -> 0 | AT48: =SUM(AK48:AR48) -> 0 | AU48: =F48+G48+J48+K48+N48+O48+R48+S48+V48+W48+Z48+AA48+AD48+AE48+AH48+AI48 -> 0
B49: 22 | C49: =EDATE($C$7,21) -> 46935 | D49: =$C$8-(F49+J49+N49+R49+V49+Z49+AD49+AH49) -> 0 | E49: =IF(H48>0.5,H48*(1+E$23)+E$24,0) -> 0 | F49: =MIN(F$23,E49) -> 0 | G49: =IF(AND(F$24=1,OR(E$25="",$C49>=E$25)),MAX(0,MIN(E49-F49,$D49-(0))),0) -> 0 | H49: =E49-F49-G49 -> 0 | I49: =IF(L48>0.5,L48*(1+I$23)+I$24,0) -> 0 | J49: =MIN(J$23,I49) -> 0 | K49: =IF(AND(J$24=1,OR(I$25="",$C49>=I$25)),MAX(0,MIN(I49-J49,$D49-(G49))),0) -> 0 | L49: =I49-J49-K49 -> 0 | M49: =IF(P48>0.5,P48*(1+M$23)+M$24,0) -> 0 | N49: =MIN(N$23,M49) -> 0 | O49: =IF(AND(N$24=1,OR(M$25="",$C49>=M$25)),MAX(0,MIN(M49-N49,$D49-(G49+K49))),0) -> 0 | P49: =M49-N49-O49 -> 0 | Q49: =IF(T48>0.5,T48*(1+Q$23)+Q$24,0) -> 0 | R49: =MIN(R$23,Q49) -> 0 | S49: =IF(AND(R$24=1,OR(Q$25="",$C49>=Q$25)),MAX(0,MIN(Q49-R49,$D49-(G49+K49+O49))),0) -> 0 | T49: =Q49-R49-S49 -> 0 | U49: =IF(X48>0.5,X48*(1+U$23)+U$24,0) -> 0 | V49: =MIN(V$23,U49) -> 0 | W49: =IF(AND(V$24=1,OR(U$25="",$C49>=U$25)),MAX(0,MIN(U49-V49,$D49-(G49+K49+O49+S49))),0) -> 0 | X49: =U49-V49-W49 -> 0 | Y49: =IF(AB48>0.5,AB48*(1+Y$23)+Y$24,0) -> 0 | Z49: =MIN(Z$23,Y49) -> 0 | AA49: =IF(AND(Z$24=1,OR(Y$25="",$C49>=Y$25)),MAX(0,MIN(Y49-Z49,$D49-(G49+K49+O49+S49+W49))),0) -> 0 | AB49: =Y49-Z49-AA49 -> 0 | AC49: =IF(AF48>0.5,AF48*(1+AC$23)+AC$24,0) -> 0 | AD49: =MIN(AD$23,AC49) -> 0 | AE49: =IF(AND(AD$24=1,OR(AC$25="",$C49>=AC$25)),MAX(0,MIN(AC49-AD49,$D49-(G49+K49+O49+S49+W49+AA49))),0) -> 0 | AF49: =AC49-AD49-AE49 -> 0 | AG49: =IF(AJ48>0.5,AJ48*(1+AG$23)+AG$24,0) -> 0 | AH49: =MIN(AH$23,AG49) -> 0 | AI49: =IF(AND(AH$24=1,OR(AG$25="",$C49>=AG$25)),MAX(0,MIN(AG49-AH49,$D49-(G49+K49+O49+S49+W49+AA49+AE49))),0) -> 0 | AJ49: =AG49-AH49-AI49 -> 0 | AK49: =IF(AK48>0.5,AK48*(1+$E$12)+$G$12-MIN($F$12,AK48*(1+$E$12)+$G$12),0) -> 0 | AL49: =IF(AL48>0.5,AL48*(1+$E$13)+$G$13-MIN($F$13,AL48*(1+$E$13)+$G$13),0) -> 0 | AM49: =IF(AM48>0.5,AM48*(1+$E$14)+$G$14-MIN($F$14,AM48*(1+$E$14)+$G$14),0) -> 0 | AN49: =IF(AN48>0.5,AN48*(1+$E$15)+$G$15-MIN($F$15,AN48*(1+$E$15)+$G$15),0) -> 0 | AO49: =IF(AO48>0.5,AO48*(1+$E$16)+$G$16-MIN($F$16,AO48*(1+$E$16)+$G$16),0) -> 0 | AP49: =IF(AP48>0.5,AP48*(1+$E$17)+$G$17-MIN($F$17,AP48*(1+$E$17)+$G$17),0) -> 0 | AQ49: =IF(AQ48>0.5,AQ48*(1+$E$18)+$G$18-MIN($F$18,AQ48*(1+$E$18)+$G$18),0) -> 0 | AR49: =IF(AR48>0.5,AR48*(1+$E$19)+$G$19-MIN($F$19,AR48*(1+$E$19)+$G$19),0) -> 0 | AS49: =H49+L49+P49+T49+X49+AB49+AF49+AJ49 -> 0 | AT49: =SUM(AK49:AR49) -> 0 | AU49: =F49+G49+J49+K49+N49+O49+R49+S49+V49+W49+Z49+AA49+AD49+AE49+AH49+AI49 -> 0
B50: 23 | C50: =EDATE($C$7,22) -> 46966 | D50: =$C$8-(F50+J50+N50+R50+V50+Z50+AD50+AH50) -> 0 | E50: =IF(H49>0.5,H49*(1+E$23)+E$24,0) -> 0 | F50: =MIN(F$23,E50) -> 0 | G50: =IF(AND(F$24=1,OR(E$25="",$C50>=E$25)),MAX(0,MIN(E50-F50,$D50-(0))),0) -> 0 | H50: =E50-F50-G50 -> 0 | I50: =IF(L49>0.5,L49*(1+I$23)+I$24,0) -> 0 | J50: =MIN(J$23,I50) -> 0 | K50: =IF(AND(J$24=1,OR(I$25="",$C50>=I$25)),MAX(0,MIN(I50-J50,$D50-(G50))),0) -> 0 | L50: =I50-J50-K50 -> 0 | M50: =IF(P49>0.5,P49*(1+M$23)+M$24,0) -> 0 | N50: =MIN(N$23,M50) -> 0 | O50: =IF(AND(N$24=1,OR(M$25="",$C50>=M$25)),MAX(0,MIN(M50-N50,$D50-(G50+K50))),0) -> 0 | P50: =M50-N50-O50 -> 0 | Q50: =IF(T49>0.5,T49*(1+Q$23)+Q$24,0) -> 0 | R50: =MIN(R$23,Q50) -> 0 | S50: =IF(AND(R$24=1,OR(Q$25="",$C50>=Q$25)),MAX(0,MIN(Q50-R50,$D50-(G50+K50+O50))),0) -> 0 | T50: =Q50-R50-S50 -> 0 | U50: =IF(X49>0.5,X49*(1+U$23)+U$24,0) -> 0 | V50: =MIN(V$23,U50) -> 0 | W50: =IF(AND(V$24=1,OR(U$25="",$C50>=U$25)),MAX(0,MIN(U50-V50,$D50-(G50+K50+O50+S50))),0) -> 0 | X50: =U50-V50-W50 -> 0 | Y50: =IF(AB49>0.5,AB49*(1+Y$23)+Y$24,0) -> 0 | Z50: =MIN(Z$23,Y50) -> 0 | AA50: =IF(AND(Z$24=1,OR(Y$25="",$C50>=Y$25)),MAX(0,MIN(Y50-Z50,$D50-(G50+K50+O50+S50+W50))),0) -> 0 | AB50: =Y50-Z50-AA50 -> 0 | AC50: =IF(AF49>0.5,AF49*(1+AC$23)+AC$24,0) -> 0 | AD50: =MIN(AD$23,AC50) -> 0 | AE50: =IF(AND(AD$24=1,OR(AC$25="",$C50>=AC$25)),MAX(0,MIN(AC50-AD50,$D50-(G50+K50+O50+S50+W50+AA50))),0) -> 0 | AF50: =AC50-AD50-AE50 -> 0 | AG50: =IF(AJ49>0.5,AJ49*(1+AG$23)+AG$24,0) -> 0 | AH50: =MIN(AH$23,AG50) -> 0 | AI50: =IF(AND(AH$24=1,OR(AG$25="",$C50>=AG$25)),MAX(0,MIN(AG50-AH50,$D50-(G50+K50+O50+S50+W50+AA50+AE50))),0) -> 0 | AJ50: =AG50-AH50-AI50 -> 0 | AK50: =IF(AK49>0.5,AK49*(1+$E$12)+$G$12-MIN($F$12,AK49*(1+$E$12)+$G$12),0) -> 0 | AL50: =IF(AL49>0.5,AL49*(1+$E$13)+$G$13-MIN($F$13,AL49*(1+$E$13)+$G$13),0) -> 0 | AM50: =IF(AM49>0.5,AM49*(1+$E$14)+$G$14-MIN($F$14,AM49*(1+$E$14)+$G$14),0) -> 0 | AN50: =IF(AN49>0.5,AN49*(1+$E$15)+$G$15-MIN($F$15,AN49*(1+$E$15)+$G$15),0) -> 0 | AO50: =IF(AO49>0.5,AO49*(1+$E$16)+$G$16-MIN($F$16,AO49*(1+$E$16)+$G$16),0) -> 0 | AP50: =IF(AP49>0.5,AP49*(1+$E$17)+$G$17-MIN($F$17,AP49*(1+$E$17)+$G$17),0) -> 0 | AQ50: =IF(AQ49>0.5,AQ49*(1+$E$18)+$G$18-MIN($F$18,AQ49*(1+$E$18)+$G$18),0) -> 0 | AR50: =IF(AR49>0.5,AR49*(1+$E$19)+$G$19-MIN($F$19,AR49*(1+$E$19)+$G$19),0) -> 0 | AS50: =H50+L50+P50+T50+X50+AB50+AF50+AJ50 -> 0 | AT50: =SUM(AK50:AR50) -> 0 | AU50: =F50+G50+J50+K50+N50+O50+R50+S50+V50+W50+Z50+AA50+AD50+AE50+AH50+AI50 -> 0
B51: 24 | C51: =EDATE($C$7,23) -> 46997 | D51: =$C$8-(F51+J51+N51+R51+V51+Z51+AD51+AH51) -> 0 | E51: =IF(H50>0.5,H50*(1+E$23)+E$24,0) -> 0 | F51: =MIN(F$23,E51) -> 0 | G51: =IF(AND(F$24=1,OR(E$25="",$C51>=E$25)),MAX(0,MIN(E51-F51,$D51-(0))),0) -> 0 | H51: =E51-F51-G51 -> 0 | I51: =IF(L50>0.5,L50*(1+I$23)+I$24,0) -> 0 | J51: =MIN(J$23,I51) -> 0 | K51: =IF(AND(J$24=1,OR(I$25="",$C51>=I$25)),MAX(0,MIN(I51-J51,$D51-(G51))),0) -> 0 | L51: =I51-J51-K51 -> 0 | M51: =IF(P50>0.5,P50*(1+M$23)+M$24,0) -> 0 | N51: =MIN(N$23,M51) -> 0 | O51: =IF(AND(N$24=1,OR(M$25="",$C51>=M$25)),MAX(0,MIN(M51-N51,$D51-(G51+K51))),0) -> 0 | P51: =M51-N51-O51 -> 0 | Q51: =IF(T50>0.5,T50*(1+Q$23)+Q$24,0) -> 0 | R51: =MIN(R$23,Q51) -> 0 | S51: =IF(AND(R$24=1,OR(Q$25="",$C51>=Q$25)),MAX(0,MIN(Q51-R51,$D51-(G51+K51+O51))),0) -> 0 | T51: =Q51-R51-S51 -> 0 | U51: =IF(X50>0.5,X50*(1+U$23)+U$24,0) -> 0 | V51: =MIN(V$23,U51) -> 0 | W51: =IF(AND(V$24=1,OR(U$25="",$C51>=U$25)),MAX(0,MIN(U51-V51,$D51-(G51+K51+O51+S51))),0) -> 0 | X51: =U51-V51-W51 -> 0 | Y51: =IF(AB50>0.5,AB50*(1+Y$23)+Y$24,0) -> 0 | Z51: =MIN(Z$23,Y51) -> 0 | AA51: =IF(AND(Z$24=1,OR(Y$25="",$C51>=Y$25)),MAX(0,MIN(Y51-Z51,$D51-(G51+K51+O51+S51+W51))),0) -> 0 | AB51: =Y51-Z51-AA51 -> 0 | AC51: =IF(AF50>0.5,AF50*(1+AC$23)+AC$24,0) -> 0 | AD51: =MIN(AD$23,AC51) -> 0 | AE51: =IF(AND(AD$24=1,OR(AC$25="",$C51>=AC$25)),MAX(0,MIN(AC51-AD51,$D51-(G51+K51+O51+S51+W51+AA51))),0) -> 0 | AF51: =AC51-AD51-AE51 -> 0 | AG51: =IF(AJ50>0.5,AJ50*(1+AG$23)+AG$24,0) -> 0 | AH51: =MIN(AH$23,AG51) -> 0 | AI51: =IF(AND(AH$24=1,OR(AG$25="",$C51>=AG$25)),MAX(0,MIN(AG51-AH51,$D51-(G51+K51+O51+S51+W51+AA51+AE51))),0) -> 0 | AJ51: =AG51-AH51-AI51 -> 0 | AK51: =IF(AK50>0.5,AK50*(1+$E$12)+$G$12-MIN($F$12,AK50*(1+$E$12)+$G$12),0) -> 0 | AL51: =IF(AL50>0.5,AL50*(1+$E$13)+$G$13-MIN($F$13,AL50*(1+$E$13)+$G$13),0) -> 0 | AM51: =IF(AM50>0.5,AM50*(1+$E$14)+$G$14-MIN($F$14,AM50*(1+$E$14)+$G$14),0) -> 0 | AN51: =IF(AN50>0.5,AN50*(1+$E$15)+$G$15-MIN($F$15,AN50*(1+$E$15)+$G$15),0) -> 0 | AO51: =IF(AO50>0.5,AO50*(1+$E$16)+$G$16-MIN($F$16,AO50*(1+$E$16)+$G$16),0) -> 0 | AP51: =IF(AP50>0.5,AP50*(1+$E$17)+$G$17-MIN($F$17,AP50*(1+$E$17)+$G$17),0) -> 0 | AQ51: =IF(AQ50>0.5,AQ50*(1+$E$18)+$G$18-MIN($F$18,AQ50*(1+$E$18)+$G$18),0) -> 0 | AR51: =IF(AR50>0.5,AR50*(1+$E$19)+$G$19-MIN($F$19,AR50*(1+$E$19)+$G$19),0) -> 0 | AS51: =H51+L51+P51+T51+X51+AB51+AF51+AJ51 -> 0 | AT51: =SUM(AK51:AR51) -> 0 | AU51: =F51+G51+J51+K51+N51+O51+R51+S51+V51+W51+Z51+AA51+AD51+AE51+AH51+AI51 -> 0
B52: 25 | C52: =EDATE($C$7,24) -> 47027 | D52: =$C$8-(F52+J52+N52+R52+V52+Z52+AD52+AH52) -> 0 | E52: =IF(H51>0.5,H51*(1+E$23)+E$24,0) -> 0 | F52: =MIN(F$23,E52) -> 0 | G52: =IF(AND(F$24=1,OR(E$25="",$C52>=E$25)),MAX(0,MIN(E52-F52,$D52-(0))),0) -> 0 | H52: =E52-F52-G52 -> 0 | I52: =IF(L51>0.5,L51*(1+I$23)+I$24,0) -> 0 | J52: =MIN(J$23,I52) -> 0 | K52: =IF(AND(J$24=1,OR(I$25="",$C52>=I$25)),MAX(0,MIN(I52-J52,$D52-(G52))),0) -> 0 | L52: =I52-J52-K52 -> 0 | M52: =IF(P51>0.5,P51*(1+M$23)+M$24,0) -> 0 | N52: =MIN(N$23,M52) -> 0 | O52: =IF(AND(N$24=1,OR(M$25="",$C52>=M$25)),MAX(0,MIN(M52-N52,$D52-(G52+K52))),0) -> 0 | P52: =M52-N52-O52 -> 0 | Q52: =IF(T51>0.5,T51*(1+Q$23)+Q$24,0) -> 0 | R52: =MIN(R$23,Q52) -> 0 | S52: =IF(AND(R$24=1,OR(Q$25="",$C52>=Q$25)),MAX(0,MIN(Q52-R52,$D52-(G52+K52+O52))),0) -> 0 | T52: =Q52-R52-S52 -> 0 | U52: =IF(X51>0.5,X51*(1+U$23)+U$24,0) -> 0 | V52: =MIN(V$23,U52) -> 0 | W52: =IF(AND(V$24=1,OR(U$25="",$C52>=U$25)),MAX(0,MIN(U52-V52,$D52-(G52+K52+O52+S52))),0) -> 0 | X52: =U52-V52-W52 -> 0 | Y52: =IF(AB51>0.5,AB51*(1+Y$23)+Y$24,0) -> 0 | Z52: =MIN(Z$23,Y52) -> 0 | AA52: =IF(AND(Z$24=1,OR(Y$25="",$C52>=Y$25)),MAX(0,MIN(Y52-Z52,$D52-(G52+K52+O52+S52+W52))),0) -> 0 | AB52: =Y52-Z52-AA52 -> 0 | AC52: =IF(AF51>0.5,AF51*(1+AC$23)+AC$24,0) -> 0 | AD52: =MIN(AD$23,AC52) -> 0 | AE52: =IF(AND(AD$24=1,OR(AC$25="",$C52>=AC$25)),MAX(0,MIN(AC52-AD52,$D52-(G52+K52+O52+S52+W52+AA52))),0) -> 0 | AF52: =AC52-AD52-AE52 -> 0 | AG52: =IF(AJ51>0.5,AJ51*(1+AG$23)+AG$24,0) -> 0 | AH52: =MIN(AH$23,AG52) -> 0 | AI52: =IF(AND(AH$24=1,OR(AG$25="",$C52>=AG$25)),MAX(0,MIN(AG52-AH52,$D52-(G52+K52+O52+S52+W52+AA52+AE52))),0) -> 0 | AJ52: =AG52-AH52-AI52 -> 0 | AK52: =IF(AK51>0.5,AK51*(1+$E$12)+$G$12-MIN($F$12,AK51*(1+$E$12)+$G$12),0) -> 0 | AL52: =IF(AL51>0.5,AL51*(1+$E$13)+$G$13-MIN($F$13,AL51*(1+$E$13)+$G$13),0) -> 0 | AM52: =IF(AM51>0.5,AM51*(1+$E$14)+$G$14-MIN($F$14,AM51*(1+$E$14)+$G$14),0) -> 0 | AN52: =IF(AN51>0.5,AN51*(1+$E$15)+$G$15-MIN($F$15,AN51*(1+$E$15)+$G$15),0) -> 0 | AO52: =IF(AO51>0.5,AO51*(1+$E$16)+$G$16-MIN($F$16,AO51*(1+$E$16)+$G$16),0) -> 0 | AP52: =IF(AP51>0.5,AP51*(1+$E$17)+$G$17-MIN($F$17,AP51*(1+$E$17)+$G$17),0) -> 0 | AQ52: =IF(AQ51>0.5,AQ51*(1+$E$18)+$G$18-MIN($F$18,AQ51*(1+$E$18)+$G$18),0) -> 0 | AR52: =IF(AR51>0.5,AR51*(1+$E$19)+$G$19-MIN($F$19,AR51*(1+$E$19)+$G$19),0) -> 0 | AS52: =H52+L52+P52+T52+X52+AB52+AF52+AJ52 -> 0 | AT52: =SUM(AK52:AR52) -> 0 | AU52: =F52+G52+J52+K52+N52+O52+R52+S52+V52+W52+Z52+AA52+AD52+AE52+AH52+AI52 -> 0
B53: 26 | C53: =EDATE($C$7,25) -> 47058 | D53: =$C$8-(F53+J53+N53+R53+V53+Z53+AD53+AH53) -> 0 | E53: =IF(H52>0.5,H52*(1+E$23)+E$24,0) -> 0 | F53: =MIN(F$23,E53) -> 0 | G53: =IF(AND(F$24=1,OR(E$25="",$C53>=E$25)),MAX(0,MIN(E53-F53,$D53-(0))),0) -> 0 | H53: =E53-F53-G53 -> 0 | I53: =IF(L52>0.5,L52*(1+I$23)+I$24,0) -> 0 | J53: =MIN(J$23,I53) -> 0 | K53: =IF(AND(J$24=1,OR(I$25="",$C53>=I$25)),MAX(0,MIN(I53-J53,$D53-(G53))),0) -> 0 | L53: =I53-J53-K53 -> 0 | M53: =IF(P52>0.5,P52*(1+M$23)+M$24,0) -> 0 | N53: =MIN(N$23,M53) -> 0 | O53: =IF(AND(N$24=1,OR(M$25="",$C53>=M$25)),MAX(0,MIN(M53-N53,$D53-(G53+K53))),0) -> 0 | P53: =M53-N53-O53 -> 0 | Q53: =IF(T52>0.5,T52*(1+Q$23)+Q$24,0) -> 0 | R53: =MIN(R$23,Q53) -> 0 | S53: =IF(AND(R$24=1,OR(Q$25="",$C53>=Q$25)),MAX(0,MIN(Q53-R53,$D53-(G53+K53+O53))),0) -> 0 | T53: =Q53-R53-S53 -> 0 | U53: =IF(X52>0.5,X52*(1+U$23)+U$24,0) -> 0 | V53: =MIN(V$23,U53) -> 0 | W53: =IF(AND(V$24=1,OR(U$25="",$C53>=U$25)),MAX(0,MIN(U53-V53,$D53-(G53+K53+O53+S53))),0) -> 0 | X53: =U53-V53-W53 -> 0 | Y53: =IF(AB52>0.5,AB52*(1+Y$23)+Y$24,0) -> 0 | Z53: =MIN(Z$23,Y53) -> 0 | AA53: =IF(AND(Z$24=1,OR(Y$25="",$C53>=Y$25)),MAX(0,MIN(Y53-Z53,$D53-(G53+K53+O53+S53+W53))),0) -> 0 | AB53: =Y53-Z53-AA53 -> 0 | AC53: =IF(AF52>0.5,AF52*(1+AC$23)+AC$24,0) -> 0 | AD53: =MIN(AD$23,AC53) -> 0 | AE53: =IF(AND(AD$24=1,OR(AC$25="",$C53>=AC$25)),MAX(0,MIN(AC53-AD53,$D53-(G53+K53+O53+S53+W53+AA53))),0) -> 0 | AF53: =AC53-AD53-AE53 -> 0 | AG53: =IF(AJ52>0.5,AJ52*(1+AG$23)+AG$24,0) -> 0 | AH53: =MIN(AH$23,AG53) -> 0 | AI53: =IF(AND(AH$24=1,OR(AG$25="",$C53>=AG$25)),MAX(0,MIN(AG53-AH53,$D53-(G53+K53+O53+S53+W53+AA53+AE53))),0) -> 0 | AJ53: =AG53-AH53-AI53 -> 0 | AK53: =IF(AK52>0.5,AK52*(1+$E$12)+$G$12-MIN($F$12,AK52*(1+$E$12)+$G$12),0) -> 0 | AL53: =IF(AL52>0.5,AL52*(1+$E$13)+$G$13-MIN($F$13,AL52*(1+$E$13)+$G$13),0) -> 0 | AM53: =IF(AM52>0.5,AM52*(1+$E$14)+$G$14-MIN($F$14,AM52*(1+$E$14)+$G$14),0) -> 0 | AN53: =IF(AN52>0.5,AN52*(1+$E$15)+$G$15-MIN($F$15,AN52*(1+$E$15)+$G$15),0) -> 0 | AO53: =IF(AO52>0.5,AO52*(1+$E$16)+$G$16-MIN($F$16,AO52*(1+$E$16)+$G$16),0) -> 0 | AP53: =IF(AP52>0.5,AP52*(1+$E$17)+$G$17-MIN($F$17,AP52*(1+$E$17)+$G$17),0) -> 0 | AQ53: =IF(AQ52>0.5,AQ52*(1+$E$18)+$G$18-MIN($F$18,AQ52*(1+$E$18)+$G$18),0) -> 0 | AR53: =IF(AR52>0.5,AR52*(1+$E$19)+$G$19-MIN($F$19,AR52*(1+$E$19)+$G$19),0) -> 0 | AS53: =H53+L53+P53+T53+X53+AB53+AF53+AJ53 -> 0 | AT53: =SUM(AK53:AR53) -> 0 | AU53: =F53+G53+J53+K53+N53+O53+R53+S53+V53+W53+Z53+AA53+AD53+AE53+AH53+AI53 -> 0
B54: 27 | C54: =EDATE($C$7,26) -> 47088 | D54: =$C$8-(F54+J54+N54+R54+V54+Z54+AD54+AH54) -> 0 | E54: =IF(H53>0.5,H53*(1+E$23)+E$24,0) -> 0 | F54: =MIN(F$23,E54) -> 0 | G54: =IF(AND(F$24=1,OR(E$25="",$C54>=E$25)),MAX(0,MIN(E54-F54,$D54-(0))),0) -> 0 | H54: =E54-F54-G54 -> 0 | I54: =IF(L53>0.5,L53*(1+I$23)+I$24,0) -> 0 | J54: =MIN(J$23,I54) -> 0 | K54: =IF(AND(J$24=1,OR(I$25="",$C54>=I$25)),MAX(0,MIN(I54-J54,$D54-(G54))),0) -> 0 | L54: =I54-J54-K54 -> 0 | M54: =IF(P53>0.5,P53*(1+M$23)+M$24,0) -> 0 | N54: =MIN(N$23,M54) -> 0 | O54: =IF(AND(N$24=1,OR(M$25="",$C54>=M$25)),MAX(0,MIN(M54-N54,$D54-(G54+K54))),0) -> 0 | P54: =M54-N54-O54 -> 0 | Q54: =IF(T53>0.5,T53*(1+Q$23)+Q$24,0) -> 0 | R54: =MIN(R$23,Q54) -> 0 | S54: =IF(AND(R$24=1,OR(Q$25="",$C54>=Q$25)),MAX(0,MIN(Q54-R54,$D54-(G54+K54+O54))),0) -> 0 | T54: =Q54-R54-S54 -> 0 | U54: =IF(X53>0.5,X53*(1+U$23)+U$24,0) -> 0 | V54: =MIN(V$23,U54) -> 0 | W54: =IF(AND(V$24=1,OR(U$25="",$C54>=U$25)),MAX(0,MIN(U54-V54,$D54-(G54+K54+O54+S54))),0) -> 0 | X54: =U54-V54-W54 -> 0 | Y54: =IF(AB53>0.5,AB53*(1+Y$23)+Y$24,0) -> 0 | Z54: =MIN(Z$23,Y54) -> 0 | AA54: =IF(AND(Z$24=1,OR(Y$25="",$C54>=Y$25)),MAX(0,MIN(Y54-Z54,$D54-(G54+K54+O54+S54+W54))),0) -> 0 | AB54: =Y54-Z54-AA54 -> 0 | AC54: =IF(AF53>0.5,AF53*(1+AC$23)+AC$24,0) -> 0 | AD54: =MIN(AD$23,AC54) -> 0 | AE54: =IF(AND(AD$24=1,OR(AC$25="",$C54>=AC$25)),MAX(0,MIN(AC54-AD54,$D54-(G54+K54+O54+S54+W54+AA54))),0) -> 0 | AF54: =AC54-AD54-AE54 -> 0 | AG54: =IF(AJ53>0.5,AJ53*(1+AG$23)+AG$24,0) -> 0 | AH54: =MIN(AH$23,AG54) -> 0 | AI54: =IF(AND(AH$24=1,OR(AG$25="",$C54>=AG$25)),MAX(0,MIN(AG54-AH54,$D54-(G54+K54+O54+S54+W54+AA54+AE54))),0) -> 0 | AJ54: =AG54-AH54-AI54 -> 0 | AK54: =IF(AK53>0.5,AK53*(1+$E$12)+$G$12-MIN($F$12,AK53*(1+$E$12)+$G$12),0) -> 0 | AL54: =IF(AL53>0.5,AL53*(1+$E$13)+$G$13-MIN($F$13,AL53*(1+$E$13)+$G$13),0) -> 0 | AM54: =IF(AM53>0.5,AM53*(1+$E$14)+$G$14-MIN($F$14,AM53*(1+$E$14)+$G$14),0) -> 0 | AN54: =IF(AN53>0.5,AN53*(1+$E$15)+$G$15-MIN($F$15,AN53*(1+$E$15)+$G$15),0) -> 0 | AO54: =IF(AO53>0.5,AO53*(1+$E$16)+$G$16-MIN($F$16,AO53*(1+$E$16)+$G$16),0) -> 0 | AP54: =IF(AP53>0.5,AP53*(1+$E$17)+$G$17-MIN($F$17,AP53*(1+$E$17)+$G$17),0) -> 0 | AQ54: =IF(AQ53>0.5,AQ53*(1+$E$18)+$G$18-MIN($F$18,AQ53*(1+$E$18)+$G$18),0) -> 0 | AR54: =IF(AR53>0.5,AR53*(1+$E$19)+$G$19-MIN($F$19,AR53*(1+$E$19)+$G$19),0) -> 0 | AS54: =H54+L54+P54+T54+X54+AB54+AF54+AJ54 -> 0 | AT54: =SUM(AK54:AR54) -> 0 | AU54: =F54+G54+J54+K54+N54+O54+R54+S54+V54+W54+Z54+AA54+AD54+AE54+AH54+AI54 -> 0
B55: 28 | C55: =EDATE($C$7,27) -> 47119 | D55: =$C$8-(F55+J55+N55+R55+V55+Z55+AD55+AH55) -> 0 | E55: =IF(H54>0.5,H54*(1+E$23)+E$24,0) -> 0 | F55: =MIN(F$23,E55) -> 0 | G55: =IF(AND(F$24=1,OR(E$25="",$C55>=E$25)),MAX(0,MIN(E55-F55,$D55-(0))),0) -> 0 | H55: =E55-F55-G55 -> 0 | I55: =IF(L54>0.5,L54*(1+I$23)+I$24,0) -> 0 | J55: =MIN(J$23,I55) -> 0 | K55: =IF(AND(J$24=1,OR(I$25="",$C55>=I$25)),MAX(0,MIN(I55-J55,$D55-(G55))),0) -> 0 | L55: =I55-J55-K55 -> 0 | M55: =IF(P54>0.5,P54*(1+M$23)+M$24,0) -> 0 | N55: =MIN(N$23,M55) -> 0 | O55: =IF(AND(N$24=1,OR(M$25="",$C55>=M$25)),MAX(0,MIN(M55-N55,$D55-(G55+K55))),0) -> 0 | P55: =M55-N55-O55 -> 0 | Q55: =IF(T54>0.5,T54*(1+Q$23)+Q$24,0) -> 0 | R55: =MIN(R$23,Q55) -> 0 | S55: =IF(AND(R$24=1,OR(Q$25="",$C55>=Q$25)),MAX(0,MIN(Q55-R55,$D55-(G55+K55+O55))),0) -> 0 | T55: =Q55-R55-S55 -> 0 | U55: =IF(X54>0.5,X54*(1+U$23)+U$24,0) -> 0 | V55: =MIN(V$23,U55) -> 0 | W55: =IF(AND(V$24=1,OR(U$25="",$C55>=U$25)),MAX(0,MIN(U55-V55,$D55-(G55+K55+O55+S55))),0) -> 0 | X55: =U55-V55-W55 -> 0 | Y55: =IF(AB54>0.5,AB54*(1+Y$23)+Y$24,0) -> 0 | Z55: =MIN(Z$23,Y55) -> 0 | AA55: =IF(AND(Z$24=1,OR(Y$25="",$C55>=Y$25)),MAX(0,MIN(Y55-Z55,$D55-(G55+K55+O55+S55+W55))),0) -> 0 | AB55: =Y55-Z55-AA55 -> 0 | AC55: =IF(AF54>0.5,AF54*(1+AC$23)+AC$24,0) -> 0 | AD55: =MIN(AD$23,AC55) -> 0 | AE55: =IF(AND(AD$24=1,OR(AC$25="",$C55>=AC$25)),MAX(0,MIN(AC55-AD55,$D55-(G55+K55+O55+S55+W55+AA55))),0) -> 0 | AF55: =AC55-AD55-AE55 -> 0 | AG55: =IF(AJ54>0.5,AJ54*(1+AG$23)+AG$24,0) -> 0 | AH55: =MIN(AH$23,AG55) -> 0 | AI55: =IF(AND(AH$24=1,OR(AG$25="",$C55>=AG$25)),MAX(0,MIN(AG55-AH55,$D55-(G55+K55+O55+S55+W55+AA55+AE55))),0) -> 0 | AJ55: =AG55-AH55-AI55 -> 0 | AK55: =IF(AK54>0.5,AK54*(1+$E$12)+$G$12-MIN($F$12,AK54*(1+$E$12)+$G$12),0) -> 0 | AL55: =IF(AL54>0.5,AL54*(1+$E$13)+$G$13-MIN($F$13,AL54*(1+$E$13)+$G$13),0) -> 0 | AM55: =IF(AM54>0.5,AM54*(1+$E$14)+$G$14-MIN($F$14,AM54*(1+$E$14)+$G$14),0) -> 0 | AN55: =IF(AN54>0.5,AN54*(1+$E$15)+$G$15-MIN($F$15,AN54*(1+$E$15)+$G$15),0) -> 0 | AO55: =IF(AO54>0.5,AO54*(1+$E$16)+$G$16-MIN($F$16,AO54*(1+$E$16)+$G$16),0) -> 0 | AP55: =IF(AP54>0.5,AP54*(1+$E$17)+$G$17-MIN($F$17,AP54*(1+$E$17)+$G$17),0) -> 0 | AQ55: =IF(AQ54>0.5,AQ54*(1+$E$18)+$G$18-MIN($F$18,AQ54*(1+$E$18)+$G$18),0) -> 0 | AR55: =IF(AR54>0.5,AR54*(1+$E$19)+$G$19-MIN($F$19,AR54*(1+$E$19)+$G$19),0) -> 0 | AS55: =H55+L55+P55+T55+X55+AB55+AF55+AJ55 -> 0 | AT55: =SUM(AK55:AR55) -> 0 | AU55: =F55+G55+J55+K55+N55+O55+R55+S55+V55+W55+Z55+AA55+AD55+AE55+AH55+AI55 -> 0
B56: 29 | C56: =EDATE($C$7,28) -> 47150 | D56: =$C$8-(F56+J56+N56+R56+V56+Z56+AD56+AH56) -> 0 | E56: =IF(H55>0.5,H55*(1+E$23)+E$24,0) -> 0 | F56: =MIN(F$23,E56) -> 0 | G56: =IF(AND(F$24=1,OR(E$25="",$C56>=E$25)),MAX(0,MIN(E56-F56,$D56-(0))),0) -> 0 | H56: =E56-F56-G56 -> 0 | I56: =IF(L55>0.5,L55*(1+I$23)+I$24,0) -> 0 | J56: =MIN(J$23,I56) -> 0 | K56: =IF(AND(J$24=1,OR(I$25="",$C56>=I$25)),MAX(0,MIN(I56-J56,$D56-(G56))),0) -> 0 | L56: =I56-J56-K56 -> 0 | M56: =IF(P55>0.5,P55*(1+M$23)+M$24,0) -> 0 | N56: =MIN(N$23,M56) -> 0 | O56: =IF(AND(N$24=1,OR(M$25="",$C56>=M$25)),MAX(0,MIN(M56-N56,$D56-(G56+K56))),0) -> 0 | P56: =M56-N56-O56 -> 0 | Q56: =IF(T55>0.5,T55*(1+Q$23)+Q$24,0) -> 0 | R56: =MIN(R$23,Q56) -> 0 | S56: =IF(AND(R$24=1,OR(Q$25="",$C56>=Q$25)),MAX(0,MIN(Q56-R56,$D56-(G56+K56+O56))),0) -> 0 | T56: =Q56-R56-S56 -> 0 | U56: =IF(X55>0.5,X55*(1+U$23)+U$24,0) -> 0 | V56: =MIN(V$23,U56) -> 0 | W56: =IF(AND(V$24=1,OR(U$25="",$C56>=U$25)),MAX(0,MIN(U56-V56,$D56-(G56+K56+O56+S56))),0) -> 0 | X56: =U56-V56-W56 -> 0 | Y56: =IF(AB55>0.5,AB55*(1+Y$23)+Y$24,0) -> 0 | Z56: =MIN(Z$23,Y56) -> 0 | AA56: =IF(AND(Z$24=1,OR(Y$25="",$C56>=Y$25)),MAX(0,MIN(Y56-Z56,$D56-(G56+K56+O56+S56+W56))),0) -> 0 | AB56: =Y56-Z56-AA56 -> 0 | AC56: =IF(AF55>0.5,AF55*(1+AC$23)+AC$24,0) -> 0 | AD56: =MIN(AD$23,AC56) -> 0 | AE56: =IF(AND(AD$24=1,OR(AC$25="",$C56>=AC$25)),MAX(0,MIN(AC56-AD56,$D56-(G56+K56+O56+S56+W56+AA56))),0) -> 0 | AF56: =AC56-AD56-AE56 -> 0 | AG56: =IF(AJ55>0.5,AJ55*(1+AG$23)+AG$24,0) -> 0 | AH56: =MIN(AH$23,AG56) -> 0 | AI56: =IF(AND(AH$24=1,OR(AG$25="",$C56>=AG$25)),MAX(0,MIN(AG56-AH56,$D56-(G56+K56+O56+S56+W56+AA56+AE56))),0) -> 0 | AJ56: =AG56-AH56-AI56 -> 0 | AK56: =IF(AK55>0.5,AK55*(1+$E$12)+$G$12-MIN($F$12,AK55*(1+$E$12)+$G$12),0) -> 0 | AL56: =IF(AL55>0.5,AL55*(1+$E$13)+$G$13-MIN($F$13,AL55*(1+$E$13)+$G$13),0) -> 0 | AM56: =IF(AM55>0.5,AM55*(1+$E$14)+$G$14-MIN($F$14,AM55*(1+$E$14)+$G$14),0) -> 0 | AN56: =IF(AN55>0.5,AN55*(1+$E$15)+$G$15-MIN($F$15,AN55*(1+$E$15)+$G$15),0) -> 0 | AO56: =IF(AO55>0.5,AO55*(1+$E$16)+$G$16-MIN($F$16,AO55*(1+$E$16)+$G$16),0) -> 0 | AP56: =IF(AP55>0.5,AP55*(1+$E$17)+$G$17-MIN($F$17,AP55*(1+$E$17)+$G$17),0) -> 0 | AQ56: =IF(AQ55>0.5,AQ55*(1+$E$18)+$G$18-MIN($F$18,AQ55*(1+$E$18)+$G$18),0) -> 0 | AR56: =IF(AR55>0.5,AR55*(1+$E$19)+$G$19-MIN($F$19,AR55*(1+$E$19)+$G$19),0) -> 0 | AS56: =H56+L56+P56+T56+X56+AB56+AF56+AJ56 -> 0 | AT56: =SUM(AK56:AR56) -> 0 | AU56: =F56+G56+J56+K56+N56+O56+R56+S56+V56+W56+Z56+AA56+AD56+AE56+AH56+AI56 -> 0
B57: 30 | C57: =EDATE($C$7,29) -> 47178 | D57: =$C$8-(F57+J57+N57+R57+V57+Z57+AD57+AH57) -> 0 | E57: =IF(H56>0.5,H56*(1+E$23)+E$24,0) -> 0 | F57: =MIN(F$23,E57) -> 0 | G57: =IF(AND(F$24=1,OR(E$25="",$C57>=E$25)),MAX(0,MIN(E57-F57,$D57-(0))),0) -> 0 | H57: =E57-F57-G57 -> 0 | I57: =IF(L56>0.5,L56*(1+I$23)+I$24,0) -> 0 | J57: =MIN(J$23,I57) -> 0 | K57: =IF(AND(J$24=1,OR(I$25="",$C57>=I$25)),MAX(0,MIN(I57-J57,$D57-(G57))),0) -> 0 | L57: =I57-J57-K57 -> 0 | M57: =IF(P56>0.5,P56*(1+M$23)+M$24,0) -> 0 | N57: =MIN(N$23,M57) -> 0 | O57: =IF(AND(N$24=1,OR(M$25="",$C57>=M$25)),MAX(0,MIN(M57-N57,$D57-(G57+K57))),0) -> 0 | P57: =M57-N57-O57 -> 0 | Q57: =IF(T56>0.5,T56*(1+Q$23)+Q$24,0) -> 0 | R57: =MIN(R$23,Q57) -> 0 | S57: =IF(AND(R$24=1,OR(Q$25="",$C57>=Q$25)),MAX(0,MIN(Q57-R57,$D57-(G57+K57+O57))),0) -> 0 | T57: =Q57-R57-S57 -> 0 | U57: =IF(X56>0.5,X56*(1+U$23)+U$24,0) -> 0 | V57: =MIN(V$23,U57) -> 0 | W57: =IF(AND(V$24=1,OR(U$25="",$C57>=U$25)),MAX(0,MIN(U57-V57,$D57-(G57+K57+O57+S57))),0) -> 0 | X57: =U57-V57-W57 -> 0 | Y57: =IF(AB56>0.5,AB56*(1+Y$23)+Y$24,0) -> 0 | Z57: =MIN(Z$23,Y57) -> 0 | AA57: =IF(AND(Z$24=1,OR(Y$25="",$C57>=Y$25)),MAX(0,MIN(Y57-Z57,$D57-(G57+K57+O57+S57+W57))),0) -> 0 | AB57: =Y57-Z57-AA57 -> 0 | AC57: =IF(AF56>0.5,AF56*(1+AC$23)+AC$24,0) -> 0 | AD57: =MIN(AD$23,AC57) -> 0 | AE57: =IF(AND(AD$24=1,OR(AC$25="",$C57>=AC$25)),MAX(0,MIN(AC57-AD57,$D57-(G57+K57+O57+S57+W57+AA57))),0) -> 0 | AF57: =AC57-AD57-AE57 -> 0 | AG57: =IF(AJ56>0.5,AJ56*(1+AG$23)+AG$24,0) -> 0 | AH57: =MIN(AH$23,AG57) -> 0 | AI57: =IF(AND(AH$24=1,OR(AG$25="",$C57>=AG$25)),MAX(0,MIN(AG57-AH57,$D57-(G57+K57+O57+S57+W57+AA57+AE57))),0) -> 0 | AJ57: =AG57-AH57-AI57 -> 0 | AK57: =IF(AK56>0.5,AK56*(1+$E$12)+$G$12-MIN($F$12,AK56*(1+$E$12)+$G$12),0) -> 0 | AL57: =IF(AL56>0.5,AL56*(1+$E$13)+$G$13-MIN($F$13,AL56*(1+$E$13)+$G$13),0) -> 0 | AM57: =IF(AM56>0.5,AM56*(1+$E$14)+$G$14-MIN($F$14,AM56*(1+$E$14)+$G$14),0) -> 0 | AN57: =IF(AN56>0.5,AN56*(1+$E$15)+$G$15-MIN($F$15,AN56*(1+$E$15)+$G$15),0) -> 0 | AO57: =IF(AO56>0.5,AO56*(1+$E$16)+$G$16-MIN($F$16,AO56*(1+$E$16)+$G$16),0) -> 0 | AP57: =IF(AP56>0.5,AP56*(1+$E$17)+$G$17-MIN($F$17,AP56*(1+$E$17)+$G$17),0) -> 0 | AQ57: =IF(AQ56>0.5,AQ56*(1+$E$18)+$G$18-MIN($F$18,AQ56*(1+$E$18)+$G$18),0) -> 0 | AR57: =IF(AR56>0.5,AR56*(1+$E$19)+$G$19-MIN($F$19,AR56*(1+$E$19)+$G$19),0) -> 0 | AS57: =H57+L57+P57+T57+X57+AB57+AF57+AJ57 -> 0 | AT57: =SUM(AK57:AR57) -> 0 | AU57: =F57+G57+J57+K57+N57+O57+R57+S57+V57+W57+Z57+AA57+AD57+AE57+AH57+AI57 -> 0
B58: 31 | C58: =EDATE($C$7,30) -> 47209 | D58: =$C$8-(F58+J58+N58+R58+V58+Z58+AD58+AH58) -> 0 | E58: =IF(H57>0.5,H57*(1+E$23)+E$24,0) -> 0 | F58: =MIN(F$23,E58) -> 0 | G58: =IF(AND(F$24=1,OR(E$25="",$C58>=E$25)),MAX(0,MIN(E58-F58,$D58-(0))),0) -> 0 | H58: =E58-F58-G58 -> 0 | I58: =IF(L57>0.5,L57*(1+I$23)+I$24,0) -> 0 | J58: =MIN(J$23,I58) -> 0 | K58: =IF(AND(J$24=1,OR(I$25="",$C58>=I$25)),MAX(0,MIN(I58-J58,$D58-(G58))),0) -> 0 | L58: =I58-J58-K58 -> 0 | M58: =IF(P57>0.5,P57*(1+M$23)+M$24,0) -> 0 | N58: =MIN(N$23,M58) -> 0 | O58: =IF(AND(N$24=1,OR(M$25="",$C58>=M$25)),MAX(0,MIN(M58-N58,$D58-(G58+K58))),0) -> 0 | P58: =M58-N58-O58 -> 0 | Q58: =IF(T57>0.5,T57*(1+Q$23)+Q$24,0) -> 0 | R58: =MIN(R$23,Q58) -> 0 | S58: =IF(AND(R$24=1,OR(Q$25="",$C58>=Q$25)),MAX(0,MIN(Q58-R58,$D58-(G58+K58+O58))),0) -> 0 | T58: =Q58-R58-S58 -> 0 | U58: =IF(X57>0.5,X57*(1+U$23)+U$24,0) -> 0 | V58: =MIN(V$23,U58) -> 0 | W58: =IF(AND(V$24=1,OR(U$25="",$C58>=U$25)),MAX(0,MIN(U58-V58,$D58-(G58+K58+O58+S58))),0) -> 0 | X58: =U58-V58-W58 -> 0 | Y58: =IF(AB57>0.5,AB57*(1+Y$23)+Y$24,0) -> 0 | Z58: =MIN(Z$23,Y58) -> 0 | AA58: =IF(AND(Z$24=1,OR(Y$25="",$C58>=Y$25)),MAX(0,MIN(Y58-Z58,$D58-(G58+K58+O58+S58+W58))),0) -> 0 | AB58: =Y58-Z58-AA58 -> 0 | AC58: =IF(AF57>0.5,AF57*(1+AC$23)+AC$24,0) -> 0 | AD58: =MIN(AD$23,AC58) -> 0 | AE58: =IF(AND(AD$24=1,OR(AC$25="",$C58>=AC$25)),MAX(0,MIN(AC58-AD58,$D58-(G58+K58+O58+S58+W58+AA58))),0) -> 0 | AF58: =AC58-AD58-AE58 -> 0 | AG58: =IF(AJ57>0.5,AJ57*(1+AG$23)+AG$24,0) -> 0 | AH58: =MIN(AH$23,AG58) -> 0 | AI58: =IF(AND(AH$24=1,OR(AG$25="",$C58>=AG$25)),MAX(0,MIN(AG58-AH58,$D58-(G58+K58+O58+S58+W58+AA58+AE58))),0) -> 0 | AJ58: =AG58-AH58-AI58 -> 0 | AK58: =IF(AK57>0.5,AK57*(1+$E$12)+$G$12-MIN($F$12,AK57*(1+$E$12)+$G$12),0) -> 0 | AL58: =IF(AL57>0.5,AL57*(1+$E$13)+$G$13-MIN($F$13,AL57*(1+$E$13)+$G$13),0) -> 0 | AM58: =IF(AM57>0.5,AM57*(1+$E$14)+$G$14-MIN($F$14,AM57*(1+$E$14)+$G$14),0) -> 0 | AN58: =IF(AN57>0.5,AN57*(1+$E$15)+$G$15-MIN($F$15,AN57*(1+$E$15)+$G$15),0) -> 0 | AO58: =IF(AO57>0.5,AO57*(1+$E$16)+$G$16-MIN($F$16,AO57*(1+$E$16)+$G$16),0) -> 0 | AP58: =IF(AP57>0.5,AP57*(1+$E$17)+$G$17-MIN($F$17,AP57*(1+$E$17)+$G$17),0) -> 0 | AQ58: =IF(AQ57>0.5,AQ57*(1+$E$18)+$G$18-MIN($F$18,AQ57*(1+$E$18)+$G$18),0) -> 0 | AR58: =IF(AR57>0.5,AR57*(1+$E$19)+$G$19-MIN($F$19,AR57*(1+$E$19)+$G$19),0) -> 0 | AS58: =H58+L58+P58+T58+X58+AB58+AF58+AJ58 -> 0 | AT58: =SUM(AK58:AR58) -> 0 | AU58: =F58+G58+J58+K58+N58+O58+R58+S58+V58+W58+Z58+AA58+AD58+AE58+AH58+AI58 -> 0
B59: 32 | C59: =EDATE($C$7,31) -> 47239 | D59: =$C$8-(F59+J59+N59+R59+V59+Z59+AD59+AH59) -> 0 | E59: =IF(H58>0.5,H58*(1+E$23)+E$24,0) -> 0 | F59: =MIN(F$23,E59) -> 0 | G59: =IF(AND(F$24=1,OR(E$25="",$C59>=E$25)),MAX(0,MIN(E59-F59,$D59-(0))),0) -> 0 | H59: =E59-F59-G59 -> 0 | I59: =IF(L58>0.5,L58*(1+I$23)+I$24,0) -> 0 | J59: =MIN(J$23,I59) -> 0 | K59: =IF(AND(J$24=1,OR(I$25="",$C59>=I$25)),MAX(0,MIN(I59-J59,$D59-(G59))),0) -> 0 | L59: =I59-J59-K59 -> 0 | M59: =IF(P58>0.5,P58*(1+M$23)+M$24,0) -> 0 | N59: =MIN(N$23,M59) -> 0 | O59: =IF(AND(N$24=1,OR(M$25="",$C59>=M$25)),MAX(0,MIN(M59-N59,$D59-(G59+K59))),0) -> 0 | P59: =M59-N59-O59 -> 0 | Q59: =IF(T58>0.5,T58*(1+Q$23)+Q$24,0) -> 0 | R59: =MIN(R$23,Q59) -> 0 | S59: =IF(AND(R$24=1,OR(Q$25="",$C59>=Q$25)),MAX(0,MIN(Q59-R59,$D59-(G59+K59+O59))),0) -> 0 | T59: =Q59-R59-S59 -> 0 | U59: =IF(X58>0.5,X58*(1+U$23)+U$24,0) -> 0 | V59: =MIN(V$23,U59) -> 0 | W59: =IF(AND(V$24=1,OR(U$25="",$C59>=U$25)),MAX(0,MIN(U59-V59,$D59-(G59+K59+O59+S59))),0) -> 0 | X59: =U59-V59-W59 -> 0 | Y59: =IF(AB58>0.5,AB58*(1+Y$23)+Y$24,0) -> 0 | Z59: =MIN(Z$23,Y59) -> 0 | AA59: =IF(AND(Z$24=1,OR(Y$25="",$C59>=Y$25)),MAX(0,MIN(Y59-Z59,$D59-(G59+K59+O59+S59+W59))),0) -> 0 | AB59: =Y59-Z59-AA59 -> 0 | AC59: =IF(AF58>0.5,AF58*(1+AC$23)+AC$24,0) -> 0 | AD59: =MIN(AD$23,AC59) -> 0 | AE59: =IF(AND(AD$24=1,OR(AC$25="",$C59>=AC$25)),MAX(0,MIN(AC59-AD59,$D59-(G59+K59+O59+S59+W59+AA59))),0) -> 0 | AF59: =AC59-AD59-AE59 -> 0 | AG59: =IF(AJ58>0.5,AJ58*(1+AG$23)+AG$24,0) -> 0 | AH59: =MIN(AH$23,AG59) -> 0 | AI59: =IF(AND(AH$24=1,OR(AG$25="",$C59>=AG$25)),MAX(0,MIN(AG59-AH59,$D59-(G59+K59+O59+S59+W59+AA59+AE59))),0) -> 0 | AJ59: =AG59-AH59-AI59 -> 0 | AK59: =IF(AK58>0.5,AK58*(1+$E$12)+$G$12-MIN($F$12,AK58*(1+$E$12)+$G$12),0) -> 0 | AL59: =IF(AL58>0.5,AL58*(1+$E$13)+$G$13-MIN($F$13,AL58*(1+$E$13)+$G$13),0) -> 0 | AM59: =IF(AM58>0.5,AM58*(1+$E$14)+$G$14-MIN($F$14,AM58*(1+$E$14)+$G$14),0) -> 0 | AN59: =IF(AN58>0.5,AN58*(1+$E$15)+$G$15-MIN($F$15,AN58*(1+$E$15)+$G$15),0) -> 0 | AO59: =IF(AO58>0.5,AO58*(1+$E$16)+$G$16-MIN($F$16,AO58*(1+$E$16)+$G$16),0) -> 0 | AP59: =IF(AP58>0.5,AP58*(1+$E$17)+$G$17-MIN($F$17,AP58*(1+$E$17)+$G$17),0) -> 0 | AQ59: =IF(AQ58>0.5,AQ58*(1+$E$18)+$G$18-MIN($F$18,AQ58*(1+$E$18)+$G$18),0) -> 0 | AR59: =IF(AR58>0.5,AR58*(1+$E$19)+$G$19-MIN($F$19,AR58*(1+$E$19)+$G$19),0) -> 0 | AS59: =H59+L59+P59+T59+X59+AB59+AF59+AJ59 -> 0 | AT59: =SUM(AK59:AR59) -> 0 | AU59: =F59+G59+J59+K59+N59+O59+R59+S59+V59+W59+Z59+AA59+AD59+AE59+AH59+AI59 -> 0
B60: 33 | C60: =EDATE($C$7,32) -> 47270 | D60: =$C$8-(F60+J60+N60+R60+V60+Z60+AD60+AH60) -> 0 | E60: =IF(H59>0.5,H59*(1+E$23)+E$24,0) -> 0 | F60: =MIN(F$23,E60) -> 0 | G60: =IF(AND(F$24=1,OR(E$25="",$C60>=E$25)),MAX(0,MIN(E60-F60,$D60-(0))),0) -> 0 | H60: =E60-F60-G60 -> 0 | I60: =IF(L59>0.5,L59*(1+I$23)+I$24,0) -> 0 | J60: =MIN(J$23,I60) -> 0 | K60: =IF(AND(J$24=1,OR(I$25="",$C60>=I$25)),MAX(0,MIN(I60-J60,$D60-(G60))),0) -> 0 | L60: =I60-J60-K60 -> 0 | M60: =IF(P59>0.5,P59*(1+M$23)+M$24,0) -> 0 | N60: =MIN(N$23,M60) -> 0 | O60: =IF(AND(N$24=1,OR(M$25="",$C60>=M$25)),MAX(0,MIN(M60-N60,$D60-(G60+K60))),0) -> 0 | P60: =M60-N60-O60 -> 0 | Q60: =IF(T59>0.5,T59*(1+Q$23)+Q$24,0) -> 0 | R60: =MIN(R$23,Q60) -> 0 | S60: =IF(AND(R$24=1,OR(Q$25="",$C60>=Q$25)),MAX(0,MIN(Q60-R60,$D60-(G60+K60+O60))),0) -> 0 | T60: =Q60-R60-S60 -> 0 | U60: =IF(X59>0.5,X59*(1+U$23)+U$24,0) -> 0 | V60: =MIN(V$23,U60) -> 0 | W60: =IF(AND(V$24=1,OR(U$25="",$C60>=U$25)),MAX(0,MIN(U60-V60,$D60-(G60+K60+O60+S60))),0) -> 0 | X60: =U60-V60-W60 -> 0 | Y60: =IF(AB59>0.5,AB59*(1+Y$23)+Y$24,0) -> 0 | Z60: =MIN(Z$23,Y60) -> 0 | AA60: =IF(AND(Z$24=1,OR(Y$25="",$C60>=Y$25)),MAX(0,MIN(Y60-Z60,$D60-(G60+K60+O60+S60+W60))),0) -> 0 | AB60: =Y60-Z60-AA60 -> 0 | AC60: =IF(AF59>0.5,AF59*(1+AC$23)+AC$24,0) -> 0 | AD60: =MIN(AD$23,AC60) -> 0 | AE60: =IF(AND(AD$24=1,OR(AC$25="",$C60>=AC$25)),MAX(0,MIN(AC60-AD60,$D60-(G60+K60+O60+S60+W60+AA60))),0) -> 0 | AF60: =AC60-AD60-AE60 -> 0 | AG60: =IF(AJ59>0.5,AJ59*(1+AG$23)+AG$24,0) -> 0 | AH60: =MIN(AH$23,AG60) -> 0 | AI60: =IF(AND(AH$24=1,OR(AG$25="",$C60>=AG$25)),MAX(0,MIN(AG60-AH60,$D60-(G60+K60+O60+S60+W60+AA60+AE60))),0) -> 0 | AJ60: =AG60-AH60-AI60 -> 0 | AK60: =IF(AK59>0.5,AK59*(1+$E$12)+$G$12-MIN($F$12,AK59*(1+$E$12)+$G$12),0) -> 0 | AL60: =IF(AL59>0.5,AL59*(1+$E$13)+$G$13-MIN($F$13,AL59*(1+$E$13)+$G$13),0) -> 0 | AM60: =IF(AM59>0.5,AM59*(1+$E$14)+$G$14-MIN($F$14,AM59*(1+$E$14)+$G$14),0) -> 0 | AN60: =IF(AN59>0.5,AN59*(1+$E$15)+$G$15-MIN($F$15,AN59*(1+$E$15)+$G$15),0) -> 0 | AO60: =IF(AO59>0.5,AO59*(1+$E$16)+$G$16-MIN($F$16,AO59*(1+$E$16)+$G$16),0) -> 0 | AP60: =IF(AP59>0.5,AP59*(1+$E$17)+$G$17-MIN($F$17,AP59*(1+$E$17)+$G$17),0) -> 0 | AQ60: =IF(AQ59>0.5,AQ59*(1+$E$18)+$G$18-MIN($F$18,AQ59*(1+$E$18)+$G$18),0) -> 0 | AR60: =IF(AR59>0.5,AR59*(1+$E$19)+$G$19-MIN($F$19,AR59*(1+$E$19)+$G$19),0) -> 0 | AS60: =H60+L60+P60+T60+X60+AB60+AF60+AJ60 -> 0 | AT60: =SUM(AK60:AR60) -> 0 | AU60: =F60+G60+J60+K60+N60+O60+R60+S60+V60+W60+Z60+AA60+AD60+AE60+AH60+AI60 -> 0
B61: 34 | C61: =EDATE($C$7,33) -> 47300 | D61: =$C$8-(F61+J61+N61+R61+V61+Z61+AD61+AH61) -> 0 | E61: =IF(H60>0.5,H60*(1+E$23)+E$24,0) -> 0 | F61: =MIN(F$23,E61) -> 0 | G61: =IF(AND(F$24=1,OR(E$25="",$C61>=E$25)),MAX(0,MIN(E61-F61,$D61-(0))),0) -> 0 | H61: =E61-F61-G61 -> 0 | I61: =IF(L60>0.5,L60*(1+I$23)+I$24,0) -> 0 | J61: =MIN(J$23,I61) -> 0 | K61: =IF(AND(J$24=1,OR(I$25="",$C61>=I$25)),MAX(0,MIN(I61-J61,$D61-(G61))),0) -> 0 | L61: =I61-J61-K61 -> 0 | M61: =IF(P60>0.5,P60*(1+M$23)+M$24,0) -> 0 | N61: =MIN(N$23,M61) -> 0 | O61: =IF(AND(N$24=1,OR(M$25="",$C61>=M$25)),MAX(0,MIN(M61-N61,$D61-(G61+K61))),0) -> 0 | P61: =M61-N61-O61 -> 0 | Q61: =IF(T60>0.5,T60*(1+Q$23)+Q$24,0) -> 0 | R61: =MIN(R$23,Q61) -> 0 | S61: =IF(AND(R$24=1,OR(Q$25="",$C61>=Q$25)),MAX(0,MIN(Q61-R61,$D61-(G61+K61+O61))),0) -> 0 | T61: =Q61-R61-S61 -> 0 | U61: =IF(X60>0.5,X60*(1+U$23)+U$24,0) -> 0 | V61: =MIN(V$23,U61) -> 0 | W61: =IF(AND(V$24=1,OR(U$25="",$C61>=U$25)),MAX(0,MIN(U61-V61,$D61-(G61+K61+O61+S61))),0) -> 0 | X61: =U61-V61-W61 -> 0 | Y61: =IF(AB60>0.5,AB60*(1+Y$23)+Y$24,0) -> 0 | Z61: =MIN(Z$23,Y61) -> 0 | AA61: =IF(AND(Z$24=1,OR(Y$25="",$C61>=Y$25)),MAX(0,MIN(Y61-Z61,$D61-(G61+K61+O61+S61+W61))),0) -> 0 | AB61: =Y61-Z61-AA61 -> 0 | AC61: =IF(AF60>0.5,AF60*(1+AC$23)+AC$24,0) -> 0 | AD61: =MIN(AD$23,AC61) -> 0 | AE61: =IF(AND(AD$24=1,OR(AC$25="",$C61>=AC$25)),MAX(0,MIN(AC61-AD61,$D61-(G61+K61+O61+S61+W61+AA61))),0) -> 0 | AF61: =AC61-AD61-AE61 -> 0 | AG61: =IF(AJ60>0.5,AJ60*(1+AG$23)+AG$24,0) -> 0 | AH61: =MIN(AH$23,AG61) -> 0 | AI61: =IF(AND(AH$24=1,OR(AG$25="",$C61>=AG$25)),MAX(0,MIN(AG61-AH61,$D61-(G61+K61+O61+S61+W61+AA61+AE61))),0) -> 0 | AJ61: =AG61-AH61-AI61 -> 0 | AK61: =IF(AK60>0.5,AK60*(1+$E$12)+$G$12-MIN($F$12,AK60*(1+$E$12)+$G$12),0) -> 0 | AL61: =IF(AL60>0.5,AL60*(1+$E$13)+$G$13-MIN($F$13,AL60*(1+$E$13)+$G$13),0) -> 0 | AM61: =IF(AM60>0.5,AM60*(1+$E$14)+$G$14-MIN($F$14,AM60*(1+$E$14)+$G$14),0) -> 0 | AN61: =IF(AN60>0.5,AN60*(1+$E$15)+$G$15-MIN($F$15,AN60*(1+$E$15)+$G$15),0) -> 0 | AO61: =IF(AO60>0.5,AO60*(1+$E$16)+$G$16-MIN($F$16,AO60*(1+$E$16)+$G$16),0) -> 0 | AP61: =IF(AP60>0.5,AP60*(1+$E$17)+$G$17-MIN($F$17,AP60*(1+$E$17)+$G$17),0) -> 0 | AQ61: =IF(AQ60>0.5,AQ60*(1+$E$18)+$G$18-MIN($F$18,AQ60*(1+$E$18)+$G$18),0) -> 0 | AR61: =IF(AR60>0.5,AR60*(1+$E$19)+$G$19-MIN($F$19,AR60*(1+$E$19)+$G$19),0) -> 0 | AS61: =H61+L61+P61+T61+X61+AB61+AF61+AJ61 -> 0 | AT61: =SUM(AK61:AR61) -> 0 | AU61: =F61+G61+J61+K61+N61+O61+R61+S61+V61+W61+Z61+AA61+AD61+AE61+AH61+AI61 -> 0
B62: 35 | C62: =EDATE($C$7,34) -> 47331 | D62: =$C$8-(F62+J62+N62+R62+V62+Z62+AD62+AH62) -> 0 | E62: =IF(H61>0.5,H61*(1+E$23)+E$24,0) -> 0 | F62: =MIN(F$23,E62) -> 0 | G62: =IF(AND(F$24=1,OR(E$25="",$C62>=E$25)),MAX(0,MIN(E62-F62,$D62-(0))),0) -> 0 | H62: =E62-F62-G62 -> 0 | I62: =IF(L61>0.5,L61*(1+I$23)+I$24,0) -> 0 | J62: =MIN(J$23,I62) -> 0 | K62: =IF(AND(J$24=1,OR(I$25="",$C62>=I$25)),MAX(0,MIN(I62-J62,$D62-(G62))),0) -> 0 | L62: =I62-J62-K62 -> 0 | M62: =IF(P61>0.5,P61*(1+M$23)+M$24,0) -> 0 | N62: =MIN(N$23,M62) -> 0 | O62: =IF(AND(N$24=1,OR(M$25="",$C62>=M$25)),MAX(0,MIN(M62-N62,$D62-(G62+K62))),0) -> 0 | P62: =M62-N62-O62 -> 0 | Q62: =IF(T61>0.5,T61*(1+Q$23)+Q$24,0) -> 0 | R62: =MIN(R$23,Q62) -> 0 | S62: =IF(AND(R$24=1,OR(Q$25="",$C62>=Q$25)),MAX(0,MIN(Q62-R62,$D62-(G62+K62+O62))),0) -> 0 | T62: =Q62-R62-S62 -> 0 | U62: =IF(X61>0.5,X61*(1+U$23)+U$24,0) -> 0 | V62: =MIN(V$23,U62) -> 0 | W62: =IF(AND(V$24=1,OR(U$25="",$C62>=U$25)),MAX(0,MIN(U62-V62,$D62-(G62+K62+O62+S62))),0) -> 0 | X62: =U62-V62-W62 -> 0 | Y62: =IF(AB61>0.5,AB61*(1+Y$23)+Y$24,0) -> 0 | Z62: =MIN(Z$23,Y62) -> 0 | AA62: =IF(AND(Z$24=1,OR(Y$25="",$C62>=Y$25)),MAX(0,MIN(Y62-Z62,$D62-(G62+K62+O62+S62+W62))),0) -> 0 | AB62: =Y62-Z62-AA62 -> 0 | AC62: =IF(AF61>0.5,AF61*(1+AC$23)+AC$24,0) -> 0 | AD62: =MIN(AD$23,AC62) -> 0 | AE62: =IF(AND(AD$24=1,OR(AC$25="",$C62>=AC$25)),MAX(0,MIN(AC62-AD62,$D62-(G62+K62+O62+S62+W62+AA62))),0) -> 0 | AF62: =AC62-AD62-AE62 -> 0 | AG62: =IF(AJ61>0.5,AJ61*(1+AG$23)+AG$24,0) -> 0 | AH62: =MIN(AH$23,AG62) -> 0 | AI62: =IF(AND(AH$24=1,OR(AG$25="",$C62>=AG$25)),MAX(0,MIN(AG62-AH62,$D62-(G62+K62+O62+S62+W62+AA62+AE62))),0) -> 0 | AJ62: =AG62-AH62-AI62 -> 0 | AK62: =IF(AK61>0.5,AK61*(1+$E$12)+$G$12-MIN($F$12,AK61*(1+$E$12)+$G$12),0) -> 0 | AL62: =IF(AL61>0.5,AL61*(1+$E$13)+$G$13-MIN($F$13,AL61*(1+$E$13)+$G$13),0) -> 0 | AM62: =IF(AM61>0.5,AM61*(1+$E$14)+$G$14-MIN($F$14,AM61*(1+$E$14)+$G$14),0) -> 0 | AN62: =IF(AN61>0.5,AN61*(1+$E$15)+$G$15-MIN($F$15,AN61*(1+$E$15)+$G$15),0) -> 0 | AO62: =IF(AO61>0.5,AO61*(1+$E$16)+$G$16-MIN($F$16,AO61*(1+$E$16)+$G$16),0) -> 0 | AP62: =IF(AP61>0.5,AP61*(1+$E$17)+$G$17-MIN($F$17,AP61*(1+$E$17)+$G$17),0) -> 0 | AQ62: =IF(AQ61>0.5,AQ61*(1+$E$18)+$G$18-MIN($F$18,AQ61*(1+$E$18)+$G$18),0) -> 0 | AR62: =IF(AR61>0.5,AR61*(1+$E$19)+$G$19-MIN($F$19,AR61*(1+$E$19)+$G$19),0) -> 0 | AS62: =H62+L62+P62+T62+X62+AB62+AF62+AJ62 -> 0 | AT62: =SUM(AK62:AR62) -> 0 | AU62: =F62+G62+J62+K62+N62+O62+R62+S62+V62+W62+Z62+AA62+AD62+AE62+AH62+AI62 -> 0
B63: 36 | C63: =EDATE($C$7,35) -> 47362 | D63: =$C$8-(F63+J63+N63+R63+V63+Z63+AD63+AH63) -> 0 | E63: =IF(H62>0.5,H62*(1+E$23)+E$24,0) -> 0 | F63: =MIN(F$23,E63) -> 0 | G63: =IF(AND(F$24=1,OR(E$25="",$C63>=E$25)),MAX(0,MIN(E63-F63,$D63-(0))),0) -> 0 | H63: =E63-F63-G63 -> 0 | I63: =IF(L62>0.5,L62*(1+I$23)+I$24,0) -> 0 | J63: =MIN(J$23,I63) -> 0 | K63: =IF(AND(J$24=1,OR(I$25="",$C63>=I$25)),MAX(0,MIN(I63-J63,$D63-(G63))),0) -> 0 | L63: =I63-J63-K63 -> 0 | M63: =IF(P62>0.5,P62*(1+M$23)+M$24,0) -> 0 | N63: =MIN(N$23,M63) -> 0 | O63: =IF(AND(N$24=1,OR(M$25="",$C63>=M$25)),MAX(0,MIN(M63-N63,$D63-(G63+K63))),0) -> 0 | P63: =M63-N63-O63 -> 0 | Q63: =IF(T62>0.5,T62*(1+Q$23)+Q$24,0) -> 0 | R63: =MIN(R$23,Q63) -> 0 | S63: =IF(AND(R$24=1,OR(Q$25="",$C63>=Q$25)),MAX(0,MIN(Q63-R63,$D63-(G63+K63+O63))),0) -> 0 | T63: =Q63-R63-S63 -> 0 | U63: =IF(X62>0.5,X62*(1+U$23)+U$24,0) -> 0 | V63: =MIN(V$23,U63) -> 0 | W63: =IF(AND(V$24=1,OR(U$25="",$C63>=U$25)),MAX(0,MIN(U63-V63,$D63-(G63+K63+O63+S63))),0) -> 0 | X63: =U63-V63-W63 -> 0 | Y63: =IF(AB62>0.5,AB62*(1+Y$23)+Y$24,0) -> 0 | Z63: =MIN(Z$23,Y63) -> 0 | AA63: =IF(AND(Z$24=1,OR(Y$25="",$C63>=Y$25)),MAX(0,MIN(Y63-Z63,$D63-(G63+K63+O63+S63+W63))),0) -> 0 | AB63: =Y63-Z63-AA63 -> 0 | AC63: =IF(AF62>0.5,AF62*(1+AC$23)+AC$24,0) -> 0 | AD63: =MIN(AD$23,AC63) -> 0 | AE63: =IF(AND(AD$24=1,OR(AC$25="",$C63>=AC$25)),MAX(0,MIN(AC63-AD63,$D63-(G63+K63+O63+S63+W63+AA63))),0) -> 0 | AF63: =AC63-AD63-AE63 -> 0 | AG63: =IF(AJ62>0.5,AJ62*(1+AG$23)+AG$24,0) -> 0 | AH63: =MIN(AH$23,AG63) -> 0 | AI63: =IF(AND(AH$24=1,OR(AG$25="",$C63>=AG$25)),MAX(0,MIN(AG63-AH63,$D63-(G63+K63+O63+S63+W63+AA63+AE63))),0) -> 0 | AJ63: =AG63-AH63-AI63 -> 0 | AK63: =IF(AK62>0.5,AK62*(1+$E$12)+$G$12-MIN($F$12,AK62*(1+$E$12)+$G$12),0) -> 0 | AL63: =IF(AL62>0.5,AL62*(1+$E$13)+$G$13-MIN($F$13,AL62*(1+$E$13)+$G$13),0) -> 0 | AM63: =IF(AM62>0.5,AM62*(1+$E$14)+$G$14-MIN($F$14,AM62*(1+$E$14)+$G$14),0) -> 0 | AN63: =IF(AN62>0.5,AN62*(1+$E$15)+$G$15-MIN($F$15,AN62*(1+$E$15)+$G$15),0) -> 0 | AO63: =IF(AO62>0.5,AO62*(1+$E$16)+$G$16-MIN($F$16,AO62*(1+$E$16)+$G$16),0) -> 0 | AP63: =IF(AP62>0.5,AP62*(1+$E$17)+$G$17-MIN($F$17,AP62*(1+$E$17)+$G$17),0) -> 0 | AQ63: =IF(AQ62>0.5,AQ62*(1+$E$18)+$G$18-MIN($F$18,AQ62*(1+$E$18)+$G$18),0) -> 0 | AR63: =IF(AR62>0.5,AR62*(1+$E$19)+$G$19-MIN($F$19,AR62*(1+$E$19)+$G$19),0) -> 0 | AS63: =H63+L63+P63+T63+X63+AB63+AF63+AJ63 -> 0 | AT63: =SUM(AK63:AR63) -> 0 | AU63: =F63+G63+J63+K63+N63+O63+R63+S63+V63+W63+Z63+AA63+AD63+AE63+AH63+AI63 -> 0
B64: 37 | C64: =EDATE($C$7,36) -> 47392 | D64: =$C$8-(F64+J64+N64+R64+V64+Z64+AD64+AH64) -> 0 | E64: =IF(H63>0.5,H63*(1+E$23)+E$24,0) -> 0 | F64: =MIN(F$23,E64) -> 0 | G64: =IF(AND(F$24=1,OR(E$25="",$C64>=E$25)),MAX(0,MIN(E64-F64,$D64-(0))),0) -> 0 | H64: =E64-F64-G64 -> 0 | I64: =IF(L63>0.5,L63*(1+I$23)+I$24,0) -> 0 | J64: =MIN(J$23,I64) -> 0 | K64: =IF(AND(J$24=1,OR(I$25="",$C64>=I$25)),MAX(0,MIN(I64-J64,$D64-(G64))),0) -> 0 | L64: =I64-J64-K64 -> 0 | M64: =IF(P63>0.5,P63*(1+M$23)+M$24,0) -> 0 | N64: =MIN(N$23,M64) -> 0 | O64: =IF(AND(N$24=1,OR(M$25="",$C64>=M$25)),MAX(0,MIN(M64-N64,$D64-(G64+K64))),0) -> 0 | P64: =M64-N64-O64 -> 0 | Q64: =IF(T63>0.5,T63*(1+Q$23)+Q$24,0) -> 0 | R64: =MIN(R$23,Q64) -> 0 | S64: =IF(AND(R$24=1,OR(Q$25="",$C64>=Q$25)),MAX(0,MIN(Q64-R64,$D64-(G64+K64+O64))),0) -> 0 | T64: =Q64-R64-S64 -> 0 | U64: =IF(X63>0.5,X63*(1+U$23)+U$24,0) -> 0 | V64: =MIN(V$23,U64) -> 0 | W64: =IF(AND(V$24=1,OR(U$25="",$C64>=U$25)),MAX(0,MIN(U64-V64,$D64-(G64+K64+O64+S64))),0) -> 0 | X64: =U64-V64-W64 -> 0 | Y64: =IF(AB63>0.5,AB63*(1+Y$23)+Y$24,0) -> 0 | Z64: =MIN(Z$23,Y64) -> 0 | AA64: =IF(AND(Z$24=1,OR(Y$25="",$C64>=Y$25)),MAX(0,MIN(Y64-Z64,$D64-(G64+K64+O64+S64+W64))),0) -> 0 | AB64: =Y64-Z64-AA64 -> 0 | AC64: =IF(AF63>0.5,AF63*(1+AC$23)+AC$24,0) -> 0 | AD64: =MIN(AD$23,AC64) -> 0 | AE64: =IF(AND(AD$24=1,OR(AC$25="",$C64>=AC$25)),MAX(0,MIN(AC64-AD64,$D64-(G64+K64+O64+S64+W64+AA64))),0) -> 0 | AF64: =AC64-AD64-AE64 -> 0 | AG64: =IF(AJ63>0.5,AJ63*(1+AG$23)+AG$24,0) -> 0 | AH64: =MIN(AH$23,AG64) -> 0 | AI64: =IF(AND(AH$24=1,OR(AG$25="",$C64>=AG$25)),MAX(0,MIN(AG64-AH64,$D64-(G64+K64+O64+S64+W64+AA64+AE64))),0) -> 0 | AJ64: =AG64-AH64-AI64 -> 0 | AK64: =IF(AK63>0.5,AK63*(1+$E$12)+$G$12-MIN($F$12,AK63*(1+$E$12)+$G$12),0) -> 0 | AL64: =IF(AL63>0.5,AL63*(1+$E$13)+$G$13-MIN($F$13,AL63*(1+$E$13)+$G$13),0) -> 0 | AM64: =IF(AM63>0.5,AM63*(1+$E$14)+$G$14-MIN($F$14,AM63*(1+$E$14)+$G$14),0) -> 0 | AN64: =IF(AN63>0.5,AN63*(1+$E$15)+$G$15-MIN($F$15,AN63*(1+$E$15)+$G$15),0) -> 0 | AO64: =IF(AO63>0.5,AO63*(1+$E$16)+$G$16-MIN($F$16,AO63*(1+$E$16)+$G$16),0) -> 0 | AP64: =IF(AP63>0.5,AP63*(1+$E$17)+$G$17-MIN($F$17,AP63*(1+$E$17)+$G$17),0) -> 0 | AQ64: =IF(AQ63>0.5,AQ63*(1+$E$18)+$G$18-MIN($F$18,AQ63*(1+$E$18)+$G$18),0) -> 0 | AR64: =IF(AR63>0.5,AR63*(1+$E$19)+$G$19-MIN($F$19,AR63*(1+$E$19)+$G$19),0) -> 0 | AS64: =H64+L64+P64+T64+X64+AB64+AF64+AJ64 -> 0 | AT64: =SUM(AK64:AR64) -> 0 | AU64: =F64+G64+J64+K64+N64+O64+R64+S64+V64+W64+Z64+AA64+AD64+AE64+AH64+AI64 -> 0
B65: 38 | C65: =EDATE($C$7,37) -> 47423 | D65: =$C$8-(F65+J65+N65+R65+V65+Z65+AD65+AH65) -> 0 | E65: =IF(H64>0.5,H64*(1+E$23)+E$24,0) -> 0 | F65: =MIN(F$23,E65) -> 0 | G65: =IF(AND(F$24=1,OR(E$25="",$C65>=E$25)),MAX(0,MIN(E65-F65,$D65-(0))),0) -> 0 | H65: =E65-F65-G65 -> 0 | I65: =IF(L64>0.5,L64*(1+I$23)+I$24,0) -> 0 | J65: =MIN(J$23,I65) -> 0 | K65: =IF(AND(J$24=1,OR(I$25="",$C65>=I$25)),MAX(0,MIN(I65-J65,$D65-(G65))),0) -> 0 | L65: =I65-J65-K65 -> 0 | M65: =IF(P64>0.5,P64*(1+M$23)+M$24,0) -> 0 | N65: =MIN(N$23,M65) -> 0 | O65: =IF(AND(N$24=1,OR(M$25="",$C65>=M$25)),MAX(0,MIN(M65-N65,$D65-(G65+K65))),0) -> 0 | P65: =M65-N65-O65 -> 0 | Q65: =IF(T64>0.5,T64*(1+Q$23)+Q$24,0) -> 0 | R65: =MIN(R$23,Q65) -> 0 | S65: =IF(AND(R$24=1,OR(Q$25="",$C65>=Q$25)),MAX(0,MIN(Q65-R65,$D65-(G65+K65+O65))),0) -> 0 | T65: =Q65-R65-S65 -> 0 | U65: =IF(X64>0.5,X64*(1+U$23)+U$24,0) -> 0 | V65: =MIN(V$23,U65) -> 0 | W65: =IF(AND(V$24=1,OR(U$25="",$C65>=U$25)),MAX(0,MIN(U65-V65,$D65-(G65+K65+O65+S65))),0) -> 0 | X65: =U65-V65-W65 -> 0 | Y65: =IF(AB64>0.5,AB64*(1+Y$23)+Y$24,0) -> 0 | Z65: =MIN(Z$23,Y65) -> 0 | AA65: =IF(AND(Z$24=1,OR(Y$25="",$C65>=Y$25)),MAX(0,MIN(Y65-Z65,$D65-(G65+K65+O65+S65+W65))),0) -> 0 | AB65: =Y65-Z65-AA65 -> 0 | AC65: =IF(AF64>0.5,AF64*(1+AC$23)+AC$24,0) -> 0 | AD65: =MIN(AD$23,AC65) -> 0 | AE65: =IF(AND(AD$24=1,OR(AC$25="",$C65>=AC$25)),MAX(0,MIN(AC65-AD65,$D65-(G65+K65+O65+S65+W65+AA65))),0) -> 0 | AF65: =AC65-AD65-AE65 -> 0 | AG65: =IF(AJ64>0.5,AJ64*(1+AG$23)+AG$24,0) -> 0 | AH65: =MIN(AH$23,AG65) -> 0 | AI65: =IF(AND(AH$24=1,OR(AG$25="",$C65>=AG$25)),MAX(0,MIN(AG65-AH65,$D65-(G65+K65+O65+S65+W65+AA65+AE65))),0) -> 0 | AJ65: =AG65-AH65-AI65 -> 0 | AK65: =IF(AK64>0.5,AK64*(1+$E$12)+$G$12-MIN($F$12,AK64*(1+$E$12)+$G$12),0) -> 0 | AL65: =IF(AL64>0.5,AL64*(1+$E$13)+$G$13-MIN($F$13,AL64*(1+$E$13)+$G$13),0) -> 0 | AM65: =IF(AM64>0.5,AM64*(1+$E$14)+$G$14-MIN($F$14,AM64*(1+$E$14)+$G$14),0) -> 0 | AN65: =IF(AN64>0.5,AN64*(1+$E$15)+$G$15-MIN($F$15,AN64*(1+$E$15)+$G$15),0) -> 0 | AO65: =IF(AO64>0.5,AO64*(1+$E$16)+$G$16-MIN($F$16,AO64*(1+$E$16)+$G$16),0) -> 0 | AP65: =IF(AP64>0.5,AP64*(1+$E$17)+$G$17-MIN($F$17,AP64*(1+$E$17)+$G$17),0) -> 0 | AQ65: =IF(AQ64>0.5,AQ64*(1+$E$18)+$G$18-MIN($F$18,AQ64*(1+$E$18)+$G$18),0) -> 0 | AR65: =IF(AR64>0.5,AR64*(1+$E$19)+$G$19-MIN($F$19,AR64*(1+$E$19)+$G$19),0) -> 0 | AS65: =H65+L65+P65+T65+X65+AB65+AF65+AJ65 -> 0 | AT65: =SUM(AK65:AR65) -> 0 | AU65: =F65+G65+J65+K65+N65+O65+R65+S65+V65+W65+Z65+AA65+AD65+AE65+AH65+AI65 -> 0
B66: 39 | C66: =EDATE($C$7,38) -> 47453 | D66: =$C$8-(F66+J66+N66+R66+V66+Z66+AD66+AH66) -> 0 | E66: =IF(H65>0.5,H65*(1+E$23)+E$24,0) -> 0 | F66: =MIN(F$23,E66) -> 0 | G66: =IF(AND(F$24=1,OR(E$25="",$C66>=E$25)),MAX(0,MIN(E66-F66,$D66-(0))),0) -> 0 | H66: =E66-F66-G66 -> 0 | I66: =IF(L65>0.5,L65*(1+I$23)+I$24,0) -> 0 | J66: =MIN(J$23,I66) -> 0 | K66: =IF(AND(J$24=1,OR(I$25="",$C66>=I$25)),MAX(0,MIN(I66-J66,$D66-(G66))),0) -> 0 | L66: =I66-J66-K66 -> 0 | M66: =IF(P65>0.5,P65*(1+M$23)+M$24,0) -> 0 | N66: =MIN(N$23,M66) -> 0 | O66: =IF(AND(N$24=1,OR(M$25="",$C66>=M$25)),MAX(0,MIN(M66-N66,$D66-(G66+K66))),0) -> 0 | P66: =M66-N66-O66 -> 0 | Q66: =IF(T65>0.5,T65*(1+Q$23)+Q$24,0) -> 0 | R66: =MIN(R$23,Q66) -> 0 | S66: =IF(AND(R$24=1,OR(Q$25="",$C66>=Q$25)),MAX(0,MIN(Q66-R66,$D66-(G66+K66+O66))),0) -> 0 | T66: =Q66-R66-S66 -> 0 | U66: =IF(X65>0.5,X65*(1+U$23)+U$24,0) -> 0 | V66: =MIN(V$23,U66) -> 0 | W66: =IF(AND(V$24=1,OR(U$25="",$C66>=U$25)),MAX(0,MIN(U66-V66,$D66-(G66+K66+O66+S66))),0) -> 0 | X66: =U66-V66-W66 -> 0 | Y66: =IF(AB65>0.5,AB65*(1+Y$23)+Y$24,0) -> 0 | Z66: =MIN(Z$23,Y66) -> 0 | AA66: =IF(AND(Z$24=1,OR(Y$25="",$C66>=Y$25)),MAX(0,MIN(Y66-Z66,$D66-(G66+K66+O66+S66+W66))),0) -> 0 | AB66: =Y66-Z66-AA66 -> 0 | AC66: =IF(AF65>0.5,AF65*(1+AC$23)+AC$24,0) -> 0 | AD66: =MIN(AD$23,AC66) -> 0 | AE66: =IF(AND(AD$24=1,OR(AC$25="",$C66>=AC$25)),MAX(0,MIN(AC66-AD66,$D66-(G66+K66+O66+S66+W66+AA66))),0) -> 0 | AF66: =AC66-AD66-AE66 -> 0 | AG66: =IF(AJ65>0.5,AJ65*(1+AG$23)+AG$24,0) -> 0 | AH66: =MIN(AH$23,AG66) -> 0 | AI66: =IF(AND(AH$24=1,OR(AG$25="",$C66>=AG$25)),MAX(0,MIN(AG66-AH66,$D66-(G66+K66+O66+S66+W66+AA66+AE66))),0) -> 0 | AJ66: =AG66-AH66-AI66 -> 0 | AK66: =IF(AK65>0.5,AK65*(1+$E$12)+$G$12-MIN($F$12,AK65*(1+$E$12)+$G$12),0) -> 0 | AL66: =IF(AL65>0.5,AL65*(1+$E$13)+$G$13-MIN($F$13,AL65*(1+$E$13)+$G$13),0) -> 0 | AM66: =IF(AM65>0.5,AM65*(1+$E$14)+$G$14-MIN($F$14,AM65*(1+$E$14)+$G$14),0) -> 0 | AN66: =IF(AN65>0.5,AN65*(1+$E$15)+$G$15-MIN($F$15,AN65*(1+$E$15)+$G$15),0) -> 0 | AO66: =IF(AO65>0.5,AO65*(1+$E$16)+$G$16-MIN($F$16,AO65*(1+$E$16)+$G$16),0) -> 0 | AP66: =IF(AP65>0.5,AP65*(1+$E$17)+$G$17-MIN($F$17,AP65*(1+$E$17)+$G$17),0) -> 0 | AQ66: =IF(AQ65>0.5,AQ65*(1+$E$18)+$G$18-MIN($F$18,AQ65*(1+$E$18)+$G$18),0) -> 0 | AR66: =IF(AR65>0.5,AR65*(1+$E$19)+$G$19-MIN($F$19,AR65*(1+$E$19)+$G$19),0) -> 0 | AS66: =H66+L66+P66+T66+X66+AB66+AF66+AJ66 -> 0 | AT66: =SUM(AK66:AR66) -> 0 | AU66: =F66+G66+J66+K66+N66+O66+R66+S66+V66+W66+Z66+AA66+AD66+AE66+AH66+AI66 -> 0
B67: 40 | C67: =EDATE($C$7,39) -> 47484 | D67: =$C$8-(F67+J67+N67+R67+V67+Z67+AD67+AH67) -> 0 | E67: =IF(H66>0.5,H66*(1+E$23)+E$24,0) -> 0 | F67: =MIN(F$23,E67) -> 0 | G67: =IF(AND(F$24=1,OR(E$25="",$C67>=E$25)),MAX(0,MIN(E67-F67,$D67-(0))),0) -> 0 | H67: =E67-F67-G67 -> 0 | I67: =IF(L66>0.5,L66*(1+I$23)+I$24,0) -> 0 | J67: =MIN(J$23,I67) -> 0 | K67: =IF(AND(J$24=1,OR(I$25="",$C67>=I$25)),MAX(0,MIN(I67-J67,$D67-(G67))),0) -> 0 | L67: =I67-J67-K67 -> 0 | M67: =IF(P66>0.5,P66*(1+M$23)+M$24,0) -> 0 | N67: =MIN(N$23,M67) -> 0 | O67: =IF(AND(N$24=1,OR(M$25="",$C67>=M$25)),MAX(0,MIN(M67-N67,$D67-(G67+K67))),0) -> 0 | P67: =M67-N67-O67 -> 0 | Q67: =IF(T66>0.5,T66*(1+Q$23)+Q$24,0) -> 0 | R67: =MIN(R$23,Q67) -> 0 | S67: =IF(AND(R$24=1,OR(Q$25="",$C67>=Q$25)),MAX(0,MIN(Q67-R67,$D67-(G67+K67+O67))),0) -> 0 | T67: =Q67-R67-S67 -> 0 | U67: =IF(X66>0.5,X66*(1+U$23)+U$24,0) -> 0 | V67: =MIN(V$23,U67) -> 0 | W67: =IF(AND(V$24=1,OR(U$25="",$C67>=U$25)),MAX(0,MIN(U67-V67,$D67-(G67+K67+O67+S67))),0) -> 0 | X67: =U67-V67-W67 -> 0 | Y67: =IF(AB66>0.5,AB66*(1+Y$23)+Y$24,0) -> 0 | Z67: =MIN(Z$23,Y67) -> 0 | AA67: =IF(AND(Z$24=1,OR(Y$25="",$C67>=Y$25)),MAX(0,MIN(Y67-Z67,$D67-(G67+K67+O67+S67+W67))),0) -> 0 | AB67: =Y67-Z67-AA67 -> 0 | AC67: =IF(AF66>0.5,AF66*(1+AC$23)+AC$24,0) -> 0 | AD67: =MIN(AD$23,AC67) -> 0 | AE67: =IF(AND(AD$24=1,OR(AC$25="",$C67>=AC$25)),MAX(0,MIN(AC67-AD67,$D67-(G67+K67+O67+S67+W67+AA67))),0) -> 0 | AF67: =AC67-AD67-AE67 -> 0 | AG67: =IF(AJ66>0.5,AJ66*(1+AG$23)+AG$24,0) -> 0 | AH67: =MIN(AH$23,AG67) -> 0 | AI67: =IF(AND(AH$24=1,OR(AG$25="",$C67>=AG$25)),MAX(0,MIN(AG67-AH67,$D67-(G67+K67+O67+S67+W67+AA67+AE67))),0) -> 0 | AJ67: =AG67-AH67-AI67 -> 0 | AK67: =IF(AK66>0.5,AK66*(1+$E$12)+$G$12-MIN($F$12,AK66*(1+$E$12)+$G$12),0) -> 0 | AL67: =IF(AL66>0.5,AL66*(1+$E$13)+$G$13-MIN($F$13,AL66*(1+$E$13)+$G$13),0) -> 0 | AM67: =IF(AM66>0.5,AM66*(1+$E$14)+$G$14-MIN($F$14,AM66*(1+$E$14)+$G$14),0) -> 0 | AN67: =IF(AN66>0.5,AN66*(1+$E$15)+$G$15-MIN($F$15,AN66*(1+$E$15)+$G$15),0) -> 0 | AO67: =IF(AO66>0.5,AO66*(1+$E$16)+$G$16-MIN($F$16,AO66*(1+$E$16)+$G$16),0) -> 0 | AP67: =IF(AP66>0.5,AP66*(1+$E$17)+$G$17-MIN($F$17,AP66*(1+$E$17)+$G$17),0) -> 0 | AQ67: =IF(AQ66>0.5,AQ66*(1+$E$18)+$G$18-MIN($F$18,AQ66*(1+$E$18)+$G$18),0) -> 0 | AR67: =IF(AR66>0.5,AR66*(1+$E$19)+$G$19-MIN($F$19,AR66*(1+$E$19)+$G$19),0) -> 0 | AS67: =H67+L67+P67+T67+X67+AB67+AF67+AJ67 -> 0 | AT67: =SUM(AK67:AR67) -> 0 | AU67: =F67+G67+J67+K67+N67+O67+R67+S67+V67+W67+Z67+AA67+AD67+AE67+AH67+AI67 -> 0
B68: 41 | C68: =EDATE($C$7,40) -> 47515 | D68: =$C$8-(F68+J68+N68+R68+V68+Z68+AD68+AH68) -> 0 | E68: =IF(H67>0.5,H67*(1+E$23)+E$24,0) -> 0 | F68: =MIN(F$23,E68) -> 0 | G68: =IF(AND(F$24=1,OR(E$25="",$C68>=E$25)),MAX(0,MIN(E68-F68,$D68-(0))),0) -> 0 | H68: =E68-F68-G68 -> 0 | I68: =IF(L67>0.5,L67*(1+I$23)+I$24,0) -> 0 | J68: =MIN(J$23,I68) -> 0 | K68: =IF(AND(J$24=1,OR(I$25="",$C68>=I$25)),MAX(0,MIN(I68-J68,$D68-(G68))),0) -> 0 | L68: =I68-J68-K68 -> 0 | M68: =IF(P67>0.5,P67*(1+M$23)+M$24,0) -> 0 | N68: =MIN(N$23,M68) -> 0 | O68: =IF(AND(N$24=1,OR(M$25="",$C68>=M$25)),MAX(0,MIN(M68-N68,$D68-(G68+K68))),0) -> 0 | P68: =M68-N68-O68 -> 0 | Q68: =IF(T67>0.5,T67*(1+Q$23)+Q$24,0) -> 0 | R68: =MIN(R$23,Q68) -> 0 | S68: =IF(AND(R$24=1,OR(Q$25="",$C68>=Q$25)),MAX(0,MIN(Q68-R68,$D68-(G68+K68+O68))),0) -> 0 | T68: =Q68-R68-S68 -> 0 | U68: =IF(X67>0.5,X67*(1+U$23)+U$24,0) -> 0 | V68: =MIN(V$23,U68) -> 0 | W68: =IF(AND(V$24=1,OR(U$25="",$C68>=U$25)),MAX(0,MIN(U68-V68,$D68-(G68+K68+O68+S68))),0) -> 0 | X68: =U68-V68-W68 -> 0 | Y68: =IF(AB67>0.5,AB67*(1+Y$23)+Y$24,0) -> 0 | Z68: =MIN(Z$23,Y68) -> 0 | AA68: =IF(AND(Z$24=1,OR(Y$25="",$C68>=Y$25)),MAX(0,MIN(Y68-Z68,$D68-(G68+K68+O68+S68+W68))),0) -> 0 | AB68: =Y68-Z68-AA68 -> 0 | AC68: =IF(AF67>0.5,AF67*(1+AC$23)+AC$24,0) -> 0 | AD68: =MIN(AD$23,AC68) -> 0 | AE68: =IF(AND(AD$24=1,OR(AC$25="",$C68>=AC$25)),MAX(0,MIN(AC68-AD68,$D68-(G68+K68+O68+S68+W68+AA68))),0) -> 0 | AF68: =AC68-AD68-AE68 -> 0 | AG68: =IF(AJ67>0.5,AJ67*(1+AG$23)+AG$24,0) -> 0 | AH68: =MIN(AH$23,AG68) -> 0 | AI68: =IF(AND(AH$24=1,OR(AG$25="",$C68>=AG$25)),MAX(0,MIN(AG68-AH68,$D68-(G68+K68+O68+S68+W68+AA68+AE68))),0) -> 0 | AJ68: =AG68-AH68-AI68 -> 0 | AK68: =IF(AK67>0.5,AK67*(1+$E$12)+$G$12-MIN($F$12,AK67*(1+$E$12)+$G$12),0) -> 0 | AL68: =IF(AL67>0.5,AL67*(1+$E$13)+$G$13-MIN($F$13,AL67*(1+$E$13)+$G$13),0) -> 0 | AM68: =IF(AM67>0.5,AM67*(1+$E$14)+$G$14-MIN($F$14,AM67*(1+$E$14)+$G$14),0) -> 0 | AN68: =IF(AN67>0.5,AN67*(1+$E$15)+$G$15-MIN($F$15,AN67*(1+$E$15)+$G$15),0) -> 0 | AO68: =IF(AO67>0.5,AO67*(1+$E$16)+$G$16-MIN($F$16,AO67*(1+$E$16)+$G$16),0) -> 0 | AP68: =IF(AP67>0.5,AP67*(1+$E$17)+$G$17-MIN($F$17,AP67*(1+$E$17)+$G$17),0) -> 0 | AQ68: =IF(AQ67>0.5,AQ67*(1+$E$18)+$G$18-MIN($F$18,AQ67*(1+$E$18)+$G$18),0) -> 0 | AR68: =IF(AR67>0.5,AR67*(1+$E$19)+$G$19-MIN($F$19,AR67*(1+$E$19)+$G$19),0) -> 0 | AS68: =H68+L68+P68+T68+X68+AB68+AF68+AJ68 -> 0 | AT68: =SUM(AK68:AR68) -> 0 | AU68: =F68+G68+J68+K68+N68+O68+R68+S68+V68+W68+Z68+AA68+AD68+AE68+AH68+AI68 -> 0
B69: 42 | C69: =EDATE($C$7,41) -> 47543 | D69: =$C$8-(F69+J69+N69+R69+V69+Z69+AD69+AH69) -> 0 | E69: =IF(H68>0.5,H68*(1+E$23)+E$24,0) -> 0 | F69: =MIN(F$23,E69) -> 0 | G69: =IF(AND(F$24=1,OR(E$25="",$C69>=E$25)),MAX(0,MIN(E69-F69,$D69-(0))),0) -> 0 | H69: =E69-F69-G69 -> 0 | I69: =IF(L68>0.5,L68*(1+I$23)+I$24,0) -> 0 | J69: =MIN(J$23,I69) -> 0 | K69: =IF(AND(J$24=1,OR(I$25="",$C69>=I$25)),MAX(0,MIN(I69-J69,$D69-(G69))),0) -> 0 | L69: =I69-J69-K69 -> 0 | M69: =IF(P68>0.5,P68*(1+M$23)+M$24,0) -> 0 | N69: =MIN(N$23,M69) -> 0 | O69: =IF(AND(N$24=1,OR(M$25="",$C69>=M$25)),MAX(0,MIN(M69-N69,$D69-(G69+K69))),0) -> 0 | P69: =M69-N69-O69 -> 0 | Q69: =IF(T68>0.5,T68*(1+Q$23)+Q$24,0) -> 0 | R69: =MIN(R$23,Q69) -> 0 | S69: =IF(AND(R$24=1,OR(Q$25="",$C69>=Q$25)),MAX(0,MIN(Q69-R69,$D69-(G69+K69+O69))),0) -> 0 | T69: =Q69-R69-S69 -> 0 | U69: =IF(X68>0.5,X68*(1+U$23)+U$24,0) -> 0 | V69: =MIN(V$23,U69) -> 0 | W69: =IF(AND(V$24=1,OR(U$25="",$C69>=U$25)),MAX(0,MIN(U69-V69,$D69-(G69+K69+O69+S69))),0) -> 0 | X69: =U69-V69-W69 -> 0 | Y69: =IF(AB68>0.5,AB68*(1+Y$23)+Y$24,0) -> 0 | Z69: =MIN(Z$23,Y69) -> 0 | AA69: =IF(AND(Z$24=1,OR(Y$25="",$C69>=Y$25)),MAX(0,MIN(Y69-Z69,$D69-(G69+K69+O69+S69+W69))),0) -> 0 | AB69: =Y69-Z69-AA69 -> 0 | AC69: =IF(AF68>0.5,AF68*(1+AC$23)+AC$24,0) -> 0 | AD69: =MIN(AD$23,AC69) -> 0 | AE69: =IF(AND(AD$24=1,OR(AC$25="",$C69>=AC$25)),MAX(0,MIN(AC69-AD69,$D69-(G69+K69+O69+S69+W69+AA69))),0) -> 0 | AF69: =AC69-AD69-AE69 -> 0 | AG69: =IF(AJ68>0.5,AJ68*(1+AG$23)+AG$24,0) -> 0 | AH69: =MIN(AH$23,AG69) -> 0 | AI69: =IF(AND(AH$24=1,OR(AG$25="",$C69>=AG$25)),MAX(0,MIN(AG69-AH69,$D69-(G69+K69+O69+S69+W69+AA69+AE69))),0) -> 0 | AJ69: =AG69-AH69-AI69 -> 0 | AK69: =IF(AK68>0.5,AK68*(1+$E$12)+$G$12-MIN($F$12,AK68*(1+$E$12)+$G$12),0) -> 0 | AL69: =IF(AL68>0.5,AL68*(1+$E$13)+$G$13-MIN($F$13,AL68*(1+$E$13)+$G$13),0) -> 0 | AM69: =IF(AM68>0.5,AM68*(1+$E$14)+$G$14-MIN($F$14,AM68*(1+$E$14)+$G$14),0) -> 0 | AN69: =IF(AN68>0.5,AN68*(1+$E$15)+$G$15-MIN($F$15,AN68*(1+$E$15)+$G$15),0) -> 0 | AO69: =IF(AO68>0.5,AO68*(1+$E$16)+$G$16-MIN($F$16,AO68*(1+$E$16)+$G$16),0) -> 0 | AP69: =IF(AP68>0.5,AP68*(1+$E$17)+$G$17-MIN($F$17,AP68*(1+$E$17)+$G$17),0) -> 0 | AQ69: =IF(AQ68>0.5,AQ68*(1+$E$18)+$G$18-MIN($F$18,AQ68*(1+$E$18)+$G$18),0) -> 0 | AR69: =IF(AR68>0.5,AR68*(1+$E$19)+$G$19-MIN($F$19,AR68*(1+$E$19)+$G$19),0) -> 0 | AS69: =H69+L69+P69+T69+X69+AB69+AF69+AJ69 -> 0 | AT69: =SUM(AK69:AR69) -> 0 | AU69: =F69+G69+J69+K69+N69+O69+R69+S69+V69+W69+Z69+AA69+AD69+AE69+AH69+AI69 -> 0
B70: 43 | C70: =EDATE($C$7,42) -> 47574 | D70: =$C$8-(F70+J70+N70+R70+V70+Z70+AD70+AH70) -> 0 | E70: =IF(H69>0.5,H69*(1+E$23)+E$24,0) -> 0 | F70: =MIN(F$23,E70) -> 0 | G70: =IF(AND(F$24=1,OR(E$25="",$C70>=E$25)),MAX(0,MIN(E70-F70,$D70-(0))),0) -> 0 | H70: =E70-F70-G70 -> 0 | I70: =IF(L69>0.5,L69*(1+I$23)+I$24,0) -> 0 | J70: =MIN(J$23,I70) -> 0 | K70: =IF(AND(J$24=1,OR(I$25="",$C70>=I$25)),MAX(0,MIN(I70-J70,$D70-(G70))),0) -> 0 | L70: =I70-J70-K70 -> 0 | M70: =IF(P69>0.5,P69*(1+M$23)+M$24,0) -> 0 | N70: =MIN(N$23,M70) -> 0 | O70: =IF(AND(N$24=1,OR(M$25="",$C70>=M$25)),MAX(0,MIN(M70-N70,$D70-(G70+K70))),0) -> 0 | P70: =M70-N70-O70 -> 0 | Q70: =IF(T69>0.5,T69*(1+Q$23)+Q$24,0) -> 0 | R70: =MIN(R$23,Q70) -> 0 | S70: =IF(AND(R$24=1,OR(Q$25="",$C70>=Q$25)),MAX(0,MIN(Q70-R70,$D70-(G70+K70+O70))),0) -> 0 | T70: =Q70-R70-S70 -> 0 | U70: =IF(X69>0.5,X69*(1+U$23)+U$24,0) -> 0 | V70: =MIN(V$23,U70) -> 0 | W70: =IF(AND(V$24=1,OR(U$25="",$C70>=U$25)),MAX(0,MIN(U70-V70,$D70-(G70+K70+O70+S70))),0) -> 0 | X70: =U70-V70-W70 -> 0 | Y70: =IF(AB69>0.5,AB69*(1+Y$23)+Y$24,0) -> 0 | Z70: =MIN(Z$23,Y70) -> 0 | AA70: =IF(AND(Z$24=1,OR(Y$25="",$C70>=Y$25)),MAX(0,MIN(Y70-Z70,$D70-(G70+K70+O70+S70+W70))),0) -> 0 | AB70: =Y70-Z70-AA70 -> 0 | AC70: =IF(AF69>0.5,AF69*(1+AC$23)+AC$24,0) -> 0 | AD70: =MIN(AD$23,AC70) -> 0 | AE70: =IF(AND(AD$24=1,OR(AC$25="",$C70>=AC$25)),MAX(0,MIN(AC70-AD70,$D70-(G70+K70+O70+S70+W70+AA70))),0) -> 0 | AF70: =AC70-AD70-AE70 -> 0 | AG70: =IF(AJ69>0.5,AJ69*(1+AG$23)+AG$24,0) -> 0 | AH70: =MIN(AH$23,AG70) -> 0 | AI70: =IF(AND(AH$24=1,OR(AG$25="",$C70>=AG$25)),MAX(0,MIN(AG70-AH70,$D70-(G70+K70+O70+S70+W70+AA70+AE70))),0) -> 0 | AJ70: =AG70-AH70-AI70 -> 0 | AK70: =IF(AK69>0.5,AK69*(1+$E$12)+$G$12-MIN($F$12,AK69*(1+$E$12)+$G$12),0) -> 0 | AL70: =IF(AL69>0.5,AL69*(1+$E$13)+$G$13-MIN($F$13,AL69*(1+$E$13)+$G$13),0) -> 0 | AM70: =IF(AM69>0.5,AM69*(1+$E$14)+$G$14-MIN($F$14,AM69*(1+$E$14)+$G$14),0) -> 0 | AN70: =IF(AN69>0.5,AN69*(1+$E$15)+$G$15-MIN($F$15,AN69*(1+$E$15)+$G$15),0) -> 0 | AO70: =IF(AO69>0.5,AO69*(1+$E$16)+$G$16-MIN($F$16,AO69*(1+$E$16)+$G$16),0) -> 0 | AP70: =IF(AP69>0.5,AP69*(1+$E$17)+$G$17-MIN($F$17,AP69*(1+$E$17)+$G$17),0) -> 0 | AQ70: =IF(AQ69>0.5,AQ69*(1+$E$18)+$G$18-MIN($F$18,AQ69*(1+$E$18)+$G$18),0) -> 0 | AR70: =IF(AR69>0.5,AR69*(1+$E$19)+$G$19-MIN($F$19,AR69*(1+$E$19)+$G$19),0) -> 0 | AS70: =H70+L70+P70+T70+X70+AB70+AF70+AJ70 -> 0 | AT70: =SUM(AK70:AR70) -> 0 | AU70: =F70+G70+J70+K70+N70+O70+R70+S70+V70+W70+Z70+AA70+AD70+AE70+AH70+AI70 -> 0
B71: 44 | C71: =EDATE($C$7,43) -> 47604 | D71: =$C$8-(F71+J71+N71+R71+V71+Z71+AD71+AH71) -> 0 | E71: =IF(H70>0.5,H70*(1+E$23)+E$24,0) -> 0 | F71: =MIN(F$23,E71) -> 0 | G71: =IF(AND(F$24=1,OR(E$25="",$C71>=E$25)),MAX(0,MIN(E71-F71,$D71-(0))),0) -> 0 | H71: =E71-F71-G71 -> 0 | I71: =IF(L70>0.5,L70*(1+I$23)+I$24,0) -> 0 | J71: =MIN(J$23,I71) -> 0 | K71: =IF(AND(J$24=1,OR(I$25="",$C71>=I$25)),MAX(0,MIN(I71-J71,$D71-(G71))),0) -> 0 | L71: =I71-J71-K71 -> 0 | M71: =IF(P70>0.5,P70*(1+M$23)+M$24,0) -> 0 | N71: =MIN(N$23,M71) -> 0 | O71: =IF(AND(N$24=1,OR(M$25="",$C71>=M$25)),MAX(0,MIN(M71-N71,$D71-(G71+K71))),0) -> 0 | P71: =M71-N71-O71 -> 0 | Q71: =IF(T70>0.5,T70*(1+Q$23)+Q$24,0) -> 0 | R71: =MIN(R$23,Q71) -> 0 | S71: =IF(AND(R$24=1,OR(Q$25="",$C71>=Q$25)),MAX(0,MIN(Q71-R71,$D71-(G71+K71+O71))),0) -> 0 | T71: =Q71-R71-S71 -> 0 | U71: =IF(X70>0.5,X70*(1+U$23)+U$24,0) -> 0 | V71: =MIN(V$23,U71) -> 0 | W71: =IF(AND(V$24=1,OR(U$25="",$C71>=U$25)),MAX(0,MIN(U71-V71,$D71-(G71+K71+O71+S71))),0) -> 0 | X71: =U71-V71-W71 -> 0 | Y71: =IF(AB70>0.5,AB70*(1+Y$23)+Y$24,0) -> 0 | Z71: =MIN(Z$23,Y71) -> 0 | AA71: =IF(AND(Z$24=1,OR(Y$25="",$C71>=Y$25)),MAX(0,MIN(Y71-Z71,$D71-(G71+K71+O71+S71+W71))),0) -> 0 | AB71: =Y71-Z71-AA71 -> 0 | AC71: =IF(AF70>0.5,AF70*(1+AC$23)+AC$24,0) -> 0 | AD71: =MIN(AD$23,AC71) -> 0 | AE71: =IF(AND(AD$24=1,OR(AC$25="",$C71>=AC$25)),MAX(0,MIN(AC71-AD71,$D71-(G71+K71+O71+S71+W71+AA71))),0) -> 0 | AF71: =AC71-AD71-AE71 -> 0 | AG71: =IF(AJ70>0.5,AJ70*(1+AG$23)+AG$24,0) -> 0 | AH71: =MIN(AH$23,AG71) -> 0 | AI71: =IF(AND(AH$24=1,OR(AG$25="",$C71>=AG$25)),MAX(0,MIN(AG71-AH71,$D71-(G71+K71+O71+S71+W71+AA71+AE71))),0) -> 0 | AJ71: =AG71-AH71-AI71 -> 0 | AK71: =IF(AK70>0.5,AK70*(1+$E$12)+$G$12-MIN($F$12,AK70*(1+$E$12)+$G$12),0) -> 0 | AL71: =IF(AL70>0.5,AL70*(1+$E$13)+$G$13-MIN($F$13,AL70*(1+$E$13)+$G$13),0) -> 0 | AM71: =IF(AM70>0.5,AM70*(1+$E$14)+$G$14-MIN($F$14,AM70*(1+$E$14)+$G$14),0) -> 0 | AN71: =IF(AN70>0.5,AN70*(1+$E$15)+$G$15-MIN($F$15,AN70*(1+$E$15)+$G$15),0) -> 0 | AO71: =IF(AO70>0.5,AO70*(1+$E$16)+$G$16-MIN($F$16,AO70*(1+$E$16)+$G$16),0) -> 0 | AP71: =IF(AP70>0.5,AP70*(1+$E$17)+$G$17-MIN($F$17,AP70*(1+$E$17)+$G$17),0) -> 0 | AQ71: =IF(AQ70>0.5,AQ70*(1+$E$18)+$G$18-MIN($F$18,AQ70*(1+$E$18)+$G$18),0) -> 0 | AR71: =IF(AR70>0.5,AR70*(1+$E$19)+$G$19-MIN($F$19,AR70*(1+$E$19)+$G$19),0) -> 0 | AS71: =H71+L71+P71+T71+X71+AB71+AF71+AJ71 -> 0 | AT71: =SUM(AK71:AR71) -> 0 | AU71: =F71+G71+J71+K71+N71+O71+R71+S71+V71+W71+Z71+AA71+AD71+AE71+AH71+AI71 -> 0
B72: 45 | C72: =EDATE($C$7,44) -> 47635 | D72: =$C$8-(F72+J72+N72+R72+V72+Z72+AD72+AH72) -> 0 | E72: =IF(H71>0.5,H71*(1+E$23)+E$24,0) -> 0 | F72: =MIN(F$23,E72) -> 0 | G72: =IF(AND(F$24=1,OR(E$25="",$C72>=E$25)),MAX(0,MIN(E72-F72,$D72-(0))),0) -> 0 | H72: =E72-F72-G72 -> 0 | I72: =IF(L71>0.5,L71*(1+I$23)+I$24,0) -> 0 | J72: =MIN(J$23,I72) -> 0 | K72: =IF(AND(J$24=1,OR(I$25="",$C72>=I$25)),MAX(0,MIN(I72-J72,$D72-(G72))),0) -> 0 | L72: =I72-J72-K72 -> 0 | M72: =IF(P71>0.5,P71*(1+M$23)+M$24,0) -> 0 | N72: =MIN(N$23,M72) -> 0 | O72: =IF(AND(N$24=1,OR(M$25="",$C72>=M$25)),MAX(0,MIN(M72-N72,$D72-(G72+K72))),0) -> 0 | P72: =M72-N72-O72 -> 0 | Q72: =IF(T71>0.5,T71*(1+Q$23)+Q$24,0) -> 0 | R72: =MIN(R$23,Q72) -> 0 | S72: =IF(AND(R$24=1,OR(Q$25="",$C72>=Q$25)),MAX(0,MIN(Q72-R72,$D72-(G72+K72+O72))),0) -> 0 | T72: =Q72-R72-S72 -> 0 | U72: =IF(X71>0.5,X71*(1+U$23)+U$24,0) -> 0 | V72: =MIN(V$23,U72) -> 0 | W72: =IF(AND(V$24=1,OR(U$25="",$C72>=U$25)),MAX(0,MIN(U72-V72,$D72-(G72+K72+O72+S72))),0) -> 0 | X72: =U72-V72-W72 -> 0 | Y72: =IF(AB71>0.5,AB71*(1+Y$23)+Y$24,0) -> 0 | Z72: =MIN(Z$23,Y72) -> 0 | AA72: =IF(AND(Z$24=1,OR(Y$25="",$C72>=Y$25)),MAX(0,MIN(Y72-Z72,$D72-(G72+K72+O72+S72+W72))),0) -> 0 | AB72: =Y72-Z72-AA72 -> 0 | AC72: =IF(AF71>0.5,AF71*(1+AC$23)+AC$24,0) -> 0 | AD72: =MIN(AD$23,AC72) -> 0 | AE72: =IF(AND(AD$24=1,OR(AC$25="",$C72>=AC$25)),MAX(0,MIN(AC72-AD72,$D72-(G72+K72+O72+S72+W72+AA72))),0) -> 0 | AF72: =AC72-AD72-AE72 -> 0 | AG72: =IF(AJ71>0.5,AJ71*(1+AG$23)+AG$24,0) -> 0 | AH72: =MIN(AH$23,AG72) -> 0 | AI72: =IF(AND(AH$24=1,OR(AG$25="",$C72>=AG$25)),MAX(0,MIN(AG72-AH72,$D72-(G72+K72+O72+S72+W72+AA72+AE72))),0) -> 0 | AJ72: =AG72-AH72-AI72 -> 0 | AK72: =IF(AK71>0.5,AK71*(1+$E$12)+$G$12-MIN($F$12,AK71*(1+$E$12)+$G$12),0) -> 0 | AL72: =IF(AL71>0.5,AL71*(1+$E$13)+$G$13-MIN($F$13,AL71*(1+$E$13)+$G$13),0) -> 0 | AM72: =IF(AM71>0.5,AM71*(1+$E$14)+$G$14-MIN($F$14,AM71*(1+$E$14)+$G$14),0) -> 0 | AN72: =IF(AN71>0.5,AN71*(1+$E$15)+$G$15-MIN($F$15,AN71*(1+$E$15)+$G$15),0) -> 0 | AO72: =IF(AO71>0.5,AO71*(1+$E$16)+$G$16-MIN($F$16,AO71*(1+$E$16)+$G$16),0) -> 0 | AP72: =IF(AP71>0.5,AP71*(1+$E$17)+$G$17-MIN($F$17,AP71*(1+$E$17)+$G$17),0) -> 0 | AQ72: =IF(AQ71>0.5,AQ71*(1+$E$18)+$G$18-MIN($F$18,AQ71*(1+$E$18)+$G$18),0) -> 0 | AR72: =IF(AR71>0.5,AR71*(1+$E$19)+$G$19-MIN($F$19,AR71*(1+$E$19)+$G$19),0) -> 0 | AS72: =H72+L72+P72+T72+X72+AB72+AF72+AJ72 -> 0 | AT72: =SUM(AK72:AR72) -> 0 | AU72: =F72+G72+J72+K72+N72+O72+R72+S72+V72+W72+Z72+AA72+AD72+AE72+AH72+AI72 -> 0
B73: 46 | C73: =EDATE($C$7,45) -> 47665 | D73: =$C$8-(F73+J73+N73+R73+V73+Z73+AD73+AH73) -> 0 | E73: =IF(H72>0.5,H72*(1+E$23)+E$24,0) -> 0 | F73: =MIN(F$23,E73) -> 0 | G73: =IF(AND(F$24=1,OR(E$25="",$C73>=E$25)),MAX(0,MIN(E73-F73,$D73-(0))),0) -> 0 | H73: =E73-F73-G73 -> 0 | I73: =IF(L72>0.5,L72*(1+I$23)+I$24,0) -> 0 | J73: =MIN(J$23,I73) -> 0 | K73: =IF(AND(J$24=1,OR(I$25="",$C73>=I$25)),MAX(0,MIN(I73-J73,$D73-(G73))),0) -> 0 | L73: =I73-J73-K73 -> 0 | M73: =IF(P72>0.5,P72*(1+M$23)+M$24,0) -> 0 | N73: =MIN(N$23,M73) -> 0 | O73: =IF(AND(N$24=1,OR(M$25="",$C73>=M$25)),MAX(0,MIN(M73-N73,$D73-(G73+K73))),0) -> 0 | P73: =M73-N73-O73 -> 0 | Q73: =IF(T72>0.5,T72*(1+Q$23)+Q$24,0) -> 0 | R73: =MIN(R$23,Q73) -> 0 | S73: =IF(AND(R$24=1,OR(Q$25="",$C73>=Q$25)),MAX(0,MIN(Q73-R73,$D73-(G73+K73+O73))),0) -> 0 | T73: =Q73-R73-S73 -> 0 | U73: =IF(X72>0.5,X72*(1+U$23)+U$24,0) -> 0 | V73: =MIN(V$23,U73) -> 0 | W73: =IF(AND(V$24=1,OR(U$25="",$C73>=U$25)),MAX(0,MIN(U73-V73,$D73-(G73+K73+O73+S73))),0) -> 0 | X73: =U73-V73-W73 -> 0 | Y73: =IF(AB72>0.5,AB72*(1+Y$23)+Y$24,0) -> 0 | Z73: =MIN(Z$23,Y73) -> 0 | AA73: =IF(AND(Z$24=1,OR(Y$25="",$C73>=Y$25)),MAX(0,MIN(Y73-Z73,$D73-(G73+K73+O73+S73+W73))),0) -> 0 | AB73: =Y73-Z73-AA73 -> 0 | AC73: =IF(AF72>0.5,AF72*(1+AC$23)+AC$24,0) -> 0 | AD73: =MIN(AD$23,AC73) -> 0 | AE73: =IF(AND(AD$24=1,OR(AC$25="",$C73>=AC$25)),MAX(0,MIN(AC73-AD73,$D73-(G73+K73+O73+S73+W73+AA73))),0) -> 0 | AF73: =AC73-AD73-AE73 -> 0 | AG73: =IF(AJ72>0.5,AJ72*(1+AG$23)+AG$24,0) -> 0 | AH73: =MIN(AH$23,AG73) -> 0 | AI73: =IF(AND(AH$24=1,OR(AG$25="",$C73>=AG$25)),MAX(0,MIN(AG73-AH73,$D73-(G73+K73+O73+S73+W73+AA73+AE73))),0) -> 0 | AJ73: =AG73-AH73-AI73 -> 0 | AK73: =IF(AK72>0.5,AK72*(1+$E$12)+$G$12-MIN($F$12,AK72*(1+$E$12)+$G$12),0) -> 0 | AL73: =IF(AL72>0.5,AL72*(1+$E$13)+$G$13-MIN($F$13,AL72*(1+$E$13)+$G$13),0) -> 0 | AM73: =IF(AM72>0.5,AM72*(1+$E$14)+$G$14-MIN($F$14,AM72*(1+$E$14)+$G$14),0) -> 0 | AN73: =IF(AN72>0.5,AN72*(1+$E$15)+$G$15-MIN($F$15,AN72*(1+$E$15)+$G$15),0) -> 0 | AO73: =IF(AO72>0.5,AO72*(1+$E$16)+$G$16-MIN($F$16,AO72*(1+$E$16)+$G$16),0) -> 0 | AP73: =IF(AP72>0.5,AP72*(1+$E$17)+$G$17-MIN($F$17,AP72*(1+$E$17)+$G$17),0) -> 0 | AQ73: =IF(AQ72>0.5,AQ72*(1+$E$18)+$G$18-MIN($F$18,AQ72*(1+$E$18)+$G$18),0) -> 0 | AR73: =IF(AR72>0.5,AR72*(1+$E$19)+$G$19-MIN($F$19,AR72*(1+$E$19)+$G$19),0) -> 0 | AS73: =H73+L73+P73+T73+X73+AB73+AF73+AJ73 -> 0 | AT73: =SUM(AK73:AR73) -> 0 | AU73: =F73+G73+J73+K73+N73+O73+R73+S73+V73+W73+Z73+AA73+AD73+AE73+AH73+AI73 -> 0
B74: 47 | C74: =EDATE($C$7,46) -> 47696 | D74: =$C$8-(F74+J74+N74+R74+V74+Z74+AD74+AH74) -> 0 | E74: =IF(H73>0.5,H73*(1+E$23)+E$24,0) -> 0 | F74: =MIN(F$23,E74) -> 0 | G74: =IF(AND(F$24=1,OR(E$25="",$C74>=E$25)),MAX(0,MIN(E74-F74,$D74-(0))),0) -> 0 | H74: =E74-F74-G74 -> 0 | I74: =IF(L73>0.5,L73*(1+I$23)+I$24,0) -> 0 | J74: =MIN(J$23,I74) -> 0 | K74: =IF(AND(J$24=1,OR(I$25="",$C74>=I$25)),MAX(0,MIN(I74-J74,$D74-(G74))),0) -> 0 | L74: =I74-J74-K74 -> 0 | M74: =IF(P73>0.5,P73*(1+M$23)+M$24,0) -> 0 | N74: =MIN(N$23,M74) -> 0 | O74: =IF(AND(N$24=1,OR(M$25="",$C74>=M$25)),MAX(0,MIN(M74-N74,$D74-(G74+K74))),0) -> 0 | P74: =M74-N74-O74 -> 0 | Q74: =IF(T73>0.5,T73*(1+Q$23)+Q$24,0) -> 0 | R74: =MIN(R$23,Q74) -> 0 | S74: =IF(AND(R$24=1,OR(Q$25="",$C74>=Q$25)),MAX(0,MIN(Q74-R74,$D74-(G74+K74+O74))),0) -> 0 | T74: =Q74-R74-S74 -> 0 | U74: =IF(X73>0.5,X73*(1+U$23)+U$24,0) -> 0 | V74: =MIN(V$23,U74) -> 0 | W74: =IF(AND(V$24=1,OR(U$25="",$C74>=U$25)),MAX(0,MIN(U74-V74,$D74-(G74+K74+O74+S74))),0) -> 0 | X74: =U74-V74-W74 -> 0 | Y74: =IF(AB73>0.5,AB73*(1+Y$23)+Y$24,0) -> 0 | Z74: =MIN(Z$23,Y74) -> 0 | AA74: =IF(AND(Z$24=1,OR(Y$25="",$C74>=Y$25)),MAX(0,MIN(Y74-Z74,$D74-(G74+K74+O74+S74+W74))),0) -> 0 | AB74: =Y74-Z74-AA74 -> 0 | AC74: =IF(AF73>0.5,AF73*(1+AC$23)+AC$24,0) -> 0 | AD74: =MIN(AD$23,AC74) -> 0 | AE74: =IF(AND(AD$24=1,OR(AC$25="",$C74>=AC$25)),MAX(0,MIN(AC74-AD74,$D74-(G74+K74+O74+S74+W74+AA74))),0) -> 0 | AF74: =AC74-AD74-AE74 -> 0 | AG74: =IF(AJ73>0.5,AJ73*(1+AG$23)+AG$24,0) -> 0 | AH74: =MIN(AH$23,AG74) -> 0 | AI74: =IF(AND(AH$24=1,OR(AG$25="",$C74>=AG$25)),MAX(0,MIN(AG74-AH74,$D74-(G74+K74+O74+S74+W74+AA74+AE74))),0) -> 0 | AJ74: =AG74-AH74-AI74 -> 0 | AK74: =IF(AK73>0.5,AK73*(1+$E$12)+$G$12-MIN($F$12,AK73*(1+$E$12)+$G$12),0) -> 0 | AL74: =IF(AL73>0.5,AL73*(1+$E$13)+$G$13-MIN($F$13,AL73*(1+$E$13)+$G$13),0) -> 0 | AM74: =IF(AM73>0.5,AM73*(1+$E$14)+$G$14-MIN($F$14,AM73*(1+$E$14)+$G$14),0) -> 0 | AN74: =IF(AN73>0.5,AN73*(1+$E$15)+$G$15-MIN($F$15,AN73*(1+$E$15)+$G$15),0) -> 0 | AO74: =IF(AO73>0.5,AO73*(1+$E$16)+$G$16-MIN($F$16,AO73*(1+$E$16)+$G$16),0) -> 0 | AP74: =IF(AP73>0.5,AP73*(1+$E$17)+$G$17-MIN($F$17,AP73*(1+$E$17)+$G$17),0) -> 0 | AQ74: =IF(AQ73>0.5,AQ73*(1+$E$18)+$G$18-MIN($F$18,AQ73*(1+$E$18)+$G$18),0) -> 0 | AR74: =IF(AR73>0.5,AR73*(1+$E$19)+$G$19-MIN($F$19,AR73*(1+$E$19)+$G$19),0) -> 0 | AS74: =H74+L74+P74+T74+X74+AB74+AF74+AJ74 -> 0 | AT74: =SUM(AK74:AR74) -> 0 | AU74: =F74+G74+J74+K74+N74+O74+R74+S74+V74+W74+Z74+AA74+AD74+AE74+AH74+AI74 -> 0
B75: 48 | C75: =EDATE($C$7,47) -> 47727 | D75: =$C$8-(F75+J75+N75+R75+V75+Z75+AD75+AH75) -> 0 | E75: =IF(H74>0.5,H74*(1+E$23)+E$24,0) -> 0 | F75: =MIN(F$23,E75) -> 0 | G75: =IF(AND(F$24=1,OR(E$25="",$C75>=E$25)),MAX(0,MIN(E75-F75,$D75-(0))),0) -> 0 | H75: =E75-F75-G75 -> 0 | I75: =IF(L74>0.5,L74*(1+I$23)+I$24,0) -> 0 | J75: =MIN(J$23,I75) -> 0 | K75: =IF(AND(J$24=1,OR(I$25="",$C75>=I$25)),MAX(0,MIN(I75-J75,$D75-(G75))),0) -> 0 | L75: =I75-J75-K75 -> 0 | M75: =IF(P74>0.5,P74*(1+M$23)+M$24,0) -> 0 | N75: =MIN(N$23,M75) -> 0 | O75: =IF(AND(N$24=1,OR(M$25="",$C75>=M$25)),MAX(0,MIN(M75-N75,$D75-(G75+K75))),0) -> 0 | P75: =M75-N75-O75 -> 0 | Q75: =IF(T74>0.5,T74*(1+Q$23)+Q$24,0) -> 0 | R75: =MIN(R$23,Q75) -> 0 | S75: =IF(AND(R$24=1,OR(Q$25="",$C75>=Q$25)),MAX(0,MIN(Q75-R75,$D75-(G75+K75+O75))),0) -> 0 | T75: =Q75-R75-S75 -> 0 | U75: =IF(X74>0.5,X74*(1+U$23)+U$24,0) -> 0 | V75: =MIN(V$23,U75) -> 0 | W75: =IF(AND(V$24=1,OR(U$25="",$C75>=U$25)),MAX(0,MIN(U75-V75,$D75-(G75+K75+O75+S75))),0) -> 0 | X75: =U75-V75-W75 -> 0 | Y75: =IF(AB74>0.5,AB74*(1+Y$23)+Y$24,0) -> 0 | Z75: =MIN(Z$23,Y75) -> 0 | AA75: =IF(AND(Z$24=1,OR(Y$25="",$C75>=Y$25)),MAX(0,MIN(Y75-Z75,$D75-(G75+K75+O75+S75+W75))),0) -> 0 | AB75: =Y75-Z75-AA75 -> 0 | AC75: =IF(AF74>0.5,AF74*(1+AC$23)+AC$24,0) -> 0 | AD75: =MIN(AD$23,AC75) -> 0 | AE75: =IF(AND(AD$24=1,OR(AC$25="",$C75>=AC$25)),MAX(0,MIN(AC75-AD75,$D75-(G75+K75+O75+S75+W75+AA75))),0) -> 0 | AF75: =AC75-AD75-AE75 -> 0 | AG75: =IF(AJ74>0.5,AJ74*(1+AG$23)+AG$24,0) -> 0 | AH75: =MIN(AH$23,AG75) -> 0 | AI75: =IF(AND(AH$24=1,OR(AG$25="",$C75>=AG$25)),MAX(0,MIN(AG75-AH75,$D75-(G75+K75+O75+S75+W75+AA75+AE75))),0) -> 0 | AJ75: =AG75-AH75-AI75 -> 0 | AK75: =IF(AK74>0.5,AK74*(1+$E$12)+$G$12-MIN($F$12,AK74*(1+$E$12)+$G$12),0) -> 0 | AL75: =IF(AL74>0.5,AL74*(1+$E$13)+$G$13-MIN($F$13,AL74*(1+$E$13)+$G$13),0) -> 0 | AM75: =IF(AM74>0.5,AM74*(1+$E$14)+$G$14-MIN($F$14,AM74*(1+$E$14)+$G$14),0) -> 0 | AN75: =IF(AN74>0.5,AN74*(1+$E$15)+$G$15-MIN($F$15,AN74*(1+$E$15)+$G$15),0) -> 0 | AO75: =IF(AO74>0.5,AO74*(1+$E$16)+$G$16-MIN($F$16,AO74*(1+$E$16)+$G$16),0) -> 0 | AP75: =IF(AP74>0.5,AP74*(1+$E$17)+$G$17-MIN($F$17,AP74*(1+$E$17)+$G$17),0) -> 0 | AQ75: =IF(AQ74>0.5,AQ74*(1+$E$18)+$G$18-MIN($F$18,AQ74*(1+$E$18)+$G$18),0) -> 0 | AR75: =IF(AR74>0.5,AR74*(1+$E$19)+$G$19-MIN($F$19,AR74*(1+$E$19)+$G$19),0) -> 0 | AS75: =H75+L75+P75+T75+X75+AB75+AF75+AJ75 -> 0 | AT75: =SUM(AK75:AR75) -> 0 | AU75: =F75+G75+J75+K75+N75+O75+R75+S75+V75+W75+Z75+AA75+AD75+AE75+AH75+AI75 -> 0
B76: 49 | C76: =EDATE($C$7,48) -> 47757 | D76: =$C$8-(F76+J76+N76+R76+V76+Z76+AD76+AH76) -> 0 | E76: =IF(H75>0.5,H75*(1+E$23)+E$24,0) -> 0 | F76: =MIN(F$23,E76) -> 0 | G76: =IF(AND(F$24=1,OR(E$25="",$C76>=E$25)),MAX(0,MIN(E76-F76,$D76-(0))),0) -> 0 | H76: =E76-F76-G76 -> 0 | I76: =IF(L75>0.5,L75*(1+I$23)+I$24,0) -> 0 | J76: =MIN(J$23,I76) -> 0 | K76: =IF(AND(J$24=1,OR(I$25="",$C76>=I$25)),MAX(0,MIN(I76-J76,$D76-(G76))),0) -> 0 | L76: =I76-J76-K76 -> 0 | M76: =IF(P75>0.5,P75*(1+M$23)+M$24,0) -> 0 | N76: =MIN(N$23,M76) -> 0 | O76: =IF(AND(N$24=1,OR(M$25="",$C76>=M$25)),MAX(0,MIN(M76-N76,$D76-(G76+K76))),0) -> 0 | P76: =M76-N76-O76 -> 0 | Q76: =IF(T75>0.5,T75*(1+Q$23)+Q$24,0) -> 0 | R76: =MIN(R$23,Q76) -> 0 | S76: =IF(AND(R$24=1,OR(Q$25="",$C76>=Q$25)),MAX(0,MIN(Q76-R76,$D76-(G76+K76+O76))),0) -> 0 | T76: =Q76-R76-S76 -> 0 | U76: =IF(X75>0.5,X75*(1+U$23)+U$24,0) -> 0 | V76: =MIN(V$23,U76) -> 0 | W76: =IF(AND(V$24=1,OR(U$25="",$C76>=U$25)),MAX(0,MIN(U76-V76,$D76-(G76+K76+O76+S76))),0) -> 0 | X76: =U76-V76-W76 -> 0 | Y76: =IF(AB75>0.5,AB75*(1+Y$23)+Y$24,0) -> 0 | Z76: =MIN(Z$23,Y76) -> 0 | AA76: =IF(AND(Z$24=1,OR(Y$25="",$C76>=Y$25)),MAX(0,MIN(Y76-Z76,$D76-(G76+K76+O76+S76+W76))),0) -> 0 | AB76: =Y76-Z76-AA76 -> 0 | AC76: =IF(AF75>0.5,AF75*(1+AC$23)+AC$24,0) -> 0 | AD76: =MIN(AD$23,AC76) -> 0 | AE76: =IF(AND(AD$24=1,OR(AC$25="",$C76>=AC$25)),MAX(0,MIN(AC76-AD76,$D76-(G76+K76+O76+S76+W76+AA76))),0) -> 0 | AF76: =AC76-AD76-AE76 -> 0 | AG76: =IF(AJ75>0.5,AJ75*(1+AG$23)+AG$24,0) -> 0 | AH76: =MIN(AH$23,AG76) -> 0 | AI76: =IF(AND(AH$24=1,OR(AG$25="",$C76>=AG$25)),MAX(0,MIN(AG76-AH76,$D76-(G76+K76+O76+S76+W76+AA76+AE76))),0) -> 0 | AJ76: =AG76-AH76-AI76 -> 0 | AK76: =IF(AK75>0.5,AK75*(1+$E$12)+$G$12-MIN($F$12,AK75*(1+$E$12)+$G$12),0) -> 0 | AL76: =IF(AL75>0.5,AL75*(1+$E$13)+$G$13-MIN($F$13,AL75*(1+$E$13)+$G$13),0) -> 0 | AM76: =IF(AM75>0.5,AM75*(1+$E$14)+$G$14-MIN($F$14,AM75*(1+$E$14)+$G$14),0) -> 0 | AN76: =IF(AN75>0.5,AN75*(1+$E$15)+$G$15-MIN($F$15,AN75*(1+$E$15)+$G$15),0) -> 0 | AO76: =IF(AO75>0.5,AO75*(1+$E$16)+$G$16-MIN($F$16,AO75*(1+$E$16)+$G$16),0) -> 0 | AP76: =IF(AP75>0.5,AP75*(1+$E$17)+$G$17-MIN($F$17,AP75*(1+$E$17)+$G$17),0) -> 0 | AQ76: =IF(AQ75>0.5,AQ75*(1+$E$18)+$G$18-MIN($F$18,AQ75*(1+$E$18)+$G$18),0) -> 0 | AR76: =IF(AR75>0.5,AR75*(1+$E$19)+$G$19-MIN($F$19,AR75*(1+$E$19)+$G$19),0) -> 0 | AS76: =H76+L76+P76+T76+X76+AB76+AF76+AJ76 -> 0 | AT76: =SUM(AK76:AR76) -> 0 | AU76: =F76+G76+J76+K76+N76+O76+R76+S76+V76+W76+Z76+AA76+AD76+AE76+AH76+AI76 -> 0
B77: 50 | C77: =EDATE($C$7,49) -> 47788 | D77: =$C$8-(F77+J77+N77+R77+V77+Z77+AD77+AH77) -> 0 | E77: =IF(H76>0.5,H76*(1+E$23)+E$24,0) -> 0 | F77: =MIN(F$23,E77) -> 0 | G77: =IF(AND(F$24=1,OR(E$25="",$C77>=E$25)),MAX(0,MIN(E77-F77,$D77-(0))),0) -> 0 | H77: =E77-F77-G77 -> 0 | I77: =IF(L76>0.5,L76*(1+I$23)+I$24,0) -> 0 | J77: =MIN(J$23,I77) -> 0 | K77: =IF(AND(J$24=1,OR(I$25="",$C77>=I$25)),MAX(0,MIN(I77-J77,$D77-(G77))),0) -> 0 | L77: =I77-J77-K77 -> 0 | M77: =IF(P76>0.5,P76*(1+M$23)+M$24,0) -> 0 | N77: =MIN(N$23,M77) -> 0 | O77: =IF(AND(N$24=1,OR(M$25="",$C77>=M$25)),MAX(0,MIN(M77-N77,$D77-(G77+K77))),0) -> 0 | P77: =M77-N77-O77 -> 0 | Q77: =IF(T76>0.5,T76*(1+Q$23)+Q$24,0) -> 0 | R77: =MIN(R$23,Q77) -> 0 | S77: =IF(AND(R$24=1,OR(Q$25="",$C77>=Q$25)),MAX(0,MIN(Q77-R77,$D77-(G77+K77+O77))),0) -> 0 | T77: =Q77-R77-S77 -> 0 | U77: =IF(X76>0.5,X76*(1+U$23)+U$24,0) -> 0 | V77: =MIN(V$23,U77) -> 0 | W77: =IF(AND(V$24=1,OR(U$25="",$C77>=U$25)),MAX(0,MIN(U77-V77,$D77-(G77+K77+O77+S77))),0) -> 0 | X77: =U77-V77-W77 -> 0 | Y77: =IF(AB76>0.5,AB76*(1+Y$23)+Y$24,0) -> 0 | Z77: =MIN(Z$23,Y77) -> 0 | AA77: =IF(AND(Z$24=1,OR(Y$25="",$C77>=Y$25)),MAX(0,MIN(Y77-Z77,$D77-(G77+K77+O77+S77+W77))),0) -> 0 | AB77: =Y77-Z77-AA77 -> 0 | AC77: =IF(AF76>0.5,AF76*(1+AC$23)+AC$24,0) -> 0 | AD77: =MIN(AD$23,AC77) -> 0 | AE77: =IF(AND(AD$24=1,OR(AC$25="",$C77>=AC$25)),MAX(0,MIN(AC77-AD77,$D77-(G77+K77+O77+S77+W77+AA77))),0) -> 0 | AF77: =AC77-AD77-AE77 -> 0 | AG77: =IF(AJ76>0.5,AJ76*(1+AG$23)+AG$24,0) -> 0 | AH77: =MIN(AH$23,AG77) -> 0 | AI77: =IF(AND(AH$24=1,OR(AG$25="",$C77>=AG$25)),MAX(0,MIN(AG77-AH77,$D77-(G77+K77+O77+S77+W77+AA77+AE77))),0) -> 0 | AJ77: =AG77-AH77-AI77 -> 0 | AK77: =IF(AK76>0.5,AK76*(1+$E$12)+$G$12-MIN($F$12,AK76*(1+$E$12)+$G$12),0) -> 0 | AL77: =IF(AL76>0.5,AL76*(1+$E$13)+$G$13-MIN($F$13,AL76*(1+$E$13)+$G$13),0) -> 0 | AM77: =IF(AM76>0.5,AM76*(1+$E$14)+$G$14-MIN($F$14,AM76*(1+$E$14)+$G$14),0) -> 0 | AN77: =IF(AN76>0.5,AN76*(1+$E$15)+$G$15-MIN($F$15,AN76*(1+$E$15)+$G$15),0) -> 0 | AO77: =IF(AO76>0.5,AO76*(1+$E$16)+$G$16-MIN($F$16,AO76*(1+$E$16)+$G$16),0) -> 0 | AP77: =IF(AP76>0.5,AP76*(1+$E$17)+$G$17-MIN($F$17,AP76*(1+$E$17)+$G$17),0) -> 0 | AQ77: =IF(AQ76>0.5,AQ76*(1+$E$18)+$G$18-MIN($F$18,AQ76*(1+$E$18)+$G$18),0) -> 0 | AR77: =IF(AR76>0.5,AR76*(1+$E$19)+$G$19-MIN($F$19,AR76*(1+$E$19)+$G$19),0) -> 0 | AS77: =H77+L77+P77+T77+X77+AB77+AF77+AJ77 -> 0 | AT77: =SUM(AK77:AR77) -> 0 | AU77: =F77+G77+J77+K77+N77+O77+R77+S77+V77+W77+Z77+AA77+AD77+AE77+AH77+AI77 -> 0
B78: 51 | C78: =EDATE($C$7,50) -> 47818 | D78: =$C$8-(F78+J78+N78+R78+V78+Z78+AD78+AH78) -> 0 | E78: =IF(H77>0.5,H77*(1+E$23)+E$24,0) -> 0 | F78: =MIN(F$23,E78) -> 0 | G78: =IF(AND(F$24=1,OR(E$25="",$C78>=E$25)),MAX(0,MIN(E78-F78,$D78-(0))),0) -> 0 | H78: =E78-F78-G78 -> 0 | I78: =IF(L77>0.5,L77*(1+I$23)+I$24,0) -> 0 | J78: =MIN(J$23,I78) -> 0 | K78: =IF(AND(J$24=1,OR(I$25="",$C78>=I$25)),MAX(0,MIN(I78-J78,$D78-(G78))),0) -> 0 | L78: =I78-J78-K78 -> 0 | M78: =IF(P77>0.5,P77*(1+M$23)+M$24,0) -> 0 | N78: =MIN(N$23,M78) -> 0 | O78: =IF(AND(N$24=1,OR(M$25="",$C78>=M$25)),MAX(0,MIN(M78-N78,$D78-(G78+K78))),0) -> 0 | P78: =M78-N78-O78 -> 0 | Q78: =IF(T77>0.5,T77*(1+Q$23)+Q$24,0) -> 0 | R78: =MIN(R$23,Q78) -> 0 | S78: =IF(AND(R$24=1,OR(Q$25="",$C78>=Q$25)),MAX(0,MIN(Q78-R78,$D78-(G78+K78+O78))),0) -> 0 | T78: =Q78-R78-S78 -> 0 | U78: =IF(X77>0.5,X77*(1+U$23)+U$24,0) -> 0 | V78: =MIN(V$23,U78) -> 0 | W78: =IF(AND(V$24=1,OR(U$25="",$C78>=U$25)),MAX(0,MIN(U78-V78,$D78-(G78+K78+O78+S78))),0) -> 0 | X78: =U78-V78-W78 -> 0 | Y78: =IF(AB77>0.5,AB77*(1+Y$23)+Y$24,0) -> 0 | Z78: =MIN(Z$23,Y78) -> 0 | AA78: =IF(AND(Z$24=1,OR(Y$25="",$C78>=Y$25)),MAX(0,MIN(Y78-Z78,$D78-(G78+K78+O78+S78+W78))),0) -> 0 | AB78: =Y78-Z78-AA78 -> 0 | AC78: =IF(AF77>0.5,AF77*(1+AC$23)+AC$24,0) -> 0 | AD78: =MIN(AD$23,AC78) -> 0 | AE78: =IF(AND(AD$24=1,OR(AC$25="",$C78>=AC$25)),MAX(0,MIN(AC78-AD78,$D78-(G78+K78+O78+S78+W78+AA78))),0) -> 0 | AF78: =AC78-AD78-AE78 -> 0 | AG78: =IF(AJ77>0.5,AJ77*(1+AG$23)+AG$24,0) -> 0 | AH78: =MIN(AH$23,AG78) -> 0 | AI78: =IF(AND(AH$24=1,OR(AG$25="",$C78>=AG$25)),MAX(0,MIN(AG78-AH78,$D78-(G78+K78+O78+S78+W78+AA78+AE78))),0) -> 0 | AJ78: =AG78-AH78-AI78 -> 0 | AK78: =IF(AK77>0.5,AK77*(1+$E$12)+$G$12-MIN($F$12,AK77*(1+$E$12)+$G$12),0) -> 0 | AL78: =IF(AL77>0.5,AL77*(1+$E$13)+$G$13-MIN($F$13,AL77*(1+$E$13)+$G$13),0) -> 0 | AM78: =IF(AM77>0.5,AM77*(1+$E$14)+$G$14-MIN($F$14,AM77*(1+$E$14)+$G$14),0) -> 0 | AN78: =IF(AN77>0.5,AN77*(1+$E$15)+$G$15-MIN($F$15,AN77*(1+$E$15)+$G$15),0) -> 0 | AO78: =IF(AO77>0.5,AO77*(1+$E$16)+$G$16-MIN($F$16,AO77*(1+$E$16)+$G$16),0) -> 0 | AP78: =IF(AP77>0.5,AP77*(1+$E$17)+$G$17-MIN($F$17,AP77*(1+$E$17)+$G$17),0) -> 0 | AQ78: =IF(AQ77>0.5,AQ77*(1+$E$18)+$G$18-MIN($F$18,AQ77*(1+$E$18)+$G$18),0) -> 0 | AR78: =IF(AR77>0.5,AR77*(1+$E$19)+$G$19-MIN($F$19,AR77*(1+$E$19)+$G$19),0) -> 0 | AS78: =H78+L78+P78+T78+X78+AB78+AF78+AJ78 -> 0 | AT78: =SUM(AK78:AR78) -> 0 | AU78: =F78+G78+J78+K78+N78+O78+R78+S78+V78+W78+Z78+AA78+AD78+AE78+AH78+AI78 -> 0
B79: 52 | C79: =EDATE($C$7,51) -> 47849 | D79: =$C$8-(F79+J79+N79+R79+V79+Z79+AD79+AH79) -> 0 | E79: =IF(H78>0.5,H78*(1+E$23)+E$24,0) -> 0 | F79: =MIN(F$23,E79) -> 0 | G79: =IF(AND(F$24=1,OR(E$25="",$C79>=E$25)),MAX(0,MIN(E79-F79,$D79-(0))),0) -> 0 | H79: =E79-F79-G79 -> 0 | I79: =IF(L78>0.5,L78*(1+I$23)+I$24,0) -> 0 | J79: =MIN(J$23,I79) -> 0 | K79: =IF(AND(J$24=1,OR(I$25="",$C79>=I$25)),MAX(0,MIN(I79-J79,$D79-(G79))),0) -> 0 | L79: =I79-J79-K79 -> 0 | M79: =IF(P78>0.5,P78*(1+M$23)+M$24,0) -> 0 | N79: =MIN(N$23,M79) -> 0 | O79: =IF(AND(N$24=1,OR(M$25="",$C79>=M$25)),MAX(0,MIN(M79-N79,$D79-(G79+K79))),0) -> 0 | P79: =M79-N79-O79 -> 0 | Q79: =IF(T78>0.5,T78*(1+Q$23)+Q$24,0) -> 0 | R79: =MIN(R$23,Q79) -> 0 | S79: =IF(AND(R$24=1,OR(Q$25="",$C79>=Q$25)),MAX(0,MIN(Q79-R79,$D79-(G79+K79+O79))),0) -> 0 | T79: =Q79-R79-S79 -> 0 | U79: =IF(X78>0.5,X78*(1+U$23)+U$24,0) -> 0 | V79: =MIN(V$23,U79) -> 0 | W79: =IF(AND(V$24=1,OR(U$25="",$C79>=U$25)),MAX(0,MIN(U79-V79,$D79-(G79+K79+O79+S79))),0) -> 0 | X79: =U79-V79-W79 -> 0 | Y79: =IF(AB78>0.5,AB78*(1+Y$23)+Y$24,0) -> 0 | Z79: =MIN(Z$23,Y79) -> 0 | AA79: =IF(AND(Z$24=1,OR(Y$25="",$C79>=Y$25)),MAX(0,MIN(Y79-Z79,$D79-(G79+K79+O79+S79+W79))),0) -> 0 | AB79: =Y79-Z79-AA79 -> 0 | AC79: =IF(AF78>0.5,AF78*(1+AC$23)+AC$24,0) -> 0 | AD79: =MIN(AD$23,AC79) -> 0 | AE79: =IF(AND(AD$24=1,OR(AC$25="",$C79>=AC$25)),MAX(0,MIN(AC79-AD79,$D79-(G79+K79+O79+S79+W79+AA79))),0) -> 0 | AF79: =AC79-AD79-AE79 -> 0 | AG79: =IF(AJ78>0.5,AJ78*(1+AG$23)+AG$24,0) -> 0 | AH79: =MIN(AH$23,AG79) -> 0 | AI79: =IF(AND(AH$24=1,OR(AG$25="",$C79>=AG$25)),MAX(0,MIN(AG79-AH79,$D79-(G79+K79+O79+S79+W79+AA79+AE79))),0) -> 0 | AJ79: =AG79-AH79-AI79 -> 0 | AK79: =IF(AK78>0.5,AK78*(1+$E$12)+$G$12-MIN($F$12,AK78*(1+$E$12)+$G$12),0) -> 0 | AL79: =IF(AL78>0.5,AL78*(1+$E$13)+$G$13-MIN($F$13,AL78*(1+$E$13)+$G$13),0) -> 0 | AM79: =IF(AM78>0.5,AM78*(1+$E$14)+$G$14-MIN($F$14,AM78*(1+$E$14)+$G$14),0) -> 0 | AN79: =IF(AN78>0.5,AN78*(1+$E$15)+$G$15-MIN($F$15,AN78*(1+$E$15)+$G$15),0) -> 0 | AO79: =IF(AO78>0.5,AO78*(1+$E$16)+$G$16-MIN($F$16,AO78*(1+$E$16)+$G$16),0) -> 0 | AP79: =IF(AP78>0.5,AP78*(1+$E$17)+$G$17-MIN($F$17,AP78*(1+$E$17)+$G$17),0) -> 0 | AQ79: =IF(AQ78>0.5,AQ78*(1+$E$18)+$G$18-MIN($F$18,AQ78*(1+$E$18)+$G$18),0) -> 0 | AR79: =IF(AR78>0.5,AR78*(1+$E$19)+$G$19-MIN($F$19,AR78*(1+$E$19)+$G$19),0) -> 0 | AS79: =H79+L79+P79+T79+X79+AB79+AF79+AJ79 -> 0 | AT79: =SUM(AK79:AR79) -> 0 | AU79: =F79+G79+J79+K79+N79+O79+R79+S79+V79+W79+Z79+AA79+AD79+AE79+AH79+AI79 -> 0
B80: 53 | C80: =EDATE($C$7,52) -> 47880 | D80: =$C$8-(F80+J80+N80+R80+V80+Z80+AD80+AH80) -> 0 | E80: =IF(H79>0.5,H79*(1+E$23)+E$24,0) -> 0 | F80: =MIN(F$23,E80) -> 0 | G80: =IF(AND(F$24=1,OR(E$25="",$C80>=E$25)),MAX(0,MIN(E80-F80,$D80-(0))),0) -> 0 | H80: =E80-F80-G80 -> 0 | I80: =IF(L79>0.5,L79*(1+I$23)+I$24,0) -> 0 | J80: =MIN(J$23,I80) -> 0 | K80: =IF(AND(J$24=1,OR(I$25="",$C80>=I$25)),MAX(0,MIN(I80-J80,$D80-(G80))),0) -> 0 | L80: =I80-J80-K80 -> 0 | M80: =IF(P79>0.5,P79*(1+M$23)+M$24,0) -> 0 | N80: =MIN(N$23,M80) -> 0 | O80: =IF(AND(N$24=1,OR(M$25="",$C80>=M$25)),MAX(0,MIN(M80-N80,$D80-(G80+K80))),0) -> 0 | P80: =M80-N80-O80 -> 0 | Q80: =IF(T79>0.5,T79*(1+Q$23)+Q$24,0) -> 0 | R80: =MIN(R$23,Q80) -> 0 | S80: =IF(AND(R$24=1,OR(Q$25="",$C80>=Q$25)),MAX(0,MIN(Q80-R80,$D80-(G80+K80+O80))),0) -> 0 | T80: =Q80-R80-S80 -> 0 | U80: =IF(X79>0.5,X79*(1+U$23)+U$24,0) -> 0 | V80: =MIN(V$23,U80) -> 0 | W80: =IF(AND(V$24=1,OR(U$25="",$C80>=U$25)),MAX(0,MIN(U80-V80,$D80-(G80+K80+O80+S80))),0) -> 0 | X80: =U80-V80-W80 -> 0 | Y80: =IF(AB79>0.5,AB79*(1+Y$23)+Y$24,0) -> 0 | Z80: =MIN(Z$23,Y80) -> 0 | AA80: =IF(AND(Z$24=1,OR(Y$25="",$C80>=Y$25)),MAX(0,MIN(Y80-Z80,$D80-(G80+K80+O80+S80+W80))),0) -> 0 | AB80: =Y80-Z80-AA80 -> 0 | AC80: =IF(AF79>0.5,AF79*(1+AC$23)+AC$24,0) -> 0 | AD80: =MIN(AD$23,AC80) -> 0 | AE80: =IF(AND(AD$24=1,OR(AC$25="",$C80>=AC$25)),MAX(0,MIN(AC80-AD80,$D80-(G80+K80+O80+S80+W80+AA80))),0) -> 0 | AF80: =AC80-AD80-AE80 -> 0 | AG80: =IF(AJ79>0.5,AJ79*(1+AG$23)+AG$24,0) -> 0 | AH80: =MIN(AH$23,AG80) -> 0 | AI80: =IF(AND(AH$24=1,OR(AG$25="",$C80>=AG$25)),MAX(0,MIN(AG80-AH80,$D80-(G80+K80+O80+S80+W80+AA80+AE80))),0) -> 0 | AJ80: =AG80-AH80-AI80 -> 0 | AK80: =IF(AK79>0.5,AK79*(1+$E$12)+$G$12-MIN($F$12,AK79*(1+$E$12)+$G$12),0) -> 0 | AL80: =IF(AL79>0.5,AL79*(1+$E$13)+$G$13-MIN($F$13,AL79*(1+$E$13)+$G$13),0) -> 0 | AM80: =IF(AM79>0.5,AM79*(1+$E$14)+$G$14-MIN($F$14,AM79*(1+$E$14)+$G$14),0) -> 0 | AN80: =IF(AN79>0.5,AN79*(1+$E$15)+$G$15-MIN($F$15,AN79*(1+$E$15)+$G$15),0) -> 0 | AO80: =IF(AO79>0.5,AO79*(1+$E$16)+$G$16-MIN($F$16,AO79*(1+$E$16)+$G$16),0) -> 0 | AP80: =IF(AP79>0.5,AP79*(1+$E$17)+$G$17-MIN($F$17,AP79*(1+$E$17)+$G$17),0) -> 0 | AQ80: =IF(AQ79>0.5,AQ79*(1+$E$18)+$G$18-MIN($F$18,AQ79*(1+$E$18)+$G$18),0) -> 0 | AR80: =IF(AR79>0.5,AR79*(1+$E$19)+$G$19-MIN($F$19,AR79*(1+$E$19)+$G$19),0) -> 0 | AS80: =H80+L80+P80+T80+X80+AB80+AF80+AJ80 -> 0 | AT80: =SUM(AK80:AR80) -> 0 | AU80: =F80+G80+J80+K80+N80+O80+R80+S80+V80+W80+Z80+AA80+AD80+AE80+AH80+AI80 -> 0
B81: 54 | C81: =EDATE($C$7,53) -> 47908 | D81: =$C$8-(F81+J81+N81+R81+V81+Z81+AD81+AH81) -> 0 | E81: =IF(H80>0.5,H80*(1+E$23)+E$24,0) -> 0 | F81: =MIN(F$23,E81) -> 0 | G81: =IF(AND(F$24=1,OR(E$25="",$C81>=E$25)),MAX(0,MIN(E81-F81,$D81-(0))),0) -> 0 | H81: =E81-F81-G81 -> 0 | I81: =IF(L80>0.5,L80*(1+I$23)+I$24,0) -> 0 | J81: =MIN(J$23,I81) -> 0 | K81: =IF(AND(J$24=1,OR(I$25="",$C81>=I$25)),MAX(0,MIN(I81-J81,$D81-(G81))),0) -> 0 | L81: =I81-J81-K81 -> 0 | M81: =IF(P80>0.5,P80*(1+M$23)+M$24,0) -> 0 | N81: =MIN(N$23,M81) -> 0 | O81: =IF(AND(N$24=1,OR(M$25="",$C81>=M$25)),MAX(0,MIN(M81-N81,$D81-(G81+K81))),0) -> 0 | P81: =M81-N81-O81 -> 0 | Q81: =IF(T80>0.5,T80*(1+Q$23)+Q$24,0) -> 0 | R81: =MIN(R$23,Q81) -> 0 | S81: =IF(AND(R$24=1,OR(Q$25="",$C81>=Q$25)),MAX(0,MIN(Q81-R81,$D81-(G81+K81+O81))),0) -> 0 | T81: =Q81-R81-S81 -> 0 | U81: =IF(X80>0.5,X80*(1+U$23)+U$24,0) -> 0 | V81: =MIN(V$23,U81) -> 0 | W81: =IF(AND(V$24=1,OR(U$25="",$C81>=U$25)),MAX(0,MIN(U81-V81,$D81-(G81+K81+O81+S81))),0) -> 0 | X81: =U81-V81-W81 -> 0 | Y81: =IF(AB80>0.5,AB80*(1+Y$23)+Y$24,0) -> 0 | Z81: =MIN(Z$23,Y81) -> 0 | AA81: =IF(AND(Z$24=1,OR(Y$25="",$C81>=Y$25)),MAX(0,MIN(Y81-Z81,$D81-(G81+K81+O81+S81+W81))),0) -> 0 | AB81: =Y81-Z81-AA81 -> 0 | AC81: =IF(AF80>0.5,AF80*(1+AC$23)+AC$24,0) -> 0 | AD81: =MIN(AD$23,AC81) -> 0 | AE81: =IF(AND(AD$24=1,OR(AC$25="",$C81>=AC$25)),MAX(0,MIN(AC81-AD81,$D81-(G81+K81+O81+S81+W81+AA81))),0) -> 0 | AF81: =AC81-AD81-AE81 -> 0 | AG81: =IF(AJ80>0.5,AJ80*(1+AG$23)+AG$24,0) -> 0 | AH81: =MIN(AH$23,AG81) -> 0 | AI81: =IF(AND(AH$24=1,OR(AG$25="",$C81>=AG$25)),MAX(0,MIN(AG81-AH81,$D81-(G81+K81+O81+S81+W81+AA81+AE81))),0) -> 0 | AJ81: =AG81-AH81-AI81 -> 0 | AK81: =IF(AK80>0.5,AK80*(1+$E$12)+$G$12-MIN($F$12,AK80*(1+$E$12)+$G$12),0) -> 0 | AL81: =IF(AL80>0.5,AL80*(1+$E$13)+$G$13-MIN($F$13,AL80*(1+$E$13)+$G$13),0) -> 0 | AM81: =IF(AM80>0.5,AM80*(1+$E$14)+$G$14-MIN($F$14,AM80*(1+$E$14)+$G$14),0) -> 0 | AN81: =IF(AN80>0.5,AN80*(1+$E$15)+$G$15-MIN($F$15,AN80*(1+$E$15)+$G$15),0) -> 0 | AO81: =IF(AO80>0.5,AO80*(1+$E$16)+$G$16-MIN($F$16,AO80*(1+$E$16)+$G$16),0) -> 0 | AP81: =IF(AP80>0.5,AP80*(1+$E$17)+$G$17-MIN($F$17,AP80*(1+$E$17)+$G$17),0) -> 0 | AQ81: =IF(AQ80>0.5,AQ80*(1+$E$18)+$G$18-MIN($F$18,AQ80*(1+$E$18)+$G$18),0) -> 0 | AR81: =IF(AR80>0.5,AR80*(1+$E$19)+$G$19-MIN($F$19,AR80*(1+$E$19)+$G$19),0) -> 0 | AS81: =H81+L81+P81+T81+X81+AB81+AF81+AJ81 -> 0 | AT81: =SUM(AK81:AR81) -> 0 | AU81: =F81+G81+J81+K81+N81+O81+R81+S81+V81+W81+Z81+AA81+AD81+AE81+AH81+AI81 -> 0
