Workbook

Sheet Inicio
C2: Asesoría Financiera Personal
C3: =IF(Supuestos!$C$6="","Tu marca aquí (Supuestos)",Supuestos!$C$6) -> Tu marca aquí (Supuestos)
C7: Cliente | D7: =IF(Supuestos!$C$7="","",Supuestos!$C$7)
C8: Fecha de corte | D8: =Supuestos!$C$12 -> 46290
B10: Orden para llenar
B11: Paso | C11: Hoja | D11: Qué hacer
B12: 1 | C12: Supuestos | D12: Datos del cliente, tasa de cambio, prueba de realidad y cuentas por cobrar.
B13: 2 | C13: Ingresos | D13: Cada fuente en su moneda (pesos o dólares); 1 o 0 en los meses en que llega. Meses de pago de seguridad social.
B14: 3 | C14: Presupuesto | D14: Valor por pago y frecuencia de cada gasto. Las filas grises son automáticas.
B15: 4 | C15: Deudas | D15: Saldo, tasa efectiva anual, cuota mínima y si acepta abonos extra. Elegir el método de pago.
B16: 5 | C16: Metas | D16: Metas con valor y fecha, o que se repiten. Calculadora de viaje en dólares.
B17: 6 | C17: Seguros | D17: Marcar qué seguros tiene y escribir primas de seguros nuevos.
B18: 7 | C18: Patrimonio | D18: Cuentas, inmuebles, vehículos y otros activos.
B19: 8 | C19: Inversión | D19: Inversiones actuales y las preguntas de perfil de riesgo.
B20: 9 | C20: Pensión | D20: Régimen, semanas, fecha y base de cotización.
B21: 10 | C21: Bolsillos | D21: Revisar el reparto del saldo y escribir saldos iniciales de otros bolsillos.
B22: 11 | C22: Resumen | D22: Revisar indicadores, estados y la lista de pendientes.
B23: 12 | C23: Control mensual y Plan de acción | D23: Seguimiento: gasto real cada mes y tareas con fecha.
B25: Leyenda
C26: Dato editable | D26: Celda para llenar o ajustar.
C27: Por confirmar | D27: Dato pendiente de confirmar.
C28: Cálculo automático | D28: Fórmula: no se edita.
C29: Fila automática | D29: Se llena desde otra hoja: no se edita.
C30: Color de las pestañas | D30: Dorada: tiene datos para llenar. Verde azulado: solo cálculos. Petróleo: portada y resumen.
B32: Ejemplo de una fila del Presupuesto
C33: Categoría | D33: Concepto | E33: Valor por pago | F33: Frecuencia | G33: Tipo / ¿Esencial?
C34: Alimentación | D34: Mercado | E34: 130000 | F34: Semanal | G34: Directo / Sí
C35: Resultado: 130.000 x 52 semanas = 6.760.000 al año, 563.333 al mes.
B37: Notas
C38: Todas las cifras están en pesos de hoy (sin inflación).
C39: Los rangos de inversión y las proyecciones son orientativos y no garantizan rendimientos. No se recomiendan productos específicos.
C40: Salario mínimo, tasa de cambio y reglas de pensión deben verificarse al inicio de cada asesoría.
C41: Impuestos, pensión y temas legales se validan con contador, administradora de pensiones y abogado.
B43: Paleta de la marca: Petróleo y Oro
C44: Petróleo | D44: #0E3B43
C45: Verde azulado | D45: #1D6A72
C46: Oro | D46: #C8A04A
C47: Bruma | D47: #E6EFEF
C48: Crema | D48: #FFF8E6

Sheet Resumen
B1: Resumen financiero
B2: Indicadores principales. Pesos de hoy. Estados: Bien, Atención, Alerta (referencias orientativas).
B4: Cliente | C4: =IF(Supuestos!$C$7="","",Supuestos!$C$7)
B5: Edad | C5: =Supuestos!$C$13
B6: Tipo de cliente | C6: =IF(Supuestos!$C$10="","",Supuestos!$C$10)
B7: Fecha de corte | C7: =Supuestos!$C$12 -> 46290
B8: Asesor | C8: =IF(Supuestos!$C$6="","",Supuestos!$C$6)
B10: Indicador | C10: Valor | D10: Estado | E10: Comentario
B11: Ingreso anual | C11: =Ingresos!$T$14 -> 0 | D11: ="" | E11: Suma de ingresos en sus meses reales.
B12: Gasto anual (sin ahorro) | C12: =Presupuesto!$H$89 -> 0 | D12: ="" | E12: Incluye bolsillos y cuotas de deuda.
B13: Ahorro programado anual | C13: =Presupuesto!$H$94 -> 0 | D13: ="" | E13: Cooperativas, fondos, pensión voluntaria.
B14: Sobrante anual | C14: ='Flujo anual'!$Q$22 -> 0 | D14: =IF(C14<0,"Alerta","Bien") -> Bien | E14: Después de gastos, bolsillos y ahorro programado.
B15: Tasa de ahorro total | C15: =IF(C11=0,"",(C13+C14)/C11) | D15: =IF(C15="","",IF(C15>=0.2,"Bien",IF(C15>=0.1,"Atención","Alerta"))) | E15: Referencia: sobre 20% es buena.
B16: Carga de deuda | C16: =Deudas!$C$24 | D16: =IF(C16="","",IF(C16<0.3,"Bien",IF(C16<0.4,"Atención","Alerta"))) | E16: Cuotas / ingreso mensual. Referencia: bajo 30%.
B17: Deuda total | C17: =Deudas!$D$21 -> 0 | D17: =""
B18: ¿Hay deuda cara? | C18: =Deudas!$C$23 -> No | D18: =IF(C18="Sí","Alerta","Bien") -> Bien | E18: Con deuda cara no se invierte: el sobrante va a deudas.
B19: Salida de la deuda cara | C19: =Deudas!$C$25 | D19: ="" | E19: Según la simulación de la hoja Deudas.
B20: Liquidez (meses de gasto esencial) | C20: =IF(Presupuesto!$I$95=0,"",Patrimonio!$C$33/Presupuesto!$I$95) | D20: =IF(C20="","",IF(C20>=3,"Bien",IF(C20>=1,"Atención","Alerta")))
B21: Meta vigente del fondo de emergencia | C21: ='Fondo emergencia'!$C$21 -> 0 | D21: =""
B22: Avance del fondo frente a la meta completa | C22: ='Fondo emergencia'!$C$25 -> 1 | D22: =IF(C22>=0.999,"Bien",IF(C22>=0.5,"Atención","Alerta")) -> Bien
B23: Faltante de los meses sin ingreso | C23: ='Flujo anual'!$T$20 -> 0 | D23: ="" | E23: Se cubre con su propio bolsillo.
B24: Aporte mensual a ese bolsillo | C24: ='Flujo anual'!$T$23 -> 0 | D24: ="" | E24: En los meses con sobrante.
B25: Inversión anual | C25: ='Flujo anual'!$Q$33 -> 0 | D25: ="" | E25: Incluye abonos de cuentas por cobrar destinados a inversión.
B26: Aporte único a inversión | C26: =Bolsillos!$C$27 -> 0 | D26: ="" | E26: Del excedente del saldo actual.
B27: Perfil de inversión | C27: =Inversión!$E$32 -> Falta responder | D27: ="" | E27: El menor entre disposición y capacidad.
B28: % en crecimiento | C28: =Inversión!$C$45 -> 0 | D28: ="" | E28: Rango orientativo según edad y perfil.
B29: Semanas estimadas al cumplir la edad de pensión | C29: =Pensión!$C$20 | D29: ="" | E29: =IF(Pensión!$C$22="","","Requeridas: "&ROUND(Pensión!$C$22,0))
B30: ¿Cumple las semanas? | C30: =Pensión!$C$24 | D30: =IF(C30="Sí","Bien",IF(C30="No","Alerta",""))
B31: Mesada neta estimada (escenario medio) | C31: =IF(OR(Pensión!$C$6="",Pensión!$C$13=""),"",Pensión!$D$63) | D31: ="" | E31: Solo Colpensiones. Confirmar con la administradora.
B32: ¿Brecha pensional? | C32: =Pensión!$C$78 | D32: =IF(C32="Sí","Alerta",IF(C32="No","Bien","")) | E32: Si deja de trabajar, escenario medio.
B33: Patrimonio neto | C33: =Patrimonio!$F$30 -> 0 | D33: =""
B34: Concentración en inmuebles y vehículos | C34: =Patrimonio!$C$39 -> 0 | D34: =IF(C34<=0.8,"Bien","Atención") -> Bien | E34: Referencia: más de 80% es poco líquido.
B35: Prueba de realidad | C35: =Supuestos!$C$41 -> Pendiente | D35: =IF(C35="Confirmada","Bien",IF(C35="Pendiente","Atención","Alerta")) -> Atención | E35: Mientras esté pendiente se invierte un % menor.
B37: Pendientes y alertas
B38: =IF(Supuestos!$C$8="","Falta la fecha de nacimiento (Supuestos).","") -> Falta la fecha de nacimiento (Supuestos).
B39: =IF(Supuestos!$C$17="","Falta la tasa de cambio (Supuestos).","") -> Falta la tasa de cambio (Supuestos).
B40: =IF(Supuestos!$C$41="Pendiente","Prueba de realidad pendiente: se invierte un % menor del sobrante.",IF(Supuestos!$C$41="Revisar gastos","La prueba de realidad muestra gastos no registrados: revisar el presupuesto.","")) -> Prueba de realidad pendiente: se invierte un % menor del sobrante.
B41: =IF(Presupuesto!$I$97>0,"Hay filas del presupuesto con valor pero sin frecuencia o tipo.","")
B42: ='Flujo anual'!$B$36
B43: =IF(Bolsillos!$C$25<-0.5,"Los saldos iniciales de los bolsillos superan lo disponible.","")
B44: =IF(Inversión!$D$20="","Falta responder el perfil de inversión (hoja Inversión).","") -> Falta responder el perfil de inversión (hoja Inversión).
B45: =IF(Pensión!$C$6="","Faltan los datos de pensión (régimen y semanas).","") -> Faltan los datos de pensión (régimen y semanas).
B46: =IF(COUNTIF(Seguros!$F$6:$F$13,"")>0,"Falta marcar qué seguros tiene el cliente.","") -> Falta marcar qué seguros tiene el cliente.
B47: =IF(Deudas!$C$26="Sí","Alguna deuda tarda más de 120 meses en pagarse (normal en hipotecarios; si no lo es, revisar).","")
B50: Sensibilidad a la tasa de cambio (solo si hay ingresos en dólares)
B51: Ingreso anual en dólares | C51: =Ingresos!$T$25 -> 0
B52: Cada 100 pesos que baje la tasa, el ingreso mensual cambia en | C52: =-C51/12*100 -> 0
B53: Si la tasa de cambio fuera | C53: Ingreso anual | D53: Carga de deuda | E53: Sobrante anual aproximado
B54: =IF(N(Supuestos!$C$17)=0,"",Supuestos!$C$17*0.85) | C54: =IF(B54="","",Ingresos!$T$14+C$51*(B54-Supuestos!$C$17)) | D54: =IF(OR(B54="",N(C54)=0),"",Deudas!$F$21/(C54/12)) | E54: =IF(B54="","",'Flujo anual'!$Q$22+C$51*(B54-Supuestos!$C$17))
B55: =IF(N(Supuestos!$C$17)=0,"",Supuestos!$C$17*0.9) | C55: =IF(B55="","",Ingresos!$T$14+C$51*(B55-Supuestos!$C$17)) | D55: =IF(OR(B55="",N(C55)=0),"",Deudas!$F$21/(C55/12)) | E55: =IF(B55="","",'Flujo anual'!$Q$22+C$51*(B55-Supuestos!$C$17))
B56: =IF(N(Supuestos!$C$17)=0,"",Supuestos!$C$17*0.95) | C56: =IF(B56="","",Ingresos!$T$14+C$51*(B56-Supuestos!$C$17)) | D56: =IF(OR(B56="",N(C56)=0),"",Deudas!$F$21/(C56/12)) | E56: =IF(B56="","",'Flujo anual'!$Q$22+C$51*(B56-Supuestos!$C$17))
B57: =IF(N(Supuestos!$C$17)=0,"",Supuestos!$C$17*1) | C57: =IF(B57="","",Ingresos!$T$14+C$51*(B57-Supuestos!$C$17)) | D57: =IF(OR(B57="",N(C57)=0),"",Deudas!$F$21/(C57/12)) | E57: =IF(B57="","",'Flujo anual'!$Q$22+C$51*(B57-Supuestos!$C$17))
B58: =IF(N(Supuestos!$C$17)=0,"",Supuestos!$C$17*1.05) | C58: =IF(B58="","",Ingresos!$T$14+C$51*(B58-Supuestos!$C$17)) | D58: =IF(OR(B58="",N(C58)=0),"",Deudas!$F$21/(C58/12)) | E58: =IF(B58="","",'Flujo anual'!$Q$22+C$51*(B58-Supuestos!$C$17))
B59: =IF(N(Supuestos!$C$17)=0,"",Supuestos!$C$17*1.1) | C59: =IF(B59="","",Ingresos!$T$14+C$51*(B59-Supuestos!$C$17)) | D59: =IF(OR(B59="",N(C59)=0),"",Deudas!$F$21/(C59/12)) | E59: =IF(B59="","",'Flujo anual'!$Q$22+C$51*(B59-Supuestos!$C$17))
B60: =IF(C51=0,"El cliente no tiene ingresos en dólares: esta tabla no aplica.","La fila en negrilla es la tasa actual. El sobrante es aproximado: supone que el cambio se reparte igual en el año.") -> El cliente no tiene ingresos en dólares: esta tabla no aplica.

Sheet Supuestos
B1: Supuestos y datos base
B2: Celdas crema: datos que se llenan o ajustan. Celdas ámbar: por confirmar. Todo lo demás se calcula solo.
B5: Datos del cliente | D5: Nota
B6: Marca o nombre del asesor | D6: Aparece en el Inicio y el Resumen.
B7: Nombre del cliente
B8: Fecha de nacimiento | D8: Formato dd/mm/aaaa.
B9: Sexo | D9: Define edad y semanas de pensión.
B10: Tipo de cliente | D10: Define los meses de fondo de emergencia sugeridos.
B11: Personas a cargo | C11: 0 | D11: Hijos u otras personas que dependen económicamente.
B12: Fecha de corte | C12: =TODAY() -> 46290 | D12: Por defecto, hoy. Se puede escribir una fecha fija.
B13: Edad | C13: =IF(C8="","",DATEDIF(C8,C12,"y"))
B14: Año del flujo anual | C14: =YEAR(C12)+1 -> 2027 | D14: Año que se proyecta mes a mes en la hoja Flujo anual.
B16: Parámetros
B17: Tasa de cambio COP por USD | D17: Buscar la tasa oficial vigente.
B18: Salario mínimo del año | C18: 1750905 | D18: Colombia 2026. Verificar cada año.
B19: Meses de fondo de emergencia sugeridos | C19: =IFERROR(VLOOKUP(C10,Listas!$H$2:$I$7,2,FALSE()),3) -> 3 | D19: Según el tipo de cliente.
B20: Meses de fondo a usar (opcional) | D20: Déjalo vacío para usar el sugerido.
B21: Meses de fondo efectivos | C21: =IF(C20="",C19,C20) -> 3
B22: Umbral de deuda cara (tasa efectiva anual) | C22: 0.2 | D22: Ajustar según las tasas vigentes.
B23: % del sobrante a inversión (prueba de realidad confirmada) | C23: 0.7 | D23: El resto queda como margen.
B24: % del sobrante a inversión (prueba pendiente) | C24: 0.5 | D24: Más prudente mientras no se confirme el sobrante.
B25: % del sobrante a deudas cuando hay deuda cara | C25: 0.9 | D25: Con deuda cara no se invierte.
B26: % del excedente actual a inversión | C26: 0.5 | D26: Del saldo que sobra después de llenar los bolsillos.
B27: Rendimiento real supuesto: crecimiento | C27: 0.05 | D27: Ilustrativo, por encima de la inflación. No garantizado.
B28: Rendimiento real supuesto: estabilidad | C28: 0.015 | D28: Ilustrativo, por encima de la inflación. No garantizado.
B29: Edad de retiro esperada | C29: =IF(C9="Hombre",62,57) -> 57 | D29: Por defecto, la edad de pensión. Se puede cambiar.
B30: Reducción anual del % en crecimiento cerca del retiro | C30: 0.02 | D30: Se aplica en los 10 años anteriores al retiro.
B31: Piso del % en crecimiento | C31: 0.1
B32: Colchón mínimo en la cuenta operativa | C32: 0 | D32: Dinero que no se reparte en bolsillos.
B34: Prueba de realidad
B35: Ahorro total hace N meses | D35: Suma de cuentas, bolsillos e inversiones en esa fecha.
B36: N (meses)
B37: Ahorro total hoy | D37: Sin contar ingresos extraordinarios (herencias, ventas).
B38: Ahorro real mensual | C38: =IF(OR(C35="",C36="",C37=""),"",(C37-C35)/C36)
B39: Ahorro esperado mensual (sobrante + ahorro programado) | C39: =('Flujo anual'!$Q$22+Presupuesto!$H$94)/12 -> 0
B40: Diferencia | C40: =IF(C38="","",IF(C39=0,"",(C38-C39)/ABS(C39)))
B41: Estado de la prueba | C41: =IF(C38="","Pendiente",IF(C40="","Pendiente",IF(C40>=-0.15,"Confirmada","Revisar gastos"))) -> Pendiente | D41: Confirmada si el ahorro real es al menos 85% del esperado.
B42: % del sobrante a inversión aplicado | C42: =IF(C41="Confirmada",C23,C24) -> 0.5
B44: Cuentas por cobrar (dinero que le deben al cliente)
B45: Deudor | C45: Saldo | D45: Cuota mensual | E45: Fecha del primer pago | F45: N.º de cuotas | G45: Último pago | H45: % a inversión | I45: Saldo pendiente hoy | J45: Aux. inicio | K45: Aux. fin
F46: =IF(OR(N(C46)=0,N(D46)=0),"",ROUNDUP(C46/D46,0)) | G46: =IF(OR(F46="",E46=""),"",EDATE(E46,F46-1)) | H46: 1 | I46: =IF(N(C46)=0,0,IF(OR(J46="",F46=""),C46,MAX(0,C46-D46*MAX(0,MIN(F46,YEAR($C$12)*12+MONTH($C$12)-J46+1))))) -> 0 | J46: =IF(E46="","",YEAR(E46)*12+MONTH(E46)) | K46: =IF(G46="","",YEAR(G46)*12+MONTH(G46))
F47: =IF(OR(N(C47)=0,N(D47)=0),"",ROUNDUP(C47/D47,0)) | G47: =IF(OR(F47="",E47=""),"",EDATE(E47,F47-1)) | H47: 1 | I47: =IF(N(C47)=0,0,IF(OR(J47="",F47=""),C47,MAX(0,C47-D47*MAX(0,MIN(F47,YEAR($C$12)*12+MONTH($C$12)-J47+1))))) -> 0 | J47: =IF(E47="","",YEAR(E47)*12+MONTH(E47)) | K47: =IF(G47="","",YEAR(G47)*12+MONTH(G47))
F48: =IF(OR(N(C48)=0,N(D48)=0),"",ROUNDUP(C48/D48,0)) | G48: =IF(OR(F48="",E48=""),"",EDATE(E48,F48-1)) | H48: 1 | I48: =IF(N(C48)=0,0,IF(OR(J48="",F48=""),C48,MAX(0,C48-D48*MAX(0,MIN(F48,YEAR($C$12)*12+MONTH($C$12)-J48+1))))) -> 0 | J48: =IF(E48="","",YEAR(E48)*12+MONTH(E48)) | K48: =IF(G48="","",YEAR(G48)*12+MONTH(G48))
B49: Total pendiente por cobrar | I49: =SUM(I46:I48) -> 0
B50: Los abonos no se cuentan como ingreso del presupuesto: se destinan a inversión (o a deuda cara si existe) en la hoja Flujo anual.

Sheet Ingresos
B1: Ingresos
B2: Un renglón por fuente, en su moneda. En los meses escribe 1 si el ingreso llega ese mes y 0 si no. Valores netos (lo que llega a la cuenta).
B5: Fuente | C5: Tipo | D5: Moneda | E5: Valor mensual en su moneda | F5: Valor mensual en pesos | G5: Ene | H5: Feb | I5: Mar | J5: Abr | K5: May | L5: Jun | M5: Jul | N5: Ago | O5: Sep | P5: Oct | Q5: Nov | R5: Dic | S5: Meses | T5: Total anual | U5: Promedio mensual | V5: Nota
D6: COP | F6: =IF(N(E6)=0,0,IF(D6="USD",E6*N(Supuestos!$C$17),E6)) -> 0 | G6: 1 | H6: 1 | I6: 1 | J6: 1 | K6: 1 | L6: 1 | M6: 1 | N6: 1 | O6: 1 | P6: 1 | Q6: 1 | R6: 1 | S6: =SUM(G6:R6) -> 12 | T6: =F6*S6 -> 0 | U6: =T6/12 -> 0
D7: COP | F7: =IF(N(E7)=0,0,IF(D7="USD",E7*N(Supuestos!$C$17),E7)) -> 0 | G7: 1 | H7: 1 | I7: 1 | J7: 1 | K7: 1 | L7: 1 | M7: 1 | N7: 1 | O7: 1 | P7: 1 | Q7: 1 | R7: 1 | S7: =SUM(G7:R7) -> 12 | T7: =F7*S7 -> 0 | U7: =T7/12 -> 0
D8: COP | F8: =IF(N(E8)=0,0,IF(D8="USD",E8*N(Supuestos!$C$17),E8)) -> 0 | G8: 1 | H8: 1 | I8: 1 | J8: 1 | K8: 1 | L8: 1 | M8: 1 | N8: 1 | O8: 1 | P8: 1 | Q8: 1 | R8: 1 | S8: =SUM(G8:R8) -> 12 | T8: =F8*S8 -> 0 | U8: =T8/12 -> 0
D9: COP | F9: =IF(N(E9)=0,0,IF(D9="USD",E9*N(Supuestos!$C$17),E9)) -> 0 | G9: 1 | H9: 1 | I9: 1 | J9: 1 | K9: 1 | L9: 1 | M9: 1 | N9: 1 | O9: 1 | P9: 1 | Q9: 1 | R9: 1 | S9: =SUM(G9:R9) -> 12 | T9: =F9*S9 -> 0 | U9: =T9/12 -> 0
D10: COP | F10: =IF(N(E10)=0,0,IF(D10="USD",E10*N(Supuestos!$C$17),E10)) -> 0 | G10: 1 | H10: 1 | I10: 1 | J10: 1 | K10: 1 | L10: 1 | M10: 1 | N10: 1 | O10: 1 | P10: 1 | Q10: 1 | R10: 1 | S10: =SUM(G10:R10) -> 12 | T10: =F10*S10 -> 0 | U10: =T10/12 -> 0
D11: COP | F11: =IF(N(E11)=0,0,IF(D11="USD",E11*N(Supuestos!$C$17),E11)) -> 0 | G11: 1 | H11: 1 | I11: 1 | J11: 1 | K11: 1 | L11: 1 | M11: 1 | N11: 1 | O11: 1 | P11: 1 | Q11: 1 | R11: 1 | S11: =SUM(G11:R11) -> 12 | T11: =F11*S11 -> 0 | U11: =T11/12 -> 0
D12: COP | F12: =IF(N(E12)=0,0,IF(D12="USD",E12*N(Supuestos!$C$17),E12)) -> 0 | G12: 1 | H12: 1 | I12: 1 | J12: 1 | K12: 1 | L12: 1 | M12: 1 | N12: 1 | O12: 1 | P12: 1 | Q12: 1 | R12: 1 | S12: =SUM(G12:R12) -> 12 | T12: =F12*S12 -> 0 | U12: =T12/12 -> 0
D13: COP | F13: =IF(N(E13)=0,0,IF(D13="USD",E13*N(Supuestos!$C$17),E13)) -> 0 | G13: 1 | H13: 1 | I13: 1 | J13: 1 | K13: 1 | L13: 1 | M13: 1 | N13: 1 | O13: 1 | P13: 1 | Q13: 1 | R13: 1 | S13: =SUM(G13:R13) -> 12 | T13: =F13*S13 -> 0 | U13: =T13/12 -> 0
B14: Total por mes | G14: =SUMPRODUCT($F$6:$F$13,G6:G13) -> 0 | H14: =SUMPRODUCT($F$6:$F$13,H6:H13) -> 0 | I14: =SUMPRODUCT($F$6:$F$13,I6:I13) -> 0 | J14: =SUMPRODUCT($F$6:$F$13,J6:J13) -> 0 | K14: =SUMPRODUCT($F$6:$F$13,K6:K13) -> 0 | L14: =SUMPRODUCT($F$6:$F$13,L6:L13) -> 0 | M14: =SUMPRODUCT($F$6:$F$13,M6:M13) -> 0 | N14: =SUMPRODUCT($F$6:$F$13,N6:N13) -> 0 | ... R14: =SUMPRODUCT($F$6:$F$13,R6:R13) -> 0 | T14: =SUM(T6:T13) -> 0 | U14: =T14/12 -> 0
G15: Totales por mes en miles de pesos. Ingresos en dólares: se convierten con la tasa de cambio de Supuestos.
B16: Seguridad social
B17: ¿Se paga seguridad social este mes? (1 = sí) | G17: 1 | H17: 1 | I17: 1 | J17: 1 | K17: 1 | L17: 1 | M17: 1 | N17: 1 | O17: 1 | P17: 1 | Q17: 1 | R17: 1 | S17: =SUM(G17:R17) -> 12 | V17: Si se cotiza mes vencido, el mes siguiente al primer mes sin contrato suele no tener pago.
B19: Totales por tipo de ingreso
B20: Laboral | T20: =SUMIFS($T$6:$T$13,$C$6:$C$13,B20) -> 0 | U20: =T20/12 -> 0
B21: Renta | T21: =SUMIFS($T$6:$T$13,$C$6:$C$13,B21) -> 0 | U21: =T21/12 -> 0
B22: Pensión | T22: =SUMIFS($T$6:$T$13,$C$6:$C$13,B22) -> 0 | U22: =T22/12 -> 0
B23: Otro | T23: =SUMIFS($T$6:$T$13,$C$6:$C$13,B23) -> 0 | U23: =T23/12 -> 0
B24: Total | T24: =SUM(T20:T23) -> 0 | U24: =T24/12 -> 0
B25: De ese total, ingreso anual en dólares (USD) | T25: =SUMPRODUCT((D6:D13="USD")*E6:E13*S6:S13) -> 0
B27: Calculadora de ingreso base (para ingresos variables)
B28: Ingreso de cada uno de los últimos 12 meses | G28: Mes 1 | H28: Mes 2 | I28: Mes 3 | J28: Mes 4 | K28: Mes 5 | L28: Mes 6 | M28: Mes 7 | N28: Mes 8 | O28: Mes 9 | P28: Mes 10 | Q28: Mes 11 | R28: Mes 12
B29: Valores (en su moneda)
B30: Promedio de 12 meses | E30: =IF(COUNT(G29:R29)=0,"",AVERAGE(G29:R29))
B31: Promedio de los 3 meses más bajos | E31: =IF(COUNT(G29:R29)<3,"",(SMALL(G29:R29,1)+SMALL(G29:R29,2)+SMALL(G29:R29,3))/3)
B32: Ingreso base sugerido | E32: =IF(OR(E30="",E31=""),"",MIN(E30,E31)) | G32: Escribe este valor como "Valor mensual en su moneda" de la fuente variable. Lo que llegue por encima se reparte con una regla fija.

Sheet Presupuesto
B1: Presupuesto detallado
B2: Cada gasto con su valor por pago y su frecuencia. Las filas grises son automáticas. "Tipo" indica cómo se paga.
B5: Categoría | C5: Concepto | D5: Valor por pago | E5: Frecuencia | F5: Días que dura | G5: Veces al año | H5: Total anual | I5: Promedio mensual | J5: Tipo | K5: Bolsillo | L5: ¿Esencial? | M5: Nota
B6: Deudas | C6: Cuotas mínimas de deudas (hoja Deudas) | D6: =Deudas!$F$21 -> 0 | E6: Mensual | G6: =IF(E6="","",IF(E6="Por duración (días)",IF(N(F6)>0,365/F6,0),IF(E6="Meses con seguridad social",Ingresos!$S$17,IFERROR(VLOOKUP(E6,Listas!$C$2:$D$10,2,FALSE()),0)))) -> 12 | H6: =IF(OR(N(D6)=0,G6=""),0,D6*G6) -> 0 | I6: =H6/12 -> 0 | J6: Deuda | L6: Sí | M6: Automático: no editar.
B7: Seguros | C7: Primas de seguros nuevos (hoja Seguros) | D7: =Seguros!$H$16 -> 0 | E7: Anual | G7: =IF(E7="","",IF(E7="Por duración (días)",IF(N(F7)>0,365/F7,0),IF(E7="Meses con seguridad social",Ingresos!$S$17,IFERROR(VLOOKUP(E7,Listas!$C$2:$D$10,2,FALSE()),0)))) -> 1 | H7: =IF(OR(N(D7)=0,G7=""),0,D7*G7) -> 0 | I7: =H7/12 -> 0 | J7: Bolsillo | K7: Seguros | L7: Sí | M7: Automático: no editar.
B8: Metas | C8: =IF(Metas!$B$6="","(Meta sin usar)","Meta: "&Metas!$B$6) -> (Meta sin usar) | D8: =Metas!$K$6 -> 0 | E8: Mensual | G8: =IF(E8="","",IF(E8="Por duración (días)",IF(N(F8)>0,365/F8,0),IF(E8="Meses con seguridad social",Ingresos!$S$17,IFERROR(VLOOKUP(E8,Listas!$C$2:$D$10,2,FALSE()),0)))) -> 12 | H8: =IF(OR(N(D8)=0,G8=""),0,D8*G8) -> 0 | I8: =H8/12 -> 0 | J8: Bolsillo | K8: =IF(Metas!$C$6="","Metas",Metas!$C$6) -> Metas | L8: No | M8: Automático: no editar.
B9: Metas | C9: =IF(Metas!$B$7="","(Meta sin usar)","Meta: "&Metas!$B$7) -> (Meta sin usar) | D9: =Metas!$K$7 -> 0 | E9: Mensual | G9: =IF(E9="","",IF(E9="Por duración (días)",IF(N(F9)>0,365/F9,0),IF(E9="Meses con seguridad social",Ingresos!$S$17,IFERROR(VLOOKUP(E9,Listas!$C$2:$D$10,2,FALSE()),0)))) -> 12 | H9: =IF(OR(N(D9)=0,G9=""),0,D9*G9) -> 0 | I9: =H9/12 -> 0 | J9: Bolsillo | K9: =IF(Metas!$C$7="","Metas",Metas!$C$7) -> Metas | L9: No | M9: Automático: no editar.
B10: Metas | C10: =IF(Metas!$B$8="","(Meta sin usar)","Meta: "&Metas!$B$8) -> (Meta sin usar) | D10: =Metas!$K$8 -> 0 | E10: Mensual | G10: =IF(E10="","",IF(E10="Por duración (días)",IF(N(F10)>0,365/F10,0),IF(E10="Meses con seguridad social",Ingresos!$S$17,IFERROR(VLOOKUP(E10,Listas!$C$2:$D$10,2,FALSE()),0)))) -> 12 | H10: =IF(OR(N(D10)=0,G10=""),0,D10*G10) -> 0 | I10: =H10/12 -> 0 | J10: Bolsillo | K10: =IF(Metas!$C$8="","Metas",Metas!$C$8) -> Metas | L10: No | M10: Automático: no editar.
B11: Metas | C11: =IF(Metas!$B$9="","(Meta sin usar)","Meta: "&Metas!$B$9) -> (Meta sin usar) | D11: =Metas!$K$9 -> 0 | E11: Mensual | G11: =IF(E11="","",IF(E11="Por duración (días)",IF(N(F11)>0,365/F11,0),IF(E11="Meses con seguridad social",Ingresos!$S$17,IFERROR(VLOOKUP(E11,Listas!$C$2:$D$10,2,FALSE()),0)))) -> 12 | H11: =IF(OR(N(D11)=0,G11=""),0,D11*G11) -> 0 | I11: =H11/12 -> 0 | J11: Bolsillo | K11: =IF(Metas!$C$9="","Metas",Metas!$C$9) -> Metas | L11: No | M11: Automático: no editar.
B12: Metas | C12: =IF(Metas!$B$10="","(Meta sin usar)","Meta: "&Metas!$B$10) -> (Meta sin usar) | D12: =Metas!$K$10 -> 0 | E12: Mensual | G12: =IF(E12="","",IF(E12="Por duración (días)",IF(N(F12)>0,365/F12,0),IF(E12="Meses con seguridad social",Ingresos!$S$17,IFERROR(VLOOKUP(E12,Listas!$C$2:$D$10,2,FALSE()),0)))) -> 12 | H12: =IF(OR(N(D12)=0,G12=""),0,D12*G12) -> 0 | I12: =H12/12 -> 0 | J12: Bolsillo | K12: =IF(Metas!$C$10="","Metas",Metas!$C$10) -> Metas | L12: No | M12: Automático: no editar.
B13: Seguridad social | C13: Salud, pensión y ARL (valor por mes de pago) | E13: Meses con seguridad social | G13: =IF(E13="","",IF(E13="Por duración (días)",IF(N(F13)>0,365/F13,0),IF(E13="Meses con seguridad social",Ingresos!$S$17,IFERROR(VLOOKUP(E13,Listas!$C$2:$D$10,2,FALSE()),0)))) -> 12 | H13: =IF(OR(N(D13)=0,G13=""),0,D13*G13) -> 0 | I13: =H13/12 -> 0 | J13: Seg. social | L13: Sí | M13: Los meses de pago se marcan en Ingresos.
B14: Vivienda | C14: Arriendo o cuota de vivienda | E14: Mensual | G14: =IF(E14="","",IF(E14="Por duración (días)",IF(N(F14)>0,365/F14,0),IF(E14="Meses con seguridad social",Ingresos!$S$17,IFERROR(VLOOKUP(E14,Listas!$C$2:$D$10,2,FALSE()),0)))) -> 12 | H14: =IF(OR(N(D14)=0,G14=""),0,D14*G14) -> 0 | I14: =H14/12 -> 0 | J14: Directo | L14: Sí
B15: Vivienda | C15: Administración | E15: Mensual | G15: =IF(E15="","",IF(E15="Por duración (días)",IF(N(F15)>0,365/F15,0),IF(E15="Meses con seguridad social",Ingresos!$S$17,IFERROR(VLOOKUP(E15,Listas!$C$2:$D$10,2,FALSE()),0)))) -> 12 | H15: =IF(OR(N(D15)=0,G15=""),0,D15*G15) -> 0 | I15: =H15/12 -> 0 | J15: Directo | L15: Sí
B16: Vivienda | C16: Servicios públicos | E16: Mensual | G16: =IF(E16="","",IF(E16="Por duración (días)",IF(N(F16)>0,365/F16,0),IF(E16="Meses con seguridad social",Ingresos!$S$17,IFERROR(VLOOKUP(E16,Listas!$C$2:$D$10,2,FALSE()),0)))) -> 12 | H16: =IF(OR(N(D16)=0,G16=""),0,D16*G16) -> 0 | I16: =H16/12 -> 0 | J16: Directo | L16: Sí
B17: Vivienda | C17: Internet y televisión | E17: Mensual | G17: =IF(E17="","",IF(E17="Por duración (días)",IF(N(F17)>0,365/F17,0),IF(E17="Meses con seguridad social",Ingresos!$S$17,IFERROR(VLOOKUP(E17,Listas!$C$2:$D$10,2,FALSE()),0)))) -> 12 | H17: =IF(OR(N(D17)=0,G17=""),0,D17*G17) -> 0 | I17: =H17/12 -> 0 | J17: Directo | L17: Sí
B18: Vivienda | C18: Aseo o empleada doméstica | E18: Mensual | G18: =IF(E18="","",IF(E18="Por duración (días)",IF(N(F18)>0,365/F18,0),IF(E18="Meses con seguridad social",Ingresos!$S$17,IFERROR(VLOOKUP(E18,Listas!$C$2:$D$10,2,FALSE()),0)))) -> 12 | H18: =IF(OR(N(D18)=0,G18=""),0,D18*G18) -> 0 | I18: =H18/12 -> 0 | J18: Directo | L18: No
B19: Vivienda | C19: Mantenimiento del hogar | E19: Mensual | G19: =IF(E19="","",IF(E19="Por duración (días)",IF(N(F19)>0,365/F19,0),IF(E19="Meses con seguridad social",Ingresos!$S$17,IFERROR(VLOOKUP(E19,Listas!$C$2:$D$10,2,FALSE()),0)))) -> 12 | H19: =IF(OR(N(D19)=0,G19=""),0,D19*G19) -> 0 | I19: =H19/12 -> 0 | J19: Directo | L19: No
B20: Impuestos y trámites | C20: Predial | E20: Anual | G20: =IF(E20="","",IF(E20="Por duración (días)",IF(N(F20)>0,365/F20,0),IF(E20="Meses con seguridad social",Ingresos!$S$17,IFERROR(VLOOKUP(E20,Listas!$C$2:$D$10,2,FALSE()),0)))) -> 1 | H20: =IF(OR(N(D20)=0,G20=""),0,D20*G20) -> 0 | I20: =H20/12 -> 0 | J20: Bolsillo | K20: Impuestos y trámites | L20: Sí
B21: Alimentación | C21: Mercado | E21: Semanal | G21: =IF(E21="","",IF(E21="Por duración (días)",IF(N(F21)>0,365/F21,0),IF(E21="Meses con seguridad social",Ingresos!$S$17,IFERROR(VLOOKUP(E21,Listas!$C$2:$D$10,2,FALSE()),0)))) -> 52 | H21: =IF(OR(N(D21)=0,G21=""),0,D21*G21) -> 0 | I21: =H21/12 -> 0 | J21: Directo | L21: Sí
B22: Alimentación | C22: Restaurantes y salidas a comer | E22: Mensual | G22: =IF(E22="","",IF(E22="Por duración (días)",IF(N(F22)>0,365/F22,0),IF(E22="Meses con seguridad social",Ingresos!$S$17,IFERROR(VLOOKUP(E22,Listas!$C$2:$D$10,2,FALSE()),0)))) -> 12 | H22: =IF(OR(N(D22)=0,G22=""),0,D22*G22) -> 0 | I22: =H22/12 -> 0 | J22: Directo | L22: No
B23: Alimentación | C23: Domicilios | E23: Mensual | G23: =IF(E23="","",IF(E23="Por duración (días)",IF(N(F23)>0,365/F23,0),IF(E23="Meses con seguridad social",Ingresos!$S$17,IFERROR(VLOOKUP(E23,Listas!$C$2:$D$10,2,FALSE()),0)))) -> 12 | H23: =IF(OR(N(D23)=0,G23=""),0,D23*G23) -> 0 | I23: =H23/12 -> 0 | J23: Directo | L23: No
B24: Transporte | C24: Gasolina | E24: Mensual | G24: =IF(E24="","",IF(E24="Por duración (días)",IF(N(F24)>0,365/F24,0),IF(E24="Meses con seguridad social",Ingresos!$S$17,IFERROR(VLOOKUP(E24,Listas!$C$2:$D$10,2,FALSE()),0)))) -> 12 | H24: =IF(OR(N(D24)=0,G24=""),0,D24*G24) -> 0 | I24: =H24/12 -> 0 | J24: Directo | L24: Sí
B25: Transporte | C25: Parqueadero y peajes | E25: Mensual | G25: =IF(E25="","",IF(E25="Por duración (días)",IF(N(F25)>0,365/F25,0),IF(E25="Meses con seguridad social",Ingresos!$S$17,IFERROR(VLOOKUP(E25,Listas!$C$2:$D$10,2,FALSE()),0)))) -> 12 | H25: =IF(OR(N(D25)=0,G25=""),0,D25*G25) -> 0 | I25: =H25/12 -> 0 | J25: Directo | L25: No
B26: Transporte | C26: Transporte público y apps | E26: Mensual | G26: =IF(E26="","",IF(E26="Por duración (días)",IF(N(F26)>0,365/F26,0),IF(E26="Meses con seguridad social",Ingresos!$S$17,IFERROR(VLOOKUP(E26,Listas!$C$2:$D$10,2,FALSE()),0)))) -> 12 | H26: =IF(OR(N(D26)=0,G26=""),0,D26*G26) -> 0 | I26: =H26/12 -> 0 | J26: Directo | L26: Sí
B27: Transporte | C27: SOAT | E27: Anual | G27: =IF(E27="","",IF(E27="Por duración (días)",IF(N(F27)>0,365/F27,0),IF(E27="Meses con seguridad social",Ingresos!$S$17,IFERROR(VLOOKUP(E27,Listas!$C$2:$D$10,2,FALSE()),0)))) -> 1 | H27: =IF(OR(N(D27)=0,G27=""),0,D27*G27) -> 0 | I27: =H27/12 -> 0 | J27: Bolsillo | K27: Vehículo | L27: Sí
B28: Transporte | C28: Seguro del carro | E28: Anual | G28: =IF(E28="","",IF(E28="Por duración (días)",IF(N(F28)>0,365/F28,0),IF(E28="Meses con seguridad social",Ingresos!$S$17,IFERROR(VLOOKUP(E28,Listas!$C$2:$D$10,2,FALSE()),0)))) -> 1 | H28: =IF(OR(N(D28)=0,G28=""),0,D28*G28) -> 0 | I28: =H28/12 -> 0 | J28: Bolsillo | K28: Vehículo | L28: Sí | M28: Seguros que ya existen van aquí, no en la hoja Seguros.
B29: Transporte | C29: Mantenimiento del carro | E29: Semestral | G29: =IF(E29="","",IF(E29="Por duración (días)",IF(N(F29)>0,365/F29,0),IF(E29="Meses con seguridad social",Ingresos!$S$17,IFERROR(VLOOKUP(E29,Listas!$C$2:$D$10,2,FALSE()),0)))) -> 2 | H29: =IF(OR(N(D29)=0,G29=""),0,D29*G29) -> 0 | I29: =H29/12 -> 0 | J29: Bolsillo | K29: Vehículo | L29: No
B30: Impuestos y trámites | C30: Impuesto vehicular | E30: Anual | G30: =IF(E30="","",IF(E30="Por duración (días)",IF(N(F30)>0,365/F30,0),IF(E30="Meses con seguridad social",Ingresos!$S$17,IFERROR(VLOOKUP(E30,Listas!$C$2:$D$10,2,FALSE()),0)))) -> 1 | H30: =IF(OR(N(D30)=0,G30=""),0,D30*G30) -> 0 | I30: =H30/12 -> 0 | J30: Bolsillo | K30: Impuestos y trámites | L30: Sí
B31: Salud y bienestar | C31: Medicina prepagada o plan complementario | E31: Mensual | G31: =IF(E31="","",IF(E31="Por duración (días)",IF(N(F31)>0,365/F31,0),IF(E31="Meses con seguridad social",Ingresos!$S$17,IFERROR(VLOOKUP(E31,Listas!$C$2:$D$10,2,FALSE()),0)))) -> 12 | H31: =IF(OR(N(D31)=0,G31=""),0,D31*G31) -> 0 | I31: =H31/12 -> 0 | J31: Directo | L31: Sí
B32: Salud y bienestar | C32: Droguería | E32: Mensual | G32: =IF(E32="","",IF(E32="Por duración (días)",IF(N(F32)>0,365/F32,0),IF(E32="Meses con seguridad social",Ingresos!$S$17,IFERROR(VLOOKUP(E32,Listas!$C$2:$D$10,2,FALSE()),0)))) -> 12 | H32: =IF(OR(N(D32)=0,G32=""),0,D32*G32) -> 0 | I32: =H32/12 -> 0 | J32: Directo | L32: Sí
B33: Salud y bienestar | C33: Terapias o psicología | E33: Mensual | G33: =IF(E33="","",IF(E33="Por duración (días)",IF(N(F33)>0,365/F33,0),IF(E33="Meses con seguridad social",Ingresos!$S$17,IFERROR(VLOOKUP(E33,Listas!$C$2:$D$10,2,FALSE()),0)))) -> 12 | H33: =IF(OR(N(D33)=0,G33=""),0,D33*G33) -> 0 | I33: =H33/12 -> 0 | J33: Directo | L33: No
B34: Salud y bienestar | C34: Gimnasio | E34: Mensual | G34: =IF(E34="","",IF(E34="Por duración (días)",IF(N(F34)>0,365/F34,0),IF(E34="Meses con seguridad social",Ingresos!$S$17,IFERROR(VLOOKUP(E34,Listas!$C$2:$D$10,2,FALSE()),0)))) -> 12 | H34: =IF(OR(N(D34)=0,G34=""),0,D34*G34) -> 0 | I34: =H34/12 -> 0 | J34: Directo | L34: No | M34: Si se paga anual, cambia la frecuencia y el tipo a Bolsillo.
B35: Salud y bienestar | C35: Suplementos | E35: Por duración (días) | G35: =IF(E35="","",IF(E35="Por duración (días)",IF(N(F35)>0,365/F35,0),IF(E35="Meses con seguridad social",Ingresos!$S$17,IFERROR(VLOOKUP(E35,Listas!$C$2:$D$10,2,FALSE()),0)))) -> 0 | H35: =IF(OR(N(D35)=0,G35=""),0,D35*G35) -> 0 | I35: =H35/12 -> 0 | J35: Bolsillo | K35: Salud y cuidado | L35: No | M35: Escribe los días que dura el frasco.
B36: Cuidado personal | C36: Peluquería y uñas | E36: Mensual | G36: =IF(E36="","",IF(E36="Por duración (días)",IF(N(F36)>0,365/F36,0),IF(E36="Meses con seguridad social",Ingresos!$S$17,IFERROR(VLOOKUP(E36,Listas!$C$2:$D$10,2,FALSE()),0)))) -> 12 | H36: =IF(OR(N(D36)=0,G36=""),0,D36*G36) -> 0 | I36: =H36/12 -> 0 | J36: Directo | L36: No
B37: Cuidado personal | C37: Skincare | E37: Cada 4 meses | G37: =IF(E37="","",IF(E37="Por duración (días)",IF(N(F37)>0,365/F37,0),IF(E37="Meses con seguridad social",Ingresos!$S$17,IFERROR(VLOOKUP(E37,Listas!$C$2:$D$10,2,FALSE()),0)))) -> 3 | H37: =IF(OR(N(D37)=0,G37=""),0,D37*G37) -> 0 | I37: =H37/12 -> 0 | J37: Bolsillo | K37: Salud y cuidado | L37: No
B38: Cuidado personal | C38: Ropa y calzado | E38: Anual | G38: =IF(E38="","",IF(E38="Por duración (días)",IF(N(F38)>0,365/F38,0),IF(E38="Meses con seguridad social",Ingresos!$S$17,IFERROR(VLOOKUP(E38,Listas!$C$2:$D$10,2,FALSE()),0)))) -> 1 | H38: =IF(OR(N(D38)=0,G38=""),0,D38*G38) -> 0 | I38: =H38/12 -> 0 | J38: Bolsillo | K38: Ropa | L38: No
B39: Hijos y familia | C39: Colegio o universidad (mensualidad) | E39: Mensual | G39: =IF(E39="","",IF(E39="Por duración (días)",IF(N(F39)>0,365/F39,0),IF(E39="Meses con seguridad social",Ingresos!$S$17,IFERROR(VLOOKUP(E39,Listas!$C$2:$D$10,2,FALSE()),0)))) -> 12 | H39: =IF(OR(N(D39)=0,G39=""),0,D39*G39) -> 0 | I39: =H39/12 -> 0 | J39: Directo | L39: Sí
B40: Hijos y familia | C40: Matrículas y útiles | E40: Anual | G40: =IF(E40="","",IF(E40="Por duración (días)",IF(N(F40)>0,365/F40,0),IF(E40="Meses con seguridad social",Ingresos!$S$17,IFERROR(VLOOKUP(E40,Listas!$C$2:$D$10,2,FALSE()),0)))) -> 1 | H40: =IF(OR(N(D40)=0,G40=""),0,D40*G40) -> 0 | I40: =H40/12 -> 0 | J40: Bolsillo | K40: Educación | L40: Sí
B41: Hijos y familia | C41: Gastos y mesadas de hijos | E41: Mensual | G41: =IF(E41="","",IF(E41="Por duración (días)",IF(N(F41)>0,365/F41,0),IF(E41="Meses con seguridad social",Ingresos!$S$17,IFERROR(VLOOKUP(E41,Listas!$C$2:$D$10,2,FALSE()),0)))) -> 12 | H41: =IF(OR(N(D41)=0,G41=""),0,D41*G41) -> 0 | I41: =H41/12 -> 0 | J41: Directo | L41: Sí
B42: Hijos y familia | C42: Ayudas a familiares | E42: Mensual | G42: =IF(E42="","",IF(E42="Por duración (días)",IF(N(F42)>0,365/F42,0),IF(E42="Meses con seguridad social",Ingresos!$S$17,IFERROR(VLOOKUP(E42,Listas!$C$2:$D$10,2,FALSE()),0)))) -> 12 | H42: =IF(OR(N(D42)=0,G42=""),0,D42*G42) -> 0 | I42: =H42/12 -> 0 | J42: Directo | L42: No
B43: Mascotas | C43: Comida de mascota | E43: Mensual | G43: =IF(E43="","",IF(E43="Por duración (días)",IF(N(F43)>0,365/F43,0),IF(E43="Meses con seguridad social",Ingresos!$S$17,IFERROR(VLOOKUP(E43,Listas!$C$2:$D$10,2,FALSE()),0)))) -> 12 | H43: =IF(OR(N(D43)=0,G43=""),0,D43*G43) -> 0 | I43: =H43/12 -> 0 | J43: Directo | L43: Sí
B44: Mascotas | C44: Baño y peluquería de mascota | E44: Mensual | G44: =IF(E44="","",IF(E44="Por duración (días)",IF(N(F44)>0,365/F44,0),IF(E44="Meses con seguridad social",Ingresos!$S$17,IFERROR(VLOOKUP(E44,Listas!$C$2:$D$10,2,FALSE()),0)))) -> 12 | H44: =IF(OR(N(D44)=0,G44=""),0,D44*G44) -> 0 | I44: =H44/12 -> 0 | J44: Directo | L44: No
B45: Mascotas | C45: Veterinario y vacunas | E45: Anual | G45: =IF(E45="","",IF(E45="Por duración (días)",IF(N(F45)>0,365/F45,0),IF(E45="Meses con seguridad social",Ingresos!$S$17,IFERROR(VLOOKUP(E45,Listas!$C$2:$D$10,2,FALSE()),0)))) -> 1 | H45: =IF(OR(N(D45)=0,G45=""),0,D45*G45) -> 0 | I45: =H45/12 -> 0 | J45: Bolsillo | K45: Hogar y mascotas | L45: Sí
B46: Servicios | C46: Celular | E46: Mensual | G46: =IF(E46="","",IF(E46="Por duración (días)",IF(N(F46)>0,365/F46,0),IF(E46="Meses con seguridad social",Ingresos!$S$17,IFERROR(VLOOKUP(E46,Listas!$C$2:$D$10,2,FALSE()),0)))) -> 12 | H46: =IF(OR(N(D46)=0,G46=""),0,D46*G46) -> 0 | I46: =H46/12 -> 0 | J46: Directo | L46: Sí
B47: Servicios | C47: Suscripciones | E47: Mensual | G47: =IF(E47="","",IF(E47="Por duración (días)",IF(N(F47)>0,365/F47,0),IF(E47="Meses con seguridad social",Ingresos!$S$17,IFERROR(VLOOKUP(E47,Listas!$C$2:$D$10,2,FALSE()),0)))) -> 12 | H47: =IF(OR(N(D47)=0,G47=""),0,D47*G47) -> 0 | I47: =H47/12 -> 0 | J47: Directo | L47: No
B48: Viajes y ocio | C48: Viaje nacional | E48: Anual | G48: =IF(E48="","",IF(E48="Por duración (días)",IF(N(F48)>0,365/F48,0),IF(E48="Meses con seguridad social",Ingresos!$S$17,IFERROR(VLOOKUP(E48,Listas!$C$2:$D$10,2,FALSE()),0)))) -> 1 | H48: =IF(OR(N(D48)=0,G48=""),0,D48*G48) -> 0 | I48: =H48/12 -> 0 | J48: Bolsillo | K48: Viajes | L48: No | M48: Viajes con cálculo detallado van en la hoja Metas.
B49: Viajes y ocio | C49: Salidas y entretenimiento | E49: Mensual | G49: =IF(E49="","",IF(E49="Por duración (días)",IF(N(F49)>0,365/F49,0),IF(E49="Meses con seguridad social",Ingresos!$S$17,IFERROR(VLOOKUP(E49,Listas!$C$2:$D$10,2,FALSE()),0)))) -> 12 | H49: =IF(OR(N(D49)=0,G49=""),0,D49*G49) -> 0 | I49: =H49/12 -> 0 | J49: Directo | L49: No
B50: Temporada | C50: Navidad, cumpleaños y celebraciones | E50: Anual | G50: =IF(E50="","",IF(E50="Por duración (días)",IF(N(F50)>0,365/F50,0),IF(E50="Meses con seguridad social",Ingresos!$S$17,IFERROR(VLOOKUP(E50,Listas!$C$2:$D$10,2,FALSE()),0)))) -> 1 | H50: =IF(OR(N(D50)=0,G50=""),0,D50*G50) -> 0 | I50: =H50/12 -> 0 | J50: Bolsillo | K50: Temporada | L50: No
B51: Impuestos y trámites | C51: Impuesto de renta a pagar | E51: Anual | G51: =IF(E51="","",IF(E51="Por duración (días)",IF(N(F51)>0,365/F51,0),IF(E51="Meses con seguridad social",Ingresos!$S$17,IFERROR(VLOOKUP(E51,Listas!$C$2:$D$10,2,FALSE()),0)))) -> 1 | H51: =IF(OR(N(D51)=0,G51=""),0,D51*G51) -> 0 | I51: =H51/12 -> 0 | J51: Bolsillo | K51: Impuestos y trámites | L51: Sí | M51: Confirmar con el contador.
B52: Impuestos y trámites | C52: Contador | E52: Anual | G52: =IF(E52="","",IF(E52="Por duración (días)",IF(N(F52)>0,365/F52,0),IF(E52="Meses con seguridad social",Ingresos!$S$17,IFERROR(VLOOKUP(E52,Listas!$C$2:$D$10,2,FALSE()),0)))) -> 1 | H52: =IF(OR(N(D52)=0,G52=""),0,D52*G52) -> 0 | I52: =H52/12 -> 0 | J52: Bolsillo | K52: Impuestos y trámites | L52: Sí
B53: Compras puntuales | C53: Compras puntuales (tecnología, hogar) | E53: Anual | G53: =IF(E53="","",IF(E53="Por duración (días)",IF(N(F53)>0,365/F53,0),IF(E53="Meses con seguridad social",Ingresos!$S$17,IFERROR(VLOOKUP(E53,Listas!$C$2:$D$10,2,FALSE()),0)))) -> 1 | H53: =IF(OR(N(D53)=0,G53=""),0,D53*G53) -> 0 | I53: =H53/12 -> 0 | J53: Bolsillo | K53: Hogar y mascotas | L53: No | M53: Fondo anual para compras grandes.
B54: Ahorro | C54: Ahorro en cooperativa o fondo | E54: Mensual | G54: =IF(E54="","",IF(E54="Por duración (días)",IF(N(F54)>0,365/F54,0),IF(E54="Meses con seguridad social",Ingresos!$S$17,IFERROR(VLOOKUP(E54,Listas!$C$2:$D$10,2,FALSE()),0)))) -> 12 | H54: =IF(OR(N(D54)=0,G54=""),0,D54*G54) -> 0 | I54: =H54/12 -> 0 | J54: Ahorro | L54: No | M54: Es ahorro, no gasto.
B55: Ahorro | C55: Pensión voluntaria o AFC | E55: Mensual | G55: =IF(E55="","",IF(E55="Por duración (días)",IF(N(F55)>0,365/F55,0),IF(E55="Meses con seguridad social",Ingresos!$S$17,IFERROR(VLOOKUP(E55,Listas!$C$2:$D$10,2,FALSE()),0)))) -> 12 | H55: =IF(OR(N(D55)=0,G55=""),0,D55*G55) -> 0 | I55: =H55/12 -> 0 | J55: Ahorro | L55: No | M55: Es ahorro, no gasto.
G56: =IF(E56="","",IF(E56="Por duración (días)",IF(N(F56)>0,365/F56,0),IF(E56="Meses con seguridad social",Ingresos!$S$17,IFERROR(VLOOKUP(E56,Listas!$C$2:$D$10,2,FALSE()),0)))) | H56: =IF(OR(N(D56)=0,G56=""),0,D56*G56) -> 0 | I56: =H56/12 -> 0
G57: =IF(E57="","",IF(E57="Por duración (días)",IF(N(F57)>0,365/F57,0),IF(E57="Meses con seguridad social",Ingresos!$S$17,IFERROR(VLOOKUP(E57,Listas!$C$2:$D$10,2,FALSE()),0)))) | H57: =IF(OR(N(D57)=0,G57=""),0,D57*G57) -> 0 | I57: =H57/12 -> 0
G58: =IF(E58="","",IF(E58="Por duración (días)",IF(N(F58)>0,365/F58,0),IF(E58="Meses con seguridad social",Ingresos!$S$17,IFERROR(VLOOKUP(E58,Listas!$C$2:$D$10,2,FALSE()),0)))) | H58: =IF(OR(N(D58)=0,G58=""),0,D58*G58) -> 0 | I58: =H58/12 -> 0
G59: =IF(E59="","",IF(E59="Por duración (días)",IF(N(F59)>0,365/F59,0),IF(E59="Meses con seguridad social",Ingresos!$S$17,IFERROR(VLOOKUP(E59,Listas!$C$2:$D$10,2,FALSE()),0)))) | H59: =IF(OR(N(D59)=0,G59=""),0,D59*G59) -> 0 | I59: =H59/12 -> 0
G60: =IF(E60="","",IF(E60="Por duración (días)",IF(N(F60)>0,365/F60,0),IF(E60="Meses con seguridad social",Ingresos!$S$17,IFERROR(VLOOKUP(E60,Listas!$C$2:$D$10,2,FALSE()),0)))) | H60: =IF(OR(N(D60)=0,G60=""),0,D60*G60) -> 0 | I60: =H60/12 -> 0
G61: =IF(E61="","",IF(E61="Por duración (días)",IF(N(F61)>0,365/F61,0),IF(E61="Meses con seguridad social",Ingresos!$S$17,IFERROR(VLOOKUP(E61,Listas!$C$2:$D$10,2,FALSE()),0)))) | H61: =IF(OR(N(D61)=0,G61=""),0,D61*G61) -> 0 | I61: =H61/12 -> 0
G62: =IF(E62="","",IF(E62="Por duración (días)",IF(N(F62)>0,365/F62,0),IF(E62="Meses con seguridad social",Ingresos!$S$17,IFERROR(VLOOKUP(E62,Listas!$C$2:$D$10,2,FALSE()),0)))) | H62: =IF(OR(N(D62)=0,G62=""),0,D62*G62) -> 0 | I62: =H62/12 -> 0
G63: =IF(E63="","",IF(E63="Por duración (días)",IF(N(F63)>0,365/F63,0),IF(E63="Meses con seguridad social",Ingresos!$S$17,IFERROR(VLOOKUP(E63,Listas!$C$2:$D$10,2,FALSE()),0)))) | H63: =IF(OR(N(D63)=0,G63=""),0,D63*G63) -> 0 | I63: =H63/12 -> 0
G64: =IF(E64="","",IF(E64="Por duración (días)",IF(N(F64)>0,365/F64,0),IF(E64="Meses con seguridad social",Ingresos!$S$17,IFERROR(VLOOKUP(E64,Listas!$C$2:$D$10,2,FALSE()),0)))) | H64: =IF(OR(N(D64)=0,G64=""),0,D64*G64) -> 0 | I64: =H64/12 -> 0
G65: =IF(E65="","",IF(E65="Por duración (días)",IF(N(F65)>0,365/F65,0),IF(E65="Meses con seguridad social",Ingresos!$S$17,IFERROR(VLOOKUP(E65,Listas!$C$2:$D$10,2,FALSE()),0)))) | H65: =IF(OR(N(D65)=0,G65=""),0,D65*G65) -> 0 | I65: =H65/12 -> 0
G66: =IF(E66="","",IF(E66="Por duración (días)",IF(N(F66)>0,365/F66,0),IF(E66="Meses con seguridad social",Ingresos!$S$17,IFERROR(VLOOKUP(E66,Listas!$C$2:$D$10,2,FALSE()),0)))) | H66: =IF(OR(N(D66)=0,G66=""),0,D66*G66) -> 0 | I66: =H66/12 -> 0
G67: =IF(E67="","",IF(E67="Por duración (días)",IF(N(F67)>0,365/F67,0),IF(E67="Meses con seguridad social",Ingresos!$S$17,IFERROR(VLOOKUP(E67,Listas!$C$2:$D$10,2,FALSE()),0)))) | H67: =IF(OR(N(D67)=0,G67=""),0,D67*G67) -> 0 | I67: =H67/12 -> 0
... G87: =IF(E87="","",IF(E87="Por duración (días)",IF(N(F87)>0,365/F87,0),IF(E87="Meses con seguridad social",Ingresos!$S$17,IFERROR(VLOOKUP(E87,Listas!$C$2:$D$10,2,FALSE()),0)))) | H87: =IF(OR(N(D87)=0,G87=""),0,D87*G87) -> 0 | I87: =H87/12 -> 0
B88: Totales | H88: Total anual | I88: Promedio mensual
C89: Total gastos (sin ahorro) | H89: =SUMIFS($H$6:$H$87,$J$6:$J$87,"<>Ahorro") -> 0 | I89: =H89/12 -> 0
C90: Pagos directos | H90: =SUMIFS($H$6:$H$87,$J$6:$J$87,"Directo") -> 0 | I90: =H90/12 -> 0
C91: Aportes a bolsillos | H91: =SUMIFS($H$6:$H$87,$J$6:$J$87,"Bolsillo") -> 0 | I91: =H91/12 -> 0
C92: Seguridad social | H92: =SUMIFS($H$6:$H$87,$J$6:$J$87,"Seg. social") -> 0 | I92: =H92/12 -> 0
C93: Cuotas de deudas | H93: =SUMIFS($H$6:$H$87,$J$6:$J$87,"Deuda") -> 0 | I93: =H93/12 -> 0
C94: Ahorro programado | H94: =SUMIFS($H$6:$H$87,$J$6:$J$87,"Ahorro") -> 0 | I94: =H94/12 -> 0
C95: Gasto esencial | H95: =SUMIFS($H$6:$H$87,$L$6:$L$87,"Sí",$J$6:$J$87,"<>Ahorro") -> 0 | I95: =H95/12 -> 0
C96: Seguridad social por cada mes de pago | I96: =SUMIFS($D$6:$D$87,$J$6:$J$87,"Seg. social") -> 0
C97: Filas con valor pero sin frecuencia o tipo | I97: =SUMPRODUCT((N(+$D$6:$D$87)>0)*(($E$6:$E$87="")+($J$6:$J$87="")>0)) -> 0 | M97: Debe ser 0 (Ver pendientes en Resumen).

Sheet Deudas
B1: Deudas
B2: Inventario, orden de pago y simulación mes a mes. El pago extra sale del sobrante (hoja Flujo anual). Para el seguimiento mensual de cada crédito usa la plantilla de créditos.
B5: Parámetros
B6: Método de pago | C6: Avalancha | D6: Avalancha: mayor tasa primero (ahorra más). Bola de nieve: menor saldo primero (motiva más).
B7: Umbral de deuda cara | C7: =Supuestos!$C$22 -> 0.2
B8: Pago extra mensual (desde el sobrante) | C8: ='Flujo anual'!$Q$34/12 -> 0
B9: Pago mensual total para deudas | C9: =F21+C8 -> 0
B10: Abono único inicial (desde el excedente) | C10: =Bolsillos!$C$26 -> 0
B11: Primer mes de la simulación | C11: =DATE(YEAR(Supuestos!$C$12),MONTH(Supuestos!$C$12)+1,1) -> 46296
B12: Deuda | C12: Tipo | D12: Saldo | E12: Tasa EA | F12: Cuota mínima mensual | G12: ¿Acepta abonos extra? | H12: Abonos extra desde | I12: Tasa mensual | J12: ¿Deuda cara? | K12: Orden de pago | L12: Meses para pagar | M12: Fecha de salida | N12: Intereses con el plan | O12: Intereses solo con la cuota (aprox.) | P12: Aux.
G13: Sí | I13: =IF(E13="","",(1+E13)^(1/12)-1) | J13: =IF(N(D13)<=0,"",IF(N(E13)>=$C$7,"Sí","No")) | K13: =IF(N(D13)<=0,"",IF($C$6="Bola de nieve",1+COUNTIFS($D$13:$D$20,">0",$D$13:$D$20,"<"&D13)+COUNTIFS($D$13:$D$20,D13,$P$13:$P$20,"<"&P13),1+COUNTIFS($D$13:$D$20,">0",$E$13:$E$20,">"&N(E13))+COUNTIFS($D$13:$D$20,">0",$E$13:$E$20,N(E13),$P$13:$P$20,"<"&P13))) | L13: =IF(K13="","",INDEX($E$86:$E$93,K13)) | M13: =IF(OR(L13="",NOT(ISNUMBER(L13))),"",IF(L13=0,$C$11,EDATE($C$11,L13-1))) | N13: =IF(K13="","",INDEX($F$86:$F$93,K13)) | O13: =IF(N(D13)<=0,"",IF(N(E13)=0,0,IFERROR(IF(N(F13)<=D13*I13,"No se paga",F13*NPER(I13,-F13,D13)-D13),"No se paga"))) | P13: =ROW() -> 13
G14: Sí | I14: =IF(E14="","",(1+E14)^(1/12)-1) | J14: =IF(N(D14)<=0,"",IF(N(E14)>=$C$7,"Sí","No")) | K14: =IF(N(D14)<=0,"",IF($C$6="Bola de nieve",1+COUNTIFS($D$13:$D$20,">0",$D$13:$D$20,"<"&D14)+COUNTIFS($D$13:$D$20,D14,$P$13:$P$20,"<"&P14),1+COUNTIFS($D$13:$D$20,">0",$E$13:$E$20,">"&N(E14))+COUNTIFS($D$13:$D$20,">0",$E$13:$E$20,N(E14),$P$13:$P$20,"<"&P14))) | L14: =IF(K14="","",INDEX($E$86:$E$93,K14)) | M14: =IF(OR(L14="",NOT(ISNUMBER(L14))),"",IF(L14=0,$C$11,EDATE($C$11,L14-1))) | N14: =IF(K14="","",INDEX($F$86:$F$93,K14)) | O14: =IF(N(D14)<=0,"",IF(N(E14)=0,0,IFERROR(IF(N(F14)<=D14*I14,"No se paga",F14*NPER(I14,-F14,D14)-D14),"No se paga"))) | P14: =ROW() -> 14
G15: Sí | I15: =IF(E15="","",(1+E15)^(1/12)-1) | J15: =IF(N(D15)<=0,"",IF(N(E15)>=$C$7,"Sí","No")) | K15: =IF(N(D15)<=0,"",IF($C$6="Bola de nieve",1+COUNTIFS($D$13:$D$20,">0",$D$13:$D$20,"<"&D15)+COUNTIFS($D$13:$D$20,D15,$P$13:$P$20,"<"&P15),1+COUNTIFS($D$13:$D$20,">0",$E$13:$E$20,">"&N(E15))+COUNTIFS($D$13:$D$20,">0",$E$13:$E$20,N(E15),$P$13:$P$20,"<"&P15))) | L15: =IF(K15="","",INDEX($E$86:$E$93,K15)) | M15: =IF(OR(L15="",NOT(ISNUMBER(L15))),"",IF(L15=0,$C$11,EDATE($C$11,L15-1))) | N15: =IF(K15="","",INDEX($F$86:$F$93,K15)) | O15: =IF(N(D15)<=0,"",IF(N(E15)=0,0,IFERROR(IF(N(F15)<=D15*I15,"No se paga",F15*NPER(I15,-F15,D15)-D15),"No se paga"))) | P15: =ROW() -> 15
G16: Sí | I16: =IF(E16="","",(1+E16)^(1/12)-1) | J16: =IF(N(D16)<=0,"",IF(N(E16)>=$C$7,"Sí","No")) | K16: =IF(N(D16)<=0,"",IF($C$6="Bola de nieve",1+COUNTIFS($D$13:$D$20,">0",$D$13:$D$20,"<"&D16)+COUNTIFS($D$13:$D$20,D16,$P$13:$P$20,"<"&P16),1+COUNTIFS($D$13:$D$20,">0",$E$13:$E$20,">"&N(E16))+COUNTIFS($D$13:$D$20,">0",$E$13:$E$20,N(E16),$P$13:$P$20,"<"&P16))) | L16: =IF(K16="","",INDEX($E$86:$E$93,K16)) | M16: =IF(OR(L16="",NOT(ISNUMBER(L16))),"",IF(L16=0,$C$11,EDATE($C$11,L16-1))) | N16: =IF(K16="","",INDEX($F$86:$F$93,K16)) | O16: =IF(N(D16)<=0,"",IF(N(E16)=0,0,IFERROR(IF(N(F16)<=D16*I16,"No se paga",F16*NPER(I16,-F16,D16)-D16),"No se paga"))) | P16: =ROW() -> 16
G17: Sí | I17: =IF(E17="","",(1+E17)^(1/12)-1) | J17: =IF(N(D17)<=0,"",IF(N(E17)>=$C$7,"Sí","No")) | K17: =IF(N(D17)<=0,"",IF($C$6="Bola de nieve",1+COUNTIFS($D$13:$D$20,">0",$D$13:$D$20,"<"&D17)+COUNTIFS($D$13:$D$20,D17,$P$13:$P$20,"<"&P17),1+COUNTIFS($D$13:$D$20,">0",$E$13:$E$20,">"&N(E17))+COUNTIFS($D$13:$D$20,">0",$E$13:$E$20,N(E17),$P$13:$P$20,"<"&P17))) | L17: =IF(K17="","",INDEX($E$86:$E$93,K17)) | M17: =IF(OR(L17="",NOT(ISNUMBER(L17))),"",IF(L17=0,$C$11,EDATE($C$11,L17-1))) | N17: =IF(K17="","",INDEX($F$86:$F$93,K17)) | O17: =IF(N(D17)<=0,"",IF(N(E17)=0,0,IFERROR(IF(N(F17)<=D17*I17,"No se paga",F17*NPER(I17,-F17,D17)-D17),"No se paga"))) | P17: =ROW() -> 17
G18: Sí | I18: =IF(E18="","",(1+E18)^(1/12)-1) | J18: =IF(N(D18)<=0,"",IF(N(E18)>=$C$7,"Sí","No")) | K18: =IF(N(D18)<=0,"",IF($C$6="Bola de nieve",1+COUNTIFS($D$13:$D$20,">0",$D$13:$D$20,"<"&D18)+COUNTIFS($D$13:$D$20,D18,$P$13:$P$20,"<"&P18),1+COUNTIFS($D$13:$D$20,">0",$E$13:$E$20,">"&N(E18))+COUNTIFS($D$13:$D$20,">0",$E$13:$E$20,N(E18),$P$13:$P$20,"<"&P18))) | L18: =IF(K18="","",INDEX($E$86:$E$93,K18)) | M18: =IF(OR(L18="",NOT(ISNUMBER(L18))),"",IF(L18=0,$C$11,EDATE($C$11,L18-1))) | N18: =IF(K18="","",INDEX($F$86:$F$93,K18)) | O18: =IF(N(D18)<=0,"",IF(N(E18)=0,0,IFERROR(IF(N(F18)<=D18*I18,"No se paga",F18*NPER(I18,-F18,D18)-D18),"No se paga"))) | P18: =ROW() -> 18
G19: Sí | I19: =IF(E19="","",(1+E19)^(1/12)-1) | J19: =IF(N(D19)<=0,"",IF(N(E19)>=$C$7,"Sí","No")) | K19: =IF(N(D19)<=0,"",IF($C$6="Bola de nieve",1+COUNTIFS($D$13:$D$20,">0",$D$13:$D$20,"<"&D19)+COUNTIFS($D$13:$D$20,D19,$P$13:$P$20,"<"&P19),1+COUNTIFS($D$13:$D$20,">0",$E$13:$E$20,">"&N(E19))+COUNTIFS($D$13:$D$20,">0",$E$13:$E$20,N(E19),$P$13:$P$20,"<"&P19))) | L19: =IF(K19="","",INDEX($E$86:$E$93,K19)) | M19: =IF(OR(L19="",NOT(ISNUMBER(L19))),"",IF(L19=0,$C$11,EDATE($C$11,L19-1))) | N19: =IF(K19="","",INDEX($F$86:$F$93,K19)) | O19: =IF(N(D19)<=0,"",IF(N(E19)=0,0,IFERROR(IF(N(F19)<=D19*I19,"No se paga",F19*NPER(I19,-F19,D19)-D19),"No se paga"))) | P19: =ROW() -> 19
G20: Sí | I20: =IF(E20="","",(1+E20)^(1/12)-1) | J20: =IF(N(D20)<=0,"",IF(N(E20)>=$C$7,"Sí","No")) | K20: =IF(N(D20)<=0,"",IF($C$6="Bola de nieve",1+COUNTIFS($D$13:$D$20,">0",$D$13:$D$20,"<"&D20)+COUNTIFS($D$13:$D$20,D20,$P$13:$P$20,"<"&P20),1+COUNTIFS($D$13:$D$20,">0",$E$13:$E$20,">"&N(E20))+COUNTIFS($D$13:$D$20,">0",$E$13:$E$20,N(E20),$P$13:$P$20,"<"&P20))) | L20: =IF(K20="","",INDEX($E$86:$E$93,K20)) | M20: =IF(OR(L20="",NOT(ISNUMBER(L20))),"",IF(L20=0,$C$11,EDATE($C$11,L20-1))) | N20: =IF(K20="","",INDEX($F$86:$F$93,K20)) | O20: =IF(N(D20)<=0,"",IF(N(E20)=0,0,IFERROR(IF(N(F20)<=D20*I20,"No se paga",F20*NPER(I20,-F20,D20)-D20),"No se paga"))) | P20: =ROW() -> 20
B21: Total | D21: =SUM(D13:D20) -> 0 | F21: =SUM(F13:F20) -> 0 | N21: =SUM(N13:N20) -> 0 | O21: =SUM(O13:O20) -> 0
B22: Saldo en deuda cara | C22: =SUMIFS(D13:D20,J13:J20,"Sí") -> 0 | E22: Ahorro en intereses con el plan | H22: =IF(OR(COUNTIF(O13:O20,"No se paga")>0,COUNTIF(L13:L20,"Más de 120")>0),"Ver detalle",SUMIFS(O13:O20,K13:K20,">0")-N21) -> 0
B23: ¿Hay deuda cara? | C23: =IF(C22>0,"Sí","No") -> No | E23: "No acepta abonos" o "desde": créditos con cobertura FRECH, préstamos familiares sin interés o con penalidad por prepago. El extra pasa al siguiente en la lista.
B24: Carga de deuda (cuotas / ingreso mensual) | C24: =IF(Ingresos!$U$14=0,"",F21/Ingresos!$U$14) | E24: Intereses solo con la cuota: cálculo aproximado si nunca se hicieran abonos extra.
B25: Fecha de salida de la deuda cara | C25: =IF(C22=0,"",IF(COUNTIFS(J13:J20,"Sí",L13:L20,"Más de 120")>0,"Más de 120 meses",_xlfn.MAXIFS(M13:M20,J13:J20,"Sí")))
B26: ¿Alguna deuda tarda más de 120 meses? | C26: =IF(COUNTIF(L13:L20,"Más de 120")>0,"Sí","No") -> No
B28: Simulación mes a mes (orden de pago; el pago total se mantiene y lo liberado pasa a la siguiente deuda que acepte abonos)
B29: Mes | E29: =EDATE($C$11,0) -> 46296 | F29: =EDATE($C$11,1) -> 46327 | G29: =EDATE($C$11,2) -> 46357 | H29: =EDATE($C$11,3) -> 46388 | I29: =EDATE($C$11,4) -> 46419 | J29: =EDATE($C$11,5) -> 46447 | K29: =EDATE($C$11,6) -> 46478 | L29: =EDATE($C$11,7) -> 46508 | M29: =EDATE($C$11,8) -> 46539 | N29: =EDATE($C$11,9) -> 46569 | O29: =EDATE($C$11,10) -> 46600 | P29: =EDATE($C$11,11) -> 46631 | Q29: =EDATE($C$11,12) -> 46661 | R29: =EDATE($C$11,13) -> 46692 | S29: =EDATE($C$11,14) -> 46722 | T29: =EDATE($C$11,15) -> 46753 | U29: =EDATE($C$11,16) -> 46784 | V29: =EDATE($C$11,17) -> 46813 | W29: =EDATE($C$11,18) -> 46844 | X29: =EDATE($C$11,19) -> 46874 | Y29: =EDATE($C$11,20) -> 46905 | Z29: =EDATE($C$11,21) -> 46935 | AA29: =EDATE($C$11,22) -> 46966 | AB29: =EDATE($C$11,23) -> 46997 | AC29: =EDATE($C$11,24) -> 47027 | AD29: =EDATE($C$11,25) -> 47058 | AE29: =EDATE($C$11,26) -> 47088 | AF29: =EDATE($C$11,27) -> 47119 | AG29: =EDATE($C$11,28) -> 47150 | AH29: =EDATE($C$11,29) -> 47178 | AI29: =EDATE($C$11,30) -> 47209 | AJ29: =EDATE($C$11,31) -> 47239 | AK29: =EDATE($C$11,32) -> 47270 | AL29: =EDATE($C$11,33) -> 47300 | AM29: =EDATE($C$11,34) -> 47331 | AN29: =EDATE($C$11,35) -> 47362 | AO29: =EDATE($C$11,36) -> 47392 | AP29: =EDATE($C$11,37) -> 47423 | AQ29: =EDATE($C$11,38) -> 47453 | AR29: =EDATE($C$11,39) -> 47484 | AS29: =EDATE($C$11,40) -> 47515 | AT29: =EDATE($C$11,41) -> 47543 | AU29: =EDATE($C$11,42) -> 47574 | AV29: =EDATE($C$11,43) -> 47604 | AW29: =EDATE($C$11,44) -> 47635 | AX29: =EDATE($C$11,45) -> 47665 | AY29: =EDATE($C$11,46) -> 47696 | AZ29: =EDATE($C$11,47) -> 47727 | BA29: =EDATE($C$11,48) -> 47757 | BB29: =EDATE($C$11,49) -> 47788 | BC29: =EDATE($C$11,50) -> 47818 | BD29: =EDATE($C$11,51) -> 47849 | BE29: =EDATE($C$11,52) -> 47880 | BF29: =EDATE($C$11,53) -> 47908 | BG29: =EDATE($C$11,54) -> 47939 | BH29: =EDATE($C$11,55) -> 47969 | BI29: =EDATE($C$11,56) -> 48000 | BJ29: =EDATE($C$11,57) -> 48030 | BK29: =EDATE($C$11,58) -> 48061 | BL29: =EDATE($C$11,59) -> 48092 | BM29: =EDATE($C$11,60) -> 48122 | BN29: =EDATE($C$11,61) -> 48153 | BO29: =EDATE($C$11,62) -> 48183 | BP29: =EDATE($C$11,63) -> 48214 | BQ29: =EDATE($C$11,64) -> 48245 | BR29: =EDATE($C$11,65) -> 48274 | BS29: =EDATE($C$11,66) -> 48305 | BT29: =EDATE($C$11,67) -> 48335 | BU29: =EDATE($C$11,68) -> 48366 | BV29: =EDATE($C$11,69) -> 48396 | BW29: =EDATE($C$11,70) -> 48427 | BX29: =EDATE($C$11,71) -> 48458 | BY29: =EDATE($C$11,72) -> 48488 | BZ29: =EDATE($C$11,73) -> 48519 | CA29: =EDATE($C$11,74) -> 48549 | CB29: =EDATE($C$11,75) -> 48580 | CC29: =EDATE($C$11,76) -> 48611 | CD29: =EDATE($C$11,77) -> 48639 | CE29: =EDATE($C$11,78) -> 48670 | CF29: =EDATE($C$11,79) -> 48700 | CG29: =EDATE($C$11,80) -> 48731 | CH29: =EDATE($C$11,81) -> 48761 | CI29: =EDATE($C$11,82) -> 48792 | CJ29: =EDATE($C$11,83) -> 48823 | CK29: =EDATE($C$11,84) -> 48853 | CL29: =EDATE($C$11,85) -> 48884 | CM29: =EDATE($C$11,86) -> 48914 | CN29: =EDATE($C$11,87) -> 48945 | CO29: =EDATE($C$11,88) -> 48976 | CP29: =EDATE($C$11,89) -> 49004 | CQ29: =EDATE($C$11,90) -> 49035 | CR29: =EDATE($C$11,91) -> 49065 | CS29: =EDATE($C$11,92) -> 49096 | CT29: =EDATE($C$11,93) -> 49126 | CU29: =EDATE($C$11,94) -> 49157 | CV29: =EDATE($C$11,95) -> 49188 | CW29: =EDATE($C$11,96) -> 49218 | CX29: =EDATE($C$11,97) -> 49249 | CY29: =EDATE($C$11,98) -> 49279 | CZ29: =EDATE($C$11,99) -> 49310 | DA29: =EDATE($C$11,100) -> 49341 | DB29: =EDATE($C$11,101) -> 49369 | DC29: =EDATE($C$11,102) -> 49400 | DD29: =EDATE($C$11,103) -> 49430 | DE29: =EDATE($C$11,104) -> 49461 | DF29: =EDATE($C$11,105) -> 49491 | DG29: =EDATE($C$11,106) -> 49522 | DH29: =EDATE($C$11,107) -> 49553 | DI29: =EDATE($C$11,108) -> 49583 | DJ29: =EDATE($C$11,109) -> 49614 | DK29: =EDATE($C$11,110) -> 49644 | DL29: =EDATE($C$11,111) -> 49675 | DM29: =EDATE($C$11,112) -> 49706 | DN29: =EDATE($C$11,113) -> 49735 | DO29: =EDATE($C$11,114) -> 49766 | DP29: =EDATE($C$11,115) -> 49796 | DQ29: =EDATE($C$11,116) -> 49827 | DR29: =EDATE($C$11,117) -> 49857 | DS29: =EDATE($C$11,118) -> 49888 | DT29: =EDATE($C$11,119) -> 49919
B30: Pago total disponible | E30: =$C$9 -> 0 | F30: =$C$9 -> 0 | G30: =$C$9 -> 0 | H30: =$C$9 -> 0 | I30: =$C$9 -> 0 | J30: =$C$9 -> 0 | K30: =$C$9 -> 0 | L30: =$C$9 -> 0 | ... DT30: =$C$9 -> 0
B31: Disponible para abono extra | E31: =E30-(E35+E41+E47+E53+E59+E65+E71+E77) -> 0 | F31: =F30-(F35+F41+F47+F53+F59+F65+F71+F77) -> 0 | G31: =G30-(G35+G41+G47+G53+G59+G65+G71+G77) -> 0 | H31: =H30-(H35+H41+H47+H53+H59+H65+H71+H77) -> 0 | I31: =I30-(I35+I41+I47+I53+I59+I65+I71+I77) -> 0 | J31: =J30-(J35+J41+J47+J53+J59+J65+J71+J77) -> 0 | K31: =K30-(K35+K41+K47+K53+K59+K65+K71+K77) -> 0 | L31: =L30-(L35+L41+L47+L53+L59+L65+L71+L77) -> 0 | ... DT31: =DT30-(DT35+DT41+DT47+DT53+DT59+DT65+DT71+DT77) -> 0
B33: ="Orden 1: "&D33 -> Orden 1: (sin deuda) | C33: =IFERROR(MATCH(1,$K$13:$K$20,0),0) -> 0 | D33: =IF(C33=0,"(sin deuda)",INDEX($B$13:$B$20,C33)) -> (sin deuda)
B34: Debe con interés | C34: =IF(C33=0,0,N(INDEX($I$13:$I$20,C33))) -> 0 | E34: =D37*(1+$C$34) -> 0 | F34: =E37*(1+$C$34) -> 0 | G34: =F37*(1+$C$34) -> 0 | H34: =G37*(1+$C$34) -> 0 | I34: =H37*(1+$C$34) -> 0 | J34: =I37*(1+$C$34) -> 0 | K34: =J37*(1+$C$34) -> 0 | L34: =K37*(1+$C$34) -> 0 | ... DT34: =DS37*(1+$C$34) -> 0
B35: Pago mínimo aplicado | C35: =IF(C33=0,0,N(INDEX($F$13:$F$20,C33))) -> 0 | E35: =MIN($C$35,E34) -> 0 | F35: =MIN($C$35,F34) -> 0 | G35: =MIN($C$35,G34) -> 0 | H35: =MIN($C$35,H34) -> 0 | I35: =MIN($C$35,I34) -> 0 | J35: =MIN($C$35,J34) -> 0 | K35: =MIN($C$35,K34) -> 0 | L35: =MIN($C$35,L34) -> 0 | ... DT35: =MIN($C$35,DT34) -> 0
B36: Abono extra | C36: =IF(C33=0,0,IF(INDEX($G$13:$G$20,C33)="No",0,1)) -> 0 | D36: =IF(C33=0,"",IF(N(INDEX($H$13:$H$20,C33))=0,"",INDEX($H$13:$H$20,C33))) | E36: =IF(AND($C$36=1,OR($D$36="",E$29>=$D$36)),MAX(0,MIN(E34-E35,E$31-(0))),0) -> 0 | F36: =IF(AND($C$36=1,OR($D$36="",F$29>=$D$36)),MAX(0,MIN(F34-F35,F$31-(0))),0) -> 0 | G36: =IF(AND($C$36=1,OR($D$36="",G$29>=$D$36)),MAX(0,MIN(G34-G35,G$31-(0))),0) -> 0 | H36: =IF(AND($C$36=1,OR($D$36="",H$29>=$D$36)),MAX(0,MIN(H34-H35,H$31-(0))),0) -> 0 | I36: =IF(AND($C$36=1,OR($D$36="",I$29>=$D$36)),MAX(0,MIN(I34-I35,I$31-(0))),0) -> 0 | J36: =IF(AND($C$36=1,OR($D$36="",J$29>=$D$36)),MAX(0,MIN(J34-J35,J$31-(0))),0) -> 0 | K36: =IF(AND($C$36=1,OR($D$36="",K$29>=$D$36)),MAX(0,MIN(K34-K35,K$31-(0))),0) -> 0 | L36: =IF(AND($C$36=1,OR($D$36="",L$29>=$D$36)),MAX(0,MIN(L34-L35,L$31-(0))),0) -> 0 | ... DT36: =IF(AND($C$36=1,OR($D$36="",DT$29>=$D$36)),MAX(0,MIN(DT34-DT35,DT$31-(0))),0) -> 0
B37: Saldo | C37: inicial | D37: =IF($C$38=0,D38,MAX(0,D38-MAX(0,$C$10-(0)))) -> 0 | E37: =E34-E35-E36 -> 0 | F37: =F34-F35-F36 -> 0 | G37: =G34-G35-G36 -> 0 | H37: =H34-H35-H36 -> 0 | I37: =I34-I35-I36 -> 0 | J37: =J34-J35-J36 -> 0 | K37: =K34-K35-K36 -> 0 | L37: =L34-L35-L36 -> 0 | ... DT37: =DT34-DT35-DT36 -> 0
C38: =IF(AND(C36=1,OR(D36="",D36<=$C$11)),1,0) -> 0 | D38: =IF(C33=0,0,N(INDEX($D$13:$D$20,C33))) -> 0
B39: ="Orden 2: "&D39 -> Orden 2: (sin deuda) | C39: =IFERROR(MATCH(2,$K$13:$K$20,0),0) -> 0 | D39: =IF(C39=0,"(sin deuda)",INDEX($B$13:$B$20,C39)) -> (sin deuda)
B40: Debe con interés | C40: =IF(C39=0,0,N(INDEX($I$13:$I$20,C39))) -> 0 | E40: =D43*(1+$C$40) -> 0 | F40: =E43*(1+$C$40) -> 0 | G40: =F43*(1+$C$40) -> 0 | H40: =G43*(1+$C$40) -> 0 | I40: =H43*(1+$C$40) -> 0 | J40: =I43*(1+$C$40) -> 0 | K40: =J43*(1+$C$40) -> 0 | L40: =K43*(1+$C$40) -> 0 | ... DT40: =DS43*(1+$C$40) -> 0
B41: Pago mínimo aplicado | C41: =IF(C39=0,0,N(INDEX($F$13:$F$20,C39))) -> 0 | E41: =MIN($C$41,E40) -> 0 | F41: =MIN($C$41,F40) -> 0 | G41: =MIN($C$41,G40) -> 0 | H41: =MIN($C$41,H40) -> 0 | I41: =MIN($C$41,I40) -> 0 | J41: =MIN($C$41,J40) -> 0 | K41: =MIN($C$41,K40) -> 0 | L41: =MIN($C$41,L40) -> 0 | ... DT41: =MIN($C$41,DT40) -> 0
B42: Abono extra | C42: =IF(C39=0,0,IF(INDEX($G$13:$G$20,C39)="No",0,1)) -> 0 | D42: =IF(C39=0,"",IF(N(INDEX($H$13:$H$20,C39))=0,"",INDEX($H$13:$H$20,C39))) | E42: =IF(AND($C$42=1,OR($D$42="",E$29>=$D$42)),MAX(0,MIN(E40-E41,E$31-(E36))),0) -> 0 | F42: =IF(AND($C$42=1,OR($D$42="",F$29>=$D$42)),MAX(0,MIN(F40-F41,F$31-(F36))),0) -> 0 | G42: =IF(AND($C$42=1,OR($D$42="",G$29>=$D$42)),MAX(0,MIN(G40-G41,G$31-(G36))),0) -> 0 | H42: =IF(AND($C$42=1,OR($D$42="",H$29>=$D$42)),MAX(0,MIN(H40-H41,H$31-(H36))),0) -> 0 | I42: =IF(AND($C$42=1,OR($D$42="",I$29>=$D$42)),MAX(0,MIN(I40-I41,I$31-(I36))),0) -> 0 | J42: =IF(AND($C$42=1,OR($D$42="",J$29>=$D$42)),MAX(0,MIN(J40-J41,J$31-(J36))),0) -> 0 | K42: =IF(AND($C$42=1,OR($D$42="",K$29>=$D$42)),MAX(0,MIN(K40-K41,K$31-(K36))),0) -> 0 | L42: =IF(AND($C$42=1,OR($D$42="",L$29>=$D$42)),MAX(0,MIN(L40-L41,L$31-(L36))),0) -> 0 | ... DT42: =IF(AND($C$42=1,OR($D$42="",DT$29>=$D$42)),MAX(0,MIN(DT40-DT41,DT$31-(DT36))),0) -> 0
B43: Saldo | C43: inicial | D43: =IF($C$44=0,D44,MAX(0,D44-MAX(0,$C$10-($D$38*$C$38)))) -> 0 | E43: =E40-E41-E42 -> 0 | F43: =F40-F41-F42 -> 0 | G43: =G40-G41-G42 -> 0 | H43: =H40-H41-H42 -> 0 | I43: =I40-I41-I42 -> 0 | J43: =J40-J41-J42 -> 0 | K43: =K40-K41-K42 -> 0 | L43: =L40-L41-L42 -> 0 | ... DT43: =DT40-DT41-DT42 -> 0
C44: =IF(AND(C42=1,OR(D42="",D42<=$C$11)),1,0) -> 0 | D44: =IF(C39=0,0,N(INDEX($D$13:$D$20,C39))) -> 0
B45: ="Orden 3: "&D45 -> Orden 3: (sin deuda) | C45: =IFERROR(MATCH(3,$K$13:$K$20,0),0) -> 0 | D45: =IF(C45=0,"(sin deuda)",INDEX($B$13:$B$20,C45)) -> (sin deuda)
B46: Debe con interés | C46: =IF(C45=0,0,N(INDEX($I$13:$I$20,C45))) -> 0 | E46: =D49*(1+$C$46) -> 0 | F46: =E49*(1+$C$46) -> 0 | G46: =F49*(1+$C$46) -> 0 | H46: =G49*(1+$C$46) -> 0 | I46: =H49*(1+$C$46) -> 0 | J46: =I49*(1+$C$46) -> 0 | K46: =J49*(1+$C$46) -> 0 | L46: =K49*(1+$C$46) -> 0 | ... DT46: =DS49*(1+$C$46) -> 0
B47: Pago mínimo aplicado | C47: =IF(C45=0,0,N(INDEX($F$13:$F$20,C45))) -> 0 | E47: =MIN($C$47,E46) -> 0 | F47: =MIN($C$47,F46) -> 0 | G47: =MIN($C$47,G46) -> 0 | H47: =MIN($C$47,H46) -> 0 | I47: =MIN($C$47,I46) -> 0 | J47: =MIN($C$47,J46) -> 0 | K47: =MIN($C$47,K46) -> 0 | L47: =MIN($C$47,L46) -> 0 | ... DT47: =MIN($C$47,DT46) -> 0
B48: Abono extra | C48: =IF(C45=0,0,IF(INDEX($G$13:$G$20,C45)="No",0,1)) -> 0 | D48: =IF(C45=0,"",IF(N(INDEX($H$13:$H$20,C45))=0,"",INDEX($H$13:$H$20,C45))) | E48: =IF(AND($C$48=1,OR($D$48="",E$29>=$D$48)),MAX(0,MIN(E46-E47,E$31-(E36+E42))),0) -> 0 | F48: =IF(AND($C$48=1,OR($D$48="",F$29>=$D$48)),MAX(0,MIN(F46-F47,F$31-(F36+F42))),0) -> 0 | G48: =IF(AND($C$48=1,OR($D$48="",G$29>=$D$48)),MAX(0,MIN(G46-G47,G$31-(G36+G42))),0) -> 0 | H48: =IF(AND($C$48=1,OR($D$48="",H$29>=$D$48)),MAX(0,MIN(H46-H47,H$31-(H36+H42))),0) -> 0 | I48: =IF(AND($C$48=1,OR($D$48="",I$29>=$D$48)),MAX(0,MIN(I46-I47,I$31-(I36+I42))),0) -> 0 | J48: =IF(AND($C$48=1,OR($D$48="",J$29>=$D$48)),MAX(0,MIN(J46-J47,J$31-(J36+J42))),0) -> 0 | K48: =IF(AND($C$48=1,OR($D$48="",K$29>=$D$48)),MAX(0,MIN(K46-K47,K$31-(K36+K42))),0) -> 0 | L48: =IF(AND($C$48=1,OR($D$48="",L$29>=$D$48)),MAX(0,MIN(L46-L47,L$31-(L36+L42))),0) -> 0 | ... DT48: =IF(AND($C$48=1,OR($D$48="",DT$29>=$D$48)),MAX(0,MIN(DT46-DT47,DT$31-(DT36+DT42))),0) -> 0
B49: Saldo | C49: inicial | D49: =IF($C$50=0,D50,MAX(0,D50-MAX(0,$C$10-($D$38*$C$38+$D$44*$C$44)))) -> 0 | E49: =E46-E47-E48 -> 0 | F49: =F46-F47-F48 -> 0 | G49: =G46-G47-G48 -> 0 | H49: =H46-H47-H48 -> 0 | I49: =I46-I47-I48 -> 0 | J49: =J46-J47-J48 -> 0 | K49: =K46-K47-K48 -> 0 | L49: =L46-L47-L48 -> 0 | ... DT49: =DT46-DT47-DT48 -> 0
C50: =IF(AND(C48=1,OR(D48="",D48<=$C$11)),1,0) -> 0 | D50: =IF(C45=0,0,N(INDEX($D$13:$D$20,C45))) -> 0
B51: ="Orden 4: "&D51 -> Orden 4: (sin deuda) | C51: =IFERROR(MATCH(4,$K$13:$K$20,0),0) -> 0 | D51: =IF(C51=0,"(sin deuda)",INDEX($B$13:$B$20,C51)) -> (sin deuda)
B52: Debe con interés | C52: =IF(C51=0,0,N(INDEX($I$13:$I$20,C51))) -> 0 | E52: =D55*(1+$C$52) -> 0 | F52: =E55*(1+$C$52) -> 0 | G52: =F55*(1+$C$52) -> 0 | H52: =G55*(1+$C$52) -> 0 | I52: =H55*(1+$C$52) -> 0 | J52: =I55*(1+$C$52) -> 0 | K52: =J55*(1+$C$52) -> 0 | L52: =K55*(1+$C$52) -> 0 | ... DT52: =DS55*(1+$C$52) -> 0
B53: Pago mínimo aplicado | C53: =IF(C51=0,0,N(INDEX($F$13:$F$20,C51))) -> 0 | E53: =MIN($C$53,E52) -> 0 | F53: =MIN($C$53,F52) -> 0 | G53: =MIN($C$53,G52) -> 0 | H53: =MIN($C$53,H52) -> 0 | I53: =MIN($C$53,I52) -> 0 | J53: =MIN($C$53,J52) -> 0 | K53: =MIN($C$53,K52) -> 0 | L53: =MIN($C$53,L52) -> 0 | ... DT53: =MIN($C$53,DT52) -> 0
B54: Abono extra | C54: =IF(C51=0,0,IF(INDEX($G$13:$G$20,C51)="No",0,1)) -> 0 | D54: =IF(C51=0,"",IF(N(INDEX($H$13:$H$20,C51))=0,"",INDEX($H$13:$H$20,C51))) | E54: =IF(AND($C$54=1,OR($D$54="",E$29>=$D$54)),MAX(0,MIN(E52-E53,E$31-(E36+E42+E48))),0) -> 0 | F54: =IF(AND($C$54=1,OR($D$54="",F$29>=$D$54)),MAX(0,MIN(F52-F53,F$31-(F36+F42+F48))),0) -> 0 | G54: =IF(AND($C$54=1,OR($D$54="",G$29>=$D$54)),MAX(0,MIN(G52-G53,G$31-(G36+G42+G48))),0) -> 0 | H54: =IF(AND($C$54=1,OR($D$54="",H$29>=$D$54)),MAX(0,MIN(H52-H53,H$31-(H36+H42+H48))),0) -> 0 | I54: =IF(AND($C$54=1,OR($D$54="",I$29>=$D$54)),MAX(0,MIN(I52-I53,I$31-(I36+I42+I48))),0) -> 0 | J54: =IF(AND($C$54=1,OR($D$54="",J$29>=$D$54)),MAX(0,MIN(J52-J53,J$31-(J36+J42+J48))),0) -> 0 | K54: =IF(AND($C$54=1,OR($D$54="",K$29>=$D$54)),MAX(0,MIN(K52-K53,K$31-(K36+K42+K48))),0) -> 0 | L54: =IF(AND($C$54=1,OR($D$54="",L$29>=$D$54)),MAX(0,MIN(L52-L53,L$31-(L36+L42+L48))),0) -> 0 | ... DT54: =IF(AND($C$54=1,OR($D$54="",DT$29>=$D$54)),MAX(0,MIN(DT52-DT53,DT$31-(DT36+DT42+DT48))),0) -> 0
B55: Saldo | C55: inicial | D55: =IF($C$56=0,D56,MAX(0,D56-MAX(0,$C$10-($D$38*$C$38+$D$44*$C$44+$D$50*$C$50)))) -> 0 | E55: =E52-E53-E54 -> 0 | F55: =F52-F53-F54 -> 0 | G55: =G52-G53-G54 -> 0 | H55: =H52-H53-H54 -> 0 | I55: =I52-I53-I54 -> 0 | J55: =J52-J53-J54 -> 0 | K55: =K52-K53-K54 -> 0 | L55: =L52-L53-L54 -> 0 | ... DT55: =DT52-DT53-DT54 -> 0
C56: =IF(AND(C54=1,OR(D54="",D54<=$C$11)),1,0) -> 0 | D56: =IF(C51=0,0,N(INDEX($D$13:$D$20,C51))) -> 0
B57: ="Orden 5: "&D57 -> Orden 5: (sin deuda) | C57: =IFERROR(MATCH(5,$K$13:$K$20,0),0) -> 0 | D57: =IF(C57=0,"(sin deuda)",INDEX($B$13:$B$20,C57)) -> (sin deuda)
B58: Debe con interés | C58: =IF(C57=0,0,N(INDEX($I$13:$I$20,C57))) -> 0 | E58: =D61*(1+$C$58) -> 0 | F58: =E61*(1+$C$58) -> 0 | G58: =F61*(1+$C$58) -> 0 | H58: =G61*(1+$C$58) -> 0 | I58: =H61*(1+$C$58) -> 0 | J58: =I61*(1+$C$58) -> 0 | K58: =J61*(1+$C$58) -> 0 | L58: =K61*(1+$C$58) -> 0 | ... DT58: =DS61*(1+$C$58) -> 0
B59: Pago mínimo aplicado | C59: =IF(C57=0,0,N(INDEX($F$13:$F$20,C57))) -> 0 | E59: =MIN($C$59,E58) -> 0 | F59: =MIN($C$59,F58) -> 0 | G59: =MIN($C$59,G58) -> 0 | H59: =MIN($C$59,H58) -> 0 | I59: =MIN($C$59,I58) -> 0 | J59: =MIN($C$59,J58) -> 0 | K59: =MIN($C$59,K58) -> 0 | L59: =MIN($C$59,L58) -> 0 | ... DT59: =MIN($C$59,DT58) -> 0
B60: Abono extra | C60: =IF(C57=0,0,IF(INDEX($G$13:$G$20,C57)="No",0,1)) -> 0 | D60: =IF(C57=0,"",IF(N(INDEX($H$13:$H$20,C57))=0,"",INDEX($H$13:$H$20,C57))) | E60: =IF(AND($C$60=1,OR($D$60="",E$29>=$D$60)),MAX(0,MIN(E58-E59,E$31-(E36+E42+E48+E54))),0) -> 0 | F60: =IF(AND($C$60=1,OR($D$60="",F$29>=$D$60)),MAX(0,MIN(F58-F59,F$31-(F36+F42+F48+F54))),0) -> 0 | G60: =IF(AND($C$60=1,OR($D$60="",G$29>=$D$60)),MAX(0,MIN(G58-G59,G$31-(G36+G42+G48+G54))),0) -> 0 | H60: =IF(AND($C$60=1,OR($D$60="",H$29>=$D$60)),MAX(0,MIN(H58-H59,H$31-(H36+H42+H48+H54))),0) -> 0 | I60: =IF(AND($C$60=1,OR($D$60="",I$29>=$D$60)),MAX(0,MIN(I58-I59,I$31-(I36+I42+I48+I54))),0) -> 0 | J60: =IF(AND($C$60=1,OR($D$60="",J$29>=$D$60)),MAX(0,MIN(J58-J59,J$31-(J36+J42+J48+J54))),0) -> 0 | K60: =IF(AND($C$60=1,OR($D$60="",K$29>=$D$60)),MAX(0,MIN(K58-K59,K$31-(K36+K42+K48+K54))),0) -> 0 | L60: =IF(AND($C$60=1,OR($D$60="",L$29>=$D$60)),MAX(0,MIN(L58-L59,L$31-(L36+L42+L48+L54))),0) -> 0 | ... DT60: =IF(AND($C$60=1,OR($D$60="",DT$29>=$D$60)),MAX(0,MIN(DT58-DT59,DT$31-(DT36+DT42+DT48+DT54))),0) -> 0
B61: Saldo | C61: inicial | D61: =IF($C$62=0,D62,MAX(0,D62-MAX(0,$C$10-($D$38*$C$38+$D$44*$C$44+$D$50*$C$50+$D$56*$C$56)))) -> 0 | E61: =E58-E59-E60 -> 0 | F61: =F58-F59-F60 -> 0 | G61: =G58-G59-G60 -> 0 | H61: =H58-H59-H60 -> 0 | I61: =I58-I59-I60 -> 0 | J61: =J58-J59-J60 -> 0 | K61: =K58-K59-K60 -> 0 | L61: =L58-L59-L60 -> 0 | ... DT61: =DT58-DT59-DT60 -> 0
C62: =IF(AND(C60=1,OR(D60="",D60<=$C$11)),1,0) -> 0 | D62: =IF(C57=0,0,N(INDEX($D$13:$D$20,C57))) -> 0
B63: ="Orden 6: "&D63 -> Orden 6: (sin deuda) | C63: =IFERROR(MATCH(6,$K$13:$K$20,0),0) -> 0 | D63: =IF(C63=0,"(sin deuda)",INDEX($B$13:$B$20,C63)) -> (sin deuda)
B64: Debe con interés | C64: =IF(C63=0,0,N(INDEX($I$13:$I$20,C63))) -> 0 | E64: =D67*(1+$C$64) -> 0 | F64: =E67*(1+$C$64) -> 0 | G64: =F67*(1+$C$64) -> 0 | H64: =G67*(1+$C$64) -> 0 | I64: =H67*(1+$C$64) -> 0 | J64: =I67*(1+$C$64) -> 0 | K64: =J67*(1+$C$64) -> 0 | L64: =K67*(1+$C$64) -> 0 | ... DT64: =DS67*(1+$C$64) -> 0
B65: Pago mínimo aplicado | C65: =IF(C63=0,0,N(INDEX($F$13:$F$20,C63))) -> 0 | E65: =MIN($C$65,E64) -> 0 | F65: =MIN($C$65,F64) -> 0 | G65: =MIN($C$65,G64) -> 0 | H65: =MIN($C$65,H64) -> 0 | I65: =MIN($C$65,I64) -> 0 | J65: =MIN($C$65,J64) -> 0 | K65: =MIN($C$65,K64) -> 0 | L65: =MIN($C$65,L64) -> 0 | ... DT65: =MIN($C$65,DT64) -> 0
B66: Abono extra | C66: =IF(C63=0,0,IF(INDEX($G$13:$G$20,C63)="No",0,1)) -> 0 | D66: =IF(C63=0,"",IF(N(INDEX($H$13:$H$20,C63))=0,"",INDEX($H$13:$H$20,C63))) | E66: =IF(AND($C$66=1,OR($D$66="",E$29>=$D$66)),MAX(0,MIN(E64-E65,E$31-(E36+E42+E48+E54+E60))),0) -> 0 | F66: =IF(AND($C$66=1,OR($D$66="",F$29>=$D$66)),MAX(0,MIN(F64-F65,F$31-(F36+F42+F48+F54+F60))),0) -> 0 | G66: =IF(AND($C$66=1,OR($D$66="",G$29>=$D$66)),MAX(0,MIN(G64-G65,G$31-(G36+G42+G48+G54+G60))),0) -> 0 | H66: =IF(AND($C$66=1,OR($D$66="",H$29>=$D$66)),MAX(0,MIN(H64-H65,H$31-(H36+H42+H48+H54+H60))),0) -> 0 | I66: =IF(AND($C$66=1,OR($D$66="",I$29>=$D$66)),MAX(0,MIN(I64-I65,I$31-(I36+I42+I48+I54+I60))),0) -> 0 | J66: =IF(AND($C$66=1,OR($D$66="",J$29>=$D$66)),MAX(0,MIN(J64-J65,J$31-(J36+J42+J48+J54+J60))),0) -> 0 | K66: =IF(AND($C$66=1,OR($D$66="",K$29>=$D$66)),MAX(0,MIN(K64-K65,K$31-(K36+K42+K48+K54+K60))),0) -> 0 | L66: =IF(AND($C$66=1,OR($D$66="",L$29>=$D$66)),MAX(0,MIN(L64-L65,L$31-(L36+L42+L48+L54+L60))),0) -> 0 | ... DT66: =IF(AND($C$66=1,OR($D$66="",DT$29>=$D$66)),MAX(0,MIN(DT64-DT65,DT$31-(DT36+DT42+DT48+DT54+DT60))),0) -> 0
B67: Saldo | C67: inicial | D67: =IF($C$68=0,D68,MAX(0,D68-MAX(0,$C$10-($D$38*$C$38+$D$44*$C$44+$D$50*$C$50+$D$56*$C$56+$D$62*$C$62)))) -> 0 | E67: =E64-E65-E66 -> 0 | F67: =F64-F65-F66 -> 0 | G67: =G64-G65-G66 -> 0 | H67: =H64-H65-H66 -> 0 | I67: =I64-I65-I66 -> 0 | J67: =J64-J65-J66 -> 0 | K67: =K64-K65-K66 -> 0 | L67: =L64-L65-L66 -> 0 | ... DT67: =DT64-DT65-DT66 -> 0
C68: =IF(AND(C66=1,OR(D66="",D66<=$C$11)),1,0) -> 0 | D68: =IF(C63=0,0,N(INDEX($D$13:$D$20,C63))) -> 0
B69: ="Orden 7: "&D69 -> Orden 7: (sin deuda) | C69: =IFERROR(MATCH(7,$K$13:$K$20,0),0) -> 0 | D69: =IF(C69=0,"(sin deuda)",INDEX($B$13:$B$20,C69)) -> (sin deuda)
B70: Debe con interés | C70: =IF(C69=0,0,N(INDEX($I$13:$I$20,C69))) -> 0 | E70: =D73*(1+$C$70) -> 0 | F70: =E73*(1+$C$70) -> 0 | G70: =F73*(1+$C$70) -> 0 | H70: =G73*(1+$C$70) -> 0 | I70: =H73*(1+$C$70) -> 0 | J70: =I73*(1+$C$70) -> 0 | K70: =J73*(1+$C$70) -> 0 | L70: =K73*(1+$C$70) -> 0 | ... DT70: =DS73*(1+$C$70) -> 0
B71: Pago mínimo aplicado | C71: =IF(C69=0,0,N(INDEX($F$13:$F$20,C69))) -> 0 | E71: =MIN($C$71,E70) -> 0 | F71: =MIN($C$71,F70) -> 0 | G71: =MIN($C$71,G70) -> 0 | H71: =MIN($C$71,H70) -> 0 | I71: =MIN($C$71,I70) -> 0 | J71: =MIN($C$71,J70) -> 0 | K71: =MIN($C$71,K70) -> 0 | L71: =MIN($C$71,L70) -> 0 | ... DT71: =MIN($C$71,DT70) -> 0
B72: Abono extra | C72: =IF(C69=0,0,IF(INDEX($G$13:$G$20,C69)="No",0,1)) -> 0 | D72: =IF(C69=0,"",IF(N(INDEX($H$13:$H$20,C69))=0,"",INDEX($H$13:$H$20,C69))) | E72: =IF(AND($C$72=1,OR($D$72="",E$29>=$D$72)),MAX(0,MIN(E70-E71,E$31-(E36+E42+E48+E54+E60+E66))),0) -> 0 | F72: =IF(AND($C$72=1,OR($D$72="",F$29>=$D$72)),MAX(0,MIN(F70-F71,F$31-(F36+F42+F48+F54+F60+F66))),0) -> 0 | G72: =IF(AND($C$72=1,OR($D$72="",G$29>=$D$72)),MAX(0,MIN(G70-G71,G$31-(G36+G42+G48+G54+G60+G66))),0) -> 0 | H72: =IF(AND($C$72=1,OR($D$72="",H$29>=$D$72)),MAX(0,MIN(H70-H71,H$31-(H36+H42+H48+H54+H60+H66))),0) -> 0 | I72: =IF(AND($C$72=1,OR($D$72="",I$29>=$D$72)),MAX(0,MIN(I70-I71,I$31-(I36+I42+I48+I54+I60+I66))),0) -> 0 | J72: =IF(AND($C$72=1,OR($D$72="",J$29>=$D$72)),MAX(0,MIN(J70-J71,J$31-(J36+J42+J48+J54+J60+J66))),0) -> 0 | K72: =IF(AND($C$72=1,OR($D$72="",K$29>=$D$72)),MAX(0,MIN(K70-K71,K$31-(K36+K42+K48+K54+K60+K66))),0) -> 0 | L72: =IF(AND($C$72=1,OR($D$72="",L$29>=$D$72)),MAX(0,MIN(L70-L71,L$31-(L36+L42+L48+L54+L60+L66))),0) -> 0 | ... DT72: =IF(AND($C$72=1,OR($D$72="",DT$29>=$D$72)),MAX(0,MIN(DT70-DT71,DT$31-(DT36+DT42+DT48+DT54+DT60+DT66))),0) -> 0
B73: Saldo | C73: inicial | D73: =IF($C$74=0,D74,MAX(0,D74-MAX(0,$C$10-($D$38*$C$38+$D$44*$C$44+$D$50*$C$50+$D$56*$C$56+$D$62*$C$62+$D$68*$C$68)))) -> 0 | E73: =E70-E71-E72 -> 0 | F73: =F70-F71-F72 -> 0 | G73: =G70-G71-G72 -> 0 | H73: =H70-H71-H72 -> 0 | I73: =I70-I71-I72 -> 0 | J73: =J70-J71-J72 -> 0 | K73: =K70-K71-K72 -> 0 | L73: =L70-L71-L72 -> 0 | ... DT73: =DT70-DT71-DT72 -> 0
C74: =IF(AND(C72=1,OR(D72="",D72<=$C$11)),1,0) -> 0 | D74: =IF(C69=0,0,N(INDEX($D$13:$D$20,C69))) -> 0
B75: ="Orden 8: "&D75 -> Orden 8: (sin deuda) | C75: =IFERROR(MATCH(8,$K$13:$K$20,0),0) -> 0 | D75: =IF(C75=0,"(sin deuda)",INDEX($B$13:$B$20,C75)) -> (sin deuda)
B76: Debe con interés | C76: =IF(C75=0,0,N(INDEX($I$13:$I$20,C75))) -> 0 | E76: =D79*(1+$C$76) -> 0 | F76: =E79*(1+$C$76) -> 0 | G76: =F79*(1+$C$76) -> 0 | H76: =G79*(1+$C$76) -> 0 | I76: =H79*(1+$C$76) -> 0 | J76: =I79*(1+$C$76) -> 0 | K76: =J79*(1+$C$76) -> 0 | L76: =K79*(1+$C$76) -> 0 | ... DT76: =DS79*(1+$C$76) -> 0
B77: Pago mínimo aplicado | C77: =IF(C75=0,0,N(INDEX($F$13:$F$20,C75))) -> 0 | E77: =MIN($C$77,E76) -> 0 | F77: =MIN($C$77,F76) -> 0 | G77: =MIN($C$77,G76) -> 0 | H77: =MIN($C$77,H76) -> 0 | I77: =MIN($C$77,I76) -> 0 | J77: =MIN($C$77,J76) -> 0 | K77: =MIN($C$77,K76) -> 0 | L77: =MIN($C$77,L76) -> 0 | ... DT77: =MIN($C$77,DT76) -> 0
B78: Abono extra | C78: =IF(C75=0,0,IF(INDEX($G$13:$G$20,C75)="No",0,1)) -> 0 | D78: =IF(C75=0,"",IF(N(INDEX($H$13:$H$20,C75))=0,"",INDEX($H$13:$H$20,C75))) | E78: =IF(AND($C$78=1,OR($D$78="",E$29>=$D$78)),MAX(0,MIN(E76-E77,E$31-(E36+E42+E48+E54+E60+E66+E72))),0) -> 0 | F78: =IF(AND($C$78=1,OR($D$78="",F$29>=$D$78)),MAX(0,MIN(F76-F77,F$31-(F36+F42+F48+F54+F60+F66+F72))),0) -> 0 | G78: =IF(AND($C$78=1,OR($D$78="",G$29>=$D$78)),MAX(0,MIN(G76-G77,G$31-(G36+G42+G48+G54+G60+G66+G72))),0) -> 0 | H78: =IF(AND($C$78=1,OR($D$78="",H$29>=$D$78)),MAX(0,MIN(H76-H77,H$31-(H36+H42+H48+H54+H60+H66+H72))),0) -> 0 | I78: =IF(AND($C$78=1,OR($D$78="",I$29>=$D$78)),MAX(0,MIN(I76-I77,I$31-(I36+I42+I48+I54+I60+I66+I72))),0) -> 0 | J78: =IF(AND($C$78=1,OR($D$78="",J$29>=$D$78)),MAX(0,MIN(J76-J77,J$31-(J36+J42+J48+J54+J60+J66+J72))),0) -> 0 | K78: =IF(AND($C$78=1,OR($D$78="",K$29>=$D$78)),MAX(0,MIN(K76-K77,K$31-(K36+K42+K48+K54+K60+K66+K72))),0) -> 0 | L78: =IF(AND($C$78=1,OR($D$78="",L$29>=$D$78)),MAX(0,MIN(L76-L77,L$31-(L36+L42+L48+L54+L60+L66+L72))),0) -> 0 | ... DT78: =IF(AND($C$78=1,OR($D$78="",DT$29>=$D$78)),MAX(0,MIN(DT76-DT77,DT$31-(DT36+DT42+DT48+DT54+DT60+DT66+DT72))),0) -> 0
B79: Saldo | C79: inicial | D79: =IF($C$80=0,D80,MAX(0,D80-MAX(0,$C$10-($D$38*$C$38+$D$44*$C$44+$D$50*$C$50+$D$56*$C$56+$D$62*$C$62+$D$68*$C$68+$D$74*$C$74)))) -> 0 | E79: =E76-E77-E78 -> 0 | F79: =F76-F77-F78 -> 0 | G79: =G76-G77-G78 -> 0 | H79: =H76-H77-H78 -> 0 | I79: =I76-I77-I78 -> 0 | J79: =J76-J77-J78 -> 0 | K79: =K76-K77-K78 -> 0 | L79: =L76-L77-L78 -> 0 | ... DT79: =DT76-DT77-DT78 -> 0
C80: =IF(AND(C78=1,OR(D78="",D78<=$C$11)),1,0) -> 0 | D80: =IF(C75=0,0,N(INDEX($D$13:$D$20,C75))) -> 0
B84: Resultado por orden de pago
B85: Orden | C85: Deuda | D85: Saldo inicial | E85: Meses para pagar | F85: Intereses
B86: 1 | C86: =D33 -> (sin deuda) | D86: =D37 -> 0 | E86: =IF(D86=0,0,IF(DT37>0.5,"Más de 120",COUNTIF(E37:DT37,">0.5")+1)) -> 0 | F86: =IF(D86=0,0,SUM(E35:DT35)+SUM(E36:DT36)+DT37-D86) -> 0
B87: 2 | C87: =D39 -> (sin deuda) | D87: =D43 -> 0 | E87: =IF(D87=0,0,IF(DT43>0.5,"Más de 120",COUNTIF(E43:DT43,">0.5")+1)) -> 0 | F87: =IF(D87=0,0,SUM(E41:DT41)+SUM(E42:DT42)+DT43-D87) -> 0
B88: 3 | C88: =D45 -> (sin deuda) | D88: =D49 -> 0 | E88: =IF(D88=0,0,IF(DT49>0.5,"Más de 120",COUNTIF(E49:DT49,">0.5")+1)) -> 0 | F88: =IF(D88=0,0,SUM(E47:DT47)+SUM(E48:DT48)+DT49-D88) -> 0
B89: 4 | C89: =D51 -> (sin deuda) | D89: =D55 -> 0 | E89: =IF(D89=0,0,IF(DT55>0.5,"Más de 120",COUNTIF(E55:DT55,">0.5")+1)) -> 0 | F89: =IF(D89=0,0,SUM(E53:DT53)+SUM(E54:DT54)+DT55-D89) -> 0
B90: 5 | C90: =D57 -> (sin deuda) | D90: =D61 -> 0 | E90: =IF(D90=0,0,IF(DT61>0.5,"Más de 120",COUNTIF(E61:DT61,">0.5")+1)) -> 0 | F90: =IF(D90=0,0,SUM(E59:DT59)+SUM(E60:DT60)+DT61-D90) -> 0
B91: 6 | C91: =D63 -> (sin deuda) | D91: =D67 -> 0 | E91: =IF(D91=0,0,IF(DT67>0.5,"Más de 120",COUNTIF(E67:DT67,">0.5")+1)) -> 0 | F91: =IF(D91=0,0,SUM(E65:DT65)+SUM(E66:DT66)+DT67-D91) -> 0
B92: 7 | C92: =D69 -> (sin deuda) | D92: =D73 -> 0 | E92: =IF(D92=0,0,IF(DT73>0.5,"Más de 120",COUNTIF(E73:DT73,">0.5")+1)) -> 0 | F92: =IF(D92=0,0,SUM(E71:DT71)+SUM(E72:DT72)+DT73-D92) -> 0
B93: 8 | C93: =D75 -> (sin deuda) | D93: =D79 -> 0 | E93: =IF(D93=0,0,IF(DT79>0.5,"Más de 120",COUNTIF(E79:DT79,">0.5")+1)) -> 0 | F93: =IF(D93=0,0,SUM(E77:DT77)+SUM(E78:DT78)+DT79-D93) -> 0
B95: Si una deuda muestra "Más de 120", el pago total no alcanza a cubrirla en 10 años (normal en hipotecarios). El detalle cuota a cuota va en la plantilla de créditos.

Sheet Flujo anual
B1: Flujo mes a mes
B2: Entradas, salidas, meses sin ingreso y destino del sobrante para el año del flujo. Pesos de hoy.
E4: =DATE(Supuestos!$C$14,1,1) -> 46388 | F4: =DATE(Supuestos!$C$14,2,1) -> 46419 | G4: =DATE(Supuestos!$C$14,3,1) -> 46447 | H4: =DATE(Supuestos!$C$14,4,1) -> 46478 | I4: =DATE(Supuestos!$C$14,5,1) -> 46508 | J4: =DATE(Supuestos!$C$14,6,1) -> 46539 | K4: =DATE(Supuestos!$C$14,7,1) -> 46569 | L4: =DATE(Supuestos!$C$14,8,1) -> 46600 | M4: =DATE(Supuestos!$C$14,9,1) -> 46631 | N4: =DATE(Supuestos!$C$14,10,1) -> 46661 | O4: =DATE(Supuestos!$C$14,11,1) -> 46692 | P4: =DATE(Supuestos!$C$14,12,1) -> 46722
B5: Concepto | E5: Ene | F5: Feb | G5: Mar | H5: Abr | I5: May | J5: Jun | K5: Jul | L5: Ago | M5: Sep | N5: Oct | O5: Nov | P5: Dic | Q5: Total año
B6: ENTRADAS
B7: Ingresos laborales | E7: =SUMPRODUCT((Ingresos!$C$6:$C$13="Laboral")*Ingresos!$F$6:$F$13*Ingresos!G$6:G$13) -> 0 | F7: =SUMPRODUCT((Ingresos!$C$6:$C$13="Laboral")*Ingresos!$F$6:$F$13*Ingresos!H$6:H$13) -> 0 | G7: =SUMPRODUCT((Ingresos!$C$6:$C$13="Laboral")*Ingresos!$F$6:$F$13*Ingresos!I$6:I$13) -> 0 | H7: =SUMPRODUCT((Ingresos!$C$6:$C$13="Laboral")*Ingresos!$F$6:$F$13*Ingresos!J$6:J$13) -> 0 | I7: =SUMPRODUCT((Ingresos!$C$6:$C$13="Laboral")*Ingresos!$F$6:$F$13*Ingresos!K$6:K$13) -> 0 | J7: =SUMPRODUCT((Ingresos!$C$6:$C$13="Laboral")*Ingresos!$F$6:$F$13*Ingresos!L$6:L$13) -> 0 | K7: =SUMPRODUCT((Ingresos!$C$6:$C$13="Laboral")*Ingresos!$F$6:$F$13*Ingresos!M$6:M$13) -> 0 | L7: =SUMPRODUCT((Ingresos!$C$6:$C$13="Laboral")*Ingresos!$F$6:$F$13*Ingresos!N$6:N$13) -> 0 | ... P7: =SUMPRODUCT((Ingresos!$C$6:$C$13="Laboral")*Ingresos!$F$6:$F$13*Ingresos!R$6:R$13) -> 0 | Q7: =SUM(E7:P7) -> 0
B8: Rentas | E8: =SUMPRODUCT((Ingresos!$C$6:$C$13="Renta")*Ingresos!$F$6:$F$13*Ingresos!G$6:G$13) -> 0 | F8: =SUMPRODUCT((Ingresos!$C$6:$C$13="Renta")*Ingresos!$F$6:$F$13*Ingresos!H$6:H$13) -> 0 | G8: =SUMPRODUCT((Ingresos!$C$6:$C$13="Renta")*Ingresos!$F$6:$F$13*Ingresos!I$6:I$13) -> 0 | H8: =SUMPRODUCT((Ingresos!$C$6:$C$13="Renta")*Ingresos!$F$6:$F$13*Ingresos!J$6:J$13) -> 0 | I8: =SUMPRODUCT((Ingresos!$C$6:$C$13="Renta")*Ingresos!$F$6:$F$13*Ingresos!K$6:K$13) -> 0 | J8: =SUMPRODUCT((Ingresos!$C$6:$C$13="Renta")*Ingresos!$F$6:$F$13*Ingresos!L$6:L$13) -> 0 | K8: =SUMPRODUCT((Ingresos!$C$6:$C$13="Renta")*Ingresos!$F$6:$F$13*Ingresos!M$6:M$13) -> 0 | L8: =SUMPRODUCT((Ingresos!$C$6:$C$13="Renta")*Ingresos!$F$6:$F$13*Ingresos!N$6:N$13) -> 0 | ... P8: =SUMPRODUCT((Ingresos!$C$6:$C$13="Renta")*Ingresos!$F$6:$F$13*Ingresos!R$6:R$13) -> 0 | Q8: =SUM(E8:P8) -> 0
B9: Pensión | E9: =SUMPRODUCT((Ingresos!$C$6:$C$13="Pensión")*Ingresos!$F$6:$F$13*Ingresos!G$6:G$13) -> 0 | F9: =SUMPRODUCT((Ingresos!$C$6:$C$13="Pensión")*Ingresos!$F$6:$F$13*Ingresos!H$6:H$13) -> 0 | G9: =SUMPRODUCT((Ingresos!$C$6:$C$13="Pensión")*Ingresos!$F$6:$F$13*Ingresos!I$6:I$13) -> 0 | H9: =SUMPRODUCT((Ingresos!$C$6:$C$13="Pensión")*Ingresos!$F$6:$F$13*Ingresos!J$6:J$13) -> 0 | I9: =SUMPRODUCT((Ingresos!$C$6:$C$13="Pensión")*Ingresos!$F$6:$F$13*Ingresos!K$6:K$13) -> 0 | J9: =SUMPRODUCT((Ingresos!$C$6:$C$13="Pensión")*Ingresos!$F$6:$F$13*Ingresos!L$6:L$13) -> 0 | K9: =SUMPRODUCT((Ingresos!$C$6:$C$13="Pensión")*Ingresos!$F$6:$F$13*Ingresos!M$6:M$13) -> 0 | L9: =SUMPRODUCT((Ingresos!$C$6:$C$13="Pensión")*Ingresos!$F$6:$F$13*Ingresos!N$6:N$13) -> 0 | ... P9: =SUMPRODUCT((Ingresos!$C$6:$C$13="Pensión")*Ingresos!$F$6:$F$13*Ingresos!R$6:R$13) -> 0 | Q9: =SUM(E9:P9) -> 0
B10: Otros ingresos | E10: =SUMPRODUCT((Ingresos!$C$6:$C$13="Otro")*Ingresos!$F$6:$F$13*Ingresos!G$6:G$13) -> 0 | F10: =SUMPRODUCT((Ingresos!$C$6:$C$13="Otro")*Ingresos!$F$6:$F$13*Ingresos!H$6:H$13) -> 0 | G10: =SUMPRODUCT((Ingresos!$C$6:$C$13="Otro")*Ingresos!$F$6:$F$13*Ingresos!I$6:I$13) -> 0 | H10: =SUMPRODUCT((Ingresos!$C$6:$C$13="Otro")*Ingresos!$F$6:$F$13*Ingresos!J$6:J$13) -> 0 | I10: =SUMPRODUCT((Ingresos!$C$6:$C$13="Otro")*Ingresos!$F$6:$F$13*Ingresos!K$6:K$13) -> 0 | J10: =SUMPRODUCT((Ingresos!$C$6:$C$13="Otro")*Ingresos!$F$6:$F$13*Ingresos!L$6:L$13) -> 0 | K10: =SUMPRODUCT((Ingresos!$C$6:$C$13="Otro")*Ingresos!$F$6:$F$13*Ingresos!M$6:M$13) -> 0 | L10: =SUMPRODUCT((Ingresos!$C$6:$C$13="Otro")*Ingresos!$F$6:$F$13*Ingresos!N$6:N$13) -> 0 | ... P10: =SUMPRODUCT((Ingresos!$C$6:$C$13="Otro")*Ingresos!$F$6:$F$13*Ingresos!R$6:R$13) -> 0 | Q10: =SUM(E10:P10) -> 0
B11: Total entradas | E11: =SUM(E7:E10) -> 0 | F11: =SUM(F7:F10) -> 0 | G11: =SUM(G7:G10) -> 0 | H11: =SUM(H7:H10) -> 0 | I11: =SUM(I7:I10) -> 0 | J11: =SUM(J7:J10) -> 0 | K11: =SUM(K7:K10) -> 0 | L11: =SUM(L7:L10) -> 0 | ... P11: =SUM(P7:P10) -> 0 | Q11: =SUM(E11:P11) -> 0
B12: SALIDAS
B13: Seguridad social | E13: =Presupuesto!$I$96*Ingresos!G$17 -> 0 | F13: =Presupuesto!$I$96*Ingresos!H$17 -> 0 | G13: =Presupuesto!$I$96*Ingresos!I$17 -> 0 | H13: =Presupuesto!$I$96*Ingresos!J$17 -> 0 | I13: =Presupuesto!$I$96*Ingresos!K$17 -> 0 | J13: =Presupuesto!$I$96*Ingresos!L$17 -> 0 | K13: =Presupuesto!$I$96*Ingresos!M$17 -> 0 | L13: =Presupuesto!$I$96*Ingresos!N$17 -> 0 | ... P13: =Presupuesto!$I$96*Ingresos!R$17 -> 0 | Q13: =SUM(E13:P13) -> 0
B14: Pagos directos | E14: =Presupuesto!$I$90 -> 0 | F14: =Presupuesto!$I$90 -> 0 | G14: =Presupuesto!$I$90 -> 0 | H14: =Presupuesto!$I$90 -> 0 | I14: =Presupuesto!$I$90 -> 0 | J14: =Presupuesto!$I$90 -> 0 | K14: =Presupuesto!$I$90 -> 0 | L14: =Presupuesto!$I$90 -> 0 | ... P14: =Presupuesto!$I$90 -> 0 | Q14: =SUM(E14:P14) -> 0
B15: Aportes a bolsillos | E15: =Presupuesto!$I$91 -> 0 | F15: =Presupuesto!$I$91 -> 0 | G15: =Presupuesto!$I$91 -> 0 | H15: =Presupuesto!$I$91 -> 0 | I15: =Presupuesto!$I$91 -> 0 | J15: =Presupuesto!$I$91 -> 0 | K15: =Presupuesto!$I$91 -> 0 | L15: =Presupuesto!$I$91 -> 0 | ... P15: =Presupuesto!$I$91 -> 0 | Q15: =SUM(E15:P15) -> 0
B16: Cuotas de deudas | E16: =Presupuesto!$I$93 -> 0 | F16: =Presupuesto!$I$93 -> 0 | G16: =Presupuesto!$I$93 -> 0 | H16: =Presupuesto!$I$93 -> 0 | I16: =Presupuesto!$I$93 -> 0 | J16: =Presupuesto!$I$93 -> 0 | K16: =Presupuesto!$I$93 -> 0 | L16: =Presupuesto!$I$93 -> 0 | ... P16: =Presupuesto!$I$93 -> 0 | Q16: =SUM(E16:P16) -> 0
B17: Ahorro programado | E17: =Presupuesto!$I$94 -> 0 | F17: =Presupuesto!$I$94 -> 0 | G17: =Presupuesto!$I$94 -> 0 | H17: =Presupuesto!$I$94 -> 0 | I17: =Presupuesto!$I$94 -> 0 | J17: =Presupuesto!$I$94 -> 0 | K17: =Presupuesto!$I$94 -> 0 | L17: =Presupuesto!$I$94 -> 0 | ... P17: =Presupuesto!$I$94 -> 0 | Q17: =SUM(E17:P17) -> 0
B18: Total salidas | E18: =SUM(E13:E17) -> 0 | F18: =SUM(F13:F17) -> 0 | G18: =SUM(G13:G17) -> 0 | H18: =SUM(H13:H17) -> 0 | I18: =SUM(I13:I17) -> 0 | J18: =SUM(J13:J17) -> 0 | K18: =SUM(K13:K17) -> 0 | L18: =SUM(L13:L17) -> 0 | ... P18: =SUM(P13:P17) -> 0 | Q18: =SUM(E18:P18) -> 0
B19: Balance del mes | E19: =E11-E18 -> 0 | F19: =F11-F18 -> 0 | G19: =G11-G18 -> 0 | H19: =H11-H18 -> 0 | I19: =I11-I18 -> 0 | J19: =J11-J18 -> 0 | K19: =K11-K18 -> 0 | L19: =L11-L18 -> 0 | ... P19: =P11-P18 -> 0 | Q19: =SUM(E19:P19) -> 0 | S19: Meses sin ingreso (cálculo) | T19: Valor
B20: Uso del bolsillo de meses sin ingreso | E20: =MAX(0,-E19)*$T$27 -> 0 | F20: =MAX(0,-F19)*$T$27 -> 0 | G20: =MAX(0,-G19)*$T$27 -> 0 | H20: =MAX(0,-H19)*$T$27 -> 0 | I20: =MAX(0,-I19)*$T$27 -> 0 | J20: =MAX(0,-J19)*$T$27 -> 0 | K20: =MAX(0,-K19)*$T$27 -> 0 | L20: =MAX(0,-L19)*$T$27 -> 0 | ... P20: =MAX(0,-P19)*$T$27 -> 0 | Q20: =SUM(E20:P20) -> 0 | S20: Faltante total de los meses en rojo | T20: =-SUMIF(E19:P19,"<0") -> 0
B21: Aporte al bolsillo de meses sin ingreso | E21: =IF(E19>0,IF($T$24>=$T$23,$T$23,IF($T$21=0,0,$T$26*E19/$T$21)),0) -> 0 | F21: =IF(F19>0,IF($T$24>=$T$23,$T$23,IF($T$21=0,0,$T$26*F19/$T$21)),0) -> 0 | G21: =IF(G19>0,IF($T$24>=$T$23,$T$23,IF($T$21=0,0,$T$26*G19/$T$21)),0) -> 0 | H21: =IF(H19>0,IF($T$24>=$T$23,$T$23,IF($T$21=0,0,$T$26*H19/$T$21)),0) -> 0 | I21: =IF(I19>0,IF($T$24>=$T$23,$T$23,IF($T$21=0,0,$T$26*I19/$T$21)),0) -> 0 | J21: =IF(J19>0,IF($T$24>=$T$23,$T$23,IF($T$21=0,0,$T$26*J19/$T$21)),0) -> 0 | K21: =IF(K19>0,IF($T$24>=$T$23,$T$23,IF($T$21=0,0,$T$26*K19/$T$21)),0) -> 0 | L21: =IF(L19>0,IF($T$24>=$T$23,$T$23,IF($T$21=0,0,$T$26*L19/$T$21)),0) -> 0 | ... P21: =IF(P19>0,IF($T$24>=$T$23,$T$23,IF($T$21=0,0,$T$26*P19/$T$21)),0) -> 0 | Q21: =SUM(E21:P21) -> 0 | S21: Suma de balances positivos | T21: =SUMIF(E19:P19,">0") -> 0
B22: Sobrante del mes | E22: =E19+E20-E21 -> 0 | F22: =F19+F20-F21 -> 0 | G22: =G19+G20-G21 -> 0 | H22: =H19+H20-H21 -> 0 | I22: =I19+I20-I21 -> 0 | J22: =J19+J20-J21 -> 0 | K22: =K19+K20-K21 -> 0 | L22: =L19+L20-L21 -> 0 | ... P22: =P19+P20-P21 -> 0 | Q22: =SUM(E22:P22) -> 0 | S22: Meses con balance positivo | T22: =COUNTIF(E19:P19,">0") -> 0
B23: DESTINO DEL SOBRANTE | S23: Aporte igual por mes positivo | T23: =IF(T22=0,0,T26/T22) -> 0
B24: Abono extra a deudas | E24: =IF(Deudas!$C$23="Sí",MAX(0,E22)*Supuestos!$C$25,0) -> 0 | F24: =IF(Deudas!$C$23="Sí",MAX(0,F22)*Supuestos!$C$25,0) -> 0 | G24: =IF(Deudas!$C$23="Sí",MAX(0,G22)*Supuestos!$C$25,0) -> 0 | H24: =IF(Deudas!$C$23="Sí",MAX(0,H22)*Supuestos!$C$25,0) -> 0 | I24: =IF(Deudas!$C$23="Sí",MAX(0,I22)*Supuestos!$C$25,0) -> 0 | J24: =IF(Deudas!$C$23="Sí",MAX(0,J22)*Supuestos!$C$25,0) -> 0 | K24: =IF(Deudas!$C$23="Sí",MAX(0,K22)*Supuestos!$C$25,0) -> 0 | L24: =IF(Deudas!$C$23="Sí",MAX(0,L22)*Supuestos!$C$25,0) -> 0 | ... P24: =IF(Deudas!$C$23="Sí",MAX(0,P22)*Supuestos!$C$25,0) -> 0 | Q24: =SUM(E24:P24) -> 0 | S24: Menor balance positivo | T24: =IF(T22=0,0,_xlfn.MINIFS(E19:P19,E19:P19,">0")) -> 0
B25: Inversión | E25: =IF(Deudas!$C$23="Sí",0,MAX(0,E22)*Supuestos!$C$42) -> 0 | F25: =IF(Deudas!$C$23="Sí",0,MAX(0,F22)*Supuestos!$C$42) -> 0 | G25: =IF(Deudas!$C$23="Sí",0,MAX(0,G22)*Supuestos!$C$42) -> 0 | H25: =IF(Deudas!$C$23="Sí",0,MAX(0,H22)*Supuestos!$C$42) -> 0 | I25: =IF(Deudas!$C$23="Sí",0,MAX(0,I22)*Supuestos!$C$42) -> 0 | J25: =IF(Deudas!$C$23="Sí",0,MAX(0,J22)*Supuestos!$C$42) -> 0 | K25: =IF(Deudas!$C$23="Sí",0,MAX(0,K22)*Supuestos!$C$42) -> 0 | L25: =IF(Deudas!$C$23="Sí",0,MAX(0,L22)*Supuestos!$C$42) -> 0 | ... P25: =IF(Deudas!$C$23="Sí",0,MAX(0,P22)*Supuestos!$C$42) -> 0 | Q25: =SUM(E25:P25) -> 0 | S25: Método de aporte | T25: =IF(T20=0,"No aplica",IF(T24>=T23,"Aporte igual","Aporte proporcional")) -> No aplica
B26: Margen libre | E26: =E22-E24-E25 -> 0 | F26: =F22-F24-F25 -> 0 | G26: =G22-G24-G25 -> 0 | H26: =H22-H24-H25 -> 0 | I26: =I22-I24-I25 -> 0 | J26: =J22-J24-J25 -> 0 | K26: =K22-K24-K25 -> 0 | L26: =L22-L24-L25 -> 0 | ... P26: =P22-P24-P25 -> 0 | Q26: =SUM(E26:P26) -> 0 | S26: Faltante que alcanza a cubrirse | T26: =MIN(T20,T21) -> 0
B27: CUENTAS POR COBRAR | S27: Cobertura del faltante | T27: =IF(T20=0,1,MIN(1,T21/T20)) -> 1
B28: Abonos recibidos | E28: =IF(AND(ISNUMBER(Supuestos!$J$46),(Supuestos!$C$14*12+1)>=Supuestos!$J$46,(Supuestos!$C$14*12+1)<=Supuestos!$K$46),N(Supuestos!$D$46),0)+IF(AND(ISNUMBER(Supuestos!$J$47),(Supuestos!$C$14*12+1)>=Supuestos!$J$47,(Supuestos!$C$14*12+1)<=Supuestos!$K$47),N(Supuestos!$D$47),0)+IF(AND(ISNUMBER(Supuestos!$J$48),(Supuestos!$C$14*12+1)>=Supuestos!$J$48,(Supuestos!$C$14*12+1)<=Supuestos!$K$48),N(Supuestos!$D$48),0) -> 0 | F28: =IF(AND(ISNUMBER(Supuestos!$J$46),(Supuestos!$C$14*12+2)>=Supuestos!$J$46,(Supuestos!$C$14*12+2)<=Supuestos!$K$46),N(Supuestos!$D$46),0)+IF(AND(ISNUMBER(Supuestos!$J$47),(Supuestos!$C$14*12+2)>=Supuestos!$J$47,(Supuestos!$C$14*12+2)<=Supuestos!$K$47),N(Supuestos!$D$47),0)+IF(AND(ISNUMBER(Supuestos!$J$48),(Supuestos!$C$14*12+2)>=Supuestos!$J$48,(Supuestos!$C$14*12+2)<=Supuestos!$K$48),N(Supuestos!$D$48),0) -> 0 | G28: =IF(AND(ISNUMBER(Supuestos!$J$46),(Supuestos!$C$14*12+3)>=Supuestos!$J$46,(Supuestos!$C$14*12+3)<=Supuestos!$K$46),N(Supuestos!$D$46),0)+IF(AND(ISNUMBER(Supuestos!$J$47),(Supuestos!$C$14*12+3)>=Supuestos!$J$47,(Supuestos!$C$14*12+3)<=Supuestos!$K$47),N(Supuestos!$D$47),0)+IF(AND(ISNUMBER(Supuestos!$J$48),(Supuestos!$C$14*12+3)>=Supuestos!$J$48,(Supuestos!$C$14*12+3)<=Supuestos!$K$48),N(Supuestos!$D$48),0) -> 0 | H28: =IF(AND(ISNUMBER(Supuestos!$J$46),(Supuestos!$C$14*12+4)>=Supuestos!$J$46,(Supuestos!$C$14*12+4)<=Supuestos!$K$46),N(Supuestos!$D$46),0)+IF(AND(ISNUMBER(Supuestos!$J$47),(Supuestos!$C$14*12+4)>=Supuestos!$J$47,(Supuestos!$C$14*12+4)<=Supuestos!$K$47),N(Supuestos!$D$47),0)+IF(AND(ISNUMBER(Supuestos!$J$48),(Supuestos!$C$14*12+4)>=Supuestos!$J$48,(Supuestos!$C$14*12+4)<=Supuestos!$K$48),N(Supuestos!$D$48),0) -> 0 | I28: =IF(AND(ISNUMBER(Supuestos!$J$46),(Supuestos!$C$14*12+5)>=Supuestos!$J$46,(Supuestos!$C$14*12+5)<=Supuestos!$K$46),N(Supuestos!$D$46),0)+IF(AND(ISNUMBER(Supuestos!$J$47),(Supuestos!$C$14*12+5)>=Supuestos!$J$47,(Supuestos!$C$14*12+5)<=Supuestos!$K$47),N(Supuestos!$D$47),0)+IF(AND(ISNUMBER(Supuestos!$J$48),(Supuestos!$C$14*12+5)>=Supuestos!$J$48,(Supuestos!$C$14*12+5)<=Supuestos!$K$48),N(Supuestos!$D$48),0) -> 0 | J28: =IF(AND(ISNUMBER(Supuestos!$J$46),(Supuestos!$C$14*12+6)>=Supuestos!$J$46,(Supuestos!$C$14*12+6)<=Supuestos!$K$46),N(Supuestos!$D$46),0)+IF(AND(ISNUMBER(Supuestos!$J$47),(Supuestos!$C$14*12+6)>=Supuestos!$J$47,(Supuestos!$C$14*12+6)<=Supuestos!$K$47),N(Supuestos!$D$47),0)+IF(AND(ISNUMBER(Supuestos!$J$48),(Supuestos!$C$14*12+6)>=Supuestos!$J$48,(Supuestos!$C$14*12+6)<=Supuestos!$K$48),N(Supuestos!$D$48),0) -> 0 | K28: =IF(AND(ISNUMBER(Supuestos!$J$46),(Supuestos!$C$14*12+7)>=Supuestos!$J$46,(Supuestos!$C$14*12+7)<=Supuestos!$K$46),N(Supuestos!$D$46),0)+IF(AND(ISNUMBER(Supuestos!$J$47),(Supuestos!$C$14*12+7)>=Supuestos!$J$47,(Supuestos!$C$14*12+7)<=Supuestos!$K$47),N(Supuestos!$D$47),0)+IF(AND(ISNUMBER(Supuestos!$J$48),(Supuestos!$C$14*12+7)>=Supuestos!$J$48,(Supuestos!$C$14*12+7)<=Supuestos!$K$48),N(Supuestos!$D$48),0) -> 0 | L28: =IF(AND(ISNUMBER(Supuestos!$J$46),(Supuestos!$C$14*12+8)>=Supuestos!$J$46,(Supuestos!$C$14*12+8)<=Supuestos!$K$46),N(Supuestos!$D$46),0)+IF(AND(ISNUMBER(Supuestos!$J$47),(Supuestos!$C$14*12+8)>=Supuestos!$J$47,(Supuestos!$C$14*12+8)<=Supuestos!$K$47),N(Supuestos!$D$47),0)+IF(AND(ISNUMBER(Supuestos!$J$48),(Supuestos!$C$14*12+8)>=Supuestos!$J$48,(Supuestos!$C$14*12+8)<=Supuestos!$K$48),N(Supuestos!$D$48),0) -> 0 | M28: =IF(AND(ISNUMBER(Supuestos!$J$46),(Supuestos!$C$14*12+9)>=Supuestos!$J$46,(Supuestos!$C$14*12+9)<=Supuestos!$K$46),N(Supuestos!$D$46),0)+IF(AND(ISNUMBER(Supuestos!$J$47),(Supuestos!$C$14*12+9)>=Supuestos!$J$47,(Supuestos!$C$14*12+9)<=Supuestos!$K$47),N(Supuestos!$D$47),0)+IF(AND(ISNUMBER(Supuestos!$J$48),(Supuestos!$C$14*12+9)>=Supuestos!$J$48,(Supuestos!$C$14*12+9)<=Supuestos!$K$48),N(Supuestos!$D$48),0) -> 0 | N28: =IF(AND(ISNUMBER(Supuestos!$J$46),(Supuestos!$C$14*12+10)>=Supuestos!$J$46,(Supuestos!$C$14*12+10)<=Supuestos!$K$46),N(Supuestos!$D$46),0)+IF(AND(ISNUMBER(Supuestos!$J$47),(Supuestos!$C$14*12+10)>=Supuestos!$J$47,(Supuestos!$C$14*12+10)<=Supuestos!$K$47),N(Supuestos!$D$47),0)+IF(AND(ISNUMBER(Supuestos!$J$48),(Supuestos!$C$14*12+10)>=Supuestos!$J$48,(Supuestos!$C$14*12+10)<=Supuestos!$K$48),N(Supuestos!$D$48),0) -> 0 | O28: =IF(AND(ISNUMBER(Supuestos!$J$46),(Supuestos!$C$14*12+11)>=Supuestos!$J$46,(Supuestos!$C$14*12+11)<=Supuestos!$K$46),N(Supuestos!$D$46),0)+IF(AND(ISNUMBER(Supuestos!$J$47),(Supuestos!$C$14*12+11)>=Supuestos!$J$47,(Supuestos!$C$14*12+11)<=Supuestos!$K$47),N(Supuestos!$D$47),0)+IF(AND(ISNUMBER(Supuestos!$J$48),(Supuestos!$C$14*12+11)>=Supuestos!$J$48,(Supuestos!$C$14*12+11)<=Supuestos!$K$48),N(Supuestos!$D$48),0) -> 0 | P28: =IF(AND(ISNUMBER(Supuestos!$J$46),(Supuestos!$C$14*12+12)>=Supuestos!$J$46,(Supuestos!$C$14*12+12)<=Supuestos!$K$46),N(Supuestos!$D$46),0)+IF(AND(ISNUMBER(Supuestos!$J$47),(Supuestos!$C$14*12+12)>=Supuestos!$J$47,(Supuestos!$C$14*12+12)<=Supuestos!$K$47),N(Supuestos!$D$47),0)+IF(AND(ISNUMBER(Supuestos!$J$48),(Supuestos!$C$14*12+12)>=Supuestos!$J$48,(Supuestos!$C$14*12+12)<=Supuestos!$K$48),N(Supuestos!$D$48),0) -> 0 | Q28: =SUM(E28:P28) -> 0
B29: Abonos a deudas | E29: =IF(Deudas!$C$23="Sí",E28,0) -> 0 | F29: =IF(Deudas!$C$23="Sí",F28,0) -> 0 | G29: =IF(Deudas!$C$23="Sí",G28,0) -> 0 | H29: =IF(Deudas!$C$23="Sí",H28,0) -> 0 | I29: =IF(Deudas!$C$23="Sí",I28,0) -> 0 | J29: =IF(Deudas!$C$23="Sí",J28,0) -> 0 | K29: =IF(Deudas!$C$23="Sí",K28,0) -> 0 | L29: =IF(Deudas!$C$23="Sí",L28,0) -> 0 | ... P29: =IF(Deudas!$C$23="Sí",P28,0) -> 0 | Q29: =SUM(E29:P29) -> 0
B30: Abonos a inversión | E30: =IF(Deudas!$C$23="Sí",0,IF(AND(ISNUMBER(Supuestos!$J$46),(Supuestos!$C$14*12+1)>=Supuestos!$J$46,(Supuestos!$C$14*12+1)<=Supuestos!$K$46),N(Supuestos!$D$46)*N(Supuestos!$H$46),0)+IF(AND(ISNUMBER(Supuestos!$J$47),(Supuestos!$C$14*12+1)>=Supuestos!$J$47,(Supuestos!$C$14*12+1)<=Supuestos!$K$47),N(Supuestos!$D$47)*N(Supuestos!$H$47),0)+IF(AND(ISNUMBER(Supuestos!$J$48),(Supuestos!$C$14*12+1)>=Supuestos!$J$48,(Supuestos!$C$14*12+1)<=Supuestos!$K$48),N(Supuestos!$D$48)*N(Supuestos!$H$48),0)) -> 0 | F30: =IF(Deudas!$C$23="Sí",0,IF(AND(ISNUMBER(Supuestos!$J$46),(Supuestos!$C$14*12+2)>=Supuestos!$J$46,(Supuestos!$C$14*12+2)<=Supuestos!$K$46),N(Supuestos!$D$46)*N(Supuestos!$H$46),0)+IF(AND(ISNUMBER(Supuestos!$J$47),(Supuestos!$C$14*12+2)>=Supuestos!$J$47,(Supuestos!$C$14*12+2)<=Supuestos!$K$47),N(Supuestos!$D$47)*N(Supuestos!$H$47),0)+IF(AND(ISNUMBER(Supuestos!$J$48),(Supuestos!$C$14*12+2)>=Supuestos!$J$48,(Supuestos!$C$14*12+2)<=Supuestos!$K$48),N(Supuestos!$D$48)*N(Supuestos!$H$48),0)) -> 0 | G30: =IF(Deudas!$C$23="Sí",0,IF(AND(ISNUMBER(Supuestos!$J$46),(Supuestos!$C$14*12+3)>=Supuestos!$J$46,(Supuestos!$C$14*12+3)<=Supuestos!$K$46),N(Supuestos!$D$46)*N(Supuestos!$H$46),0)+IF(AND(ISNUMBER(Supuestos!$J$47),(Supuestos!$C$14*12+3)>=Supuestos!$J$47,(Supuestos!$C$14*12+3)<=Supuestos!$K$47),N(Supuestos!$D$47)*N(Supuestos!$H$47),0)+IF(AND(ISNUMBER(Supuestos!$J$48),(Supuestos!$C$14*12+3)>=Supuestos!$J$48,(Supuestos!$C$14*12+3)<=Supuestos!$K$48),N(Supuestos!$D$48)*N(Supuestos!$H$48),0)) -> 0 | H30: =IF(Deudas!$C$23="Sí",0,IF(AND(ISNUMBER(Supuestos!$J$46),(Supuestos!$C$14*12+4)>=Supuestos!$J$46,(Supuestos!$C$14*12+4)<=Supuestos!$K$46),N(Supuestos!$D$46)*N(Supuestos!$H$46),0)+IF(AND(ISNUMBER(Supuestos!$J$47),(Supuestos!$C$14*12+4)>=Supuestos!$J$47,(Supuestos!$C$14*12+4)<=Supuestos!$K$47),N(Supuestos!$D$47)*N(Supuestos!$H$47),0)+IF(AND(ISNUMBER(Supuestos!$J$48),(Supuestos!$C$14*12+4)>=Supuestos!$J$48,(Supuestos!$C$14*12+4)<=Supuestos!$K$48),N(Supuestos!$D$48)*N(Supuestos!$H$48),0)) -> 0 | I30: =IF(Deudas!$C$23="Sí",0,IF(AND(ISNUMBER(Supuestos!$J$46),(Supuestos!$C$14*12+5)>=Supuestos!$J$46,(Supuestos!$C$14*12+5)<=Supuestos!$K$46),N(Supuestos!$D$46)*N(Supuestos!$H$46),0)+IF(AND(ISNUMBER(Supuestos!$J$47),(Supuestos!$C$14*12+5)>=Supuestos!$J$47,(Supuestos!$C$14*12+5)<=Supuestos!$K$47),N(Supuestos!$D$47)*N(Supuestos!$H$47),0)+IF(AND(ISNUMBER(Supuestos!$J$48),(Supuestos!$C$14*12+5)>=Supuestos!$J$48,(Supuestos!$C$14*12+5)<=Supuestos!$K$48),N(Supuestos!$D$48)*N(Supuestos!$H$48),0)) -> 0 | J30: =IF(Deudas!$C$23="Sí",0,IF(AND(ISNUMBER(Supuestos!$J$46),(Supuestos!$C$14*12+6)>=Supuestos!$J$46,(Supuestos!$C$14*12+6)<=Supuestos!$K$46),N(Supuestos!$D$46)*N(Supuestos!$H$46),0)+IF(AND(ISNUMBER(Supuestos!$J$47),(Supuestos!$C$14*12+6)>=Supuestos!$J$47,(Supuestos!$C$14*12+6)<=Supuestos!$K$47),N(Supuestos!$D$47)*N(Supuestos!$H$47),0)+IF(AND(ISNUMBER(Supuestos!$J$48),(Supuestos!$C$14*12+6)>=Supuestos!$J$48,(Supuestos!$C$14*12+6)<=Supuestos!$K$48),N(Supuestos!$D$48)*N(Supuestos!$H$48),0)) -> 0 | K30: =IF(Deudas!$C$23="Sí",0,IF(AND(ISNUMBER(Supuestos!$J$46),(Supuestos!$C$14*12+7)>=Supuestos!$J$46,(Supuestos!$C$14*12+7)<=Supuestos!$K$46),N(Supuestos!$D$46)*N(Supuestos!$H$46),0)+IF(AND(ISNUMBER(Supuestos!$J$47),(Supuestos!$C$14*12+7)>=Supuestos!$J$47,(Supuestos!$C$14*12+7)<=Supuestos!$K$47),N(Supuestos!$D$47)*N(Supuestos!$H$47),0)+IF(AND(ISNUMBER(Supuestos!$J$48),(Supuestos!$C$14*12+7)>=Supuestos!$J$48,(Supuestos!$C$14*12+7)<=Supuestos!$K$48),N(Supuestos!$D$48)*N(Supuestos!$H$48),0)) -> 0 | L30: =IF(Deudas!$C$23="Sí",0,IF(AND(ISNUMBER(Supuestos!$J$46),(Supuestos!$C$14*12+8)>=Supuestos!$J$46,(Supuestos!$C$14*12+8)<=Supuestos!$K$46),N(Supuestos!$D$46)*N(Supuestos!$H$46),0)+IF(AND(ISNUMBER(Supuestos!$J$47),(Supuestos!$C$14*12+8)>=Supuestos!$J$47,(Supuestos!$C$14*12+8)<=Supuestos!$K$47),N(Supuestos!$D$47)*N(Supuestos!$H$47),0)+IF(AND(ISNUMBER(Supuestos!$J$48),(Supuestos!$C$14*12+8)>=Supuestos!$J$48,(Supuestos!$C$14*12+8)<=Supuestos!$K$48),N(Supuestos!$D$48)*N(Supuestos!$H$48),0)) -> 0 | M30: =IF(Deudas!$C$23="Sí",0,IF(AND(ISNUMBER(Supuestos!$J$46),(Supuestos!$C$14*12+9)>=Supuestos!$J$46,(Supuestos!$C$14*12+9)<=Supuestos!$K$46),N(Supuestos!$D$46)*N(Supuestos!$H$46),0)+IF(AND(ISNUMBER(Supuestos!$J$47),(Supuestos!$C$14*12+9)>=Supuestos!$J$47,(Supuestos!$C$14*12+9)<=Supuestos!$K$47),N(Supuestos!$D$47)*N(Supuestos!$H$47),0)+IF(AND(ISNUMBER(Supuestos!$J$48),(Supuestos!$C$14*12+9)>=Supuestos!$J$48,(Supuestos!$C$14*12+9)<=Supuestos!$K$48),N(Supuestos!$D$48)*N(Supuestos!$H$48),0)) -> 0 | N30: =IF(Deudas!$C$23="Sí",0,IF(AND(ISNUMBER(Supuestos!$J$46),(Supuestos!$C$14*12+10)>=Supuestos!$J$46,(Supuestos!$C$14*12+10)<=Supuestos!$K$46),N(Supuestos!$D$46)*N(Supuestos!$H$46),0)+IF(AND(ISNUMBER(Supuestos!$J$47),(Supuestos!$C$14*12+10)>=Supuestos!$J$47,(Supuestos!$C$14*12+10)<=Supuestos!$K$47),N(Supuestos!$D$47)*N(Supuestos!$H$47),0)+IF(AND(ISNUMBER(Supuestos!$J$48),(Supuestos!$C$14*12+10)>=Supuestos!$J$48,(Supuestos!$C$14*12+10)<=Supuestos!$K$48),N(Supuestos!$D$48)*N(Supuestos!$H$48),0)) -> 0 | O30: =IF(Deudas!$C$23="Sí",0,IF(AND(ISNUMBER(Supuestos!$J$46),(Supuestos!$C$14*12+11)>=Supuestos!$J$46,(Supuestos!$C$14*12+11)<=Supuestos!$K$46),N(Supuestos!$D$46)*N(Supuestos!$H$46),0)+IF(AND(ISNUMBER(Supuestos!$J$47),(Supuestos!$C$14*12+11)>=Supuestos!$J$47,(Supuestos!$C$14*12+11)<=Supuestos!$K$47),N(Supuestos!$D$47)*N(Supuestos!$H$47),0)+IF(AND(ISNUMBER(Supuestos!$J$48),(Supuestos!$C$14*12+11)>=Supuestos!$J$48,(Supuestos!$C$14*12+11)<=Supuestos!$K$48),N(Supuestos!$D$48)*N(Supuestos!$H$48),0)) -> 0 | P30: =IF(Deudas!$C$23="Sí",0,IF(AND(ISNUMBER(Supuestos!$J$46),(Supuestos!$C$14*12+12)>=Supuestos!$J$46,(Supuestos!$C$14*12+12)<=Supuestos!$K$46),N(Supuestos!$D$46)*N(Supuestos!$H$46),0)+IF(AND(ISNUMBER(Supuestos!$J$47),(Supuestos!$C$14*12+12)>=Supuestos!$J$47,(Supuestos!$C$14*12+12)<=Supuestos!$K$47),N(Supuestos!$D$47)*N(Supuestos!$H$47),0)+IF(AND(ISNUMBER(Supuestos!$J$48),(Supuestos!$C$14*12+12)>=Supuestos!$J$48,(Supuestos!$C$14*12+12)<=Supuestos!$K$48),N(Supuestos!$D$48)*N(Supuestos!$H$48),0)) -> 0 | Q30: =SUM(E30:P30) -> 0
B31: Abonos libres | E31: =E28-E29-E30 -> 0 | F31: =F28-F29-F30 -> 0 | G31: =G28-G29-G30 -> 0 | H31: =H28-H29-H30 -> 0 | I31: =I28-I29-I30 -> 0 | J31: =J28-J29-J30 -> 0 | K31: =K28-K29-K30 -> 0 | L31: =L28-L29-L30 -> 0 | ... P31: =P28-P29-P30 -> 0 | Q31: =SUM(E31:P31) -> 0
B32: TOTALES
B33: Total a inversión | E33: =E25+E30 -> 0 | F33: =F25+F30 -> 0 | G33: =G25+G30 -> 0 | H33: =H25+H30 -> 0 | I33: =I25+I30 -> 0 | J33: =J25+J30 -> 0 | K33: =K25+K30 -> 0 | L33: =L25+L30 -> 0 | ... P33: =P25+P30 -> 0 | Q33: =SUM(E33:P33) -> 0
B34: Total extra a deudas | E34: =E24+E29 -> 0 | F34: =F24+F29 -> 0 | G34: =G24+G29 -> 0 | H34: =H24+H29 -> 0 | I34: =I24+I29 -> 0 | J34: =J24+J29 -> 0 | K34: =K24+K29 -> 0 | L34: =L24+L29 -> 0 | ... P34: =P24+P29 -> 0 | Q34: =SUM(E34:P34) -> 0
B36: =IF(T20>T21+0.5,"Alerta: el año cierra en déficit. Los meses con sobrante no alcanzan a cubrir los meses en rojo.","")
B37: El aporte al bolsillo se hace en los meses con balance positivo y se usa en los meses en rojo. Si todos los aportes caben, se aporta el mismo valor cada mes. Si el año no alcanza, la parte no cubierta queda como sobrante negativo.
B38: Con deuda cara, el sobrante y los abonos por cobrar van a deudas y no se invierte.

Sheet Bolsillos
B1: Bolsillos
B2: Aporte mensual a cada bolsillo y reparto del saldo actual. Los nombres de bolsillos se cambian en la hoja Listas.
B5: Bolsillo | C5: Qué guarda | D5: Meta anual | E5: Aporte mensual | F5: Cuándo se usa | G5: Saldo inicial sugerido | H5: Nota
B6: Fondo de emergencia | C6: Solo emergencias reales. | D6: ='Fondo emergencia'!$C$21 -> 0 | E6: =MAX(0,D6-G6)/12 -> 0 | F6: Solo emergencias | G6: =MIN(D6,$C$23) -> 0 | H6: Aporte para completarlo en 12 meses si hoy no alcanza.
B7: Meses sin ingreso | C7: Cubre los meses en rojo del flujo. | D7: ='Flujo anual'!$T$20 -> 0 | E7: ='Flujo anual'!$T$23 -> 0 | F7: Meses sin ingreso | G7: =MIN(D7,MAX(0,$C$23-G6)) -> 0 | H7: Aporte en los meses con sobrante (ver Flujo anual).
B8: =IF(Listas!$F$2="","",Listas!$F$2) -> Viajes | D8: =IF(B8="",0,SUMIFS(Presupuesto!$H$6:$H$87,Presupuesto!$K$6:$K$87,B8)) -> 0 | E8: =IF(B8="",0,SUMIFS(Presupuesto!$I$6:$I$87,Presupuesto!$K$6:$K$87,B8)) -> 0 | G8: 0
B9: =IF(Listas!$F$3="","",Listas!$F$3) -> Temporada | D9: =IF(B9="",0,SUMIFS(Presupuesto!$H$6:$H$87,Presupuesto!$K$6:$K$87,B9)) -> 0 | E9: =IF(B9="",0,SUMIFS(Presupuesto!$I$6:$I$87,Presupuesto!$K$6:$K$87,B9)) -> 0 | G9: 0
B10: =IF(Listas!$F$4="","",Listas!$F$4) -> Salud y cuidado | D10: =IF(B10="",0,SUMIFS(Presupuesto!$H$6:$H$87,Presupuesto!$K$6:$K$87,B10)) -> 0 | E10: =IF(B10="",0,SUMIFS(Presupuesto!$I$6:$I$87,Presupuesto!$K$6:$K$87,B10)) -> 0 | G10: 0
B11: =IF(Listas!$F$5="","",Listas!$F$5) -> Ropa | D11: =IF(B11="",0,SUMIFS(Presupuesto!$H$6:$H$87,Presupuesto!$K$6:$K$87,B11)) -> 0 | E11: =IF(B11="",0,SUMIFS(Presupuesto!$I$6:$I$87,Presupuesto!$K$6:$K$87,B11)) -> 0 | G11: 0
B12: =IF(Listas!$F$6="","",Listas!$F$6) -> Impuestos y trámites | D12: =IF(B12="",0,SUMIFS(Presupuesto!$H$6:$H$87,Presupuesto!$K$6:$K$87,B12)) -> 0 | E12: =IF(B12="",0,SUMIFS(Presupuesto!$I$6:$I$87,Presupuesto!$K$6:$K$87,B12)) -> 0 | G12: 0
B13: =IF(Listas!$F$7="","",Listas!$F$7) -> Hogar y mascotas | D13: =IF(B13="",0,SUMIFS(Presupuesto!$H$6:$H$87,Presupuesto!$K$6:$K$87,B13)) -> 0 | E13: =IF(B13="",0,SUMIFS(Presupuesto!$I$6:$I$87,Presupuesto!$K$6:$K$87,B13)) -> 0 | G13: 0
B14: =IF(Listas!$F$8="","",Listas!$F$8) -> Vehículo | D14: =IF(B14="",0,SUMIFS(Presupuesto!$H$6:$H$87,Presupuesto!$K$6:$K$87,B14)) -> 0 | E14: =IF(B14="",0,SUMIFS(Presupuesto!$I$6:$I$87,Presupuesto!$K$6:$K$87,B14)) -> 0 | G14: 0
B15: =IF(Listas!$F$9="","",Listas!$F$9) -> Educación | D15: =IF(B15="",0,SUMIFS(Presupuesto!$H$6:$H$87,Presupuesto!$K$6:$K$87,B15)) -> 0 | E15: =IF(B15="",0,SUMIFS(Presupuesto!$I$6:$I$87,Presupuesto!$K$6:$K$87,B15)) -> 0 | G15: 0
B16: =IF(Listas!$F$10="","",Listas!$F$10) -> Seguros | D16: =IF(B16="",0,SUMIFS(Presupuesto!$H$6:$H$87,Presupuesto!$K$6:$K$87,B16)) -> 0 | E16: =IF(B16="",0,SUMIFS(Presupuesto!$I$6:$I$87,Presupuesto!$K$6:$K$87,B16)) -> 0 | G16: 0
B17: =IF(Listas!$F$11="","",Listas!$F$11) -> Metas | D17: =IF(B17="",0,SUMIFS(Presupuesto!$H$6:$H$87,Presupuesto!$K$6:$K$87,B17)) -> 0 | E17: =IF(B17="",0,SUMIFS(Presupuesto!$I$6:$I$87,Presupuesto!$K$6:$K$87,B17)) -> 0 | G17: 0
B18: Total | D18: =SUM(D6:D17) -> 0 | E18: =SUM(E6:E17) -> 0 | G18: =SUM(G6:G17) -> 0
B20: Reparto del saldo actual
B21: Saldo líquido disponible (hoja Patrimonio) | C21: =Patrimonio!$C$33 -> 0
B22: Colchón en la cuenta operativa | C22: =Supuestos!$C$32 -> 0
B23: Disponible para repartir | C23: =MAX(0,C21-C22) -> 0
B24: Asignado a bolsillos | C24: =G18 -> 0
B25: Excedente | C25: =C23-C24 -> 0
B26: Abono único a deuda cara | C26: =IF(Deudas!$C$23="Sí",MAX(0,C25)*Supuestos!$C$25,0) -> 0
B27: Aporte único a inversión | C27: =IF(Deudas!$C$23="Sí",0,MAX(0,C25)*Supuestos!$C$26) -> 0
B28: Queda sin asignar | C28: =C25-C26-C27 -> 0
B29: Bolsillos con aporte (verificar límite del banco) | C29: =COUNTIF(E6:E17,">0") -> 0
B30: =IF(C25<-0.5,"Alerta: los saldos iniciales superan lo disponible. Ajusta la columna G.","")
B31: Orden del reparto: fondo de emergencia, meses sin ingreso y luego los saldos que escribas en la columna G (por ejemplo, gastos grandes cercanos).

Sheet Fondo emergencia
B1: Fondo de emergencia
B2: Se calcula sobre el gasto esencial y según los ingresos que se mantienen en cada escenario.
B5: Dato | C5: Valor | D5: Nota
B6: Gasto mensual promedio total | C6: =Presupuesto!$I$89 -> 0
B7: Gasto esencial mensual | C7: =Presupuesto!$I$95 -> 0 | D7: Lo marcado "Sí" en ¿Esencial? del Presupuesto.
B8: Ingreso laboral mensual promedio | C8: =Ingresos!$U$20 -> 0
B9: Rentas mensuales promedio | C9: =Ingresos!$U$21 -> 0
B10: Pensión mensual | C10: =Ingresos!$U$22 -> 0
B11: Otros ingresos mensuales | C11: =Ingresos!$U$23 -> 0
B13: Escenario | C13: Ingreso que se mantiene | D13: Faltante mensual | E13: Meses que cubre la meta
B14: A. Pierde el ingreso laboral | C14: =C9+C10+C11 -> 0 | D14: =MAX(0,$C$7-C14) -> 0 | E14: =IF(D14=0,"Cubierto por el ingreso",IF($C$21=0,0,$C$21/D14)) -> Cubierto por el ingreso
B15: B. Pierde las rentas | C15: =C8+C10+C11 -> 0 | D15: =MAX(0,$C$7-C15) -> 0 | E15: =IF(D15=0,"Cubierto por el ingreso",IF($C$21=0,0,$C$21/D15)) -> Cubierto por el ingreso
B16: C. Pierde laboral y rentas (peor caso) | C16: =C10 -> 0 | D16: =MAX(0,$C$7-C16) -> 0 | E16: =IF(D16=0,"Cubierto por el ingreso",IF($C$21=0,0,$C$21/D16)) -> Cubierto por el ingreso
B17: Meses de cobertura | C17: =Supuestos!$C$21 -> 3
B18: Meta por el peor caso | C18: =C17*D16 -> 0
B19: Mínimo (1 mes de gasto esencial) | C19: =C7 -> 0
B20: Meta completa | C20: =MAX(C18,C19) -> 0
B21: Meta vigente | C21: =IF(Deudas!$C$23="Sí",MIN(C20,C7),C20) -> 0 | D21: Con deuda cara: 1 mes de lo esencial; luego se paga la deuda y se completa el fondo.
B22: Comparación: 6 meses de gasto total | C22: =6*C6 -> 0
B23: Capital que se libera frente a esa regla | C23: =C22-C20 -> 0
B24: Saldo asignado hoy (hoja Bolsillos) | C24: =Bolsillos!$G$6 -> 0
B25: Avance frente a la meta completa | C25: =IF(C20=0,1,C24/C20) -> 1
B27: El fondo se guarda en una cuenta o bolsillo con liquidez inmediata, nunca en inversiones volátiles.

Sheet Metas
B1: Metas
B2: Metas con valor y fecha, o que se repiten cada cierto número de años. El aporte pasa solo al Presupuesto.
B5: Meta | C5: Bolsillo | D5: Valor ingresado | E5: ¿Usa calculadora de viaje? | F5: Valor usado | G5: Ya ahorrado | H5: Se repite cada (años) | I5: Fecha objetivo | J5: Meses restantes | K5: Aporte mensual | L5: Nota
E6: No | F6: =IF(E6="Sí",$E$30,N(D6)) -> 0 | J6: =IF(I6="","",IFERROR(MAX(1,DATEDIF(Supuestos!$C$12,I6,"m")),1)) | K6: =IF(B6="",0,IF(N(H6)>0,F6/(H6*12),IF(J6="",0,MAX(0,(F6-N(G6))/J6)))) -> 0
E7: No | F7: =IF(E7="Sí",$E$30,N(D7)) -> 0 | J7: =IF(I7="","",IFERROR(MAX(1,DATEDIF(Supuestos!$C$12,I7,"m")),1)) | K7: =IF(B7="",0,IF(N(H7)>0,F7/(H7*12),IF(J7="",0,MAX(0,(F7-N(G7))/J7)))) -> 0
E8: No | F8: =IF(E8="Sí",$E$30,N(D8)) -> 0 | J8: =IF(I8="","",IFERROR(MAX(1,DATEDIF(Supuestos!$C$12,I8,"m")),1)) | K8: =IF(B8="",0,IF(N(H8)>0,F8/(H8*12),IF(J8="",0,MAX(0,(F8-N(G8))/J8)))) -> 0
E9: No | F9: =IF(E9="Sí",$E$30,N(D9)) -> 0 | J9: =IF(I9="","",IFERROR(MAX(1,DATEDIF(Supuestos!$C$12,I9,"m")),1)) | K9: =IF(B9="",0,IF(N(H9)>0,F9/(H9*12),IF(J9="",0,MAX(0,(F9-N(G9))/J9)))) -> 0
E10: No | F10: =IF(E10="Sí",$E$30,N(D10)) -> 0 | J10: =IF(I10="","",IFERROR(MAX(1,DATEDIF(Supuestos!$C$12,I10,"m")),1)) | K10: =IF(B10="",0,IF(N(H10)>0,F10/(H10*12),IF(J10="",0,MAX(0,(F10-N(G10))/J10)))) -> 0
B11: Total | K11: =SUM(K6:K10) -> 0
B12: Meta que se repite (por ejemplo, un viaje cada 2 años): llena "Se repite cada" y deja la fecha vacía. Meta única: llena la fecha y lo ya ahorrado.
B13: Calculadora de viaje (en dólares)
B14: Concepto | C14: Valor unitario (USD) | D14: Cantidad | E14: Total USD | F14: Nota
B15: Tiquete ida y vuelta con maleta | D15: 1 | E15: =N(C15)*N(D15) -> 0 | F15: Buscar precios reales y actuales.
B16: Alojamiento por noche | D16: 7 | E16: =N(C16)*N(D16) -> 0 | F16: Cantidad = noches.
B17: Impuestos del alojamiento (%) | C17: 0 | E17: =E16*C17 -> 0
B18: Comida por día | D18: 7 | E18: =N(C18)*N(D18) -> 0 | F18: Cantidad = días.
B19: Transporte local | D19: 1 | E19: =N(C19)*N(D19) -> 0 | F19: Pases y taxis.
B20: Atracciones | D20: 1 | E20: =N(C20)*N(D20) -> 0
B21: Seguro de viaje | D21: 1 | E21: =N(C21)*N(D21) -> 0
B22: Compras y gastos varios | D22: 1 | E22: =N(C22)*N(D22) -> 0
B23: Subtotal | E23: =SUM(E15:E22) -> 0
B24: Colchón por tasa de cambio y comisiones (%) | C24: 0.05 | E24: =E23*C24 -> 0
B25: Total en dólares | E25: =E23+E24 -> 0
B26: Tasa de cambio | E26: =Supuestos!$C$17 -> 0
B27: Total en pesos | E27: =E25*N(E26) -> 0
B28: Trayecto nacional hasta el aeropuerto (pesos) | E28: 0
B29: Visa, si no la tiene (pesos) | E29: 0
B30: Total del viaje en pesos | E30: =E27+E28+E29 -> 0

Sheet Seguros
B1: Análisis de seguros
B2: Trasladar los riesgos grandes a pólizas. Escribe primas solo de seguros nuevos: los que ya se pagan van en el Presupuesto.
B5: Seguro | C5: Qué cubre | D5: Ojo: qué no cubre o qué revisar | E5: Prioridad típica | F5: ¿Lo tiene? | G5: Beneficiarios | H5: Prima anual cotizada | I5: Costo mensual
B6: Hogar para inmuebles | C6: Terremoto, incendio, inundación, daños y responsabilidad civil. | D6: Revisar qué cubre la póliza de la copropiedad. | E6: Alta si hay inmuebles | I6: =IF(F6="Sí",0,N(H6)/12) -> 0
B7: Arrendamiento | C7: Canon y administración si el arrendatario no paga. | D7: No cubre el inmueble desocupado. | E7: Alta si hay arriendos | I7: =IF(F7="Sí",0,N(H7)/12) -> 0
B8: Enfermedades graves | C8: Pago único al diagnóstico. | D8: Lista de enfermedades, preexistencias, carencias y edad máxima. | E8: Alta desde 45-50 años | I8: =IF(F8="Sí",0,N(H8)/12) -> 0
B9: Renta por hospitalización o incapacidad | C9: Valor diario mientras está hospitalizado o incapacitado. | D9: Complementa el pago de la EPS. | E9: Media | I9: =IF(F9="Sí",0,N(H9)/12) -> 0
B10: Vida e incapacidad permanente | C10: Pago a beneficiarios o al asegurado. | D10: Suma asegurada: ver calculadora abajo. | E10: Alta con dependientes o deudas | I10: =IF(F10="Sí",0,N(H10)/12) -> 0
B11: Plan complementario o prepagada | C11: Acceso a especialistas y menos copagos. | D11: Sube con la edad; puede excluir preexistencias. | E11: Opcional | I11: =IF(F11="Sí",0,N(H11)/12) -> 0
B12: Desempleo o protección de ingresos | C12: Pago mensual si se pierde el ingreso. | D12: Limitado para contratistas e independientes. | E12: Baja | I12: =IF(F12="Sí",0,N(H12)/12) -> 0
B13: Vehículo (todo riesgo) | C13: Daños y robo del vehículo. | D13: Confirmar quién lo paga hoy. | E13: Media si hay vehículo | I13: =IF(F13="Sí",0,N(H13)/12) -> 0
I14: =IF(F14="Sí",0,N(H14)/12) -> 0
I15: =IF(F15="Sí",0,N(H15)/12) -> 0
B16: Total seguros nuevos | H16: =SUMIFS(H6:H15,F6:F15,"<>Sí") -> 0 | I16: =H16/12 -> 0
B17: El total pasa al Presupuesto (fila automática) y al bolsillo Seguros. Las pólizas marcadas "Sí" no se suman.
B19: Suma asegurada orientativa de vida
B20: Deudas pendientes | C20: =Deudas!$D$21 -> 0
B21: Gasto anual que se quiere cubrir | C21: =Presupuesto!$H$89 -> 0
B22: Años de apoyo a dependientes | C22: =IF(Supuestos!$C$11>0,10,0) -> 0
B23: Patrimonio líquido e inversiones | C23: =Patrimonio!$C$33+Patrimonio!$C$34 -> 0
B24: Suma asegurada orientativa | C24: =MAX(0,C20+C21*C22-C23) -> 0 | D24: Orientativa. Cotizar con 2 o 3 aseguradoras y comparar exclusiones.

Sheet Inversión
B1: Inversión por plazos, edad y perfil
B2: Rangos orientativos, no recomendación personalizada. No se nombran productos. Validar con un asesor certificado.
B4: Inversiones actuales
B5: Inversión o plataforma | C5: Tipo | D5: Moneda | E5: Saldo en su moneda | F5: Valor en pesos | G5: Nota
D6: COP | F6: =IF(N(E6)=0,0,IF(D6="USD",E6*N(Supuestos!$C$17),E6)) -> 0
D7: COP | F7: =IF(N(E7)=0,0,IF(D7="USD",E7*N(Supuestos!$C$17),E7)) -> 0
D8: COP | F8: =IF(N(E8)=0,0,IF(D8="USD",E8*N(Supuestos!$C$17),E8)) -> 0
D9: COP | F9: =IF(N(E9)=0,0,IF(D9="USD",E9*N(Supuestos!$C$17),E9)) -> 0
D10: COP | F10: =IF(N(E10)=0,0,IF(D10="USD",E10*N(Supuestos!$C$17),E10)) -> 0
D11: COP | F11: =IF(N(E11)=0,0,IF(D11="USD",E11*N(Supuestos!$C$17),E11)) -> 0
B12: Total invertido | F12: =SUM(F6:F11) -> 0
B13: En crecimiento | F13: =SUMIFS(F6:F11,C6:C11,"Crecimiento") -> 0
B14: En estabilidad | F14: =SUMIFS(F6:F11,C6:C11,"Estabilidad") -> 0
B16: Perfil de riesgo: disposición (lo que quiere asumir)
B17: Pregunta | C17: Respuesta | D17: Puntos | E17: Resultado
B18: a. Si su inversión bajara 15% en un año, ¿qué haría? | D18: =IFERROR(VLOOKUP(C18,Listas!$N$2:$O$4,2,FALSE()),"")
B19: b. ¿Qué experiencia tiene invirtiendo? | D19: =IFERROR(VLOOKUP(C19,Listas!$P$2:$Q$4,2,FALSE()),"")
B20: Disposición | D20: =IF(OR(D18="",D19=""),"",IF(D18+D19<=3,1,IF(D18+D19<=5,2,3))) | E20: =IF(D20="","Falta responder",CHOOSE(D20,"Conservador","Moderado","Tolerante")) -> Falta responder
B21: Plazo en que podría necesitar el dinero | E21: No suma puntos: si es menos de 3 años, todo va a estabilidad.
B23: Perfil de riesgo: capacidad (lo que puede asumir)
B24: Condición | C24: ¿Se cumple? | E24: Origen
B25: Ingresos variables o contrato inestable | C25: =IF(Supuestos!$C$10="Independiente variable","Sí","No") -> No | E25: Automático según tipo de cliente; se puede cambiar.
B26: Personas a cargo sin seguro de vida | C26: =IF(AND(N(Supuestos!$C$11)>0,Seguros!$F$10<>"Sí"),"Sí","No") -> No | E26: Automático; se puede cambiar.
B27: Brecha pensional (la mesada y las rentas no cubren lo básico) | C27: =IF(Pensión!$C$78="Sí","Sí","No") -> No | E27: Automático (hoja Pensión).
B28: Fondo de emergencia incompleto | C28: =IF('Fondo emergencia'!$C$25<0.999,"Sí","No") -> No | E28: Automático (hoja Fondo emergencia).
B29: Menos de 5 años para el retiro sin pensión asegurada | C29: =IF(AND(Supuestos!$C$13<>"",Supuestos!$C$29-N(Supuestos!$C$13)<5,Pensión!$C$24<>"Sí"),"Sí","No") -> No | E29: Automático (hoja Pensión).
B30: Condiciones que se cumplen | C30: =COUNTIF(C25:C29,"Sí") -> 0
B31: Capacidad | D31: =IF(Deudas!$C$23="Sí",0,IF(C30>=4,0,MAX(1,3-C30))) -> 3 | E31: =CHOOSE(D31+1,"No invertir todavía","Conservador","Moderado","Tolerante") -> Tolerante
B32: Perfil final (el menor entre disposición y capacidad) | D32: =IF(D20="","",MIN(D20,D31)) | E32: =IF(D32="","Falta responder",CHOOSE(D32+1,"No invertir todavía","Conservador","Moderado","Tolerante")) -> Falta responder
B34: Rango orientativo en crecimiento según edad y perfil
B35: Edad desde | C35: Tramo | D35: Conservador mín. | E35: Conservador máx. | F35: Moderado mín. | G35: Moderado máx. | H35: Tolerante mín. | I35: Tolerante máx.
B36: 0 | C36: Menos de 35 | D36: 0.4 | E36: 0.55 | F36: 0.6 | G36: 0.75 | H36: 0.8 | I36: 0.9
B37: 35 | C37: 35 a 49 | D37: 0.3 | E37: 0.45 | F37: 0.5 | G37: 0.65 | H37: 0.7 | I37: 0.8
B38: 50 | C38: 50 a 59 | D38: 0.2 | E38: 0.35 | F38: 0.4 | G38: 0.55 | H38: 0.55 | I38: 0.7
B39: 60 | C39: 60 o más | D39: 0.1 | E39: 0.25 | F39: 0.25 | G39: 0.4 | H39: 0.4 | I39: 0.55
B41: Tramo de edad del cliente | C41: =IF(Supuestos!$C$13="","",MATCH(Supuestos!$C$13,$B$36:$B$39,1)) | D41: =IF(C41="","",INDEX($C$36:$C$39,C41))
B42: Rango mínimo | C42: =IF(OR(C41="",D32="",N(D32)=0),0,INDEX($D$36:$I$39,C41,2*D32-1)) -> 0
B43: Rango máximo | C43: =IF(OR(C41="",D32="",N(D32)=0),0,INDEX($D$36:$I$39,C41,2*D32)) -> 0
B44: Posición dentro del rango (0% = mínimo, 100% = máximo) | C44: 0.5 | D44: Hacia el máximo si la pensión y las rentas cubren lo básico o el dinero es para herencia; hacia el mínimo si hay brecha, dependientes o metas cercanas.
B45: % en crecimiento | C45: =IF(OR(D32="",N(D32)=0,C21="Menos de 3 años"),0,C42+C44*(C43-C42)) -> 0
B46: % en estabilidad | C46: =1-C45 -> 1
B47: =IF(C21="Menos de 3 años","El dinero se necesitaría en menos de 3 años: todo va a estabilidad.",IF(D32=0,"Primero estabilidad: pagar la deuda cara o fortalecer la capacidad antes de invertir en crecimiento.",IF(D32="","Responde las preguntas de disposición para calcular el perfil.",""))) -> Responde las preguntas de disposición para calcular el perfil.
B49: Distribución
B50: Concepto | C50: Total | D50: Crecimiento | E50: Estabilidad
B51: Inversión mensual promedio | C51: ='Flujo anual'!$Q$33/12 -> 0 | D51: =C51*$C$45 -> 0 | E51: =C51*$C$46 -> 0
B52: Inversión anual | C52: ='Flujo anual'!$Q$33 -> 0 | D52: =C52*$C$45 -> 0 | E52: =C52*$C$46 -> 0
B53: Aporte único desde el excedente | C53: =Bolsillos!$C$27 -> 0 | D53: =C53*$C$45 -> 0 | E53: =C53*$C$46 -> 0
B54: Saldo invertido hoy | C54: =F12 -> 0 | D54: =F13 -> 0 | E54: =F14 -> 0
B55: Objetivo del total (saldo + aporte único) | C55: =C53+C54 -> 0 | D55: =C55*$C$45 -> 0 | E55: =C55*$C$46 -> 0
B56: Movimiento sugerido hacia el objetivo | D56: =D55-D54 -> 0 | E56: =E55-E54 -> 0
B57: Positivo: llevar dinero a ese tramo. Negativo: el tramo está por encima del objetivo. Los aportes nuevos pueden hacer el ajuste sin vender.
B59: Proyección ilustrativa (pesos de hoy, rendimientos no garantizados)
B60: Año | C60: Edad al cierre | D60: % en crecimiento | E60: Rendimiento real mezclado | F60: Saldo inicial | G60: Aporte del sobrante | H60: Abonos por cobrar | I60: Rendimiento | J60: Saldo final
B61: =Supuestos!$C$14+0 -> 2027 | C61: =IF(Supuestos!$C$8="","",B61-YEAR(Supuestos!$C$8)) | D61: =IF($C$45=0,0,MAX(MIN(Supuestos!$C$31,$C$45),$C$45-Supuestos!$C$30*MAX(0,MIN(0,$C$71)-MAX(0,$C$71-10)))) -> 0 | E61: =D61*Supuestos!$C$27+(1-D61)*Supuestos!$C$28 -> 0.015 | F61: =C55 -> 0 | G61: ='Flujo anual'!$Q$25 -> 0 | H61: =IF(Deudas!$C$23="Sí",0,IF(ISNUMBER(Supuestos!$J$46),MAX(0,MIN(B61*12+12,Supuestos!$K$46)-MAX(B61*12+1,Supuestos!$J$46)+1)*N(Supuestos!$D$46)*N(Supuestos!$H$46),0)+IF(ISNUMBER(Supuestos!$J$47),MAX(0,MIN(B61*12+12,Supuestos!$K$47)-MAX(B61*12+1,Supuestos!$J$47)+1)*N(Supuestos!$D$47)*N(Supuestos!$H$47),0)+IF(ISNUMBER(Supuestos!$J$48),MAX(0,MIN(B61*12+12,Supuestos!$K$48)-MAX(B61*12+1,Supuestos!$J$48)+1)*N(Supuestos!$D$48)*N(Supuestos!$H$48),0)) -> 0 | I61: =(F61+(G61+H61)/2)*E61 -> 0 | J61: =F61+G61+H61+I61 -> 0
B62: =Supuestos!$C$14+1 -> 2028 | C62: =IF(Supuestos!$C$8="","",B62-YEAR(Supuestos!$C$8)) | D62: =IF($C$45=0,0,MAX(MIN(Supuestos!$C$31,$C$45),$C$45-Supuestos!$C$30*MAX(0,MIN(1,$C$71)-MAX(0,$C$71-10)))) -> 0 | E62: =D62*Supuestos!$C$27+(1-D62)*Supuestos!$C$28 -> 0.015 | F62: =J61 -> 0 | G62: ='Flujo anual'!$Q$25 -> 0 | H62: =IF(Deudas!$C$23="Sí",0,IF(ISNUMBER(Supuestos!$J$46),MAX(0,MIN(B62*12+12,Supuestos!$K$46)-MAX(B62*12+1,Supuestos!$J$46)+1)*N(Supuestos!$D$46)*N(Supuestos!$H$46),0)+IF(ISNUMBER(Supuestos!$J$47),MAX(0,MIN(B62*12+12,Supuestos!$K$47)-MAX(B62*12+1,Supuestos!$J$47)+1)*N(Supuestos!$D$47)*N(Supuestos!$H$47),0)+IF(ISNUMBER(Supuestos!$J$48),MAX(0,MIN(B62*12+12,Supuestos!$K$48)-MAX(B62*12+1,Supuestos!$J$48)+1)*N(Supuestos!$D$48)*N(Supuestos!$H$48),0)) -> 0 | I62: =(F62+(G62+H62)/2)*E62 -> 0 | J62: =F62+G62+H62+I62 -> 0
B63: =Supuestos!$C$14+2 -> 2029 | C63: =IF(Supuestos!$C$8="","",B63-YEAR(Supuestos!$C$8)) | D63: =IF($C$45=0,0,MAX(MIN(Supuestos!$C$31,$C$45),$C$45-Supuestos!$C$30*MAX(0,MIN(2,$C$71)-MAX(0,$C$71-10)))) -> 0 | E63: =D63*Supuestos!$C$27+(1-D63)*Supuestos!$C$28 -> 0.015 | F63: =J62 -> 0 | G63: ='Flujo anual'!$Q$25 -> 0 | H63: =IF(Deudas!$C$23="Sí",0,IF(ISNUMBER(Supuestos!$J$46),MAX(0,MIN(B63*12+12,Supuestos!$K$46)-MAX(B63*12+1,Supuestos!$J$46)+1)*N(Supuestos!$D$46)*N(Supuestos!$H$46),0)+IF(ISNUMBER(Supuestos!$J$47),MAX(0,MIN(B63*12+12,Supuestos!$K$47)-MAX(B63*12+1,Supuestos!$J$47)+1)*N(Supuestos!$D$47)*N(Supuestos!$H$47),0)+IF(ISNUMBER(Supuestos!$J$48),MAX(0,MIN(B63*12+12,Supuestos!$K$48)-MAX(B63*12+1,Supuestos!$J$48)+1)*N(Supuestos!$D$48)*N(Supuestos!$H$48),0)) -> 0 | I63: =(F63+(G63+H63)/2)*E63 -> 0 | J63: =F63+G63+H63+I63 -> 0
B64: =Supuestos!$C$14+3 -> 2030 | C64: =IF(Supuestos!$C$8="","",B64-YEAR(Supuestos!$C$8)) | D64: =IF($C$45=0,0,MAX(MIN(Supuestos!$C$31,$C$45),$C$45-Supuestos!$C$30*MAX(0,MIN(3,$C$71)-MAX(0,$C$71-10)))) -> 0 | E64: =D64*Supuestos!$C$27+(1-D64)*Supuestos!$C$28 -> 0.015 | F64: =J63 -> 0 | G64: ='Flujo anual'!$Q$25 -> 0 | H64: =IF(Deudas!$C$23="Sí",0,IF(ISNUMBER(Supuestos!$J$46),MAX(0,MIN(B64*12+12,Supuestos!$K$46)-MAX(B64*12+1,Supuestos!$J$46)+1)*N(Supuestos!$D$46)*N(Supuestos!$H$46),0)+IF(ISNUMBER(Supuestos!$J$47),MAX(0,MIN(B64*12+12,Supuestos!$K$47)-MAX(B64*12+1,Supuestos!$J$47)+1)*N(Supuestos!$D$47)*N(Supuestos!$H$47),0)+IF(ISNUMBER(Supuestos!$J$48),MAX(0,MIN(B64*12+12,Supuestos!$K$48)-MAX(B64*12+1,Supuestos!$J$48)+1)*N(Supuestos!$D$48)*N(Supuestos!$H$48),0)) -> 0 | I64: =(F64+(G64+H64)/2)*E64 -> 0 | J64: =F64+G64+H64+I64 -> 0
B65: =Supuestos!$C$14+4 -> 2031 | C65: =IF(Supuestos!$C$8="","",B65-YEAR(Supuestos!$C$8)) | D65: =IF($C$45=0,0,MAX(MIN(Supuestos!$C$31,$C$45),$C$45-Supuestos!$C$30*MAX(0,MIN(4,$C$71)-MAX(0,$C$71-10)))) -> 0 | E65: =D65*Supuestos!$C$27+(1-D65)*Supuestos!$C$28 -> 0.015 | F65: =J64 -> 0 | G65: ='Flujo anual'!$Q$25 -> 0 | H65: =IF(Deudas!$C$23="Sí",0,IF(ISNUMBER(Supuestos!$J$46),MAX(0,MIN(B65*12+12,Supuestos!$K$46)-MAX(B65*12+1,Supuestos!$J$46)+1)*N(Supuestos!$D$46)*N(Supuestos!$H$46),0)+IF(ISNUMBER(Supuestos!$J$47),MAX(0,MIN(B65*12+12,Supuestos!$K$47)-MAX(B65*12+1,Supuestos!$J$47)+1)*N(Supuestos!$D$47)*N(Supuestos!$H$47),0)+IF(ISNUMBER(Supuestos!$J$48),MAX(0,MIN(B65*12+12,Supuestos!$K$48)-MAX(B65*12+1,Supuestos!$J$48)+1)*N(Supuestos!$D$48)*N(Supuestos!$H$48),0)) -> 0 | I65: =(F65+(G65+H65)/2)*E65 -> 0 | J65: =F65+G65+H65+I65 -> 0
B66: =Supuestos!$C$14+5 -> 2032 | C66: =IF(Supuestos!$C$8="","",B66-YEAR(Supuestos!$C$8)) | D66: =IF($C$45=0,0,MAX(MIN(Supuestos!$C$31,$C$45),$C$45-Supuestos!$C$30*MAX(0,MIN(5,$C$71)-MAX(0,$C$71-10)))) -> 0 | E66: =D66*Supuestos!$C$27+(1-D66)*Supuestos!$C$28 -> 0.015 | F66: =J65 -> 0 | G66: ='Flujo anual'!$Q$25 -> 0 | H66: =IF(Deudas!$C$23="Sí",0,IF(ISNUMBER(Supuestos!$J$46),MAX(0,MIN(B66*12+12,Supuestos!$K$46)-MAX(B66*12+1,Supuestos!$J$46)+1)*N(Supuestos!$D$46)*N(Supuestos!$H$46),0)+IF(ISNUMBER(Supuestos!$J$47),MAX(0,MIN(B66*12+12,Supuestos!$K$47)-MAX(B66*12+1,Supuestos!$J$47)+1)*N(Supuestos!$D$47)*N(Supuestos!$H$47),0)+IF(ISNUMBER(Supuestos!$J$48),MAX(0,MIN(B66*12+12,Supuestos!$K$48)-MAX(B66*12+1,Supuestos!$J$48)+1)*N(Supuestos!$D$48)*N(Supuestos!$H$48),0)) -> 0 | I66: =(F66+(G66+H66)/2)*E66 -> 0 | J66: =F66+G66+H66+I66 -> 0
B67: =Supuestos!$C$14+6 -> 2033 | C67: =IF(Supuestos!$C$8="","",B67-YEAR(Supuestos!$C$8)) | D67: =IF($C$45=0,0,MAX(MIN(Supuestos!$C$31,$C$45),$C$45-Supuestos!$C$30*MAX(0,MIN(6,$C$71)-MAX(0,$C$71-10)))) -> 0 | E67: =D67*Supuestos!$C$27+(1-D67)*Supuestos!$C$28 -> 0.015 | F67: =J66 -> 0 | G67: ='Flujo anual'!$Q$25 -> 0 | H67: =IF(Deudas!$C$23="Sí",0,IF(ISNUMBER(Supuestos!$J$46),MAX(0,MIN(B67*12+12,Supuestos!$K$46)-MAX(B67*12+1,Supuestos!$J$46)+1)*N(Supuestos!$D$46)*N(Supuestos!$H$46),0)+IF(ISNUMBER(Supuestos!$J$47),MAX(0,MIN(B67*12+12,Supuestos!$K$47)-MAX(B67*12+1,Supuestos!$J$47)+1)*N(Supuestos!$D$47)*N(Supuestos!$H$47),0)+IF(ISNUMBER(Supuestos!$J$48),MAX(0,MIN(B67*12+12,Supuestos!$K$48)-MAX(B67*12+1,Supuestos!$J$48)+1)*N(Supuestos!$D$48)*N(Supuestos!$H$48),0)) -> 0 | I67: =(F67+(G67+H67)/2)*E67 -> 0 | J67: =F67+G67+H67+I67 -> 0
B68: =Supuestos!$C$14+7 -> 2034 | C68: =IF(Supuestos!$C$8="","",B68-YEAR(Supuestos!$C$8)) | D68: =IF($C$45=0,0,MAX(MIN(Supuestos!$C$31,$C$45),$C$45-Supuestos!$C$30*MAX(0,MIN(7,$C$71)-MAX(0,$C$71-10)))) -> 0 | E68: =D68*Supuestos!$C$27+(1-D68)*Supuestos!$C$28 -> 0.015 | F68: =J67 -> 0 | G68: ='Flujo anual'!$Q$25 -> 0 | H68: =IF(Deudas!$C$23="Sí",0,IF(ISNUMBER(Supuestos!$J$46),MAX(0,MIN(B68*12+12,Supuestos!$K$46)-MAX(B68*12+1,Supuestos!$J$46)+1)*N(Supuestos!$D$46)*N(Supuestos!$H$46),0)+IF(ISNUMBER(Supuestos!$J$47),MAX(0,MIN(B68*12+12,Supuestos!$K$47)-MAX(B68*12+1,Supuestos!$J$47)+1)*N(Supuestos!$D$47)*N(Supuestos!$H$47),0)+IF(ISNUMBER(Supuestos!$J$48),MAX(0,MIN(B68*12+12,Supuestos!$K$48)-MAX(B68*12+1,Supuestos!$J$48)+1)*N(Supuestos!$D$48)*N(Supuestos!$H$48),0)) -> 0 | I68: =(F68+(G68+H68)/2)*E68 -> 0 | J68: =F68+G68+H68+I68 -> 0
B69: =Supuestos!$C$14+8 -> 2035 | C69: =IF(Supuestos!$C$8="","",B69-YEAR(Supuestos!$C$8)) | D69: =IF($C$45=0,0,MAX(MIN(Supuestos!$C$31,$C$45),$C$45-Supuestos!$C$30*MAX(0,MIN(8,$C$71)-MAX(0,$C$71-10)))) -> 0 | E69: =D69*Supuestos!$C$27+(1-D69)*Supuestos!$C$28 -> 0.015 | F69: =J68 -> 0 | G69: ='Flujo anual'!$Q$25 -> 0 | H69: =IF(Deudas!$C$23="Sí",0,IF(ISNUMBER(Supuestos!$J$46),MAX(0,MIN(B69*12+12,Supuestos!$K$46)-MAX(B69*12+1,Supuestos!$J$46)+1)*N(Supuestos!$D$46)*N(Supuestos!$H$46),0)+IF(ISNUMBER(Supuestos!$J$47),MAX(0,MIN(B69*12+12,Supuestos!$K$47)-MAX(B69*12+1,Supuestos!$J$47)+1)*N(Supuestos!$D$47)*N(Supuestos!$H$47),0)+IF(ISNUMBER(Supuestos!$J$48),MAX(0,MIN(B69*12+12,Supuestos!$K$48)-MAX(B69*12+1,Supuestos!$J$48)+1)*N(Supuestos!$D$48)*N(Supuestos!$H$48),0)) -> 0 | I69: =(F69+(G69+H69)/2)*E69 -> 0 | J69: =F69+G69+H69+I69 -> 0
B70: =Supuestos!$C$14+9 -> 2036 | C70: =IF(Supuestos!$C$8="","",B70-YEAR(Supuestos!$C$8)) | D70: =IF($C$45=0,0,MAX(MIN(Supuestos!$C$31,$C$45),$C$45-Supuestos!$C$30*MAX(0,MIN(9,$C$71)-MAX(0,$C$71-10)))) -> 0 | E70: =D70*Supuestos!$C$27+(1-D70)*Supuestos!$C$28 -> 0.015 | F70: =J69 -> 0 | G70: ='Flujo anual'!$Q$25 -> 0 | H70: =IF(Deudas!$C$23="Sí",0,IF(ISNUMBER(Supuestos!$J$46),MAX(0,MIN(B70*12+12,Supuestos!$K$46)-MAX(B70*12+1,Supuestos!$J$46)+1)*N(Supuestos!$D$46)*N(Supuestos!$H$46),0)+IF(ISNUMBER(Supuestos!$J$47),MAX(0,MIN(B70*12+12,Supuestos!$K$47)-MAX(B70*12+1,Supuestos!$J$47)+1)*N(Supuestos!$D$47)*N(Supuestos!$H$47),0)+IF(ISNUMBER(Supuestos!$J$48),MAX(0,MIN(B70*12+12,Supuestos!$K$48)-MAX(B70*12+1,Supuestos!$J$48)+1)*N(Supuestos!$D$48)*N(Supuestos!$H$48),0)) -> 0 | I70: =(F70+(G70+H70)/2)*E70 -> 0 | J70: =F70+G70+H70+I70 -> 0
B71: Años para el retiro hoy | C71: =IF(Supuestos!$C$13="",0,MAX(0,Supuestos!$C$29-Supuestos!$C$13)) -> 0
B72: El % en crecimiento baja gradualmente en los 10 años anteriores al retiro (Supuestos). El aporte del sobrante se supone constante.

Sheet Pensión
B1: Pensión de vejez (Colombia)
B2: Estimación en pesos de hoy. Verificar reglas vigentes y pedir el cálculo oficial a la administradora.
B5: Dato | C5: Valor | D5: Nota
B6: Régimen
B7: Semanas cotizadas | D7: Según la historia laboral.
B8: Fecha de esas semanas
B9: Sexo | C9: =IF(Supuestos!$C$9="","",Supuestos!$C$9) | D9: Desde Supuestos.
B10: Edad de pensión | C10: =IF(C9="Hombre",62,57) -> 57
B11: Fecha en que cumple la edad | C11: =IF(Supuestos!$C$8="","",DATE(YEAR(Supuestos!$C$8)+C10,MONTH(Supuestos!$C$8),DAY(Supuestos!$C$8)))
B12: Meses cotizados por año | C12: =Ingresos!$S$17 -> 12 | D12: Meses con seguridad social (hoja Ingresos).
B13: Base de cotización actual (en salarios mínimos) | D13: Por ejemplo, 3. Contratistas: suele ser el 40% del contrato.
B14: Base de cotización en pesos | C14: =N(C13)*Supuestos!$C$18 -> 0
B15: Hijos | C15: 0
B16: ¿Aplicar descuento de semanas por hijos? | C16: No | D16: Solo si la administradora lo reconoce.
B17: Semanas de descuento | C17: =IF(AND(C16="Sí",C9="Mujer"),MIN(3,N(C15))*50,0) -> 0 | D17: 50 por hijo, máximo 3.
B19: Proyección de semanas
B20: Semanas estimadas al cumplir la edad | C20: =IF(OR(C7="",C8="",C11=""),"",C7+IFERROR(DATEDIF(C8,C11,"m"),0)*C12/12*30/7)
B21: Año en que cumple la edad | C21: =IF(C11="","",YEAR(C11))
B22: Semanas requeridas ese año | C22: =IF(OR(C21="",C6=""),"",IF($C$9="Hombre",IF($C$6="Fondo privado",1150,1300),IF($C$6="Fondo privado",IF(C21<2026,1150,MAX(1000,1135-15*(C21-2026))),IF(C21<2026,1300,MAX(1000,1250-25*(C21-2026)))))-$C$17) | D22: Colpensiones: mujeres según el año (1.250 en 2026, -25/año hasta 1.000); hombres 1.300. Fondo privado: semanas de la garantía de pensión mínima.
B23: Semanas de sobra (o faltantes) | C23: =IF(OR(C20="",C22=""),"",C20-C22)
B24: ¿Cumple las semanas al llegar a la edad? | C24: =IF(C23="","",IF(C23>=0,"Sí","No"))
B25: Si faltan: meses adicionales de cotización al ritmo actual | C25: =IF(OR(C23="",N(C23)>=0),0,ROUNDUP(-C23/(30/7)/MAX(C12,1)*12,0)) -> 0
B27: Semanas mujeres por año
B28: Año | C28: Colpensiones | D28: Fondo privado (garantía mínima)
B29: 2026 | C29: 1250 | D29: 1135
B30: 2027 | C30: 1225 | D30: 1120
B31: 2028 | C31: 1200 | D31: 1105
B32: 2029 | C32: 1175 | D32: 1090
B33: 2030 | C33: 1150 | D33: 1075
B34: 2031 | C34: 1125 | D34: 1060
B35: 2032 | C35: 1100 | D35: 1045
B36: 2033 | C36: 1075 | D36: 1030
B37: 2034 | C37: 1050 | D37: 1015
B38: 2035 | C38: 1025 | D38: 1000
B39: 2036 | C39: 1000 | D39: 1000
B41: Semanas año por año
B42: Año | C42: Edad al cierre | D42: Semanas al cierre del año | E42: Semanas requeridas | F42: ¿Alcanza?
B43: =YEAR(Supuestos!$C$12)+0 -> 2026 | C43: =IF(Supuestos!$C$8="","",B43-YEAR(Supuestos!$C$8)) | D43: =IF(OR($C$7="",$C$8=""),"",$C$7+IFERROR(DATEDIF($C$8,DATE(B43,12,31),"m"),0)*$C$12/12*30/7) | E43: =IF($C$6="","",IF($C$9="Hombre",IF($C$6="Fondo privado",1150,1300),IF($C$6="Fondo privado",IF(B43<2026,1150,MAX(1000,1135-15*(B43-2026))),IF(B43<2026,1300,MAX(1000,1250-25*(B43-2026)))))-$C$17) | F43: =IF(OR(D43="",E43=""),"",IF(D43>=E43,"Sí","No"))
B44: =YEAR(Supuestos!$C$12)+1 -> 2027 | C44: =IF(Supuestos!$C$8="","",B44-YEAR(Supuestos!$C$8)) | D44: =IF(OR($C$7="",$C$8=""),"",$C$7+IFERROR(DATEDIF($C$8,DATE(B44,12,31),"m"),0)*$C$12/12*30/7) | E44: =IF($C$6="","",IF($C$9="Hombre",IF($C$6="Fondo privado",1150,1300),IF($C$6="Fondo privado",IF(B44<2026,1150,MAX(1000,1135-15*(B44-2026))),IF(B44<2026,1300,MAX(1000,1250-25*(B44-2026)))))-$C$17) | F44: =IF(OR(D44="",E44=""),"",IF(D44>=E44,"Sí","No"))
B45: =YEAR(Supuestos!$C$12)+2 -> 2028 | C45: =IF(Supuestos!$C$8="","",B45-YEAR(Supuestos!$C$8)) | D45: =IF(OR($C$7="",$C$8=""),"",$C$7+IFERROR(DATEDIF($C$8,DATE(B45,12,31),"m"),0)*$C$12/12*30/7) | E45: =IF($C$6="","",IF($C$9="Hombre",IF($C$6="Fondo privado",1150,1300),IF($C$6="Fondo privado",IF(B45<2026,1150,MAX(1000,1135-15*(B45-2026))),IF(B45<2026,1300,MAX(1000,1250-25*(B45-2026)))))-$C$17) | F45: =IF(OR(D45="",E45=""),"",IF(D45>=E45,"Sí","No"))
B46: =YEAR(Supuestos!$C$12)+3 -> 2029 | C46: =IF(Supuestos!$C$8="","",B46-YEAR(Supuestos!$C$8)) | D46: =IF(OR($C$7="",$C$8=""),"",$C$7+IFERROR(DATEDIF($C$8,DATE(B46,12,31),"m"),0)*$C$12/12*30/7) | E46: =IF($C$6="","",IF($C$9="Hombre",IF($C$6="Fondo privado",1150,1300),IF($C$6="Fondo privado",IF(B46<2026,1150,MAX(1000,1135-15*(B46-2026))),IF(B46<2026,1300,MAX(1000,1250-25*(B46-2026)))))-$C$17) | F46: =IF(OR(D46="",E46=""),"",IF(D46>=E46,"Sí","No"))
B47: =YEAR(Supuestos!$C$12)+4 -> 2030 | C47: =IF(Supuestos!$C$8="","",B47-YEAR(Supuestos!$C$8)) | D47: =IF(OR($C$7="",$C$8=""),"",$C$7+IFERROR(DATEDIF($C$8,DATE(B47,12,31),"m"),0)*$C$12/12*30/7) | E47: =IF($C$6="","",IF($C$9="Hombre",IF($C$6="Fondo privado",1150,1300),IF($C$6="Fondo privado",IF(B47<2026,1150,MAX(1000,1135-15*(B47-2026))),IF(B47<2026,1300,MAX(1000,1250-25*(B47-2026)))))-$C$17) | F47: =IF(OR(D47="",E47=""),"",IF(D47>=E47,"Sí","No"))
B48: =YEAR(Supuestos!$C$12)+5 -> 2031 | C48: =IF(Supuestos!$C$8="","",B48-YEAR(Supuestos!$C$8)) | D48: =IF(OR($C$7="",$C$8=""),"",$C$7+IFERROR(DATEDIF($C$8,DATE(B48,12,31),"m"),0)*$C$12/12*30/7) | E48: =IF($C$6="","",IF($C$9="Hombre",IF($C$6="Fondo privado",1150,1300),IF($C$6="Fondo privado",IF(B48<2026,1150,MAX(1000,1135-15*(B48-2026))),IF(B48<2026,1300,MAX(1000,1250-25*(B48-2026)))))-$C$17) | F48: =IF(OR(D48="",E48=""),"",IF(D48>=E48,"Sí","No"))
B49: =YEAR(Supuestos!$C$12)+6 -> 2032 | C49: =IF(Supuestos!$C$8="","",B49-YEAR(Supuestos!$C$8)) | D49: =IF(OR($C$7="",$C$8=""),"",$C$7+IFERROR(DATEDIF($C$8,DATE(B49,12,31),"m"),0)*$C$12/12*30/7) | E49: =IF($C$6="","",IF($C$9="Hombre",IF($C$6="Fondo privado",1150,1300),IF($C$6="Fondo privado",IF(B49<2026,1150,MAX(1000,1135-15*(B49-2026))),IF(B49<2026,1300,MAX(1000,1250-25*(B49-2026)))))-$C$17) | F49: =IF(OR(D49="",E49=""),"",IF(D49>=E49,"Sí","No"))
B50: =YEAR(Supuestos!$C$12)+7 -> 2033 | C50: =IF(Supuestos!$C$8="","",B50-YEAR(Supuestos!$C$8)) | D50: =IF(OR($C$7="",$C$8=""),"",$C$7+IFERROR(DATEDIF($C$8,DATE(B50,12,31),"m"),0)*$C$12/12*30/7) | E50: =IF($C$6="","",IF($C$9="Hombre",IF($C$6="Fondo privado",1150,1300),IF($C$6="Fondo privado",IF(B50<2026,1150,MAX(1000,1135-15*(B50-2026))),IF(B50<2026,1300,MAX(1000,1250-25*(B50-2026)))))-$C$17) | F50: =IF(OR(D50="",E50=""),"",IF(D50>=E50,"Sí","No"))
B51: =YEAR(Supuestos!$C$12)+8 -> 2034 | C51: =IF(Supuestos!$C$8="","",B51-YEAR(Supuestos!$C$8)) | D51: =IF(OR($C$7="",$C$8=""),"",$C$7+IFERROR(DATEDIF($C$8,DATE(B51,12,31),"m"),0)*$C$12/12*30/7) | E51: =IF($C$6="","",IF($C$9="Hombre",IF($C$6="Fondo privado",1150,1300),IF($C$6="Fondo privado",IF(B51<2026,1150,MAX(1000,1135-15*(B51-2026))),IF(B51<2026,1300,MAX(1000,1250-25*(B51-2026)))))-$C$17) | F51: =IF(OR(D51="",E51=""),"",IF(D51>=E51,"Sí","No"))
B52: =YEAR(Supuestos!$C$12)+9 -> 2035 | C52: =IF(Supuestos!$C$8="","",B52-YEAR(Supuestos!$C$8)) | D52: =IF(OR($C$7="",$C$8=""),"",$C$7+IFERROR(DATEDIF($C$8,DATE(B52,12,31),"m"),0)*$C$12/12*30/7) | E52: =IF($C$6="","",IF($C$9="Hombre",IF($C$6="Fondo privado",1150,1300),IF($C$6="Fondo privado",IF(B52<2026,1150,MAX(1000,1135-15*(B52-2026))),IF(B52<2026,1300,MAX(1000,1250-25*(B52-2026)))))-$C$17) | F52: =IF(OR(D52="",E52=""),"",IF(D52>=E52,"Sí","No"))
B53: =YEAR(Supuestos!$C$12)+10 -> 2036 | C53: =IF(Supuestos!$C$8="","",B53-YEAR(Supuestos!$C$8)) | D53: =IF(OR($C$7="",$C$8=""),"",$C$7+IFERROR(DATEDIF($C$8,DATE(B53,12,31),"m"),0)*$C$12/12*30/7) | E53: =IF($C$6="","",IF($C$9="Hombre",IF($C$6="Fondo privado",1150,1300),IF($C$6="Fondo privado",IF(B53<2026,1150,MAX(1000,1135-15*(B53-2026))),IF(B53<2026,1300,MAX(1000,1250-25*(B53-2026)))))-$C$17) | F53: =IF(OR(D53="",E53=""),"",IF(D53>=E53,"Sí","No"))
B54: =YEAR(Supuestos!$C$12)+11 -> 2037 | C54: =IF(Supuestos!$C$8="","",B54-YEAR(Supuestos!$C$8)) | D54: =IF(OR($C$7="",$C$8=""),"",$C$7+IFERROR(DATEDIF($C$8,DATE(B54,12,31),"m"),0)*$C$12/12*30/7) | E54: =IF($C$6="","",IF($C$9="Hombre",IF($C$6="Fondo privado",1150,1300),IF($C$6="Fondo privado",IF(B54<2026,1150,MAX(1000,1135-15*(B54-2026))),IF(B54<2026,1300,MAX(1000,1250-25*(B54-2026)))))-$C$17) | F54: =IF(OR(D54="",E54=""),"",IF(D54>=E54,"Sí","No"))
B56: Mesada estimada (solo Colpensiones)
B57: Concepto | C57: Escenario bajo | D57: Escenario medio | E57: Escenario alto
B58: IBL en salarios mínimos (promedio últimos 10 años) | C58: =MAX(1,N($C$13)-1) -> 1 | D58: =MAX(1,N($C$13)-0.5) -> 1 | E58: =MAX(1,N($C$13)) -> 1
B59: IBL en pesos | C59: =C58*Supuestos!$C$18 -> 1750905 | D59: =D58*Supuestos!$C$18 -> 1750905 | E59: =E58*Supuestos!$C$18 -> 1750905
B60: Tasa de reemplazo | C60: =MAX(0.55,MIN(0.65,(65.5-0.5*C58)/100)) -> 0.65 | D60: =MAX(0.55,MIN(0.65,(65.5-0.5*D58)/100)) -> 0.65 | E60: =MAX(0.55,MIN(0.65,(65.5-0.5*E58)/100)) -> 0.65
B61: Mesada bruta | C61: =MAX(Supuestos!$C$18,C59*C60) -> 1750905 | D61: =MAX(Supuestos!$C$18,D59*D60) -> 1750905 | E61: =MAX(Supuestos!$C$18,E59*E60) -> 1750905
B62: Descuento de salud | C62: =C61*$C$64 -> 210108.6 | D62: =D61*$C$64 -> 210108.6 | E62: =E61*$C$64 -> 210108.6
B63: Mesada neta | C63: =C61-C62 -> 1540796.4 | D63: =D61-D62 -> 1540796.4 | E63: =E61-E62 -> 1540796.4
B64: Aporte a salud del pensionado | C64: 0.12 | D64: Puede ser menor en mesadas bajas: verificar.
B66: Flujo mensual después de pensionarse (pesos de hoy)
B67: Concepto | C67: Escenario bajo | D67: Escenario medio | E67: Escenario alto
B68: Mesada neta | C68: =C63 -> 1540796.4 | D68: =D63 -> 1540796.4 | E68: =E63 -> 1540796.4
B69: Rentas y otros ingresos | C69: =Ingresos!$U$21+Ingresos!$U$23 -> 0 | D69: =Ingresos!$U$21+Ingresos!$U$23 -> 0 | E69: =Ingresos!$U$21+Ingresos!$U$23 -> 0
B70: Gastos del mes sin seguridad social | C70: =Presupuesto!$I$89-Presupuesto!$I$92 -> 0 | D70: =Presupuesto!$I$89-Presupuesto!$I$92 -> 0 | E70: =Presupuesto!$I$89-Presupuesto!$I$92 -> 0
B71: Ahorro programado | C71: =Presupuesto!$I$94 -> 0 | D71: =Presupuesto!$I$94 -> 0 | E71: =Presupuesto!$I$94 -> 0
B72: Escenario 1: deja de trabajar. Sobrante mensual | C72: =C68+C69-C70-C71 -> 1540796.4 | D72: =D68+D69-D70-D71 -> 1540796.4 | E72: =E68+E69-E70-E71 -> 1540796.4
B73: Ingreso laboral promedio si sigue trabajando | C73: =Ingresos!$U$20 -> 0 | D73: =Ingresos!$U$20 -> 0 | E73: =Ingresos!$U$20 -> 0
B74: Salud y ARL del contrato (promedio mensual) | C74: =$C$14*$C$75*$C$12/12 -> 0 | D74: =$C$14*$C$75*$C$12/12 -> 0 | E74: =$C$14*$C$75*$C$12/12 -> 0
B75: Salud y ARL del contrato (% de la base) | C75: 0.13022 | D75: Pensionado que trabaja: no cotiza pensión. Confirmar con el contador.
B76: Escenario 2: sigue trabajando. Sobrante mensual | C76: =C68+C69+C73-C70-C71-C74 -> 1540796.4 | D76: =D68+D69+D73-D70-D71-D74 -> 1540796.4 | E76: =E68+E69+E73-E70-E71-E74 -> 1540796.4
B77: Para comparar: sobrante mensual promedio hoy | C77: ='Flujo anual'!$Q$22/12 -> 0 | D77: ='Flujo anual'!$Q$22/12 -> 0 | E77: ='Flujo anual'!$Q$22/12 -> 0
B78: ¿Brecha pensional? (escenario medio, deja de trabajar) | C78: =IF(C6="","",IF(C6="Fondo privado","Revisar con el fondo",IF(D72<0,"Sí","No")))
B80: Tasa de reemplazo = 65,5% - 0,5 x IBL en salarios mínimos, entre 55% y 65%, con mesada mínima de un salario mínimo. Colpensiones toma 1.300 semanas como referencia para sumar 1,5% por cada 50 adicionales.
B81: Fondo privado: la mesada depende del capital ahorrado. Pedir la proyección oficial y la doble asesoría.

Sheet Patrimonio
B1: Patrimonio
B2: Activos, deudas y composición. Las inversiones se registran en la hoja Inversión y aparecen aquí solas.
B5: Activo | C5: Tipo | D5: Moneda | E5: Valor en su moneda | F5: Valor en pesos | G5: ¿Genera ingreso? | H5: Nota
B6: Inversiones (hoja Inversión) | C6: Inversión | D6: COP | F6: =Inversión!$F$12 -> 0 | H6: Automático.
B7: Cuentas por cobrar (Supuestos) | C7: Por cobrar | D7: COP | F7: =Supuestos!$I$49 -> 0 | H7: Automático.
D8: COP | F8: =IF(N(E8)=0,0,IF(D8="USD",E8*N(Supuestos!$C$17),E8)) -> 0
D9: COP | F9: =IF(N(E9)=0,0,IF(D9="USD",E9*N(Supuestos!$C$17),E9)) -> 0
D10: COP | F10: =IF(N(E10)=0,0,IF(D10="USD",E10*N(Supuestos!$C$17),E10)) -> 0
D11: COP | F11: =IF(N(E11)=0,0,IF(D11="USD",E11*N(Supuestos!$C$17),E11)) -> 0
D12: COP | F12: =IF(N(E12)=0,0,IF(D12="USD",E12*N(Supuestos!$C$17),E12)) -> 0
D13: COP | F13: =IF(N(E13)=0,0,IF(D13="USD",E13*N(Supuestos!$C$17),E13)) -> 0
D14: COP | F14: =IF(N(E14)=0,0,IF(D14="USD",E14*N(Supuestos!$C$17),E14)) -> 0
D15: COP | F15: =IF(N(E15)=0,0,IF(D15="USD",E15*N(Supuestos!$C$17),E15)) -> 0
D16: COP | F16: =IF(N(E16)=0,0,IF(D16="USD",E16*N(Supuestos!$C$17),E16)) -> 0
D17: COP | F17: =IF(N(E17)=0,0,IF(D17="USD",E17*N(Supuestos!$C$17),E17)) -> 0
D18: COP | F18: =IF(N(E18)=0,0,IF(D18="USD",E18*N(Supuestos!$C$17),E18)) -> 0
D19: COP | F19: =IF(N(E19)=0,0,IF(D19="USD",E19*N(Supuestos!$C$17),E19)) -> 0
... D27: COP | F27: =IF(N(E27)=0,0,IF(D27="USD",E27*N(Supuestos!$C$17),E27)) -> 0
B28: Total activos | F28: =SUM(F6:F27) -> 0
B29: Deudas (hoja Deudas) | F29: =Deudas!$D$21 -> 0
B30: Patrimonio neto | F30: =F28-F29 -> 0
B32: Composición | C32: Valor | D32: % de activos
B33: Líquido | C33: =SUMIFS($F$6:$F$27,$C$6:$C$27,B33) -> 0 | D33: =IF($F$28=0,0,C33/$F$28) -> 0
B34: Inversión | C34: =SUMIFS($F$6:$F$27,$C$6:$C$27,B34) -> 0 | D34: =IF($F$28=0,0,C34/$F$28) -> 0
B35: Inmueble | C35: =SUMIFS($F$6:$F$27,$C$6:$C$27,B35) -> 0 | D35: =IF($F$28=0,0,C35/$F$28) -> 0
B36: Vehículo | C36: =SUMIFS($F$6:$F$27,$C$6:$C$27,B36) -> 0 | D36: =IF($F$28=0,0,C36/$F$28) -> 0
B37: Por cobrar | C37: =SUMIFS($F$6:$F$27,$C$6:$C$27,B37) -> 0 | D37: =IF($F$28=0,0,C37/$F$28) -> 0
B38: Otro | C38: =SUMIFS($F$6:$F$27,$C$6:$C$27,B38) -> 0 | D38: =IF($F$28=0,0,C38/$F$28) -> 0
B39: Concentración en inmuebles y vehículos | C39: =IF(F28=0,0,(C35+C36)/F28) -> 0
B40: Líquido: cuentas, bolsillos y efectivo disponibles. Aportes a cooperativas, cesantías o pensión voluntaria: tipo Otro.

Sheet Control mensual
B1: Control mensual
B2: Escribe cada mes el gasto real por categoría. Se compara con el presupuesto; desviaciones mayores al 10% se resaltan.
B5: Categoría | C5: Presupuesto mensual | D5: Ene | E5: Feb | F5: Mar | G5: Abr | H5: May | I5: Jun | J5: Jul | K5: Ago | L5: Sep | M5: Oct | N5: Nov | O5: Dic | P5: Promedio real | Q5: Diferencia | R5: % desviación | S5: Meses registrados
B6: =Listas!$E$2 -> Vivienda | C6: =SUMIFS(Presupuesto!$I$6:$I$87,Presupuesto!$B$6:$B$87,B6) -> 0 | P6: =IF(COUNT(D6:O6)=0,"",AVERAGE(D6:O6)) | Q6: =IF(P6="","",P6-C6) | R6: =IF(OR(P6="",C6=0),"",Q6/C6) | S6: =COUNT(D6:O6) -> 0
B7: =Listas!$E$3 -> Alimentación | C7: =SUMIFS(Presupuesto!$I$6:$I$87,Presupuesto!$B$6:$B$87,B7) -> 0 | P7: =IF(COUNT(D7:O7)=0,"",AVERAGE(D7:O7)) | Q7: =IF(P7="","",P7-C7) | R7: =IF(OR(P7="",C7=0),"",Q7/C7) | S7: =COUNT(D7:O7) -> 0
B8: =Listas!$E$4 -> Transporte | C8: =SUMIFS(Presupuesto!$I$6:$I$87,Presupuesto!$B$6:$B$87,B8) -> 0 | P8: =IF(COUNT(D8:O8)=0,"",AVERAGE(D8:O8)) | Q8: =IF(P8="","",P8-C8) | R8: =IF(OR(P8="",C8=0),"",Q8/C8) | S8: =COUNT(D8:O8) -> 0
B9: =Listas!$E$5 -> Salud y bienestar | C9: =SUMIFS(Presupuesto!$I$6:$I$87,Presupuesto!$B$6:$B$87,B9) -> 0 | P9: =IF(COUNT(D9:O9)=0,"",AVERAGE(D9:O9)) | Q9: =IF(P9="","",P9-C9) | R9: =IF(OR(P9="",C9=0),"",Q9/C9) | S9: =COUNT(D9:O9) -> 0
B10: =Listas!$E$6 -> Cuidado personal | C10: =SUMIFS(Presupuesto!$I$6:$I$87,Presupuesto!$B$6:$B$87,B10) -> 0 | P10: =IF(COUNT(D10:O10)=0,"",AVERAGE(D10:O10)) | Q10: =IF(P10="","",P10-C10) | R10: =IF(OR(P10="",C10=0),"",Q10/C10) | S10: =COUNT(D10:O10) -> 0
B11: =Listas!$E$7 -> Hijos y familia | C11: =SUMIFS(Presupuesto!$I$6:$I$87,Presupuesto!$B$6:$B$87,B11) -> 0 | P11: =IF(COUNT(D11:O11)=0,"",AVERAGE(D11:O11)) | Q11: =IF(P11="","",P11-C11) | R11: =IF(OR(P11="",C11=0),"",Q11/C11) | S11: =COUNT(D11:O11) -> 0
B12: =Listas!$E$8 -> Mascotas | C12: =SUMIFS(Presupuesto!$I$6:$I$87,Presupuesto!$B$6:$B$87,B12) -> 0 | P12: =IF(COUNT(D12:O12)=0,"",AVERAGE(D12:O12)) | Q12: =IF(P12="","",P12-C12) | R12: =IF(OR(P12="",C12=0),"",Q12/C12) | S12: =COUNT(D12:O12) -> 0
B13: =Listas!$E$9 -> Servicios | C13: =SUMIFS(Presupuesto!$I$6:$I$87,Presupuesto!$B$6:$B$87,B13) -> 0 | P13: =IF(COUNT(D13:O13)=0,"",AVERAGE(D13:O13)) | Q13: =IF(P13="","",P13-C13) | R13: =IF(OR(P13="",C13=0),"",Q13/C13) | S13: =COUNT(D13:O13) -> 0
B14: =Listas!$E$10 -> Viajes y ocio | C14: =SUMIFS(Presupuesto!$I$6:$I$87,Presupuesto!$B$6:$B$87,B14) -> 0 | P14: =IF(COUNT(D14:O14)=0,"",AVERAGE(D14:O14)) | Q14: =IF(P14="","",P14-C14) | R14: =IF(OR(P14="",C14=0),"",Q14/C14) | S14: =COUNT(D14:O14) -> 0
B15: =Listas!$E$11 -> Temporada | C15: =SUMIFS(Presupuesto!$I$6:$I$87,Presupuesto!$B$6:$B$87,B15) -> 0 | P15: =IF(COUNT(D15:O15)=0,"",AVERAGE(D15:O15)) | Q15: =IF(P15="","",P15-C15) | R15: =IF(OR(P15="",C15=0),"",Q15/C15) | S15: =COUNT(D15:O15) -> 0
B16: =Listas!$E$12 -> Impuestos y trámites | C16: =SUMIFS(Presupuesto!$I$6:$I$87,Presupuesto!$B$6:$B$87,B16) -> 0 | P16: =IF(COUNT(D16:O16)=0,"",AVERAGE(D16:O16)) | Q16: =IF(P16="","",P16-C16) | R16: =IF(OR(P16="",C16=0),"",Q16/C16) | S16: =COUNT(D16:O16) -> 0
B17: =Listas!$E$13 -> Compras puntuales | C17: =SUMIFS(Presupuesto!$I$6:$I$87,Presupuesto!$B$6:$B$87,B17) -> 0 | P17: =IF(COUNT(D17:O17)=0,"",AVERAGE(D17:O17)) | Q17: =IF(P17="","",P17-C17) | R17: =IF(OR(P17="",C17=0),"",Q17/C17) | S17: =COUNT(D17:O17) -> 0
B18: =Listas!$E$14 -> Seguros | C18: =SUMIFS(Presupuesto!$I$6:$I$87,Presupuesto!$B$6:$B$87,B18) -> 0 | P18: =IF(COUNT(D18:O18)=0,"",AVERAGE(D18:O18)) | Q18: =IF(P18="","",P18-C18) | R18: =IF(OR(P18="",C18=0),"",Q18/C18) | S18: =COUNT(D18:O18) -> 0
B19: =Listas!$E$15 -> Seguridad social | C19: =SUMIFS(Presupuesto!$I$6:$I$87,Presupuesto!$B$6:$B$87,B19) -> 0 | P19: =IF(COUNT(D19:O19)=0,"",AVERAGE(D19:O19)) | Q19: =IF(P19="","",P19-C19) | R19: =IF(OR(P19="",C19=0),"",Q19/C19) | S19: =COUNT(D19:O19) -> 0
B20: =Listas!$E$16 -> Deudas | C20: =SUMIFS(Presupuesto!$I$6:$I$87,Presupuesto!$B$6:$B$87,B20) -> 0 | P20: =IF(COUNT(D20:O20)=0,"",AVERAGE(D20:O20)) | Q20: =IF(P20="","",P20-C20) | R20: =IF(OR(P20="",C20=0),"",Q20/C20) | S20: =COUNT(D20:O20) -> 0
B21: =Listas!$E$17 -> Ahorro | C21: =SUMIFS(Presupuesto!$I$6:$I$87,Presupuesto!$B$6:$B$87,B21) -> 0 | P21: =IF(COUNT(D21:O21)=0,"",AVERAGE(D21:O21)) | Q21: =IF(P21="","",P21-C21) | R21: =IF(OR(P21="",C21=0),"",Q21/C21) | S21: =COUNT(D21:O21) -> 0
B22: =Listas!$E$18 -> Metas | C22: =SUMIFS(Presupuesto!$I$6:$I$87,Presupuesto!$B$6:$B$87,B22) -> 0 | P22: =IF(COUNT(D22:O22)=0,"",AVERAGE(D22:O22)) | Q22: =IF(P22="","",P22-C22) | R22: =IF(OR(P22="",C22=0),"",Q22/C22) | S22: =COUNT(D22:O22) -> 0
B23: =Listas!$E$19 -> Otros | C23: =SUMIFS(Presupuesto!$I$6:$I$87,Presupuesto!$B$6:$B$87,B23) -> 0 | P23: =IF(COUNT(D23:O23)=0,"",AVERAGE(D23:O23)) | Q23: =IF(P23="","",P23-C23) | R23: =IF(OR(P23="",C23=0),"",Q23/C23) | S23: =COUNT(D23:O23) -> 0
B24: Total | C24: =SUM(C6:C23) -> 0 | D24: =IF(COUNT(D6:D23)=0,"",SUM(D6:D23)) | E24: =IF(COUNT(E6:E23)=0,"",SUM(E6:E23)) | F24: =IF(COUNT(F6:F23)=0,"",SUM(F6:F23)) | G24: =IF(COUNT(G6:G23)=0,"",SUM(G6:G23)) | H24: =IF(COUNT(H6:H23)=0,"",SUM(H6:H23)) | I24: =IF(COUNT(I6:I23)=0,"",SUM(I6:I23)) | J24: =IF(COUNT(J6:J23)=0,"",SUM(J6:J23)) | K24: =IF(COUNT(K6:K23)=0,"",SUM(K6:K23)) | ... O24: =IF(COUNT(O6:O23)=0,"",SUM(O6:O23)) | P24: =IF(COUNT(D24:O24)=0,"",AVERAGE(D24:O24)) | Q24: =IF(P24="","",P24-C24) | R24: =IF(OR(P24="",C24=0),"",Q24/C24)
B26: El presupuesto mensual es el promedio (los gastos anuales se reparten en 12). Compara el promedio real de varios meses, no un mes aislado.

Sheet Plan de acción
B1: Plan de acción
B2: Tareas con prioridad, responsable y fecha. Las vencidas se resaltan en rojo; las hechas, en verde.
B5: # | C5: Tarea | D5: Prioridad | E5: Responsable | F5: Fecha límite | G5: Estado | H5: Nota
B6: 1 | C6: Crear los bolsillos y repartir el saldo actual | D6: Alta | E6: Cliente | F6: =Supuestos!$C$12+7 -> 46297 | G6: Pendiente
B7: 2 | C7: Programar transferencias automáticas el día de pago | D7: Alta | E7: Cliente | F7: =Supuestos!$C$12+7 -> 46297 | G7: Pendiente
B8: 3 | C8: Registrar gastos reales en la hoja Control mensual | D8: Alta | E8: Cliente | F8: =Supuestos!$C$12+30 -> 46320 | G8: Pendiente
B9: 4 | C9: Completar la prueba de realidad del presupuesto | D9: Alta | E9: Asesor | F9: =Supuestos!$C$12+90 -> 46380 | G9: Pendiente
B10: 5 | C10: Pagar deudas según el orden de la hoja Deudas | D10: Alta | E10: Cliente | F10: =Supuestos!$C$12+30 -> 46320 | G10: Pendiente
B11: 6 | C11: Cotizar los seguros de prioridad alta | D11: Alta | E11: Cliente | F11: =Supuestos!$C$12+60 -> 46350 | G11: Pendiente
B12: 7 | C12: Revisar beneficiarios de seguros, pensión y cuentas | D12: Media | E12: Cliente | F12: =Supuestos!$C$12+60 -> 46350 | G12: Pendiente
B13: 8 | C13: Consultar al contador: renta, retenciones y beneficios tributarios | D13: Media | E13: Contador | F13: =Supuestos!$C$12+60 -> 46350 | G13: Pendiente
B14: 9 | C14: Descargar la historia laboral y pedir la proyección de pensión | D14: Media | E14: Administradora de pensiones | F14: =Supuestos!$C$12+60 -> 46350 | G14: Pendiente
B15: 10 | C15: Evaluar testamento y preparar la carpeta familiar | D15: Media | E15: Abogado | F15: =Supuestos!$C$12+120 -> 46410 | G15: Pendiente
B16: 11 | C16: Definir el perfil de inversión y la distribución | D16: Media | E16: Asesor | F16: =Supuestos!$C$12+30 -> 46320 | G16: Pendiente
B17: 12 | C17: Revisión de seguimiento a 30 días | D17: Alta | E17: Asesor | F17: =Supuestos!$C$12+30 -> 46320 | G17: Pendiente
B18: 13 | C18: Revisión de seguimiento a 90 días | D18: Alta | E18: Asesor | F18: =Supuestos!$C$12+90 -> 46380 | G18: Pendiente
B19: 14 | C19: Revisión anual del plan | D19: Media | E19: Asesor | F19: =Supuestos!$C$12+365 -> 46655 | G19: Pendiente
B20: 15
B21: 16
B22: 17
B23: 18
B24: 19
B25: 20
B26: 21
B27: 22

Sheet Listas
A1: Tipo de gasto | B1: Sí / No | C1: Frecuencia | D1: Veces al año | E1: Categoría | F1: Bolsillos (editable) | G1: Tipo de ingreso | H1: Tipo de cliente | I1: Meses de fondo sugeridos | J1: Sexo | K1: Régimen de pensión | L1: Tipo de activo | M1: Moneda | N1: Si la inversión cae 15% | O1: Puntos | P1: Experiencia invirtiendo | Q1: Puntos | R1: Plazo del dinero | S1: Método de pago de deudas | T1: Tipo de deuda | U1: Prioridad | V1: Responsable | W1: Estado | X1: Tipo de inversión | Y1: ¿Tiene el seguro?
A2: Directo | B2: Sí | C2: Semanal | D2: 52 | E2: Vivienda | F2: Viajes | G2: Laboral | H2: Empleado | I2: 3 | J2: Mujer | K2: Colpensiones | L2: Líquido | M2: COP | N2: Vendería | O2: 1 | P2: Ninguna | Q2: 1 | R2: Menos de 3 años | S2: Avalancha | T2: Tarjeta de crédito | U2: Alta | V2: Cliente | W2: Pendiente | X2: Crecimiento | Y2: Sí
A3: Bolsillo | B3: No | C3: Quincenal | D3: 24 | E3: Alimentación | F3: Temporada | G3: Renta | H3: Contratista | I3: 4 | J3: Hombre | K3: Fondo privado | L3: Inversión | M3: USD | N3: Esperaría | O3: 2 | P3: Algo | Q3: 2 | R3: 3 a 7 años | S3: Bola de nieve | T3: Libre inversión | U3: Media | V3: Asesor | W3: En curso | X3: Estabilidad | Y3: No
A4: Seg. social | C4: Mensual | D4: 12 | E4: Transporte | F4: Salud y cuidado | G4: Pensión | H4: Independiente variable | I4: 6 | L4: Inmueble | N4: Invertiría más | O4: 3 | P4: Bastante | Q4: 3 | R4: Más de 7 años | T4: Vehículo | U4: Baja | V4: Contador | W4: Hecho | Y4: Cotizando
A5: Deuda | C5: Bimestral | D5: 6 | E5: Salud y bienestar | F5: Ropa | G5: Otro | H5: Pensionado | I5: 3 | L5: Vehículo | T5: Hipotecario | V5: Abogado
A6: Ahorro | C6: Trimestral | D6: 4 | E6: Cuidado personal | F6: Impuestos y trámites | H6: Rentista | I6: 4 | L6: Por cobrar | T6: Libranza | V6: Aseguradora
C7: Cada 4 meses | D7: 3 | E7: Hijos y familia | F7: Hogar y mascotas | H7: Mixto | I7: 4 | L7: Otro | T7: Informal | V7: Administradora de pensiones
C8: Semestral | D8: 2 | E8: Mascotas | F8: Vehículo | T8: Otro
C9: Anual | D9: 1 | E9: Servicios | F9: Educación
C10: Cada 2 años | D10: 0.5 | E10: Viajes y ocio | F10: Seguros
C11: Por duración (días) | D11: Calculado | E11: Temporada | F11: Metas
C12: Meses con seguridad social | D12: Calculado | E12: Impuestos y trámites
E13: Compras puntuales
E14: Seguros
E15: Seguridad social
E16: Deudas
E17: Ahorro
E18: Metas
E19: Otros
B20: Los nombres de bolsillos (columna F) se pueden cambiar; las demás listas no deben modificarse.
